Workbook

Sheet Calculations
E1: Prime interest rate | G1: 0.1025
E2: Monthly Nett profit framework | G2: $/R RoE | H2: 17.2
E3: ARPU | G3: =G12/G10 -> 89.3254 | H3: =H12/H10 -> 87.566073 | I3: =I12/I10 -> 86.980144 | J3: =J12/J10 -> 86.687565 | K3: =K12/K10 -> 86.512325 | L3: =L12/L10 -> 86.395754 | M3: =M12/M10 -> 86.312707 | N3: =N12/N10 -> 86.250613 | ... R3: =R12/R10 -> 86.106984 | T3: =T12/T10 -> 86.085175 | U3: =U12/U10 -> 86.066587 | V3: =V12/V10 -> 86.050575 | W3: =W12/W10 -> 86.036656 | X3: =X12/X10 -> 86.024459 | Y3: =Y12/Y10 -> 86.013696 | Z3: =Z12/Z10 -> 86.004142 | AA3: =AA12/AA10 -> 85.995613 | ... AE3: =AE12/AE10 -> 85.969177 | AG3: =AG12/AG10 -> 85.964025 | AH3: =AH12/AH10 -> 85.959319 | AI3: =AI12/AI10 -> 85.95501 | AJ3: =AJ12/AJ10 -> 85.951054 | AK3: =AK12/AK10 -> 85.947415 | AL3: =AL12/AL10 -> 85.94406 | AM3: =AM12/AM10 -> 85.94096 | AN3: =AN12/AN10 -> 85.938092 | ... BP3: =BP12/BP10 -> 85.903432
F4: Example | G4: Month 1 | H4: Month 2 | I4: Month 3 | J4: Month 4 | K4: Month 5 | L4: Month 6 | M4: Month 7 | N4: Month 8 | O4: Month 9 | P4: Month 10 | Q4: Month 11 | R4: Month 12 | S4: TOTAL | T4: Month 13 | U4: Month 14 | V4: Month 15 | W4: Month 16 | X4: Month 17 | Y4: Month 18 | Z4: Month 19 | AA4: Month 20 | AB4: Month 21 | AC4: Month 22 | AD4: Month 23 | AE4: Month 24 | AF4: TOTAL | AG4: Month 25 | AH4: Month 26 | AI4: Month 27 | AJ4: Month 28 | AK4: Month 29 | AL4: Month 30 | AM4: Month 31 | AN4: Month 32 | AO4: Month 33 | AP4: Month 34 | AQ4: Month 35 | AR4: Month 36 | AS4: Month 37 | AT4: Month 38 | AU4: Month 39 | AV4: Month 40 | AW4: Month 41 | AX4: Month 42 | AY4: Month 43 | AZ4: Month 44 | BA4: Month 45 | BB4: Month 46 | BC4: Month 47 | BD4: Month 48 | BE4: Month 49 | BF4: Month 50 | BG4: Month 51 | BH4: Month 52 | BI4: Month 53 | BJ4: Month 54 | BK4: Month 55 | BL4: Month 56 | BM4: Month 57 | BN4: Month 58 | BO4: Month 59 | BP4: Month 60 | BQ4: Totals | BS4: Annual Nett profit framework | BT4: Yr 1 | BU4: Yr 2 | BV4: Yr 3 | BW4: Yr 4 | BX4: Yr5 | BY4: Totals
D5: Monthly SIM distribution | G5: 16000 | H5: =G10 -> 16000 | I5: =H10 -> 31200 | J5: =I10 -> 45640 | K5: =J10 -> 59358 | L5: =K10 -> 72390.1 | M5: =L10 -> 84770.595 | N5: =M10 -> 96532.065 | O5: =N10 -> 107705.46 | ... R5: =Q10 -> 137983.97 | S5: =SUM(G5:R5) -> 914304.56 | T5: 16000 | U5: 16000 | V5: 16000 | W5: 16000 | X5: 16000 | Y5: 16000 | Z5: 16000 | AA5: 16000 | AB5: 16000 | AC5: 16000 | AD5: 16000 | AE5: 16000 | AG5: 16000 | AH5: 16000 | AI5: 16000 | AJ5: 16000 | AK5: 16000 | AL5: 16000 | AM5: 16000 | AN5: 16000 | AO5: 16000 | AP5: 16000 | AQ5: 16000 | AR5: 16000 | AS5: 16000 | AT5: 16000 | AU5: 16000 | AV5: 16000 | AW5: 16000 | AX5: 16000 | AY5: 16000 | AZ5: 16000 | BA5: 16000 | BB5: 16000 | BC5: 16000 | BD5: 16000 | BE5: 16000 | BF5: 16000 | BG5: 16000 | BH5: 16000 | BI5: 16000 | BJ5: 16000 | BK5: 16000 | BL5: 16000 | BM5: 16000 | BN5: 16000 | BO5: 16000 | BP5: 16000 | BQ5: =SUM(G5:BP5)-AF5-S5 -> 1682304.6
D6: SIM card purchases physical | G6: 15800 | H6: 15800 | I6: 15800 | J6: 15800 | K6: 15800 | L6: 15800 | M6: 15800 | N6: 15800 | O6: 15800 | P6: 15800 | Q6: 15800 | R6: 15800 | S6: =SUM(G6:R6) -> 189600 | T6: 15800 | U6: 15800 | V6: 15800 | W6: 15800 | X6: 15800 | Y6: 15800 | Z6: 15800 | AA6: 15800 | AB6: 15800 | AC6: 15800 | AD6: 15800 | AE6: 15800 | AG6: 15800 | AH6: 15800 | AI6: 15800 | AJ6: 15800 | AK6: 15800 | AL6: 15800 | AM6: 15800 | AN6: 15800 | AO6: 15800 | AP6: 15800 | AQ6: 15800 | AR6: 15800 | AS6: 15800 | AT6: 15800 | AU6: 15800 | AV6: 15800 | AW6: 15800 | AX6: 15800 | AY6: 15800 | AZ6: 15800 | BA6: 15800 | BB6: 15800 | BC6: 15800 | BD6: 15800 | BE6: 15800 | BF6: 15800 | BG6: 15800 | BH6: 15800 | BI6: 15800 | BJ6: 15800 | BK6: 15800 | BL6: 15800 | BM6: 15800 | BN6: 15800 | BO6: 15800 | BP6: 15800 | BQ6: =SUM(G6:BP6)-AF6-S6 -> 948000
D7: SIM card purchases eSIM | G7: 200 | H7: 200 | I7: 200 | J7: 200 | K7: 200 | L7: 200 | M7: 200 | N7: 200 | O7: 200 | P7: 200 | Q7: 200 | R7: 200 | S7: =SUM(G7:R7) -> 2400 | T7: 200 | U7: 200 | V7: 200 | W7: 200 | X7: 200 | Y7: 200 | Z7: 200 | AA7: 200 | AB7: 200 | AC7: 200 | AD7: 200 | AE7: 200 | AG7: 200 | AH7: 200 | AI7: 200 | AJ7: 200 | AK7: 200 | AL7: 200 | AM7: 200 | AN7: 200 | AO7: 200 | AP7: 200 | AQ7: 200 | AR7: 200 | AS7: 200 | AT7: 200 | AU7: 200 | AV7: 200 | AW7: 200 | AX7: 200 | AY7: 200 | AZ7: 200 | BA7: 200 | BB7: 200 | BC7: 200 | BD7: 200 | BE7: 200 | BF7: 200 | BG7: 200 | BH7: 200 | BI7: 200 | BJ7: 200 | BK7: 200 | BL7: 200 | BM7: 200 | BN7: 200 | BO7: 200 | BP7: 200 | BQ7: =SUM(G7:BP7)-AF7-S7 -> 12000
D8: Gross Total | G8: =SUM(G6:G7) -> 16000 | H8: =SUM(H5:H7) -> 32000 | I8: =SUM(I5:I7) -> 47200 | J8: =SUM(J5:J7) -> 61640 | K8: =SUM(K5:K7) -> 75358 | L8: =SUM(L5:L7) -> 88390.1 | M8: =SUM(M5:M7) -> 100770.6 | N8: =SUM(N5:N7) -> 112532.07 | O8: =SUM(O5:O7) -> 123705.46 | ... R8: =SUM(R5:R7) -> 153983.97 | S8: =SUM(G8:R8) -> 1090304.6 | BQ8: =SUM(G8:BP8)-AF8-S8 -> 1090304.6
D9: Churn | G9: 0 | H9: =-H5*0.05 -> -800 | I9: =-I5*0.05 -> -1560 | J9: =-J5*0.05 -> -2282 | K9: =-K5*0.05 -> -2967.9 | L9: =-L5*0.05 -> -3619.505 | M9: =-M5*0.05 -> -4238.5298 | N9: =-N5*0.05 -> -4826.6033 | O9: =-O5*0.05 -> -5385.2731 | ... S9: =-S5*0.05 -> -45715.228 | BQ9: =SUM(G9:BP9)-AF9-S9 -> -44915.228
D10: Subscriber numbers net of 5% monthly churn churn (5% Churn is the MVNO Avg) | G10: =G8+G9 -> 16000 | H10: =H8+H9 -> 31200 | I10: =I8+I9 -> 45640 | J10: =J8+J9 -> 59358 | K10: =K8+K9 -> 72390.1 | L10: =L8+L9 -> 84770.595 | M10: =M8+M9 -> 96532.065 | N10: =N8+N9 -> 107705.46 | ... R10: =R8+R9 -> 147084.77 | S10: =R10 -> 147084.77 | T10: =R10-(R10*0.05)+T5 -> 155730.53 | U10: =T10-(T10*0.05)+U5 -> 163944.01 | V10: =U10-(U10*0.05)+V5 -> 171746.81 | W10: =V10-(V10*0.05)+W5 -> 179159.47 | X10: =W10-(W10*0.05)+X5 -> 186201.49 | Y10: =X10-(X10*0.05)+Y5 -> 192891.42 | Z10: =Y10-(Y10*0.05)+Z5 -> 199246.85 | AA10: =Z10-(Z10*0.05)+AA5 -> 205284.5 | AB10: =AA10-(AA10*0.05)+AB5 -> 211020.28 | ... AE10: =AD10-(AD10*0.05)+AE5 -> 226563.51 | AG10: =AE10-(AE10*0.05)+AG5 -> 231235.34 | AH10: =AG10-(AG10*0.05)+AH5 -> 235673.57 | AI10: =AH10-(AH10*0.05)+AI5 -> 239889.89 | AJ10: =AI10-(AI10*0.05)+AJ5 -> 243895.4 | AK10: =AJ10-(AJ10*0.05)+AK5 -> 247700.63 | AL10: =AK10-(AK10*0.05)+AL5 -> 251315.6 | AM10: =AL10-(AL10*0.05)+AM5 -> 254749.82 | AN10: =AM10-(AM10*0.05)+AN5 -> 258012.32 | AO10: =AN10-(AN10*0.05)+AO5 -> 261111.71 | ... BP10: =BO10-(BO10*0.05)+BP5 -> 305257.66 | BQ10: =SUM(G10:BP10)-AF10-S10 -> 13400104
D11: No churn in month 1, churn is on the monthly total of subscribers from Month 2 | S11: =R10*0.0615 -> 9045.7135 | BQ11: =SUM(G11:BP11)-AF11-S11 -> 0
D12: Total Revenue | G12: =SUM(G13:G18) -> 1429206.4 | H12: =SUM(H13:H18) -> 2732061.5 | I12: =SUM(I13:I18) -> 3969773.8 | J12: =SUM(J13:J18) -> 5145600.5 | K12: =SUM(K13:K18) -> 6262635.9 | L12: =SUM(L13:L18) -> 7323819.5 | M12: =SUM(M13:M18) -> 8331943.9 | N12: =SUM(N13:N18) -> 9289662.1 | ... R12: =SUM(R13:R18) -> 12665026 | S12: =SUM(G12:R12) -> 90298018 | T12: =SUM(T13:T18) -> 13406090 | U12: =SUM(U13:U18) -> 14110101 | V12: =SUM(V13:V18) -> 14778911 | W12: =SUM(W13:W18) -> 15414281 | X12: =SUM(X13:X18) -> 16017883 | Y12: =SUM(Y13:Y18) -> 16591304 | Z12: =SUM(Z13:Z18) -> 17136054 | AA12: =SUM(AA13:AA18) -> 17653567 | ... BP12: =SUM(BP13:BP18) -> 26222681 | BQ12: =SUM(G12:BP12)-AF12-S12 -> 1.1520454e+09 | BR12: Total Revenue | BT12: =SUM(G12:R12) -> 90298018 | BU12: =SUM(T12:AE12) -> 2.0039909e+08 | BV12: =SUM(AG12:AR12) -> 2.5989332e+08 | BW12: =SUM(AS12:BD12) -> 2.9204163e+08 | BX12: =SUM(BE12:BP12) -> 3.0941329e+08
D13: Physical sim recovery R3.60 ex VAT (Recovered from Trade partners) | G13: =G6*3.6 -> 56880 | H13: =H6*3.6 -> 56880 | I13: =I6*3.6 -> 56880 | J13: =J6*3.6 -> 56880 | K13: =K6*3.6 -> 56880 | L13: =L6*3.6 -> 56880 | M13: =M6*3.6 -> 56880 | N13: =N6*3.6 -> 56880 | ... R13: =R6*3.6 -> 56880 | S13: =SUM(G13:R13) -> 682560 | T13: =T6*3.6 -> 56880 | U13: =U6*3.6 -> 56880 | V13: =V6*3.6 -> 56880 | W13: =W6*3.6 -> 56880 | X13: =X6*3.6 -> 56880 | Y13: =Y6*3.6 -> 56880 | Z13: =Z6*3.6 -> 56880 | AA13: =AA6*3.6 -> 56880 | ... AE13: =AE6*3.6 -> 56880 | AF13: =SUM(T13:AE13) -> 682560 | AG13: =AG6*3.6 -> 56880 | AH13: =AH6*3.6 -> 56880 | AI13: =AI6*3.6 -> 56880 | AJ13: =AJ6*3.6 -> 56880 | AK13: =AK6*3.6 -> 56880 | AL13: =AL6*3.6 -> 56880 | AM13: =AM6*3.6 -> 56880 | AN13: =AN6*3.6 -> 56880 | ... BP13: =BP6*3.6 -> 56880 | BQ13: =SUM(G13:BP13)-AF13-S13 -> 3412800 | BR13: Physical sim recovery R3.60 ex VAT | BT13: =SUM(G13:R13) -> 682560 | BU13: =SUM(T13:AE13) -> 682560 | BV13: =SUM(AG13:AR13) -> 682560 | BW13: =SUM(AS13:BD13) -> 682560 | BX13: =SUM(BE13:BP13) -> 682560
D14: eSIM recovery R4.50 ex VAT | G14: =G7*4.5 -> 900 | H14: =H7*4.5 -> 900 | I14: =I7*4.5 -> 900 | J14: =J7*4.5 -> 900 | K14: =K7*4.5 -> 900 | L14: =L7*4.5 -> 900 | M14: =M7*4.5 -> 900 | N14: =N7*4.5 -> 900 | ... R14: =R7*4.5 -> 900 | S14: =SUM(G14:R14) -> 10800 | T14: =T7*4.5 -> 900 | U14: =U7*4.5 -> 900 | V14: =V7*4.5 -> 900 | W14: =W7*4.5 -> 900 | X14: =X7*4.5 -> 900 | Y14: =Y7*4.5 -> 900 | Z14: =Z7*4.5 -> 900 | AA14: =AA7*4.5 -> 900 | ... AE14: =AE7*4.5 -> 900 | AF14: =SUM(T14:AE14) -> 10800 | AG14: =AG7*4.5 -> 900 | AH14: =AH7*4.5 -> 900 | AI14: =AI7*4.5 -> 900 | AJ14: =AJ7*4.5 -> 900 | AK14: =AK7*4.5 -> 900 | AL14: =AL7*4.5 -> 900 | AM14: =AM7*4.5 -> 900 | AN14: =AN7*4.5 -> 900 | ... BP14: =BP7*4.5 -> 900 | BQ14: =SUM(G14:BP14)-AF14-S14 -> 54000 | BR14: eSIM recovery R4.50 ex VAT | BT14: =SUM(G14:R14) -> 10800 | BU14: =SUM(T14:AE14) -> 10800 | BV14: =SUM(AG14:AR14) -> 10800 | BW14: =SUM(AS14:BD14) -> 10800 | BX14: =SUM(BE14:BP14) -> 10800
D15: McAfee Revenue 5% uptake @ R15.22 (Identity theft Security) | G15: =(G10*0.05)*15.22 -> 12176 | H15: =(H10*0.05)*15.22 -> 23743.2 | I15: =(I10*0.05)*15.22 -> 34732.04 | J15: =(J10*0.05)*15.22 -> 45171.438 | K15: =(K10*0.05)*15.22 -> 55088.866 | L15: =(L10*0.05)*15.22 -> 64510.423 | M15: =(M10*0.05)*15.22 -> 73460.902 | N15: =(N10*0.05)*15.22 -> 81963.857 | ... R15: =(R10*0.05)*15.22 -> 111931.51 | S15: =SUM(G15:R15) -> 795541.28 | T15: =(T10*0.05)*15.22 -> 118510.94 | U15: =(U10*0.05)*15.22 -> 124761.39 | V15: =(V10*0.05)*15.22 -> 130699.32 | W15: =(W10*0.05)*15.22 -> 136340.35 | X15: =(X10*0.05)*15.22 -> 141699.34 | Y15: =(Y10*0.05)*15.22 -> 146790.37 | Z15: =(Z10*0.05)*15.22 -> 151626.85 | AA15: =(AA10*0.05)*15.22 -> 156221.51 | ... AE15: =(AE10*0.05)*15.22 -> 172414.83 | AF15: =SUM(T15:AE15) -> 1773056.9 | AG15: =(AG10*0.05)*15.22 -> 175970.09 | AH15: =(AH10*0.05)*15.22 -> 179347.59 | AI15: =(AI10*0.05)*15.22 -> 182556.21 | AJ15: =(AJ10*0.05)*15.22 -> 185604.4 | AK15: =(AK10*0.05)*15.22 -> 188500.18 | AL15: =(AL10*0.05)*15.22 -> 191251.17 | AM15: =(AM10*0.05)*15.22 -> 193864.61 | AN15: =(AN10*0.05)*15.22 -> 196347.38 | ... BP15: =(BP10*0.05)*15.22 -> 232301.08 | BQ15: =SUM(G15:BP15)-AF15-S15 -> 10197479 | BR15: McAfee Revenue 5% uptake @ R15.22 | BT15: =SUM(G15:R15) -> 795541.28 | BU15: =SUM(T15:AE15) -> 1773056.9 | BV15: =SUM(AG15:AR15) -> 2301267.3 | BW15: =SUM(AS15:BD15) -> 2586691.1 | BX15: =SUM(BE15:BP15) -> 2740922.8
D16: Travel eSIM revenue 1% @ R 249.23 (USD14,49) | G16: =(14.49*$H$2)*(G10*0.01) -> 39876.48 | H16: =(14.49*$H$2)*(H10*0.01) -> 77759.136 | I16: =(14.49*$H$2)*(I10*0.01) -> 113747.66 | J16: =(14.49*$H$2)*(J10*0.01) -> 147936.76 | K16: =(14.49*$H$2)*(K10*0.01) -> 180416.4 | L16: =(14.49*$H$2)*(L10*0.01) -> 211272.06 | M16: =(14.49*$H$2)*(M10*0.01) -> 240584.94 | N16: =(14.49*$H$2)*(N10*0.01) -> 268432.17 | ... R16: =(14.49*$H$2)*(R10*0.01) -> 366576.44 | S16: =SUM(G16:R16) -> 2605402.9 | T16: =(14.49*$H$2)*(T10*0.01) -> 388124.09 | U16: =(14.49*$H$2)*(U10*0.01) -> 408594.37 | V16: =(14.49*$H$2)*(V10*0.01) -> 428041.13 | W16: =(14.49*$H$2)*(W10*0.01) -> 446515.55 | X16: =(14.49*$H$2)*(X10*0.01) -> 464066.26 | Y16: =(14.49*$H$2)*(Y10*0.01) -> 480739.42 | Z16: =(14.49*$H$2)*(Z10*0.01) -> 496578.93 | AA16: =(14.49*$H$2)*(AA10*0.01) -> 511626.47 | ... AE16: =(14.49*$H$2)*(AE10*0.01) -> 564659.71 | AF16: =SUM(T16:AE16) -> 5806773 | AG16: =(14.49*$H$2)*(AG10*0.01) -> 576303.2 | AH16: =(14.49*$H$2)*(AH10*0.01) -> 587364.52 | AI16: =(14.49*$H$2)*(AI10*0.01) -> 597872.78 | AJ16: =(14.49*$H$2)*(AJ10*0.01) -> 607855.62 | AK16: =(14.49*$H$2)*(AK10*0.01) -> 617339.32 | AL16: =(14.49*$H$2)*(AL10*0.01) -> 626348.83 | AM16: =(14.49*$H$2)*(AM10*0.01) -> 634907.87 | AN16: =(14.49*$H$2)*(AN10*0.01) -> 643038.96 | ... BP16: =(14.49*$H$2)*(BP10*0.01) -> 760787.57 | BQ16: =SUM(G16:BP16)-AF16-S16 -> 33396812 | BR16: Travel eSIM revenue 1% @ R 249.23 (USD14,49) | BT16: =SUM(G16:R16) -> 2605402.9 | BU16: =SUM(T16:AE16) -> 5806773 | BV16: =SUM(AG16:AR16) -> 7536665.6 | BW16: =SUM(AS16:BD16) -> 8471430.5 | BX16: =SUM(BE16:BP16) -> 8976540.2
D17: Content revenue 5% @ R20 | G17: =(G10*0.05)*20 -> 16000 | H17: =(H10*0.05)*20 -> 31200 | I17: =(I10*0.05)*20 -> 45640 | J17: =(J10*0.05)*20 -> 59358 | K17: =(K10*0.05)*20 -> 72390.1 | L17: =(L10*0.05)*20 -> 84770.595 | M17: =(M10*0.05)*20 -> 96532.065 | N17: =(N10*0.05)*20 -> 107705.46 | ... R17: =(R10*0.05)*20 -> 147084.77 | S17: =SUM(G17:R17) -> 1045389.3 | T17: =(T10*0.05)*20 -> 155730.53 | U17: =(U10*0.05)*20 -> 163944.01 | V17: =(V10*0.05)*20 -> 171746.81 | W17: =(W10*0.05)*20 -> 179159.47 | X17: =(X10*0.05)*20 -> 186201.49 | Y17: =(Y10*0.05)*20 -> 192891.42 | Z17: =(Z10*0.05)*20 -> 199246.85 | AA17: =(AA10*0.05)*20 -> 205284.5 | ... AE17: =(AE10*0.05)*20 -> 226563.51 | AF17: =SUM(T17:AE17) -> 2329903.9 | AG17: =(AG10*0.05)*20 -> 231235.34 | AH17: =(AH10*0.05)*20 -> 235673.57 | AI17: =(AI10*0.05)*20 -> 239889.89 | AJ17: =(AJ10*0.05)*20 -> 243895.4 | AK17: =(AK10*0.05)*20 -> 247700.63 | AL17: =(AL10*0.05)*20 -> 251315.6 | AM17: =(AM10*0.05)*20 -> 254749.82 | AN17: =(AN10*0.05)*20 -> 258012.32 | ... BP17: =(BP10*0.05)*20 -> 305257.66 | BQ17: =SUM(G17:BP17)-AF17-S17 -> 13400104 | BR17: Content revenue 5% @ R20 | BT17: =SUM(G17:R17) -> 1045389.3 | BU17: =SUM(T17:AE17) -> 2329903.9 | BV17: =SUM(AG17:AR17) -> 3024004.4 | BW17: =SUM(AS17:BD17) -> 3399068.5 | BX17: =SUM(BE17:BP17) -> 3601738.2
D18: Revenue (Voice and Data Revenue) | F18: 100 | G18: =((((G10)*Packages!$E$5)*(Packages!$J$5)+(((G10)*Packages!$E$6)*Packages!$J$6)+(((G10)*Packages!$E$7)*Packages!$J$7)))+((((G10)*Packages!$E$8)*(Packages!$J$8))) -> 1303373.9 | H18: =((((H10)*Packages!$E$5)*(Packages!$J$5)+(((H10)*Packages!$E$6)*Packages!$J$6)+(((H10)*Packages!$E$7)*Packages!$J$7)))+((((H10)*Packages!$E$8)*(Packages!$J$8))) -> 2541579.1 | I18: =((((I10)*Packages!$E$5)*(Packages!$J$5)+(((I10)*Packages!$E$6)*Packages!$J$6)+(((I10)*Packages!$E$7)*Packages!$J$7)))+((((I10)*Packages!$E$8)*(Packages!$J$8))) -> 3717874.1 | J18: =((((J10)*Packages!$E$5)*(Packages!$J$5)+(((J10)*Packages!$E$6)*Packages!$J$6)+(((J10)*Packages!$E$7)*Packages!$J$7)))+((((J10)*Packages!$E$8)*(Packages!$J$8))) -> 4835354.3 | K18: =((((K10)*Packages!$E$5)*(Packages!$J$5)+(((K10)*Packages!$E$6)*Packages!$J$6)+(((K10)*Packages!$E$7)*Packages!$J$7)))+((((K10)*Packages!$E$8)*(Packages!$J$8))) -> 5896960.5 | L18: =((((L10)*Packages!$E$5)*(Packages!$J$5)+(((L10)*Packages!$E$6)*Packages!$J$6)+(((L10)*Packages!$E$7)*Packages!$J$7)))+((((L10)*Packages!$E$8)*(Packages!$J$8))) -> 6905486.4 | M18: =((((M10)*Packages!$E$5)*(Packages!$J$5)+(((M10)*Packages!$E$6)*Packages!$J$6)+(((M10)*Packages!$E$7)*Packages!$J$7)))+((((M10)*Packages!$E$8)*(Packages!$J$8))) -> 7863586 | N18: =((((N10)*Packages!$E$5)*(Packages!$J$5)+(((N10)*Packages!$E$6)*Packages!$J$6)+(((N10)*Packages!$E$7)*Packages!$J$7)))+((((N10)*Packages!$E$8)*(Packages!$J$8))) -> 8773780.6 | ... R18: =((((R10)*Packages!$E$5)*(Packages!$J$5)+(((R10)*Packages!$E$6)*Packages!$J$6)+(((R10)*Packages!$E$7)*Packages!$J$7)))+((((R10)*Packages!$E$8)*(Packages!$J$8))) -> 11981653 | S18: =SUM(G18:R18) -> 85158324 | T18: =((((T10)*Packages!$E$5)*(Packages!$J$5)+(((T10)*Packages!$E$6)*Packages!$J$6)+(((T10)*Packages!$E$7)*Packages!$J$7)))+((((T10)*Packages!$E$8)*(Packages!$J$8))) -> 12685945 | U18: =((((U10)*Packages!$E$5)*(Packages!$J$5)+(((U10)*Packages!$E$6)*Packages!$J$6)+(((U10)*Packages!$E$7)*Packages!$J$7)))+((((U10)*Packages!$E$8)*(Packages!$J$8))) -> 13355021 | V18: =((((V10)*Packages!$E$5)*(Packages!$J$5)+(((V10)*Packages!$E$6)*Packages!$J$6)+(((V10)*Packages!$E$7)*Packages!$J$7)))+((((V10)*Packages!$E$8)*(Packages!$J$8))) -> 13990644 | W18: =((((W10)*Packages!$E$5)*(Packages!$J$5)+(((W10)*Packages!$E$6)*Packages!$J$6)+(((W10)*Packages!$E$7)*Packages!$J$7)))+((((W10)*Packages!$E$8)*(Packages!$J$8))) -> 14594486 | X18: =((((X10)*Packages!$E$5)*(Packages!$J$5)+(((X10)*Packages!$E$6)*Packages!$J$6)+(((X10)*Packages!$E$7)*Packages!$J$7)))+((((X10)*Packages!$E$8)*(Packages!$J$8))) -> 15168136 | Y18: =((((Y10)*Packages!$E$5)*(Packages!$J$5)+(((Y10)*Packages!$E$6)*Packages!$J$6)+(((Y10)*Packages!$E$7)*Packages!$J$7)))+((((Y10)*Packages!$E$8)*(Packages!$J$8))) -> 15713103 | Z18: =((((Z10)*Packages!$E$5)*(Packages!$J$5)+(((Z10)*Packages!$E$6)*Packages!$J$6)+(((Z10)*Packages!$E$7)*Packages!$J$7)))+((((Z10)*Packages!$E$8)*(Packages!$J$8))) -> 16230821 | AA18: =((((AA10)*Packages!$E$5)*(Packages!$J$5)+(((AA10)*Packages!$E$6)*Packages!$J$6)+(((AA10)*Packages!$E$7)*Packages!$J$7)))+((((AA10)*Packages!$E$8)*(Packages!$J$8))) -> 16722654 | ... AE18: =((((AE10)*Packages!$E$5)*(Packages!$J$5)+(((AE10)*Packages!$E$6)*Packages!$J$6)+(((AE10)*Packages!$E$7)*Packages!$J$7)))+((((AE10)*Packages!$E$8)*(Packages!$J$8))) -> 18456061 | AF18: =SUM(T18:AE18) -> 1.89796e+08 | AG18: =((((AG10)*Packages!$E$5)*(Packages!$J$5)+(((AG10)*Packages!$E$6)*Packages!$J$6)+(((AG10)*Packages!$E$7)*Packages!$J$7)))+((((AG10)*Packages!$E$8)*(Packages!$J$8))) -> 18836632 | AH18: =((((AH10)*Packages!$E$5)*(Packages!$J$5)+(((AH10)*Packages!$E$6)*Packages!$J$6)+(((AH10)*Packages!$E$7)*Packages!$J$7)))+((((AH10)*Packages!$E$8)*(Packages!$J$8))) -> 19198174 | AI18: =((((AI10)*Packages!$E$5)*(Packages!$J$5)+(((AI10)*Packages!$E$6)*Packages!$J$6)+(((AI10)*Packages!$E$7)*Packages!$J$7)))+((((AI10)*Packages!$E$8)*(Packages!$J$8))) -> 19541639 | AJ18: =((((AJ10)*Packages!$E$5)*(Packages!$J$5)+(((AJ10)*Packages!$E$6)*Packages!$J$6)+(((AJ10)*Packages!$E$7)*Packages!$J$7)))+((((AJ10)*Packages!$E$8)*(Packages!$J$8))) -> 19867931 | AK18: =((((AK10)*Packages!$E$5)*(Packages!$J$5)+(((AK10)*Packages!$E$6)*Packages!$J$6)+(((AK10)*Packages!$E$7)*Packages!$J$7)))+((((AK10)*Packages!$E$8)*(Packages!$J$8))) -> 20177908 | AL18: =((((AL10)*Packages!$E$5)*(Packages!$J$5)+(((AL10)*Packages!$E$6)*Packages!$J$6)+(((AL10)*Packages!$E$7)*Packages!$J$7)))+((((AL10)*Packages!$E$8)*(Packages!$J$8))) -> 20472387 | AM18: =((((AM10)*Packages!$E$5)*(Packages!$J$5)+(((AM10)*Packages!$E$6)*Packages!$J$6)+(((AM10)*Packages!$E$7)*Packages!$J$7)))+((((AM10)*Packages!$E$8)*(Packages!$J$8))) -> 20752142 | AN18: =((((AN10)*Packages!$E$5)*(Packages!$J$5)+(((AN10)*Packages!$E$6)*Packages!$J$6)+(((AN10)*Packages!$E$7)*Packages!$J$7)))+((((AN10)*Packages!$E$8)*(Packages!$J$8))) -> 21017908 | ... BP18: =((((BP10)*Packages!$E$5)*(Packages!$J$5)+(((BP10)*Packages!$E$6)*Packages!$J$6)+(((BP10)*Packages!$E$7)*Packages!$J$7)))+((((BP10)*Packages!$E$8)*(Packages!$J$8))) -> 24866555 | BQ18: =SUM(G18:BP18)-AF18-S18 -> 1.0915842e+09 | BR18: Revenue | BT18: =SUM(G18:R18) -> 85158324 | BU18: =SUM(T18:AE18) -> 1.89796e+08 | BV18: =SUM(AG18:AR18) -> 2.4633802e+08 | BW18: =SUM(AS18:BD18) -> 2.7689108e+08 | BX18: =SUM(BE18:BP18) -> 2.9340073e+08 | BY18: =BQ18 -> 1.0915842e+09
D19: ARPU per month | F19: 100 | G19: =G18/G10 -> 81.46087 | H19: =H18/H10 -> 81.46087 | I19: =I18/I10 -> 81.46087 | J19: =J18/J10 -> 81.46087 | K19: =K18/K10 -> 81.46087 | L19: =L18/L10 -> 81.46087 | M19: =M18/M10 -> 81.46087 | N19: =N18/N10 -> 81.46087 | ... AE19: =AE18/AE10 -> 81.46087 | AG19: =AG18/AG10 -> 81.46087 | AH19: =AH18/AH10 -> 81.46087 | AI19: =AI18/AI10 -> 81.46087 | AJ19: =AJ18/AJ10 -> 81.46087 | AK19: =AK18/AK10 -> 81.46087 | AL19: =AL18/AL10 -> 81.46087 | AM19: =AM18/AM10 -> 81.46087 | AN19: =AN18/AN10 -> 81.46087 | ... BP19: =BP18/BP10 -> 81.46087 | BQ19: =SUM(G19:BP19)-AF19-S19 -> 4887.6522 | BR19: ARPU per month | BT19: =SUM(G19:R19)/12 -> 81.46087 | BU19: =SUM(H19:T19)/12 -> 129.70874 | BV19: =SUM(I19:U19)/12 -> 129.70874 | BW19: =SUM(J19:V19)/12 -> 129.70874 | BX19: =SUM(K19:W19)/12 -> 129.70874
E20: Call agents | G20: 2 | H20: 2 | I20: 3 | J20: 3 | K20: 4 | L20: 5 | M20: 5 | N20: 5 | O20: 6 | P20: 6 | Q20: 7 | R20: 7 | T20: 7 | U20: 7 | V20: 8 | W20: 8 | X20: 8 | Y20: 9 | Z20: 9 | AA20: 9 | AB20: 9 | AC20: 9 | AD20: 10 | AE20: 10 | AG20: 10 | AH20: 10 | AI20: 10 | AJ20: 10 | AK20: 10 | AL20: 10 | AM20: 10 | AN20: 11 | AO20: 11 | AP20: 11 | AQ20: 11 | AR20: 11 | AS20: 11 | AT20: 11 | AU20: 11 | AV20: 11 | AW20: 11 | AX20: 11 | AY20: 12 | AZ20: 12 | BA20: 12 | BB20: 12 | BC20: 12 | BD20: 12 | BE20: 12 | BF20: 12 | BG20: 12 | BH20: 12 | BI20: 12 | BJ20: 12 | BK20: 12 | BL20: 12 | BM20: 12 | BN20: 12 | BO20: 12 | BP20: 12
D21: Total COS | G21: =G22+G26+G27+G30+G35+G36 -> 1415622.2 | H21: =H22+H26+H27+H30+H35+H36 -> 1978213.3 | I21: =I22+I26+I27+I30+I35+I36 -> 2779924.9 | J21: =J22+J26+J27+J30+J35+J36 -> 3517800.8 | K21: =K22+K26+K27+K30+K35+K36 -> 4243783 | L21: =L22+L26+L27+L30+L35+L36 -> 4934716.1 | M21: =M22+M26+M27+M30+M35+M36 -> 5567352.5 | N21: =N22+N26+N27+N30+N35+N36 -> 6168357.1 | ... R21: =R22+R26+R27+R30+R35+R36 -> 8336526.4 | S21: =SUM(G21:R21) -> 60860330 | T21: =T22+T26+T27+T30+T35+T36 -> 8806522.3 | U21: =U22+U26+U27+U30+U35+U36 -> 9248315.9 | V21: =V22+V26+V27+V30+V35+V36 -> 9693019.8 | W21: =W22+W26+W27+W30+W35+W36 -> 10091739 | X21: =X22+X26+X27+X30+X35+X36 -> 10470521 | Y21: =Y22+Y26+Y27+Y30+Y35+Y36 -> 10855365 | Z21: =Z22+Z26+Z27+Z30+Z35+Z36 -> 11197216 | AA21: =AA22+AA26+AA27+AA30+AA35+AA36 -> 11521975 | ... AE21: =AE22+AE26+AE27+AE30+AE35+AE36 -> 12691549 | AF21: =SUM(T21:AE21) -> 1.3095734e+08 | AG21: =AG22+AG26+AG27+AG30+AG35+AG36 -> 12948039 | AH21: =AH22+AH26+AH27+AH30+AH35+AH36 -> 13186767 | AI21: =AI22+AI26+AI27+AI30+AI35+AI36 -> 13413558 | AJ21: =AJ22+AJ26+AJ27+AJ30+AJ35+AJ36 -> 13629010 | AK21: =AK22+AK26+AK27+AK30+AK35+AK36 -> 13833689 | AL21: =AL22+AL26+AL27+AL30+AL35+AL36 -> 14028134 | AM21: =AM22+AM26+AM27+AM30+AM35+AM36 -> 14212857 | AN21: =AN22+AN26+AN27+AN30+AN35+AN36 -> 14413344 | ... BP21: =BP22+BP26+BP27+BP30+BP35+BP36 -> 16990806 | BQ21: =SUM(G21:BP21)-AF21-S21 -> 7.5078117e+08 | BR21: Total COS | BT21: =SUM(G21:R21) -> 60860330 | BU21: =SUM(T21:AE21) -> 1.3095734e+08 | BV21: =SUM(AG21:AR21) -> 1.689046e+08 | BW21: =SUM(AS21:BD21) -> 1.8946938e+08 | BX21: =SUM(BE21:BP21) -> 2.0058952e+08
C22: m | E22: Wholesale Network Tarrif Costs | F22: 50 | G22: =(((G10)*Packages!$J$5)*Packages!$N$5)+(((G10)*Packages!$J$6)*Packages!$N$6)+(((G10)*Packages!$J$7)*Packages!$N$7)+(((G10)*Packages!$J$8)*Packages!$N$8) -> 665116.13 | H22: =(((H10)*Packages!$J$5)*Packages!$N$5)+(((H10)*Packages!$J$6)*Packages!$N$6)+(((H10)*Packages!$J$7)*Packages!$N$7)+(((H10)*Packages!$J$8)*Packages!$N$8) -> 1296976.5 | I22: =(((I10)*Packages!$J$5)*Packages!$N$5)+(((I10)*Packages!$J$6)*Packages!$N$6)+(((I10)*Packages!$J$7)*Packages!$N$7)+(((I10)*Packages!$J$8)*Packages!$N$8) -> 1897243.8 | J22: =(((J10)*Packages!$J$5)*Packages!$N$5)+(((J10)*Packages!$J$6)*Packages!$N$6)+(((J10)*Packages!$J$7)*Packages!$N$7)+(((J10)*Packages!$J$8)*Packages!$N$8) -> 2467497.7 | K22: =(((K10)*Packages!$J$5)*Packages!$N$5)+(((K10)*Packages!$J$6)*Packages!$N$6)+(((K10)*Packages!$J$7)*Packages!$N$7)+(((K10)*Packages!$J$8)*Packages!$N$8) -> 3009238.9 | L22: =(((L10)*Packages!$J$5)*Packages!$N$5)+(((L10)*Packages!$J$6)*Packages!$N$6)+(((L10)*Packages!$J$7)*Packages!$N$7)+(((L10)*Packages!$J$8)*Packages!$N$8) -> 3523893.1 | M22: =(((M10)*Packages!$J$5)*Packages!$N$5)+(((M10)*Packages!$J$6)*Packages!$N$6)+(((M10)*Packages!$J$7)*Packages!$N$7)+(((M10)*Packages!$J$8)*Packages!$N$8) -> 4012814.6 | N22: =(((N10)*Packages!$J$5)*Packages!$N$5)+(((N10)*Packages!$J$6)*Packages!$N$6)+(((N10)*Packages!$J$7)*Packages!$N$7)+(((N10)*Packages!$J$8)*Packages!$N$8) -> 4477290 | ... R22: =(((R10)*Packages!$J$5)*Packages!$N$5)+(((R10)*Packages!$J$6)*Packages!$N$6)+(((R10)*Packages!$J$7)*Packages!$N$7)+(((R10)*Packages!$J$8)*Packages!$N$8) -> 6114278.4 | S22: =SUM(G22:R22) -> 43456582 | T22: =(((T10)*Packages!$J$5)*Packages!$N$5)+(((T10)*Packages!$J$6)*Packages!$N$6)+(((T10)*Packages!$J$7)*Packages!$N$7)+(((T10)*Packages!$J$8)*Packages!$N$8) -> 6473680.6 | U22: =(((U10)*Packages!$J$5)*Packages!$N$5)+(((U10)*Packages!$J$6)*Packages!$N$6)+(((U10)*Packages!$J$7)*Packages!$N$7)+(((U10)*Packages!$J$8)*Packages!$N$8) -> 6815112.7 | V22: =(((V10)*Packages!$J$5)*Packages!$N$5)+(((V10)*Packages!$J$6)*Packages!$N$6)+(((V10)*Packages!$J$7)*Packages!$N$7)+(((V10)*Packages!$J$8)*Packages!$N$8) -> 7139473.2 | W22: =(((W10)*Packages!$J$5)*Packages!$N$5)+(((W10)*Packages!$J$6)*Packages!$N$6)+(((W10)*Packages!$J$7)*Packages!$N$7)+(((W10)*Packages!$J$8)*Packages!$N$8) -> 7447615.7 | X22: =(((X10)*Packages!$J$5)*Packages!$N$5)+(((X10)*Packages!$J$6)*Packages!$N$6)+(((X10)*Packages!$J$7)*Packages!$N$7)+(((X10)*Packages!$J$8)*Packages!$N$8) -> 7740351 | Y22: =(((Y10)*Packages!$J$5)*Packages!$N$5)+(((Y10)*Packages!$J$6)*Packages!$N$6)+(((Y10)*Packages!$J$7)*Packages!$N$7)+(((Y10)*Packages!$J$8)*Packages!$N$8) -> 8018449.6 | Z22: =(((Z10)*Packages!$J$5)*Packages!$N$5)+(((Z10)*Packages!$J$6)*Packages!$N$6)+(((Z10)*Packages!$J$7)*Packages!$N$7)+(((Z10)*Packages!$J$8)*Packages!$N$8) -> 8282643.2 | AA22: =(((AA10)*Packages!$J$5)*Packages!$N$5)+(((AA10)*Packages!$J$6)*Packages!$N$6)+(((AA10)*Packages!$J$7)*Packages!$N$7)+(((AA10)*Packages!$J$8)*Packages!$N$8) -> 8533627.2 | ... AE22: =(((AE10)*Packages!$J$5)*Packages!$N$5)+(((AE10)*Packages!$J$6)*Packages!$N$6)+(((AE10)*Packages!$J$7)*Packages!$N$7)+(((AE10)*Packages!$J$8)*Packages!$N$8) -> 9418190.4 | AF22: =SUM(T22:AE22) -> 96853543 | AG22: =(((AG10)*Packages!$J$5)*Packages!$N$5)+(((AG10)*Packages!$J$6)*Packages!$N$6)+(((AG10)*Packages!$J$7)*Packages!$N$7)+(((AG10)*Packages!$J$8)*Packages!$N$8) -> 9612397 | AH22: =(((AH10)*Packages!$J$5)*Packages!$N$5)+(((AH10)*Packages!$J$6)*Packages!$N$6)+(((AH10)*Packages!$J$7)*Packages!$N$7)+(((AH10)*Packages!$J$8)*Packages!$N$8) -> 9796893.3 | AI22: =(((AI10)*Packages!$J$5)*Packages!$N$5)+(((AI10)*Packages!$J$6)*Packages!$N$6)+(((AI10)*Packages!$J$7)*Packages!$N$7)+(((AI10)*Packages!$J$8)*Packages!$N$8) -> 9972164.7 | AJ22: =(((AJ10)*Packages!$J$5)*Packages!$N$5)+(((AJ10)*Packages!$J$6)*Packages!$N$6)+(((AJ10)*Packages!$J$7)*Packages!$N$7)+(((AJ10)*Packages!$J$8)*Packages!$N$8) -> 10138673 | AK22: =(((AK10)*Packages!$J$5)*Packages!$N$5)+(((AK10)*Packages!$J$6)*Packages!$N$6)+(((AK10)*Packages!$J$7)*Packages!$N$7)+(((AK10)*Packages!$J$8)*Packages!$N$8) -> 10296855 | AL22: =(((AL10)*Packages!$J$5)*Packages!$N$5)+(((AL10)*Packages!$J$6)*Packages!$N$6)+(((AL10)*Packages!$J$7)*Packages!$N$7)+(((AL10)*Packages!$J$8)*Packages!$N$8) -> 10447129 | AM22: =(((AM10)*Packages!$J$5)*Packages!$N$5)+(((AM10)*Packages!$J$6)*Packages!$N$6)+(((AM10)*Packages!$J$7)*Packages!$N$7)+(((AM10)*Packages!$J$8)*Packages!$N$8) -> 10589888 | AN22: =(((AN10)*Packages!$J$5)*Packages!$N$5)+(((AN10)*Packages!$J$6)*Packages!$N$6)+(((AN10)*Packages!$J$7)*Packages!$N$7)+(((AN10)*Packages!$J$8)*Packages!$N$8) -> 10725510 | ... BP22: =(((BP10)*Packages!$J$5)*Packages!$N$5)+(((BP10)*Packages!$J$6)*Packages!$N$6)+(((BP10)*Packages!$J$7)*Packages!$N$7)+(((BP10)*Packages!$J$8)*Packages!$N$8) -> 12689487 | BQ22: =SUM(G22:BP22)-AF22-S22 -> 5.570391e+08 | BS22: Wholesale Network Tarrifs | BT22: =SUM(G22:R22) -> 43456582 | BU22: =SUM(T22:AE22) -> 96853543 | BV22: =SUM(AG22:AR22) -> 1.2570713e+08 | BW22: =SUM(AS22:BD22) -> 1.4129846e+08 | BX22: =SUM(BE22:BP22) -> 1.4972339e+08 | BY22: =BQ22 -> 5.570391e+08
D23: Dependent on final product composition of voice and/or data and/or SMS | BR23: Dependent on final product composition of voice and/or data and/or SMS
E24: Gross Profit Margin | G24: =G22/G18 -> 0.51030339 | H24: =H22/H18 -> 0.51030339 | I24: =I22/I18 -> 0.51030339 | J24: =J22/J18 -> 0.51030339 | K24: =K22/K18 -> 0.51030339 | L24: =L22/L18 -> 0.51030339 | M24: =M22/M18 -> 0.51030339 | N24: =N22/N18 -> 0.51030339 | ... R24: =R22/R18 -> 0.51030339 | T24: =T22/T18 -> 0.51030339 | U24: =U22/U18 -> 0.51030339 | V24: =V22/V18 -> 0.51030339 | W24: =W22/W18 -> 0.51030339 | X24: =X22/X18 -> 0.51030339 | Y24: =Y22/Y18 -> 0.51030339 | Z24: =Z22/Z18 -> 0.51030339 | AA24: =AA22/AA18 -> 0.51030339 | ... AE24: =AE22/AE18 -> 0.51030339 | AG24: =AG22/AG18 -> 0.51030339 | AH24: =AH22/AH18 -> 0.51030339 | AI24: =AI22/AI18 -> 0.51030339 | AJ24: =AJ22/AJ18 -> 0.51030339 | AK24: =AK22/AK18 -> 0.51030339 | AL24: =AL22/AL18 -> 0.51030339 | AM24: =AM22/AM18 -> 0.51030339 | AN24: =AN22/AN18 -> 0.51030339 | ... BP24: =BP22/BP18 -> 0.51030339 | BQ24: =SUM(G24:BP24)-AF24-S24 -> 30.618204 | BS24: Gross Profit Margin | BT24: 0.51 | BU24: 0.51 | BV24: 0.51 | BW24: 0.51 | BX24: 0.51
C26: m | D26: Contact Centre fixed per seat (seat subject to call centre vol) | F26: 3 | G26: =G20*25000 -> 50000 | H26: =H20*25000 -> 50000 | I26: =I20*25000 -> 75000 | J26: =J20*25000 -> 75000 | K26: =K20*25000 -> 100000 | L26: =L20*25000 -> 125000 | M26: =M20*25000 -> 125000 | N26: =N20*25000 -> 125000 | ... R26: =R20*25000 -> 175000 | S26: =SUM(F26:R26) -> 1375003 | T26: =T20*25000 -> 175000 | U26: =U20*25000 -> 175000 | V26: =V20*25000 -> 200000 | W26: =W20*25000 -> 200000 | X26: =X20*25000 -> 200000 | Y26: =Y20*25000 -> 225000 | Z26: =Z20*25000 -> 225000 | AA26: =AA20*25000 -> 225000 | ... AE26: =AE20*25000 -> 250000 | AG26: =AG20*25000 -> 250000 | AH26: =AH20*25000 -> 250000 | AI26: =AI20*25000 -> 250000 | AJ26: =AJ20*25000 -> 250000 | AK26: =AK20*25000 -> 250000 | AL26: =AL20*25000 -> 250000 | AM26: =AM20*25000 -> 250000 | AN26: =AN20*25000 -> 275000 | ... BP26: =BP20*25000 -> 300000 | BQ26: =SUM(G26:BP26)-AF26-S26 -> 14125000 | BR26: Contact Centre fixed per seat (seat subject to call centre vol) | BT26: =SUM(G26:R26) -> 1375000 | BU26: =SUM(T26:AE26) -> 2575000 | BV26: =SUM(AG26:AR26) -> 3125000 | BW26: =SUM(AS26:BD26) -> 3450000 | BX26: =SUM(BE26:BP26) -> 3600000 | BY26: =BQ26 -> 14125000
C27: k | D27: Total Commission payable to disti channels | E27: 0.13 | F27: 18 | G27: =G18*0.15 -> 195506.09 | H27: =H18*0.15 -> 381236.87 | I27: =I18*0.15 -> 557681.11 | J27: =J18*0.15 -> 725303.14 | K27: =K18*0.15 -> 884544.07 | L27: =L18*0.15 -> 1035823 | M27: =M18*0.15 -> 1179537.9 | N27: =N18*0.15 -> 1316067.1 | ... R27: =R18*0.15 -> 1797248 | S27: =SUM(G27:R27) -> 12773749 | T27: =T18*0.15 -> 1902891.7 | U27: =U18*0.15 -> 2003253.2 | V27: =V18*0.15 -> 2098596.6 | W27: =W18*0.15 -> 2189172.9 | X27: =X18*0.15 -> 2275220.3 | Y27: =Y18*0.15 -> 2356965.4 | Z27: =Z18*0.15 -> 2434623.2 | AA27: =AA18*0.15 -> 2508398.1 | ... AE27: =AE18*0.15 -> 2768409.1 | AF27: =SUM(T27:AE27) -> 28469400 | AG27: =AG18*0.15 -> 2825494.7 | AH27: =AH18*0.15 -> 2879726.1 | AI27: =AI18*0.15 -> 2931245.9 | AJ27: =AJ18*0.15 -> 2980189.7 | AK27: =AK18*0.15 -> 3026686.3 | AL27: =AL18*0.15 -> 3070858 | AM27: =AM18*0.15 -> 3112821.2 | AN27: =AN18*0.15 -> 3152686.3 | ... BP27: =BP18*0.15 -> 3729983.2 | BQ27: =SUM(G27:BP27)-AF27-S27 -> 1.6373762e+08 | BR27: Total Commission payable to disti channels | BS27: 0.13 | BT27: =SUM(G27:R27) -> 12773749 | BU27: =SUM(T27:AE27) -> 28469400 | BV27: =SUM(AG27:AR27) -> 36950704 | BW27: =SUM(AS27:BD27) -> 41533662 | BX27: =SUM(BE27:BP27) -> 44010109 | BY27: =BQ27 -> 1.6373762e+08
D28: OGR - Ongoing commission to trade partner @7% | E28: 0.07 | G28: =$E$28*G18 -> 91236.174 | H28: =$E$28*H18 -> 177910.54 | I28: =$E$28*I18 -> 260251.19 | J28: =$E$28*J18 -> 338474.8 | K28: =$E$28*K18 -> 412787.23 | L28: =$E$28*L18 -> 483384.05 | M28: =$E$28*M18 -> 550451.02 | N28: =$E$28*N18 -> 614164.64 | ... R28: =$E$28*R18 -> 838715.74 | S28: =SUM(G28:R28) -> 5961082.7 | T28: =$E$28*T18 -> 888016.13 | U28: =$E$28*U18 -> 934851.49 | V28: =$E$28*V18 -> 979345.09 | W28: =$E$28*W18 -> 1021614 | X28: =$E$28*X18 -> 1061769.5 | Y28: =$E$28*Y18 -> 1099917.2 | Z28: =$E$28*Z18 -> 1136157.5 | AA28: =$E$28*AA18 -> 1170585.8 | ... AE28: =$E$28*AE18 -> 1291924.3 | AF28: =SUM(T28:AE28) -> 13285720 | AG28: =$E$28*AG18 -> 1318564.2 | AH28: =$E$28*AH18 -> 1343872.2 | AI28: =$E$28*AI18 -> 1367914.7 | AJ28: =$E$28*AJ18 -> 1390755.2 | AK28: =$E$28*AK18 -> 1412453.6 | AL28: =$E$28*AL18 -> 1433067.1 | AM28: =$E$28*AM18 -> 1452649.9 | AN28: =$E$28*AN18 -> 1471253.6 | ... BP28: =$E$28*BP18 -> 1740658.8 | BQ28: =SUM(G28:BP28)-AF28-S28 -> 76410891 | BR28: Ongoing commission to trade partner @7% | BS28: 0.07 | BT28: =SUM(G28:R28) -> 5961082.7 | BU28: =SUM(T28:AE28) -> 13285720 | BV28: =SUM(AG28:AR28) -> 17243662 | BW28: =SUM(AS28:BD28) -> 19382375 | BX28: =SUM(BE28:BP28) -> 20538051 | BY28: =BQ28 -> 76410891
D29: Once off commission to airtime dist. @6% (Airtime Merchants and switching platform) | E29: 0.06 | G29: =$E$29*G18 -> 78202.435 | H29: =$E$29*H18 -> 152494.75 | I29: =$E$29*I18 -> 223072.45 | J29: =$E$29*J18 -> 290121.26 | K29: =$E$29*K18 -> 353817.63 | L29: =$E$29*L18 -> 414329.18 | M29: =$E$29*M18 -> 471815.16 | N29: =$E$29*N18 -> 526426.84 | ... R29: =$E$29*R18 -> 718899.21 | S29: =SUM(G29:R29) -> 5109499.4 | T29: =$E$29*T18 -> 761156.68 | U29: =$E$29*U18 -> 801301.28 | V29: =$E$29*V18 -> 839438.65 | W29: =$E$29*W18 -> 875669.15 | X29: =$E$29*X18 -> 910088.13 | Y29: =$E$29*Y18 -> 942786.16 | Z29: =$E$29*Z18 -> 973849.29 | AA29: =$E$29*AA18 -> 1003359.3 | ... AE29: =$E$29*AE18 -> 1107363.6 | AF29: =SUM(T29:AE29) -> 11387760 | AG29: =$E$29*AG18 -> 1130197.9 | AH29: =$E$29*AH18 -> 1151890.4 | AI29: =$E$29*AI18 -> 1172498.3 | AJ29: =$E$29*AJ18 -> 1192075.9 | AK29: =$E$29*AK18 -> 1210674.5 | AL29: =$E$29*AL18 -> 1228343.2 | AM29: =$E$29*AM18 -> 1245128.5 | AN29: =$E$29*AN18 -> 1261074.5 | ... BP29: =$E$29*BP18 -> 1491993.3 | BQ29: =SUM(G29:BP29)-AF29-S29 -> 65495049 | BR29: Once off commission to airtime dist. @6% (Airtime Merchants and switching platform) | BS29: 0.06 | BT29: =SUM(G29:R29) -> 5109499.4 | BU29: =SUM(T29:AE29) -> 11387760 | BV29: =SUM(AG29:AR29) -> 14780281 | BW29: =SUM(AS29:BD29) -> 16613465 | BX29: =SUM(BE29:BP29) -> 17604044 | BY29: =BQ29 -> 65495049
C30: m | D30: Total SIM costs | E30: 9.5 | G30: =G31+G32+G33 -> 151000 | H30: =H31+H32+H33 -> 151000 | I30: =I31+I32+I33 -> 151000 | J30: =J31+J32+J33 -> 151000 | K30: =K31+K32+K33 -> 151000 | L30: =L31+L32+L33 -> 151000 | M30: =M31+M32+M33 -> 151000 | N30: =N31+N32+N33 -> 151000 | ... R30: =R31+R32+R33 -> 151000 | S30: =SUM(G30:R30) -> 1812000 | T30: =T31+T32+T33 -> 151000 | U30: =U31+U32+U33 -> 151000 | V30: =V31+V32+V33 -> 151000 | W30: =W31+W32+W33 -> 151000 | X30: =X31+X32+X33 -> 151000 | Y30: =Y31+Y32+Y33 -> 151000 | Z30: =Z31+Z32+Z33 -> 151000 | AA30: =AA31+AA32+AA33 -> 151000 | ... AE30: =AE31+AE32+AE33 -> 151000 | AF30: =SUM(T30:AE30) -> 1812000 | AG30: =AG31+AG32+AG33 -> 151000 | AH30: =AH31+AH32+AH33 -> 151000 | AI30: =AI31+AI32+AI33 -> 151000 | AJ30: =AJ31+AJ32+AJ33 -> 151000 | AK30: =AK31+AK32+AK33 -> 151000 | AL30: =AL31+AL32+AL33 -> 151000 | AM30: =AM31+AM32+AM33 -> 151000 | AN30: =AN31+AN32+AN33 -> 151000 | ... BP30: =BP31+BP32+BP33 -> 151000 | BQ30: =SUM(G30:BP30)-AF30-S30 -> 9060000 | BR30: Total SIM costs | BS30: 9.5 | BT30: =SUM(G30:R30) -> 1812000 | BU30: =SUM(T30:AE30) -> 1812000 | BV30: =SUM(AG30:AR30) -> 1812000 | BW30: =SUM(AS30:BD30) -> 1812000 | BX30: =SUM(BE30:BP30) -> 1812000 | BY30: =BQ30 -> 9060000
D31: Physical SIM card Cost | E31: 7.5 | F31: 6.5 | G31: =G6*$E$31 -> 118500 | H31: =H6*$E$31 -> 118500 | I31: =I6*$E$31 -> 118500 | J31: =J6*$E$31 -> 118500 | K31: =K6*$E$31 -> 118500 | L31: =L6*$E$31 -> 118500 | M31: =M6*$E$31 -> 118500 | N31: =N6*$E$31 -> 118500 | ... R31: =R6*$E$31 -> 118500 | S31: =SUM(G31:R31) -> 1422000 | T31: =T6*$E$31 -> 118500 | U31: =U6*$E$31 -> 118500 | V31: =V6*$E$31 -> 118500 | W31: =W6*$E$31 -> 118500 | X31: =X6*$E$31 -> 118500 | Y31: =Y6*$E$31 -> 118500 | Z31: =Z6*$E$31 -> 118500 | AA31: =AA6*$E$31 -> 118500 | ... AE31: =AE6*$E$31 -> 118500 | AF31: =SUM(T31:AE31) -> 1422000 | AG31: =AG6*$E$31 -> 118500 | AH31: =AH6*$E$31 -> 118500 | AI31: =AI6*$E$31 -> 118500 | AJ31: =AJ6*$E$31 -> 118500 | AK31: =AK6*$E$31 -> 118500 | AL31: =AL6*$E$31 -> 118500 | AM31: =AM6*$E$31 -> 118500 | AN31: =AN6*$E$31 -> 118500 | ... BP31: =BP6*$E$31 -> 118500 | BQ31: =SUM(G31:BP31)-AF31-S31 -> 7110000 | BR31: Physical SIM card Cost | BS31: 7.5 | BT31: =SUM(G31:R31) -> 1422000 | BU31: =SUM(T31:AE31) -> 1422000 | BV31: =SUM(AG31:AR31) -> 1422000 | BW31: =SUM(AS31:BD31) -> 1422000 | BX31: =SUM(BE31:BP31) -> 1422000 | BY31: =BQ31 -> 7110000
D32: Physical SIM packaging | E32: 2 | G32: =G6*$E$32 -> 31600 | H32: =H6*$E$32 -> 31600 | I32: =I6*$E$32 -> 31600 | J32: =J6*$E$32 -> 31600 | K32: =K6*$E$32 -> 31600 | L32: =L6*$E$32 -> 31600 | M32: =M6*$E$32 -> 31600 | N32: =N6*$E$32 -> 31600 | ... R32: =R6*$E$32 -> 31600 | S32: =SUM(G32:R32) -> 379200 | T32: =T6*$E$32 -> 31600 | U32: =U6*$E$32 -> 31600 | V32: =V6*$E$32 -> 31600 | W32: =W6*$E$32 -> 31600 | X32: =X6*$E$32 -> 31600 | Y32: =Y6*$E$32 -> 31600 | Z32: =Z6*$E$32 -> 31600 | AA32: =AA6*$E$32 -> 31600 | ... AE32: =AE6*$E$32 -> 31600 | AF32: =SUM(T32:AE32) -> 379200 | AG32: =AG6*$E$32 -> 31600 | AH32: =AH6*$E$32 -> 31600 | AI32: =AI6*$E$32 -> 31600 | AJ32: =AJ6*$E$32 -> 31600 | AK32: =AK6*$E$32 -> 31600 | AL32: =AL6*$E$32 -> 31600 | AM32: =AM6*$E$32 -> 31600 | AN32: =AN6*$E$32 -> 31600 | ... BP32: =BP6*$E$32 -> 31600 | BQ32: =SUM(G32:BP32)-AF32-S32 -> 1896000 | BR32: Physical SIM packaging | BS32: 2 | BT32: =SUM(G32:R32) -> 379200 | BU32: =SUM(T32:AE32) -> 379200 | BV32: =SUM(AG32:AR32) -> 379200 | BW32: =SUM(AS32:BD32) -> 379200 | BX32: =SUM(BE32:BP32) -> 379200 | BY32: =BQ32 -> 1896000
D33: eSIM card Cost | E33: 4.5 | G33: =$E$33*G7 -> 900 | H33: =$E$33*H7 -> 900 | I33: =$E$33*I7 -> 900 | J33: =$E$33*J7 -> 900 | K33: =$E$33*K7 -> 900 | L33: =$E$33*L7 -> 900 | M33: =$E$33*M7 -> 900 | N33: =$E$33*N7 -> 900 | ... R33: =$E$33*R7 -> 900 | S33: =SUM(G33:R33) -> 10800 | T33: =$E$33*T7 -> 900 | U33: =$E$33*U7 -> 900 | V33: =$E$33*V7 -> 900 | W33: =$E$33*W7 -> 900 | X33: =$E$33*X7 -> 900 | Y33: =$E$33*Y7 -> 900 | Z33: =$E$33*Z7 -> 900 | AA33: =$E$33*AA7 -> 900 | ... AE33: =$E$33*AE7 -> 900 | AF33: =SUM(T33:AE33) -> 10800 | AG33: =$E$33*AG7 -> 900 | AH33: =$E$33*AH7 -> 900 | AI33: =$E$33*AI7 -> 900 | AJ33: =$E$33*AJ7 -> 900 | AK33: =$E$33*AK7 -> 900 | AL33: =$E$33*AL7 -> 900 | AM33: =$E$33*AM7 -> 900 | AN33: =$E$33*AN7 -> 900 | ... BP33: =$E$33*BP7 -> 900 | BQ33: =SUM(G33:BP33)-AF33-S33 -> 54000 | BR33: eSIM card Cost | BS33: 4.5 | BT33: =SUM(G33:R33) -> 10800 | BU33: =SUM(T33:AE33) -> 10800 | BV33: =SUM(AG33:AR33) -> 10800 | BW33: =SUM(AS33:BD33) -> 10800 | BX33: =SUM(BE33:BP33) -> 10800 | BY33: =BQ33 -> 54000
AF34: =SUM(T34:AE34) -> 0 | BQ34: =SUM(G34:BP34)-AF34-S34 -> 0
C35: m | D35: Paperless RICA | E35: 0 | F35: 21 | G35: =55000+20000 -> 75000 | H35: 20000 | I35: 20000 | J35: 20000 | K35: 20000 | L35: 20000 | M35: 20000 | N35: 20000 | O35: 20000 | P35: 20000 | Q35: 20000 | R35: 20000 | S35: =SUM(G35:R35) -> 295000 | T35: =R35*1.05 -> 21000 | U35: =T35 -> 21000 | V35: =U35 -> 21000 | W35: =V35 -> 21000 | X35: =W35 -> 21000 | Y35: =X35 -> 21000 | Z35: =Y35 -> 21000 | AA35: =Z35 -> 21000 | AB35: =AA35 -> 21000 | ... AE35: =AD35 -> 21000 | AF35: =SUM(T35:AE35) -> 252000 | AG35: =AE35*1.05 -> 22050 | AH35: =AG35 -> 22050 | AI35: =AH35 -> 22050 | AJ35: =AI35 -> 22050 | AK35: =AJ35 -> 22050 | AL35: =AK35 -> 22050 | AM35: =AL35 -> 22050 | AN35: =AM35 -> 22050 | AO35: =AN35 -> 22050 | ... AR35: =AQ35 -> 22050 | AS35: =AR35*1.05 -> 23152.5 | AT35: =AS35 -> 23152.5 | AU35: =AT35 -> 23152.5 | AV35: =AU35 -> 23152.5 | AW35: =AV35 -> 23152.5 | AX35: =AW35 -> 23152.5 | AY35: =AX35 -> 23152.5 | AZ35: =AY35 -> 23152.5 | BA35: =AZ35 -> 23152.5 | ... BD35: =BC35 -> 23152.5 | BE35: =BD35*1.05 -> 24310.125 | BF35: =BE35 -> 24310.125 | BG35: =BF35 -> 24310.125 | BH35: =BG35 -> 24310.125 | BI35: =BH35 -> 24310.125 | BJ35: =BI35 -> 24310.125 | BK35: =BJ35 -> 24310.125 | BL35: =BK35 -> 24310.125 | BM35: =BL35 -> 24310.125 | ... BP35: =BO35 -> 24310.125 | BQ35: =SUM(G35:BP35)-AF35-S35 -> 1381151.5 | BR35: Paperless RICA | BS35: 0 | BT35: =SUM(G35:R35) -> 295000 | BU35: =SUM(T35:AE35) -> 252000 | BV35: =SUM(AG35:AR35) -> 264600 | BW35: =SUM(AS35:BD35) -> 277830 | BX35: =SUM(BE35:BP35) -> 291721.5 | BY35: =SUM(BT35:BX35) -> 1381151.5
C36: m | D36: KCM App | G36: 279000 | H36: 79000 | I36: 79000 | J36: 79000 | K36: 79000 | L36: 79000 | M36: 79000 | N36: 79000 | O36: 79000 | P36: 79000 | Q36: 79000 | R36: 79000 | S36: =SUM(G36:R36) -> 1148000 | T36: =R36*1.05 -> 82950 | U36: =T36 -> 82950 | V36: =U36 -> 82950 | W36: =V36 -> 82950 | X36: =W36 -> 82950 | Y36: =X36 -> 82950 | Z36: =Y36 -> 82950 | AA36: =Z36 -> 82950 | AB36: =AA36 -> 82950 | ... AE36: =AD36 -> 82950 | AF36: =SUM(T36:AE36) -> 995400 | AG36: =AE36*1.05 -> 87097.5 | AH36: =AG36 -> 87097.5 | AI36: =AH36 -> 87097.5 | AJ36: =AI36 -> 87097.5 | AK36: =AJ36 -> 87097.5 | AL36: =AK36 -> 87097.5 | AM36: =AL36 -> 87097.5 | AN36: =AM36 -> 87097.5 | AO36: =AN36 -> 87097.5 | ... AR36: =AQ36 -> 87097.5 | AS36: =AR36*1.05 -> 91452.375 | AT36: =AS36 -> 91452.375 | AU36: =AT36 -> 91452.375 | AV36: =AU36 -> 91452.375 | AW36: =AV36 -> 91452.375 | AX36: =AW36 -> 91452.375 | AY36: =AX36 -> 91452.375 | AZ36: =AY36 -> 91452.375 | BA36: =AZ36 -> 91452.375 | ... BD36: =BC36 -> 91452.375 | BE36: =BD36*1.05 -> 96024.994 | BF36: =BE36 -> 96024.994 | BG36: =BF36 -> 96024.994 | BH36: =BG36 -> 96024.994 | BI36: =BH36 -> 96024.994 | BJ36: =BI36 -> 96024.994 | BK36: =BJ36 -> 96024.994 | BL36: =BK36 -> 96024.994 | BM36: =BL36 -> 96024.994 | ... BP36: =BO36 -> 96024.994 | BQ36: =SUM(G36:BP36)-AF36-S36 -> 5438298.4 | BR36: KCM App | BT36: =SUM(G36:R36) -> 1148000 | BU36: =SUM(T36:AE36) -> 995400 | BV36: =SUM(AG36:AR36) -> 1045170 | BW36: =SUM(AS36:BD36) -> 1097428.5 | BX36: =SUM(BE36:BP36) -> 1152299.9
D37: KCM app = Super utility app with: | E37: Support, Maint + 30 dev hours pm | BR37: KCM app = Super utility app with: | BS37: Support, Maint + 30 dev hrs pm
D38: Packages, Payments, eSIM, Travel eSIM, McAfee, Consolidation of packages with VAS, Integrate KC services, Voucher dist, Number porting, RICA | F38: GP | G38: =G12-G21 -> 13584.177 | H38: =H12-H21 -> 753848.14 | I38: =I12-I21 -> 1189848.9 | J38: =J12-J21 -> 1627799.6 | K38: =K12-K21 -> 2018852.8 | L38: =L12-L21 -> 2389103.4 | M38: =M12-M21 -> 2764591.4 | N38: =N12-N21 -> 3121305 | ... AF38: =AF12-AF21 -> 69441751 | BR38: Packages, Payments, eSIM, Travel eSIM, McAfee, Consolidation of packages with VAS, Integrate KC services, Voucher dist, Number porting, RICA
D40: Total Operating costs | G40: =G42+G51+G52+G53+G57+G58+G61+G43 -> 1436365.6 | H40: =H42+H51+H52+H53+H57+H58+H61+H43 -> 1316084.8 | I40: =I42+I51+I52+I53+I57+I58+I61+I43 -> 1477318.1 | J40: =J42+J51+J52+J53+J57+J58+J61+J43 -> 1630489.7 | K40: =K42+K51+K52+K53+K57+K58+K61+K43 -> 1776002.7 | L40: =L42+L51+L52+L53+L57+L58+L61+L43 -> 1914240.1 | M40: =M42+M51+M52+M53+M57+M58+M61+M43 -> 2045565.6 | N40: =N42+N51+N52+N53+N57+N58+N61+N43 -> 2170324.8 | ... R40: =R42+R51+R52+R53+R57+R58+R61+R43 -> 2610023.9 | S40: =SUM(G40:R40) -> 23575109 | T40: =T42+T51+T52+T53+T57+T58+T61+T43 -> 2281886.6 | U40: =U42+U51+U52+U53+U57+U58+U61+U43 -> 2343487.7 | V40: =V42+V51+V52+V53+V57+V58+V61+V43 -> 2402008.6 | W40: =W42+W51+W52+W53+W57+W58+W61+W43 -> 2457603.6 | X40: =X42+X51+X52+X53+X57+X58+X61+X43 -> 2510418.8 | Y40: =Y42+Y51+Y52+Y53+Y57+Y58+Y61+Y43 -> 2560593.2 | Z40: =Z42+Z51+Z52+Z53+Z57+Z58+Z61+Z43 -> 2608259 | AA40: =AA42+AA51+AA52+AA53+AA57+AA58+AA61+AA43 -> 2653541.4 | ... AE40: =AE42+AE51+AE52+AE53+AE57+AE58+AE61+AE43 -> 2813133.9 | AF40: =SUM(T40:AE40) -> 30841171 | AG40: =AG42+AG51+AG52+AG53+AG57+AG58+AG61+AG43 -> 3887091.2 | AH40: =AH42+AH51+AH52+AH53+AH57+AH58+AH61+AH43 -> 2867089.9 | AI40: =AI42+AI51+AI52+AI53+AI57+AI58+AI61+AI43 -> 2898712.3 | AJ40: =AJ42+AJ51+AJ52+AJ53+AJ57+AJ58+AJ61+AJ43 -> 2928753.6 | AK40: =AK42+AK51+AK52+AK53+AK57+AK58+AK61+AK43 -> 2957292.8 | AL40: =AL42+AL51+AL52+AL53+AL57+AL58+AL61+AL43 -> 2984405.1 | AM40: =AM42+AM51+AM52+AM53+AM57+AM58+AM61+AM43 -> 3010161.7 | AN40: =AN42+AN51+AN52+AN53+AN57+AN58+AN61+AN43 -> 3034630.6 | ... BP40: =BP42+BP51+BP52+BP53+BP57+BP58+BP61+BP43 -> 3439798.7 | BQ40: =SUM(G40:BP40)-AF40-S40 -> 1.7038825e+08 | BR40: Total Operating costs | BT40: =SUM(G40:R40) -> 23575109 | BU40: =SUM(T40:AE40) -> 30841171 | BV40: =SUM(AG40:AR40) -> 36927778 | BW40: =SUM(AS40:BD40) -> 38226756 | BX40: =SUM(BE40:BP40) -> 40817432 | BY40: =SUM(BT40:BX40) -> 1.7038825e+08
C42: m | D42: SIM Mgt fee on MVNE platform R7.50 per subscriber or R75k, whichever is higher + R250k for KCM network name | E42: =(S12*0.05)/12 -> 376241.74 | F42: 7.5 | G42: =G10*7.5+250000 -> 370000 | H42: =H10*7.5 -> 234000 | I42: =I10*7.5 -> 342300 | J42: =J10*7.5 -> 445185 | K42: =K10*7.5 -> 542925.75 | L42: =L10*7.5 -> 635779.46 | M42: =M10*7.5 -> 723990.49 | N42: =N10*7.5 -> 807790.96 | O42: =O10*7.5 -> 887401.42 | ... R42: =R10*7.5 -> 1103135.8 | S42: =SUM(F42:R42) -> 8090427.5 | T42: =T10*7.5 -> 1167979 | U42: =U10*7.5 -> 1229580.1 | V42: =V10*7.5 -> 1288101 | W42: =W10*7.5 -> 1343696 | X42: =X10*7.5 -> 1396511.2 | Y42: =Y10*7.5 -> 1446685.6 | Z42: =Z10*7.5 -> 1494351.4 | AA42: =AA10*7.5 -> 1539633.8 | ... AE42: =AE10*7.5 -> 1699226.3 | AF42: =SUM(T42:AE42) -> 17474280 | AG42: =AG10*7.5 -> 1734265 | AH42: =AH10*7.5 -> 1767551.8 | AI42: =AI10*7.5 -> 1799174.2 | AJ42: =AJ10*7.5 -> 1829215.5 | AK42: =AK10*7.5 -> 1857754.7 | AL42: =AL10*7.5 -> 1884867 | AM42: =AM10*7.5 -> 1910623.6 | AN42: =AN10*7.5 -> 1935092.4 | ... BP42: =BP10*7.5 -> 2289432.5 | BQ42: =SUM(G42:BP42)-AF42-S42 -> 1.0075078e+08 | BR42: SIM Mgt fee on MVNE platform R7.50 per subscriber or R75k, whichever is higher | BT42: =SUM(G42:R42) -> 8090420 | BU42: =SUM(T42:AE42) -> 17474280 | BV42: =SUM(AG42:AR42) -> 22680033 | BW42: =SUM(AS42:BD42) -> 25493014 | BX42: =SUM(BE42:BP42) -> 27013037 | BY42: =BQ42 -> 1.0075078e+08
C43: kc | E43: Facilities | G43: =SUM(G44:G50) -> 108151.83 | H43: =SUM(H44:H50) -> 163871.06 | I43: =SUM(I44:I50) -> 216804.33 | J43: =SUM(J44:J50) -> 267090.94 | K43: =SUM(K44:K50) -> 314863.22 | L43: =SUM(L44:L50) -> 360246.89 | M43: =SUM(M44:M50) -> 403361.37 | N43: =SUM(N44:N50) -> 444320.13 | ... R43: =SUM(R44:R50) -> 588674.4 | S43: =SUM(G43:R43) -> 4426124.6 | T43: =SUM(T44:T50) -> 43887 | U43: =SUM(U44:U50) -> 43887 | V43: =SUM(V44:V50) -> 43887 | W43: =SUM(W44:W50) -> 43887 | X43: =SUM(X44:X50) -> 43887 | Y43: =SUM(Y44:Y50) -> 43887 | Z43: =SUM(Z44:Z50) -> 43887 | AA43: =SUM(AA44:AA50) -> 43887 | ... AE43: =SUM(AE44:AE50) -> 43887 | AF43: =SUM(T43:AE43) -> 526644 | AG43: =SUM(T43:AF43) -> 1053288 | BQ43: =SUM(G43:BP43)-AF43-S43 -> 6006056.6
S44: =SUM(F44:R44) -> 0 | AF44: =SUM(T44:AE44) -> 0 | AG44: =AG45+AG46 -> 1508 | AH44: =AH45+AH46 -> 0 | AI44: =AI45+AI46 -> 0 | AJ44: =AJ45+AJ46 -> 1509 | AK44: =AK45+AK46 -> 0 | AL44: =AL45+AL46 -> 0 | AM44: =AM45+AM46 -> 1510 | AN44: =AN45+AN46 -> 0 | ... BP44: =BP45+BP46 -> 0 | BQ44: =SUM(G44:BP44)-AF44-S44 -> 18162
C45: kc | E45: Rental | G45: 17500 | H45: 17500 | I45: 17500 | J45: 17500 | K45: 17500 | L45: 17500 | M45: 17500 | N45: 17500 | O45: 17500 | P45: 17500 | Q45: 17500 | R45: 17500 | S45: =SUM(F45:R45) -> 210000 | T45: =R45*1.05 -> 18375 | U45: =T45 -> 18375 | V45: =U45 -> 18375 | W45: =V45 -> 18375 | X45: =W45 -> 18375 | Y45: =X45 -> 18375 | Z45: =Y45 -> 18375 | AA45: =Z45 -> 18375 | AB45: =AA45 -> 18375 | ... AE45: =AD45 -> 18375 | AF45: =SUM(T45:AE45) -> 220500 | BQ45: =SUM(G45:BP45)-AF45-S45 -> 430500
C46: kc | E46: Office consumables | G46: 2000 | H46: 2000 | I46: 2000 | J46: 2000 | K46: 2000 | L46: 2000 | M46: 2000 | N46: 2000 | O46: 2000 | P46: 2000 | Q46: 2000 | R46: 2000 | S46: =SUM(F46:R46) -> 24000 | T46: 1504 | U46: =T46 -> 1504 | V46: =U46 -> 1504 | W46: =V46 -> 1504 | X46: =W46 -> 1504 | Y46: =X46 -> 1504 | Z46: =Y46 -> 1504 | AA46: =Z46 -> 1504 | AB46: =AA46 -> 1504 | ... AE46: =AD46 -> 1504 | AF46: =SUM(T46:AE46) -> 18048 | AG46: 1508 | AJ46: 1509 | AM46: 1510 | AP46: 1511 | AS46: 1512 | AV46: 1513 | AY46: 1514 | BB46: 1515 | BE46: 1516 | BH46: 1517 | BK46: 1518 | BN46: 1519 | BQ46: =SUM(G46:BP46)-AF46-S46 -> 60210
C47: kc | E47: IT & Infrastructure | G47: =6000+2000+2000 -> 10000 | H47: =6000+2000+2000 -> 10000 | I47: =6000+2000+2000 -> 10000 | J47: =6000+2000+2000 -> 10000 | K47: =6000+2000+2000 -> 10000 | L47: =6000+2000+2000 -> 10000 | M47: =6000+2000+2000 -> 10000 | N47: =6000+2000+2000 -> 10000 | ... R47: =6000+2000+2000 -> 10000 | S47: =SUM(F47:R47) -> 120000 | T47: 1504 | U47: =T47 -> 1504 | V47: =U47 -> 1504 | W47: =V47 -> 1504 | X47: =W47 -> 1504 | Y47: =X47 -> 1504 | Z47: =Y47 -> 1504 | AA47: =Z47 -> 1504 | AB47: =AA47 -> 1504 | ... AE47: =AD47 -> 1504 | AF47: =SUM(T47:AE47) -> 18048 | BQ47: =SUM(G47:BP47)-AF47-S47 -> 138048
C48: kc | E48: Brand License | G48: =G18*0.045 -> 58651.826 | H48: =H18*0.045 -> 114371.06 | I48: =I18*0.045 -> 167304.33 | J48: =J18*0.045 -> 217590.94 | K48: =K18*0.045 -> 265363.22 | L48: =L18*0.045 -> 310746.89 | M48: =M18*0.045 -> 353861.37 | N48: =N18*0.045 -> 394820.13 | ... R48: =R18*0.045 -> 539174.4 | S48: =SUM(F48:R48) -> 3832124.6 | T48: 1504 | U48: =T48 -> 1504 | V48: =U48 -> 1504 | W48: =V48 -> 1504 | X48: =W48 -> 1504 | Y48: =X48 -> 1504 | Z48: =Y48 -> 1504 | AA48: =Z48 -> 1504 | AB48: =AA48 -> 1504 | ... AE48: =AD48 -> 1504 | AF48: =SUM(T48:AE48) -> 18048 | BQ48: =SUM(G48:BP48)-AF48-S48 -> 3850172.6
E49: Insurance for business
C50: kc | D50: Finance/admin | E50: Internal finance resource (KC) | G50: 20000 | H50: 20000 | I50: 20000 | J50: 20000 | K50: 20000 | L50: 20000 | M50: 20000 | N50: 20000 | O50: 20000 | P50: 20000 | Q50: 20000 | R50: 20000 | S50: =SUM(F50:R50) -> 240000 | T50: =R50*1.05 -> 21000 | U50: =T50 -> 21000 | V50: =U50 -> 21000 | W50: =V50 -> 21000 | X50: =W50 -> 21000 | Y50: =X50 -> 21000 | Z50: =Y50 -> 21000 | AA50: =Z50 -> 21000 | AB50: =AA50 -> 21000 | ... AE50: =AD50 -> 21000 | AF50: =SUM(T50:AE50) -> 252000 | BQ50: =SUM(G50:BP50)-AF50-S50 -> 492000
C51: m | D51: Marketing costs | E51: Campaign, launch + marketing | G51: =376241.74 -> 376241.74 | H51: =E42 -> 376241.74 | I51: =H51 -> 376241.74 | J51: =I51 -> 376241.74 | K51: =J51 -> 376241.74 | L51: =K51 -> 376241.74 | M51: =L51 -> 376241.74 | N51: =M51 -> 376241.74 | O51: =N51 -> 376241.74 | P51: =O51 -> 376241.74 | ... R51: =Q51 -> 376241.74 | S51: =SUM(F51:R51) -> 4514900.9 | T51: 500000 | U51: 500000 | V51: 500000 | W51: 500000 | X51: 500000 | Y51: 500000 | Z51: 500000 | AA51: 500000 | AB51: 500000 | AC51: 500000 | AD51: 500000 | AE51: 500000 | AF51: =SUM(T51:AE51) -> 6000000 | AG51: 500000 | AH51: 500000 | AI51: 500000 | AJ51: 500000 | AK51: 500000 | AL51: 500000 | AM51: 500000 | AN51: 500000 | AO51: 500000 | AP51: 500000 | AQ51: 500000 | AR51: 500000 | AS51: 500000 | AT51: 500000 | AU51: 500000 | AV51: 500000 | AW51: 500000 | AX51: 500000 | AY51: 500000 | AZ51: 500000 | BA51: 500000 | BB51: 500000 | BC51: 500000 | BD51: 500000 | BE51: 500000 | BF51: 500000 | BG51: 500000 | BH51: 500000 | BI51: 500000 | BJ51: 500000 | BK51: 500000 | BL51: 500000 | BM51: 500000 | BN51: 500000 | BO51: 500000 | BP51: 500000 | BQ51: =SUM(G51:BP51)-AF51-S51 -> 28514901 | BT51: 2134926.5 | BU51: 2134926.5 | BV51: 2134926.5 | BW51: 2134926.5 | BX51: 2134926.5 | BY51: 10674632
C52: kc | D52: Vehicle costs total all escaleted @ 5% | E52: KCM trucks consumables X 8 | G52: =G53+G54+G55+G56 -> 84472 | H52: =H54+H55+H56 -> 44472 | I52: =I54+I55+I56 -> 44472 | J52: =J54+J55+J56 -> 44472 | K52: =K54+K55+K56 -> 44472 | L52: =L54+L55+L56 -> 44472 | M52: =M54+M55+M56 -> 44472 | N52: =N54+N55+N56 -> 44472 | O52: =O54+O55+O56 -> 44472 | ... R52: =R54+R55+R56 -> 44472 | S52: =SUM(F52:R52) -> 573664 | T52: =T54+T55+T56 -> 46695.6 | U52: =U54+U55+U56 -> 46695.6 | V52: =V54+V55+V56 -> 46695.6 | W52: =W54+W55+W56 -> 46695.6 | X52: =X54+X55+X56 -> 46695.6 | Y52: =Y54+Y55+Y56 -> 46695.6 | Z52: =Z54+Z55+Z56 -> 46695.6 | AA52: =AA54+AA55+AA56 -> 46695.6 | ... AE52: =AE54+AE55+AE56 -> 46695.6 | AF52: =SUM(T52:AE52) -> 560347.2 | AG52: =AG54+AG55+AG56 -> 49030.38 | AH52: =AH54+AH55+AH56 -> 49030.38 | AI52: =AI54+AI55+AI56 -> 49030.38 | AJ52: =AJ54+AJ55+AJ56 -> 49030.38 | AK52: =AK54+AK55+AK56 -> 49030.38 | AL52: =AL54+AL55+AL56 -> 49030.38 | AM52: =AM54+AM55+AM56 -> 49030.38 | AN52: =AN54+AN55+AN56 -> 49030.38 | ... BP52: =BP54+BP55+BP56 -> 54055.994 | BQ52: =SUM(G52:BP52)-AF52-S52 -> 2988830.5 | BR52: Vehicle costs total all escaleted @ 5% | BS52: KCM trucks consumables X 8 | BT52: =SUM(G52:R52) -> 573664 | BU52: =SUM(T52:AE52) -> 560347.2 | BV52: =SUM(AG52:AR52) -> 588364.56 | BW52: =SUM(AS52:BD52) -> 617782.79 | BX52: =SUM(BE52:BP52) -> 648671.93 | BY52: =BQ52 -> 2988830.5
E53: Avanaza rental | G53: 40000 | H53: 40000 | I53: 40000 | J53: 40000 | K53: 40000 | L53: 40000 | M53: 40000 | N53: 40000 | O53: 40000 | P53: 40000 | Q53: 40000 | R53: 40000 | S53: =SUM(F53:R53) -> 480000 | T53: =R53*1.05 -> 42000 | U53: =T53 -> 42000 | V53: =U53 -> 42000 | W53: =V53 -> 42000 | X53: =W53 -> 42000 | Y53: =X53 -> 42000 | Z53: =Y53 -> 42000 | AA53: =Z53 -> 42000 | AB53: =AA53 -> 42000 | ... AE53: =AD53 -> 42000 | AF53: =SUM(T53:AE53) -> 504000 | AG53: =AE53*1.05 -> 44100 | AH53: =AG53 -> 44100 | AI53: =AH53 -> 44100 | AJ53: =AI53 -> 44100 | AK53: =AJ53 -> 44100 | AL53: =AK53 -> 44100 | AM53: =AL53 -> 44100 | AN53: =AM53 -> 44100 | AO53: =AN53 -> 44100 | ... AR53: =AQ53 -> 44100 | AS53: =AQ53*1.05 -> 46305 | AT53: =AS53 -> 46305 | AU53: =AT53 -> 46305 | AV53: =AU53 -> 46305 | AW53: =AV53 -> 46305 | AX53: =AW53 -> 46305 | AY53: =AX53 -> 46305 | AZ53: =AY53 -> 46305 | BA53: =AZ53 -> 46305 | ... BD53: =BC53 -> 46305 | BE53: =BC53*1.05 -> 48620.25 | BF53: =BE53 -> 48620.25 | BG53: =BF53 -> 48620.25 | BH53: =BG53 -> 48620.25 | BI53: =BH53 -> 48620.25 | BJ53: =BI53 -> 48620.25 | BK53: =BJ53 -> 48620.25 | BL53: =BK53 -> 48620.25 | BM53: =BL53 -> 48620.25 | ... BP53: =BO53 -> 48620.25 | BQ53: =SUM(G53:BP53)-AF53-S53 -> 2652303
C54: kc | E54: Fuel (variable cost) | G54: =4360*8 -> 34880 | H54: =4360*8 -> 34880 | I54: =4360*8 -> 34880 | J54: =4360*8 -> 34880 | K54: =4360*8 -> 34880 | L54: =4360*8 -> 34880 | M54: =4360*8 -> 34880 | N54: =4360*8 -> 34880 | ... R54: =4360*8 -> 34880 | S54: =SUM(F54:R54) -> 418560 | T54: =R54*1.05 -> 36624 | U54: =T54 -> 36624 | V54: =U54 -> 36624 | W54: =V54 -> 36624 | X54: =W54 -> 36624 | Y54: =X54 -> 36624 | Z54: =Y54 -> 36624 | AA54: =Z54 -> 36624 | AB54: =AA54 -> 36624 | ... AE54: =AD54 -> 36624 | AF54: =SUM(T54:AE54) -> 439488 | AG54: =AE54*1.05 -> 38455.2 | AH54: =AG54 -> 38455.2 | AI54: =AH54 -> 38455.2 | AJ54: =AI54 -> 38455.2 | AK54: =AJ54 -> 38455.2 | AL54: =AK54 -> 38455.2 | AM54: =AL54 -> 38455.2 | AN54: =AM54 -> 38455.2 | AO54: =AN54 -> 38455.2 | ... AR54: =AQ54 -> 38455.2 | AS54: =AR54*1.05 -> 40377.96 | AT54: =AS54 -> 40377.96 | AU54: =AT54 -> 40377.96 | AV54: =AU54 -> 40377.96 | AW54: =AV54 -> 40377.96 | AX54: =AW54 -> 40377.96 | AY54: =AX54 -> 40377.96 | AZ54: =AY54 -> 40377.96 | BA54: =AZ54 -> 40377.96 | ... BD54: =BC54 -> 40377.96 | BE54: =BD54*1.05 -> 42396.858 | BF54: =BE54 -> 42396.858 | BG54: =BF54 -> 42396.858 | BH54: =BG54 -> 42396.858 | BI54: =BH54 -> 42396.858 | BJ54: =BI54 -> 42396.858 | BK54: =BJ54 -> 42396.858 | BL54: =BK54 -> 42396.858 | BM54: =BL54 -> 42396.858 | ... BP54: =BO54 -> 42396.858 | BQ54: =SUM(G54:BP54)-AF54-S54 -> 2312808.2 | BS54: Fuel (variable cost) | BT54: =SUM(G54:R54) -> 418560 | BU54: =SUM(T54:AE54) -> 439488 | BV54: =SUM(AG54:AR54) -> 461462.4 | BW54: =SUM(AS54:BD54) -> 484535.52 | BX54: =SUM(BE54:BP54) -> 508762.3 | BY54: =BQ54 -> 2312808.2
C55: kc | E55: Satellite tracker R209 per vehicle X 8 | G55: =209*8 -> 1672 | H55: =209*8 -> 1672 | I55: =209*8 -> 1672 | J55: =209*8 -> 1672 | K55: =209*8 -> 1672 | L55: =209*8 -> 1672 | M55: =209*8 -> 1672 | N55: =209*8 -> 1672 | ... R55: =209*8 -> 1672 | S55: =SUM(F55:R55) -> 20064 | T55: =R55*1.05 -> 1755.6 | U55: =T55 -> 1755.6 | V55: =U55 -> 1755.6 | W55: =V55 -> 1755.6 | X55: =W55 -> 1755.6 | Y55: =X55 -> 1755.6 | Z55: =Y55 -> 1755.6 | AA55: =Z55 -> 1755.6 | AB55: =AA55 -> 1755.6 | ... AE55: =AD55 -> 1755.6 | AF55: =SUM(T55:AE55) -> 21067.2 | AG55: =AE55*1.05 -> 1843.38 | AH55: =AG55 -> 1843.38 | AI55: =AH55 -> 1843.38 | AJ55: =AI55 -> 1843.38 | AK55: =AJ55 -> 1843.38 | AL55: =AK55 -> 1843.38 | AM55: =AL55 -> 1843.38 | AN55: =AM55 -> 1843.38 | AO55: =AN55 -> 1843.38 | ... AR55: =AQ55 -> 1843.38 | AS55: =AR55*1.05 -> 1935.549 | AT55: =AS55 -> 1935.549 | AU55: =AT55 -> 1935.549 | AV55: =AU55 -> 1935.549 | AW55: =AV55 -> 1935.549 | AX55: =AW55 -> 1935.549 | AY55: =AX55 -> 1935.549 | AZ55: =AY55 -> 1935.549 | BA55: =AZ55 -> 1935.549 | ... BD55: =BC55 -> 1935.549 | BE55: =BD55*1.05 -> 2032.3265 | BF55: =BE55 -> 2032.3265 | BG55: =BF55 -> 2032.3265 | BH55: =BG55 -> 2032.3265 | BI55: =BH55 -> 2032.3265 | BJ55: =BI55 -> 2032.3265 | BK55: =BJ55 -> 2032.3265 | BL55: =BK55 -> 2032.3265 | BM55: =BL55 -> 2032.3265 | ... BP55: =BO55 -> 2032.3265 | BQ55: =SUM(G55:BP55)-AF55-S55 -> 110866.27 | BS55: Satellite tracker R209 per vehicle X 8 | BT55: =SUM(G55:R55) -> 20064 | BU55: =SUM(T55:AE55) -> 21067.2 | BV55: =SUM(AG55:AR55) -> 22120.56 | BW55: =SUM(AS55:BD55) -> 23226.588 | BX55: =SUM(BE55:BP55) -> 24387.917 | BY55: =BQ55 -> 110866.27
C56: kc | E56: Insurance @ R990 per vehicle X 8 | G56: =990*8 -> 7920 | H56: =990*8 -> 7920 | I56: =990*8 -> 7920 | J56: =990*8 -> 7920 | K56: =990*8 -> 7920 | L56: =990*8 -> 7920 | M56: =990*8 -> 7920 | N56: =990*8 -> 7920 | ... R56: =990*8 -> 7920 | S56: =SUM(F56:R56) -> 95040 | T56: =R56*1.05 -> 8316 | U56: =T56 -> 8316 | V56: =U56 -> 8316 | W56: =V56 -> 8316 | X56: =W56 -> 8316 | Y56: =X56 -> 8316 | Z56: =Y56 -> 8316 | AA56: =Z56 -> 8316 | AB56: =AA56 -> 8316 | ... AE56: =AD56 -> 8316 | AF56: =SUM(T56:AE56) -> 99792 | AG56: =AE56*1.05 -> 8731.8 | AH56: =AG56 -> 8731.8 | AI56: =AH56 -> 8731.8 | AJ56: =AI56 -> 8731.8 | AK56: =AJ56 -> 8731.8 | AL56: =AK56 -> 8731.8 | AM56: =AL56 -> 8731.8 | AN56: =AM56 -> 8731.8 | AO56: =AN56 -> 8731.8 | ... AR56: =AQ56 -> 8731.8 | AS56: =AR56*1.05 -> 9168.39 | AT56: =AS56 -> 9168.39 | AU56: =AT56 -> 9168.39 | AV56: =AU56 -> 9168.39 | AW56: =AV56 -> 9168.39 | AX56: =AW56 -> 9168.39 | AY56: =AX56 -> 9168.39 | AZ56: =AY56 -> 9168.39 | BA56: =AZ56 -> 9168.39 | ... BD56: =BC56 -> 9168.39 | BE56: =BD56*1.05 -> 9626.8095 | BF56: =BE56 -> 9626.8095 | BG56: =BF56 -> 9626.8095 | BH56: =BG56 -> 9626.8095 | BI56: =BH56 -> 9626.8095 | BJ56: =BI56 -> 9626.8095 | BK56: =BJ56 -> 9626.8095 | BL56: =BK56 -> 9626.8095 | BM56: =BL56 -> 9626.8095 | ... BP56: =BO56 -> 9626.8095 | BQ56: =SUM(G56:BP56)-AF56-S56 -> 525155.99 | BS56: Insurance @ R990 per vehicle X 8 | BT56: =SUM(G56:R56) -> 95040 | BU56: =SUM(T56:AE56) -> 99792 | BV56: =SUM(AG56:AR56) -> 104781.6 | BW56: =SUM(AS56:BD56) -> 110020.68 | BX56: =SUM(BE56:BP56) -> 115521.71 | BY56: =BQ56 -> 525155.99
D57: Insurance | G57: 60000 | H57: 60000 | I57: 60000 | J57: 60000 | K57: 60000 | L57: 60000 | M57: 60000 | N57: 60000 | O57: 60000 | P57: 60000 | Q57: 60000 | R57: 60000 | S57: =SUM(G57:R57) -> 720000 | T57: =R57*1.05 -> 63000 | U57: =T57 -> 63000 | V57: =U57 -> 63000 | W57: =V57 -> 63000 | X57: =W57 -> 63000 | Y57: =X57 -> 63000 | Z57: =Y57 -> 63000 | AA57: =Z57 -> 63000 | AB57: =AA57 -> 63000 | ... AE57: =AD57 -> 63000 | AF57: =SUM(T57:AE57) -> 756000 | AG57: =AE57*1.05 -> 66150 | AH57: =AG57 -> 66150 | AI57: =AH57 -> 66150 | AJ57: =AI57 -> 66150 | AK57: =AJ57 -> 66150 | AL57: =AK57 -> 66150 | AM57: =AL57 -> 66150 | AN57: =AM57 -> 66150 | AO57: =AN57 -> 66150 | ... AR57: =AQ57 -> 66150 | BE57: 60000 | BF57: 60000 | BG57: 60000 | BH57: 60000 | BI57: 60000 | BJ57: 60000 | BK57: 60000 | BL57: 60000 | BM57: 60000 | BN57: 60000 | BO57: 60000 | BP57: 60000 | BQ57: =SUM(G57:BP57)-AF57-S57 -> 2989800 | BU57: =SUM(T57:AE57) -> 756000 | BV57: =SUM(AG57:AR57) -> 793800
C58: kc | D58: Courier fees total | G58: =G59+G60 -> 47500 | H58: =H59+H60 -> 47500 | I58: =I59+I60 -> 47500 | J58: =J59+J60 -> 47500 | K58: =K59+K60 -> 47500 | L58: =L59+L60 -> 47500 | M58: =M59+M60 -> 47500 | N58: =N59+N60 -> 47500 | ... AE58: =AE59+AE60 -> 50825 | AF58: =SUM(T58:AE58) -> 609900 | AG58: =AG59+AG60 -> 54382.75 | AH58: =AH59+AH60 -> 54382.75 | AI58: =AI59+AI60 -> 54382.75 | AJ58: =AJ59+AJ60 -> 54382.75 | AK58: =AK59+AK60 -> 54382.75 | AL58: =AL59+AL60 -> 54382.75 | AM58: =AM59+AM60 -> 54382.75 | AN58: =AN59+AN60 -> 54382.75 | ... BP58: =BP59+BP60 -> 62262.81 | BQ58: =SUM(G58:BP58)-AF58-S58 -> 3277921.2 | BR58: Courier fees total | BT58: =SUM(G58:R58) -> 570000 | BU58: =SUM(T58:AE58) -> 609900 | BV58: =SUM(AG58:AR58) -> 652593 | BW58: =SUM(AS58:BD58) -> 698274.51 | BX58: =SUM(BE58:BP58) -> 747153.73 | BY58: =BQ58 -> 3277921.2
C59: kc | D59: RTT - Physical distribution | E59: Fixed fee | G59: 11000 | H59: 11000 | I59: 11000 | J59: 11000 | K59: 11000 | L59: 11000 | M59: 11000 | N59: 11000 | O59: 11000 | P59: 11000 | Q59: 11000 | R59: 11000 | S59: =SUM(G59:R59) -> 132000 | T59: =R59*1.07 -> 11770 | U59: =T59 -> 11770 | V59: =U59 -> 11770 | W59: =V59 -> 11770 | X59: =W59 -> 11770 | Y59: =X59 -> 11770 | Z59: =Y59 -> 11770 | AA59: =Z59 -> 11770 | AB59: =AA59 -> 11770 | ... AE59: =AD59 -> 11770 | AF59: =SUM(T59:AE59) -> 141240 | AG59: =AE59*1.07 -> 12593.9 | AH59: =AG59 -> 12593.9 | AI59: =AH59 -> 12593.9 | AJ59: =AI59 -> 12593.9 | AK59: =AJ59 -> 12593.9 | AL59: =AK59 -> 12593.9 | AM59: =AL59 -> 12593.9 | AN59: =AM59 -> 12593.9 | AO59: =AN59 -> 12593.9 | ... AR59: =AQ59 -> 12593.9 | AS59: =AR59*1.07 -> 13475.473 | AT59: =AS59 -> 13475.473 | AU59: =AT59 -> 13475.473 | AV59: =AU59 -> 13475.473 | AW59: =AV59 -> 13475.473 | AX59: =AW59 -> 13475.473 | AY59: =AX59 -> 13475.473 | AZ59: =AY59 -> 13475.473 | BA59: =AZ59 -> 13475.473 | ... BD59: =BC59 -> 13475.473 | BE59: =BD59*1.07 -> 14418.756 | BF59: =BE59 -> 14418.756 | BG59: =BF59 -> 14418.756 | BH59: =BG59 -> 14418.756 | BI59: =BH59 -> 14418.756 | BJ59: =BI59 -> 14418.756 | BK59: =BJ59 -> 14418.756 | BL59: =BK59 -> 14418.756 | BM59: =BL59 -> 14418.756 | ... BP59: =BO59 -> 14418.756 | BQ59: =SUM(G59:BP59)-AF59-S59 -> 759097.55 | BR59: Physical distribution | BS59: Fixed fee | BT59: =SUM(G59:R59) -> 132000 | BU59: =SUM(T59:AE59) -> 141240 | BV59: =SUM(AG59:AR59) -> 151126.8 | BW59: =SUM(AS59:BD59) -> 161705.68 | BX59: =SUM(BE59:BP59) -> 173025.07 | BY59: =BQ59 -> 759097.55
C60: kc | D60: RTT - Warehousing | E60: Warehousing | G60: 36500 | H60: 36500 | I60: 36500 | J60: 36500 | K60: 36500 | L60: 36500 | M60: 36500 | N60: 36500 | O60: 36500 | P60: 36500 | Q60: 36500 | R60: 36500 | S60: =SUM(G60:R60) -> 438000 | T60: =R60*1.07 -> 39055 | U60: =T60 -> 39055 | V60: =U60 -> 39055 | W60: =V60 -> 39055 | X60: =W60 -> 39055 | Y60: =X60 -> 39055 | Z60: =Y60 -> 39055 | AA60: =Z60 -> 39055 | AB60: =AA60 -> 39055 | ... AE60: =AD60 -> 39055 | AF60: =SUM(T60:AE60) -> 468660 | AG60: =AE60*1.07 -> 41788.85 | AH60: =AG60 -> 41788.85 | AI60: =AH60 -> 41788.85 | AJ60: =AI60 -> 41788.85 | AK60: =AJ60 -> 41788.85 | AL60: =AK60 -> 41788.85 | AM60: =AL60 -> 41788.85 | AN60: =AM60 -> 41788.85 | AO60: =AN60 -> 41788.85 | ... AR60: =AQ60 -> 41788.85 | AS60: =AR60*1.07 -> 44714.07 | AT60: =AS60 -> 44714.07 | AU60: =AT60 -> 44714.07 | AV60: =AU60 -> 44714.07 | AW60: =AV60 -> 44714.07 | AX60: =AW60 -> 44714.07 | AY60: =AX60 -> 44714.07 | AZ60: =AY60 -> 44714.07 | BA60: =AZ60 -> 44714.07 | ... BD60: =BC60 -> 44714.07 | BE60: =BD60*1.07 -> 47844.054 | BF60: =BE60 -> 47844.054 | BG60: =BF60 -> 47844.054 | BH60: =BG60 -> 47844.054 | BI60: =BH60 -> 47844.054 | BJ60: =BI60 -> 47844.054 | BK60: =BJ60 -> 47844.054 | BL60: =BK60 -> 47844.054 | BM60: =BL60 -> 47844.054 | ... BP60: =BO60 -> 47844.054 | BQ60: =SUM(G60:BP60)-AF60-S60 -> 2518823.7 | BR60: Warehousing | BS60: Warehousing | BT60: =SUM(G60:R60) -> 438000 | BU60: =SUM(T60:AE60) -> 468660 | BV60: =SUM(AG60:AR60) -> 501466.2 | BW60: =SUM(AS60:BD60) -> 536568.83 | BX60: =SUM(BE60:BP60) -> 574128.65 | BY60: =BQ60 -> 2518823.7
C61: kc | D61: KC resources (5% CPI annual increase) | G61: 350000 | H61: 350000 | I61: 350000 | J61: 350000 | K61: 350000 | L61: 350000 | M61: 350000 | N61: 350000 | O61: 350000 | P61: =P62+P63 -> 350000 | Q61: =Q62+Q63 -> 350000 | R61: =R62+R63 -> 350000 | S61: =S62+S63 -> 4200000 | T61: =T62+T63 -> 367500 | U61: =U62+U63 -> 367500 | V61: =V62+V63 -> 367500 | W61: =W62+W63 -> 367500 | ... AE61: =AE62+AE63 -> 367500 | AF61: =SUM(T61:AE61) -> 4410000 | AG61: =AG62+AG63 -> 385875 | AH61: =AH62+AH63 -> 385875 | AI61: =AI62+AI63 -> 385875 | AJ61: =AJ62+AJ63 -> 385875 | AK61: =AK62+AK63 -> 385875 | AL61: =AL62+AL63 -> 385875 | AM61: =AM62+AM63 -> 385875 | AN61: =AN62+AN63 -> 385875 | ... BP61: =BP62+BP63 -> 425427.19 | BQ61: =SUM(G61:BP61)-AF61-S61 -> 23207651 | BR61: KC resources | BT61: =SUM(G61:R61) -> 4200000 | BU61: =SUM(T61:AE61) -> 4410000 | BV61: =SUM(AG61:AR61) -> 4630500 | BW61: =SUM(AS61:BD61) -> 4862025 | BX61: =SUM(BE61:BP61) -> 5105126.2 | BY61: =BQ61 -> 23207651
C62: kc | D62: Current KCM resource costs | G62: 310000 | H62: 310000 | I62: 310000 | J62: 310000 | K62: 310000 | L62: 310000 | M62: 310000 | N62: 310000 | O62: 310000 | P62: 310000 | Q62: 310000 | R62: 310000 | S62: =SUM(G62:R62) -> 3720000 | T62: =R62*1.05 -> 325500 | U62: =T62 -> 325500 | V62: =U62 -> 325500 | W62: =V62 -> 325500 | X62: =W62 -> 325500 | Y62: =X62 -> 325500 | Z62: =Y62 -> 325500 | AA62: =Z62 -> 325500 | AB62: =AA62 -> 325500 | ... AE62: =AD62 -> 325500 | AF62: =SUM(T62:AE62) -> 3906000 | AG62: =AE62*1.05 -> 341775 | AH62: =AG62 -> 341775 | AI62: =AH62 -> 341775 | AJ62: =AI62 -> 341775 | AK62: =AJ62 -> 341775 | AL62: =AK62 -> 341775 | AM62: =AL62 -> 341775 | AN62: =AM62 -> 341775 | AO62: =AN62 -> 341775 | ... AR62: =AQ62 -> 341775 | AS62: =AR62*1.05 -> 358863.75 | AT62: =AS62 -> 358863.75 | AU62: =AT62 -> 358863.75 | AV62: =AU62 -> 358863.75 | AW62: =AV62 -> 358863.75 | AX62: =AW62 -> 358863.75 | AY62: =AX62 -> 358863.75 | AZ62: =AY62 -> 358863.75 | BA62: =AZ62 -> 358863.75 | ... BD62: =BC62 -> 358863.75 | BE62: =BD62*1.05 -> 376806.94 | BF62: =BE62 -> 376806.94 | BG62: =BF62 -> 376806.94 | BH62: =BG62 -> 376806.94 | BI62: =BH62 -> 376806.94 | BJ62: =BI62 -> 376806.94 | BK62: =BJ62 -> 376806.94 | BL62: =BK62 -> 376806.94 | BM62: =BL62 -> 376806.94 | ... BP62: =BO62 -> 376806.94 | BQ62: =SUM(G62:BP62)-AF62-S62 -> 20555348
C63: kc | D63: MVNO Campaign manager | G63: 40000 | H63: 40000 | I63: 40000 | J63: 40000 | K63: 40000 | L63: 40000 | M63: 40000 | N63: 40000 | O63: 40000 | P63: 40000 | Q63: 40000 | R63: 40000 | S63: =SUM(G63:R63) -> 480000 | T63: =R63*1.05 -> 42000 | U63: =T63 -> 42000 | V63: =U63 -> 42000 | W63: =V63 -> 42000 | X63: =W63 -> 42000 | Y63: =X63 -> 42000 | Z63: =Y63 -> 42000 | AA63: =Z63 -> 42000 | AB63: =AA63 -> 42000 | ... AE63: =AD63 -> 42000 | AF63: =SUM(T63:AE63) -> 504000 | AG63: =AE63*1.05 -> 44100 | AH63: =AG63 -> 44100 | AI63: =AH63 -> 44100 | AJ63: =AI63 -> 44100 | AK63: =AJ63 -> 44100 | AL63: =AK63 -> 44100 | AM63: =AL63 -> 44100 | AN63: =AM63 -> 44100 | AO63: =AN63 -> 44100 | ... AR63: =AQ63 -> 44100 | AS63: =AR63*1.05 -> 46305 | AT63: =AS63 -> 46305 | AU63: =AT63 -> 46305 | AV63: =AU63 -> 46305 | AW63: =AV63 -> 46305 | AX63: =AW63 -> 46305 | AY63: =AX63 -> 46305 | AZ63: =AY63 -> 46305 | BA63: =AZ63 -> 46305 | ... BD63: =BC63 -> 46305 | BE63: =BD63*1.05 -> 48620.25 | BF63: =BE63 -> 48620.25 | BG63: =BF63 -> 48620.25 | BH63: =BG63 -> 48620.25 | BI63: =BH63 -> 48620.25 | BJ63: =BI63 -> 48620.25 | BK63: =BJ63 -> 48620.25 | BL63: =BK63 -> 48620.25 | BM63: =BL63 -> 48620.25 | ... BP63: =BO63 -> 48620.25 | BQ63: =SUM(G63:BP63)-AF63-S63 -> 2652303
D64: Existing resources + campaign manager | G64: =G65/G12 -> -0.9955045 | H64: =H65/H12 -> -0.2057921 | I64: =I65/I12 -> -0.072414494 | J64: =J65/J12 -> -0.00052278409 | K64: =K65/K12 -> 0.038777622 | L64: =L65/L12 -> 0.064838202 | M64: =M65/M12 -> 0.086297483 | N64: =N65/N12 -> 0.10236973 | ... R64: =R65/R12 -> 0.13568672 | T64: =T65/T12 -> 0.17288272 | U64: =U65/U12 -> 0.17847481 | V64: =V65/V12 -> 0.18160221 | W64: =W65/W12 -> 0.18586265 | X64: =X65/X12 -> 0.189597 | Y64: =Y65/Y12 -> 0.19138614 | Z64: =Z65/Z12 -> 0.19436089 | AA64: =AA65/AA12 -> 0.19701684 | ... BP64: =BP65/BP12 -> 0.22088042 | BQ64: =SUM(G64:BP64)-AF64-S64 -> 9.586754 | BR64: Existing resources + campaign manager | BT64: =BT65/BT12 -> 0.064924768 | BU64: =BU65/BU12 -> 0.19261854 | BV64: =BV65/BV12 -> 0.20801204 | BW64: =BW65/BW12 -> 0.22032987 | BX64: =BX65/BX12 -> 0.21979127
D65: Net profit | F65: =F19-F22-F42-F26-F27-F31-F35 -> -6 | G65: =G12-G21-G40 -> -1422781.4 | H65: =H12-H21-H40 -> -562236.66 | I65: =I12-I21-I40 -> -287469.16 | J65: =J12-J21-J40 -> -2690.038 | K65: =K12-K21-K40 -> 242850.13 | L65: =L12-L21-L40 -> 474863.28 | M65: =M12-M21-M40 -> 719025.78 | N65: =N12-N21-N40 -> 950980.16 | ... R65: =R12-R21-R40 -> 1718475.8 | S65: =SUM(F65:R65) -> 5862571.9 | T65: =T12-T21-T40 -> 2317681.3 | U65: =U12-U21-U40 -> 2518297.6 | V65: =V12-V21-V40 -> 2683883 | W65: =W12-W21-W40 -> 2864939.1 | X65: =X12-X21-X40 -> 3036942.5 | Y65: =Y12-Y21-Y40 -> 3175345.6 | Z65: =Z12-Z21-Z40 -> 3330578.7 | AA65: =AA12-AA21-AA40 -> 3478050 | ... AE65: =AE12-AE21-AE40 -> 3972795.3 | AF65: =SUM(T65:AE65) -> 38600581 | AG65: =AG12-AG21-AG40 -> 3042789.8 | AH65: =AH12-AH21-AH40 -> 4204482.8 | AI65: =AI12-AI21-AI40 -> 4307467.6 | AJ65: =AJ12-AJ21-AJ40 -> 4405303.1 | AK65: =AK12-AK21-AK40 -> 4498246.8 | AL65: =AL12-AL21-AL40 -> 4586543.4 | AM65: =AM12-AM21-AM40 -> 4670425.1 | AN65: =AN12-AN21-AN40 -> 4725112.8 | ... BP65: =BP12-BP21-BP40 -> 5792076.8 | BQ65: =SUM(G65:BP65)-AF65-S65 -> 2.3087593e+08 | BR65: Net profit | BT65: =SUM(G65:R65) -> 5862577.9 | BU65: =SUM(T65:AE65) -> 38600581 | BV65: =SUM(AG65:AR65) -> 54060940 | BW65: =SUM(AS65:BD65) -> 64345495 | BX65: =SUM(BE65:BP65) -> 68006340 | BY65: =BQ65 -> 2.3087593e+08
D67: Model 1 | G67: =G65/G18 -> -1.0916141 | H67: =H65/H18 -> -0.22121548 | I67: =I65/I18 -> -0.077320843 | J67: =J65/J18 -> -0.00055632698 | K67: =K65/K18 -> 0.041182254 | L67: =L65/L18 -> 0.068766088 | M67: =M65/M18 -> 0.091437391 | N67: =N65/N18 -> 0.10838887 | ... R67: =R65/R18 -> 0.1434256 | T67: =T65/T18 -> 0.18269679 | U67: =U65/U18 -> 0.1885656 | V67: =V65/V18 -> 0.19183412 | W67: =W65/W18 -> 0.19630285 | X67: =X65/X18 -> 0.20021857 | Y67: =Y65/Y18 -> 0.20208266 | Z67: =Z65/Z18 -> 0.20520087 | AA67: =AA65/AA18 -> 0.20798433 | ... AE67: =AE65/AE18 -> 0.21525695 | AG67: =AG65/AG18 -> 0.16153577 | AH67: =AH65/AH18 -> 0.21900431 | AI67: =AI65/AI18 -> 0.22042509 | AJ67: =AJ65/AJ18 -> 0.22172933 | AK67: =AK65/AK18 -> 0.22292929 | AL67: =AL65/AL18 -> 0.2240356 | AM67: =AM65/AM18 -> 0.2250575 | AN67: =AN65/AN18 -> 0.22481365 | ... BP67: =BP65/BP18 -> 0.23292639 | BQ67: =SUM(G67:BP67)-AF67-S67 -> 10.070581 | BR67: Model 1
BQ68: =SUM(G68:BP68)-AF68-S68 -> 0
C69: To KC | E69: KCM Share @ 50% | F69: =F65*0.5 -> -3 | G69: =G65/2 -> -711390.69 | H69: =H65/2 -> -281118.33 | I69: =I65/2 -> -143734.58 | J69: =J65/2 -> -1345.019 | K69: =K65/2 -> 121425.06 | L69: =L65/2 -> 237431.64 | M69: =M65/2 -> 359512.89 | N69: =N65/2 -> 475490.08 | ... R69: =R65/2 -> 859237.9 | S69: =SUM(F69:R69) -> 2931285.9 | T69: =T65/2 -> 1158840.7 | U69: =U65/2 -> 1259148.8 | V69: =V65/2 -> 1341941.5 | W69: =W65/2 -> 1432469.6 | X69: =X65/2 -> 1518471.2 | Y69: =Y65/2 -> 1587672.8 | Z69: =Z65/2 -> 1665289.3 | AA69: =AA65/2 -> 1739025 | ... AE69: =AE65/2 -> 1986397.7 | AG69: =AG65/2 -> 1521394.9 | AH69: =AH65/2 -> 2102241.4 | AI69: =AI65/2 -> 2153733.8 | AJ69: =AJ65/2 -> 2202651.6 | AK69: =AK65/2 -> 2249123.4 | AL69: =AL65/2 -> 2293271.7 | AM69: =AM65/2 -> 2335212.6 | AN69: =AN65/2 -> 2362556.4 | ... BP69: =BP65/2 -> 2896038.4 | BQ69: =SUM(G69:BP69)-AF69-S69 -> 1.1543797e+08 | BS69: KCM Share @ 50% | BT69: =BT65*0.5 -> 2931288.9 | BU69: =BU65*0.5 -> 19300290 | BV69: =BV65*0.5 -> 27030470 | BW69: =BW65*0.5 -> 32172748 | BX69: =BX65*0.5 -> 34003170 | BY69: =SUM(BT69:BX69) -> 1.1543797e+08
C70: To DM | E70: DM Share @ 50% | F70: =F65*0.5 -> -3 | G70: =G65/2 -> -711390.69 | H70: =H65/2 -> -281118.33 | I70: =I65/2 -> -143734.58 | J70: =J65/2 -> -1345.019 | K70: =K65/2 -> 121425.06 | L70: =L65/2 -> 237431.64 | M70: =M65/2 -> 359512.89 | N70: =N65/2 -> 475490.08 | ... R70: =R65/2 -> 859237.9 | S70: =SUM(F70:R70) -> 2931285.9 | T70: =T65/2 -> 1158840.7 | U70: =U65/2 -> 1259148.8 | V70: =V65/2 -> 1341941.5 | W70: =W65/2 -> 1432469.6 | X70: =X65/2 -> 1518471.2 | Y70: =Y65/2 -> 1587672.8 | Z70: =Z65/2 -> 1665289.3 | AA70: =AA65/2 -> 1739025 | ... AE70: =AE65/2 -> 1986397.7 | AG70: =AG65/2 -> 1521394.9 | AH70: =AH65/2 -> 2102241.4 | AI70: =AI65/2 -> 2153733.8 | AJ70: =AJ65/2 -> 2202651.6 | AK70: =AK65/2 -> 2249123.4 | AL70: =AL65/2 -> 2293271.7 | AM70: =AM65/2 -> 2335212.6 | AN70: =AN65/2 -> 2362556.4 | ... BP70: =BP65/2 -> 2896038.4 | BQ70: =SUM(G70:BP70)-AF70-S70 -> 1.1543797e+08 | BS70: DM Share @ 50% | BT70: =BT65*0.5 -> 2931288.9 | BU70: =BU65*0.5 -> 19300290 | BV70: =BV65*0.5 -> 27030470 | BW70: =BW65*0.5 -> 32172748 | BX70: =BX65*0.5 -> 34003170 | BY70: =SUM(BT70:BX70) -> 1.1543797e+08
E71: Loan account | G71: =G69+G70 -> -1422781.4 | H71: =G71+H69+H70 -> -1985018 | I71: =H71+I69+I70 -> -2272487.2 | J71: =I71+J69+J70 -> -2275177.2 | K71: =J71+K69+K70 -> -2032327.1 | L71: =K71+L69+L70 -> -1557463.8 | M71: =L71+M69+M70 -> -838438.05 | N71: =M71+N69+N70 -> 112542.11 | O71: =N71+O69+O70 -> 1258878.9 | ... Q71: =P71+Q69+Q70 -> 4144102.1 | R71: =Q71+R70 -> 5003340 | S71: =SUM(F71:R71) -> 749724.8 | T71: =R71+T70 -> 6162180.7 | U71: =T71+U70 -> 7421329.4 | V71: =U71+V70 -> 8763270.9 | W71: =V71+W70 -> 10195740 | X71: =W71+X70 -> 11714212 | Y71: =X71+Y70 -> 13301885 | Z71: =Y71+Z70 -> 14967174 | AA71: =Z71+AA70 -> 16706199 | AB71: =AA71+AB70 -> 18515273 | ... AE71: =AD71+AE70 -> 24303630 | AG71: =AE71+AG70 -> 25825025 | AH71: =AG71+AH70 -> 27927267 | AI71: =AH71+AI70 -> 30081000 | AJ71: =AI71+AJ70 -> 32283652 | AK71: =AJ71+AK70 -> 34532775 | AL71: =AK71+AL70 -> 36826047 | AM71: =AL71+AM70 -> 39161260 | AN71: =AM71+AN70 -> 41523816 | AO71: =AN71+AO70 -> 43924224 | ... BP71: =BO71+BP70 -> 1.1751002e+08 | BS71: Loan account | BT71: =R71 -> 5003340 | BU71: =AE71 -> 24303630 | BV71: =AR71 -> 51334100 | BW71: =BD71 -> 83506848 | BX71: =BP71 -> 1.1751002e+08 | BY71: =BX71 -> 1.1751002e+08
E72: Interest | G72: =((G71*$G$1)/365)*30 -> -11986.446 | H72: =((H71*$G$1)/365)*30 -> -16723.097 | I72: =((I71*$G$1)/365)*30 -> -19144.926 | J72: =((J71*$G$1)/365)*30 -> -19167.589 | K72: =((K71*$G$1)/365)*30 -> -17121.66 | L72: =((L71*$G$1)/365)*30 -> -13121.099 | M72: =((M71*$G$1)/365)*30 -> -7063.5534 | N72: =((N71*$G$1)/365)*30 -> 948.12875 | ... Q72: =((Q71*$G$1)/365)*30 -> 34912.641
E73: Loan repsyment | G73: =G71+G72 -> -1434767.8 | H73: =H71+H72 -> -2001741.1 | I73: =I71+I72 -> -2291632.1 | J73: =J71+J72 -> -2294344.8 | K73: =K71+K72 -> -2049448.8 | L73: =L71+L72 -> -1570584.9 | M73: =M71+M72 -> -845501.6 | N73: =N71+N72 -> 113490.24 | ... Q73: =Q71+Q72 -> 4179014.7
D74: Although profitable in month 3, as agreed profit share will only be made once the loan account is cleared - month 4. | BR74: Although profitable in month 3, as agreed profit share will only be made once the loan account is cleared - month 4.
R79: MVNE payments | S79: =S22+S26+S30+S35+S36+S42+S51+S57 -> 61411913
R80: KC payments | S80: =S61+S58+S53+S52+S50+S43 -> 10489789
S81: =S80+S79 -> 71901702

Sheet Annual Calculations
B2: $/R RoE
A4: Example | D4: Annual Nett profit framework | E4: Month 1 | F4: Yr 1 | G4: Yr 2 | H4: Yr 3 | I4: Yr 4 | J4: Yr5 | K4: Totals
E9: Month 1 | F9: Yr 1 | G9: Yr 2 | H9: Yr 3 | I9: Yr 4 | J9: Yr5
C10: Total Revenue | E10: 1429206.4 | F10: 90298018 | G10: 2.0039909e+08 | H10: 2.5989332e+08 | I10: 2.9204163e+08 | J10: 3.0941329e+08
C11: Physical sim recovery R3.60 ex VAT | E11: 56880 | F11: 682560 | G11: 682560 | H11: 682560 | I11: 682560 | J11: 682560
C12: eSIM recovery R4.50 ex VAT | E12: 900 | F12: 10800 | G12: 10800 | H12: 10800 | I12: 10800 | J12: 10800
C13: McAfee Revenue 5% uptake @ R15.22 | E13: 12176 | F13: 795541.28 | G13: 1773056.9 | H13: 2301267.3 | I13: 2586691.1 | J13: 2740922.8
C14: Travel eSIM revenue 1% @ R 249.23 (USD14,49) | E14: 39876.48 | F14: 2605402.9 | G14: 5806773 | H14: 7536665.6 | I14: 8471430.5 | J14: 8976540.2
C15: Content revenue 5% @ R20 | E15: 16000 | F15: 1045389.3 | G15: 2329903.9 | H15: 3024004.4 | I15: 3399068.5 | J15: 3601738.2
A16: 100 | C16: Revenue | E16: 1303373.9 | F16: 85158324 | G16: 1.89796e+08 | H16: 2.4633802e+08 | I16: 2.7689108e+08 | J16: 2.9340073e+08 | K16: 1.0915842e+09
A17: 100 | C17: ARPU per month | E17: 81.46087 | F17: 81.46087 | G17: 81.46087 | H17: 81.46087 | I17: 81.46087 | J17: 81.46087
C19: Total COS | E19: 1390622.2 | F19: 59935330 | G19: 1.2943234e+08 | H19: 1.674296e+08 | I19: 1.8826938e+08 | J19: 1.9983952e+08
A20: 50 | D20: Wholesale Network Tarrifs | E20: 665116.13 | F20: 43456582 | G20: 96853543 | H20: 1.2570713e+08 | I20: 1.4129846e+08 | J20: 1.4972339e+08 | K20: 5.570391e+08
C21: Dependent on final product composition of voice and/or data and/or SMS
D22: Gross Profit Margin | E22: 0.51030339 | F22: 0.51 | G22: 0.51 | H22: 0.51 | I22: 0.51 | J22: 0.51
A24: 3 | C24: Contact Centre fixed per seat (seat subject to call centre vol) | E24: 25000 | F24: 450000 | G24: 1050000 | H24: 1650000 | I24: 2250000 | J24: 2850000 | K24: 8250000
A25: 18 | C25: Total Commission payable to disti channels | D25: 0.13 | E25: 195506.09 | F25: 12773749 | G25: 28469400 | H25: 36950704 | I25: 41533662 | J25: 44010109 | K25: 1.6373762e+08
C26: Ongoing commission to trade partner @7% | D26: 0.07 | E26: 91236.174 | F26: 5961082.7 | G26: 13285720 | H26: 17243662 | I26: 19382375 | J26: 20538051 | K26: 0
C27: Once off commission to airtime dist. @6% (Airtime Merchants and switching platform) | D27: 0.06 | E27: 78202.435 | F27: 5109499.4 | G27: 11387760 | H27: 14780281 | I27: 16613465 | J27: 17604044 | K27: 0
C28: Total SIM costs | D28: 9.5 | E28: 151000 | F28: 1812000 | G28: 1812000 | H28: 1812000 | I28: 1812000 | J28: 1812000 | K28: 0
A29: 6.5 | C29: Physical SIM card Cost | D29: 7.5 | E29: 118500 | F29: 1422000 | G29: 1422000 | H29: 1422000 | I29: 1422000 | J29: 1422000 | K29: 7110000
C30: Physical SIM packaging | D30: 2 | E30: 31600 | F30: 379200 | G30: 379200 | H30: 379200 | I30: 379200 | J30: 379200 | K30: 0
C31: eSIM card Cost | D31: 4.5 | E31: 900 | F31: 10800 | G31: 10800 | H31: 10800 | I31: 10800 | J31: 10800 | K31: 0
A33: 21 | C33: Paperless RICA | D33: 0 | E33: 75000 | F33: 295000 | G33: 252000 | H33: 264600 | I33: 277830 | J33: 291721.5 | K33: 1381151.5
C34: KCM App | E34: 279000 | F34: 1148000 | G34: 995400 | H34: 1045170 | I34: 1097428.5 | J34: 1152299.9
C35: KCM app = Super utility app with: | D35: Support, Maint + 30 dev hrs pm
C36: Packages, Payments, eSIM, Travel eSIM, McAfee, Consolidation of packages with VAS, Integrate KC services, Voucher dist, Number porting, RICA
C38: Total Operating costs | E38: 739882.54 | F38: 15279010 | G38: 25189453 | H38: 30686417 | I38: 33806023 | J38: 35648915 | K38: 1.4060982e+08
A40: 7.5 | C40: SIM Mgt fee on MVNE platform R7.50 per subscriber or R75k, whichever is higher | E40: 120000 | F40: 7840420 | G40: 17474280 | H40: 22680033 | I40: 25493014 | J40: 27013037 | K40: 1.0050078e+08
E41: 1500
E43: 1500
E46: 177910.54 | F46: 2134926.5 | G46: 2134926.5 | H46: 2134926.5 | I46: 2134926.5 | J46: 2134926.5 | K46: 10674632
C47: Vehicle costs total all escaleted @ 5% | D47: KCM trucks consumables X 8 | E47: 44472 | F47: 533664 | G47: 560347.2 | H47: 588364.56 | I47: 617782.79 | J47: 648671.93 | K47: 2948830.5
D48: Fuel (variable cost) | E48: 34880 | F48: 418560 | G48: 439488 | H48: 461462.4 | I48: 484535.52 | J48: 508762.3 | K48: 2312808.2
D49: Satellite tracker R209 per vehicle X 8 | E49: 1672 | F49: 20064 | G49: 21067.2 | H49: 22120.56 | I49: 23226.588 | J49: 24387.917 | K49: 110866.27
D50: Insurance @ R990 per vehicle X 8 | E50: 7920 | F50: 95040 | G50: 99792 | H50: 104781.6 | I50: 110020.68 | J50: 115521.71 | K50: 525155.99
C52: Courier fees total | E52: 47500 | F52: 570000 | G52: 609900 | H52: 652593 | I52: 698274.51 | J52: 747153.73 | K52: 3277921.2
C53: Physical distribution | D53: Fixed fee | E53: 11000 | F53: 132000 | G53: 141240 | H53: 151126.8 | I53: 161705.68 | J53: 173025.07 | K53: 759097.55
C54: Warehousing | D54: Warehousing | E54: 36500 | F54: 438000 | G54: 468660 | H54: 501466.2 | I54: 536568.83 | J54: 574128.65 | K54: 2518823.7
C55: KC resources | E55: 350000 | F55: 4200000 | G55: 4410000 | H55: 4630500 | I55: 4862025 | J55: 5105126.2 | K55: 23207651
E56: 310000
E57: 40000
C58: Existing resources + campaign manager
A59: =A17-A20-A40-A24-A25-A29-A33 -> -6 | C59: Net profit | E59: -701298.36 | F59: 15083677 | G59: 45777298 | H59: 61777302 | I59: 69966229 | J59: 73924857 | K59: 2.6652936e+08
E61: -0.53806383
A63: =A59*0.5 -> -3 | D63: KCM Share @ 50% | E63: -350649.18 | F63: 7541838.4 | G63: 22888649 | H63: 30888651 | I63: 34983114 | J63: 36962428 | K63: 1.3326468e+08
A64: =A59*0.5 -> -3 | D64: DM Share @ 50% | E64: -350649.18 | F64: 7541838.4 | G64: 22888649 | H64: 30888651 | I64: 34983114 | J64: 36962428 | K64: 1.3326468e+08
C66: Although profitable in month 3, as agreed profit share will only be made once the loan account is cleared - month 4.

Sheet Graphs
A3: Annual Nett profit framework
B4: Yr 1 | C4: Yr 2 | D4: Yr 3 | E4: Yr 4 | F4: Yr5 | G4: Totals
A5: Revenue | B5: =Calculations!BT12 -> 90298018 | C5: =Calculations!BU12 -> 2.0039909e+08 | D5: =Calculations!BV12 -> 2.5989332e+08 | E5: =Calculations!BW12 -> 2.9204163e+08 | F5: =Calculations!BX12 -> 3.0941329e+08 | G5: =SUM(B5:F5) -> 1.1520454e+09
A6: COS | B6: =Calculations!BT21 -> 60860330 | C6: =Calculations!BU21 -> 1.3095734e+08 | D6: =Calculations!BV21 -> 1.689046e+08 | E6: =Calculations!BW21 -> 1.8946938e+08 | F6: =Calculations!BX21 -> 2.0058952e+08 | G6: =SUM(B6:F6) -> 7.5078117e+08
A7: Operating costs | B7: =Calculations!BT40 -> 23575109 | C7: =Calculations!BU40 -> 30841171 | D7: =Calculations!BV40 -> 36927778 | E7: =Calculations!BW40 -> 38226756 | F7: =Calculations!BX40 -> 40817432 | G7: =SUM(B7:F7) -> 1.7038825e+08
A8: Net profit | B8: =Calculations!BT65 -> 5862577.9 | C8: =Calculations!BU65 -> 38600581 | D8: =Calculations!BV65 -> 54060940 | E8: =Calculations!BW65 -> 64345495 | F8: =Calculations!BX65 -> 68006340 | G8: =SUM(B8:F8) -> 2.3087593e+08
A9: KCMShare @ 50% | B9: =Calculations!BT69 -> 2931288.9 | C9: 22587925 | D9: 30552572 | E9: 34609486 | F9: 36548916 | G9: =SUM(B9:F9) -> 1.2723019e+08
A10: DM Share @ 50% | B10: =Calculations!BT70 -> 2931288.9 | C10: 22587925 | D10: 30552572 | E10: 34609486 | F10: 36548916 | G10: =SUM(B10:F10) -> 1.2723019e+08

Sheet Packages
D3: Price | E3: Price ex VAT | F3: Inclusive Minutes | G3: Inclusive Megabytes | H3: Inclusive SMS | I3: Sim card | J3: Subscribers | K3: Minute cost | L3: Data Cost | M3: SMS Cost | N3: Total cost | O3: Margin
C5: KCM 1.5 GB | D5: 85 | E5: =D5/1.15 -> 73.913043 | F5: 10 | G5: 1536 | H5: 20 | I5: 6.5 | J5: 0.9 | K5: =F5*0.38 -> 3.8 | L5: =G5*0.01921 -> 29.50656 | M5: =H5*0.16 -> 3.2 | N5: =SUM(K5:M5) -> 36.50656 | O5: =1-(N5/E5) -> 0.50608772
C6: KCM 3 GB | D6: 159 | E6: =D6/1.15 -> 138.26087 | F6: 20 | G6: 3072 | H6: 50 | I6: 6.5 | J6: 0.05 | K6: =F6*0.38 -> 7.6 | L6: =G6*0.01921 -> 59.01312 | M6: =H6*0.16 -> 8 | N6: =SUM(K6:M6) -> 74.61312 | O6: =1-(N6/E6) -> 0.46034536
C7: KCM 5 GB | D7: 175 | E7: =D7/1.15 -> 152.17391 | F7: 30 | G7: 5324.8 | H7: 50 | I7: 6.5 | J7: 0.03 | K7: =F7*0.38 -> 11.4 | L7: =G7*0.01225 -> 65.2288 | M7: =H7*0.16 -> 8 | N7: =SUM(K7:M7) -> 84.6288 | O7: =1-(N7/E7) -> 0.44386789
C8: KCM 10 GB | D8: 199 | E8: =D8/1.15 -> 173.04348 | F8: 40 | G8: 10444.8 | H8: 50 | I8: 6.5 | J8: 0.02 | K8: =F8*0.38 -> 15.2 | L8: =G8*0.00948 -> 99.016704 | M8: =H8*0.16 -> 8 | N8: =SUM(K8:M8) -> 122.2167 | O8: =1-(N8/E8) -> 0.29372256

Sheet Bundles
B1: nd Jan
C2: Data Bundle | D2: Retail Price inc VAT
C3: 250mb | D3: 18
C4: 550mb | D4: 35
C5: 750mb | D5: 50
C6: 1,5GB | D6: 55
C7: 2,25GB | D7: 80
C8: 5,5GB | D8: 110
C9: 7GB | D9: 135
C10: 10,25GB | D10: 150
C12: Voice bundle | D12: Included Minutes
C13: 8 | D13: 5
C14: 12 | D14: 15
C15: 25 | D15: 40
C16: 45 | D16: 80
C17: 80 | D17: 160
C19: SMS Bundle | D19: Included SMS
C20: 5 | D20: 15
C21: 10 | D21: 35
C22: 17 | D22: 60
C23: 30 | D23: 110
C24: 50 | D24: 200
C25: 72.5 | D25: 300
C26: 115 | D26: 500
