Workbook
Name _dave005: #REF!
Name _dave005: #REF!
Name _dave005: #REF!
Name _jas005: #REF!
Name _jas005: #REF!
Name _jas005: #REF!
Name _jas006: #REF!
Name _jas006: #REF!
Name _jas006: #REF!
Name _jas007: #REF!
Name _jas007: #REF!
Name _jas007: #REF!
Name _john005: #REF!
Name _john005: #REF!
Name _john005: #REF!
Name _sam005: #REF!
Name _sam005: #REF!
Name _sam005: #REF!
Name exchange_rate: [1]Data!$C$272
Name myCurviness: '[2]SUBSCRIBER NORMALIZATION'!$C$12
Name myCurviness: '[2]SUBSCRIBER NORMALIZATION'!$C$12
Name myCurviness: '[2]SUBSCRIBER NORMALIZATION'!$C$12
Name myCurviness: '[2]SUBSCRIBER NORMALIZATION'!$C$12
Name myCurviness: 'SUBSCRIBER NORMALIZATION'!$C$12
Name myCurviness1: #REF!
Name myReferenceBand: 'SUBSCRIBER NORMALIZATION'!#REF!
Name myReferenceBand: 'SUBSCRIBER NORMALIZATION FLTE'!#REF!
Name myReferenceBand: 'SUBSCRIBER NORMALIZATION'!#REF!
Name myReferenceBand: 'SUBSCRIBER NORMALIZATION FLTE'!#REF!
Name myReferenceBand: '[2]SUBSCRIBER NORMALIZATION'!#REF!
Name myReferenceBand: '[2]SUBSCRIBER NORMALIZATION'!#REF!
Name myReferenceBand: '[2]SUBSCRIBER NORMALIZATION'!#REF!
Name myReferenceBand: '[2]SUBSCRIBER NORMALIZATION'!#REF!
Name myReferenceBand: 'SUBSCRIBER NORMALIZATION'!#REF!
Name myReferenceBand: #REF!
Name myReferenceBand: 'SUBSCRIBER NORMALIZATION FLTE'!#REF!
Name myReferenceBand: 'SUBSCRIBER NORMALIZATION'!#REF!
Name myReferenceBand: 'SUBSCRIBER NORMALIZATION FLTE'!#REF!
Name myReferenceBand: 'SUBSCRIBER NORMALIZATION'!#REF!
Name myReferenceBand: 'SUBSCRIBER NORMALIZATION FLTE'!#REF!
Name myReferenceBand: 'SUBSCRIBER NORMALIZATION'!#REF!
Name myReferenceBand: 'SUBSCRIBER NORMALIZATION FLTE'!#REF!
Name myReferenceBand: 'SUBSCRIBER NORMALIZATION'!#REF!
Name myReferenceBand: 'SUBSCRIBER NORMALIZATION FLTE'!#REF!
Name myReferenceBand: 'SUBSCRIBER NORMALIZATION'!#REF!
Name myReferenceBand: 'SUBSCRIBER NORMALIZATION FLTE'!#REF!
Name myReferenceBand: 'SUBSCRIBER NORMALIZATION'!#REF!
Name myReferenceBand: 'SUBSCRIBER NORMALIZATION FLTE'!#REF!
Name myReferenceBand: 'SUBSCRIBER NORMALIZATION'!#REF!
Name myReferenceBand: 'SUBSCRIBER NORMALIZATION FLTE'!#REF!
Name myReferenceBand: 'SUBSCRIBER NORMALIZATION'!#REF!
Name myReferenceBand1: #REF!
Name myStartofFastGrowth: '[2]SUBSCRIBER NORMALIZATION'!$C$10
Name myStartofFastGrowth: '[2]SUBSCRIBER NORMALIZATION'!$C$10
Name myStartofFastGrowth: '[2]SUBSCRIBER NORMALIZATION'!$C$10
Name myStartofFastGrowth: '[2]SUBSCRIBER NORMALIZATION'!$C$10
Name myStartofFastGrowth: 'SUBSCRIBER NORMALIZATION'!$C$10
Name myStartofFastGrowth1: #REF!
Name myStartValue: '[2]SUBSCRIBER NORMALIZATION'!$C$8
Name myStartValue: '[2]SUBSCRIBER NORMALIZATION'!$C$8

Sheet <<KEY FINANCIAL INDICATORS> TOT
B3: =UPPER('<<VERSIONING NOTES>>'!$F$2)&TEXT(" KEY FINANCIAL INDICATORS VERSION ","")&'<<VERSIONING NOTES>>'!$F$3 -> METL KEY FINANCIAL INDICATORS VERSION MVNE Financial Framework Template Metl 20250604 1m | H3: =TEXT("Prepared by ","") -> Prepared by
H4: ='<<VERSIONING NOTES>>'!F4 -> Edward Wicks | J4: 0.08
J5: =H26/2300000 -> 0.96636954
C6: Rewards value | D6: Projected | E6: Cumulative EBIT | F6: Cash Flow First | G6: Cash Flow First | H6: Cumulative Revenue
C7: Generated | D7: Peak Funding | E7: over 60 Months | F7: Positive in Month | G7: BreakEven in Month | H7: Over 60 Months
C8: ='<<KEY FINANCIAL INDICATORS>>'!C8+'<<KEY FINANCIAL INDICATORS>FLTE'!C8 -> 1.3007635e+10 | D8: =ABS(MIN('<<CASH FLOW PROJECTIONS>> TOT'!C62:BR62)) -> 7.718054e+09 | E8: =H21 -> 4.0569124e+10 | F8: =MIN('<<CASH FLOW PROJECTIONS>> TOT'!C64:BR64) -> 25 | G8: =MIN('<<CASH FLOW PROJECTIONS>> TOT'!C65:BR65) -> 35 | H8: =SUM('<<CASH FLOW PROJECTIONS>> TOT'!C8:BR8) -> 4.3358782e+11
B10: Projections | C10: Project Phase | D10: Year 1 | E10: Year 2 | F10: Year 3 | G10: Year 4 | H10: Year 5
B12: Revenue | C12: =SUM('<<CASH FLOW PROJECTIONS>> TOT'!C8:H8) -> 0 | D12: =SUM('<<CASH FLOW PROJECTIONS>> TOT'!I8:V8) -> 8.7970996e+09 | E12: =SUM('<<CASH FLOW PROJECTIONS>> TOT'!W8:AH8) -> 3.7571707e+10 | F12: =SUM('<<CASH FLOW PROJECTIONS>> TOT'!AI8:AT8) -> 9.6092394e+10 | G12: =SUM('<<CASH FLOW PROJECTIONS>> TOT'!AU8:BF8) -> 1.2897483e+11 | H12: =SUM('<<CASH FLOW PROJECTIONS>> TOT'!BG8:BR8) -> 1.6215179e+11
B13: Direct Costs | C13: =SUM('<<CASH FLOW PROJECTIONS>> TOT'!C20:H20) -> 0 | D13: =SUM('<<CASH FLOW PROJECTIONS>> TOT'!I20:V20) -> 1.0274608e+10 | E13: =SUM('<<CASH FLOW PROJECTIONS>> TOT'!W20:AH20) -> 3.7047177e+10 | F13: =SUM('<<CASH FLOW PROJECTIONS>> TOT'!AI20:AT20) -> 8.1531382e+10 | G13: =SUM('<<CASH FLOW PROJECTIONS>> TOT'!AU20:BF20) -> 1.0794837e+11 | H13: =SUM('<<CASH FLOW PROJECTIONS>> TOT'!BG20:BR20) -> 1.2860298e+11
B14: Gross Profit | C14: =C12-C13 -> 0 | D14: =D12-D13 -> -1.4775087e+09 | E14: =E12-E13 -> 5.2453033e+08 | F14: =F12-F13 -> 1.4561011e+10 | G14: =G12-G13 -> 2.1026459e+10 | H14: =H12-H13 -> 3.3548815e+10
B15: Operational Expenditure | C15: =SUM('<<CASH FLOW PROJECTIONS>> TOT'!C39:H39) -> 1764000000 | D15: =SUM('<<CASH FLOW PROJECTIONS>> TOT'!I39:V39) -> 1.3117959e+09 | E15: =SUM('<<CASH FLOW PROJECTIONS>> TOT'!W39:AH39) -> 1.4952687e+09 | F15: =SUM('<<CASH FLOW PROJECTIONS>> TOT'!AI39:AT39) -> 2.1413438e+09 | G15: =SUM('<<CASH FLOW PROJECTIONS>> TOT'!AU39:BF39) -> 2.5347536e+09 | H15: =SUM('<<CASH FLOW PROJECTIONS>> TOT'!BG39:BR39) -> 2.9351265e+09
B16: EBITDA | C16: =C14-C15 -> -1764000000 | D16: =D14-D15 -> -2.7893046e+09 | E16: =E14-E15 -> -9.7073835e+08 | F16: =F14-F15 -> 1.2419668e+10 | G16: =G14-G15 -> 1.8491706e+10 | H16: =H14-H15 -> 3.0613689e+10
B17: Capital Expenditure | C17: =SUM('<<CASH FLOW PROJECTIONS>> TOT'!C47:H47) -> 608300000 | D17: =SUM('<<CASH FLOW PROJECTIONS>> TOT'!I47:V47) -> 500000 | E17: =SUM('<<CASH FLOW PROJECTIONS>> TOT'!W47:AH47) -> 0 | F17: =SUM('<<CASH FLOW PROJECTIONS>> TOT'!AI47:AT47) -> 0 | G17: =SUM('<<CASH FLOW PROJECTIONS>> TOT'!AU47:BF47) -> 0 | H17: =SUM('<<CASH FLOW PROJECTIONS>> TOT'!BG47:BR47) -> 0
B18: Depreciation | C18: 0 | D18: 0 | E18: 0 | F18: 0 | G18: 0 | H18: 0
B19: Provisions | C19: =SUM('<<CASH FLOW PROJECTIONS>> TOT'!C55:H55) -> 0 | D19: =SUM('<<CASH FLOW PROJECTIONS>> TOT'!I55:V55) -> 3.0074266e+08 | E19: =SUM('<<CASH FLOW PROJECTIONS>> TOT'!W55:AH55) -> 1.2844684e+09 | F19: =SUM('<<CASH FLOW PROJECTIONS>> TOT'!AI55:AT55) -> 3.2848761e+09 | G19: =SUM('<<CASH FLOW PROJECTIONS>> TOT'!AU55:BF55) -> 4.4093023e+09 | H19: =SUM('<<CASH FLOW PROJECTIONS>> TOT'!BG55:BR55) -> 5.5437052e+09
B20: EBIT | C20: =C16-C17-C18-C19 -> -2372300000 | D20: =D16-D17-D18-D19 -> -3.0905472e+09 | E20: =E16-E17-E18-E19 -> -2.2552067e+09 | F20: =F16-F17-F18-F19 -> 9.1347915e+09 | G20: =G16-G17-G18-G19 -> 1.4082403e+10 | H20: =H16-H17-H18-H19 -> 2.5069983e+10
B21: CUMULATIVE EBIT | C21: =C20 -> -2372300000 | D21: =D20+C21 -> -5.4628472e+09 | E21: =E20+D21 -> -7.718054e+09 | F21: =F20+E21 -> 1.4167376e+09 | G21: =G20+F21 -> 1.5499141e+10 | H21: =H20+G21 -> 4.0569124e+10
B22: Value of the base | D22: =D28*D27*24 -> 2.0743442e+10 | E22: =E28*E27*24 -> 6.4314685e+10 | F22: =F28*F27*24 -> 1.293656e+11 | G22: =G28*G27*24 -> 1.5605553e+11 | H22: =H28*H27*24 -> 1.9373755e+11
C23: Susbcriber Base | D23: Year 1 | E23: Year 2 | F23: Year 3 | G23: Year 4 | H23: Year 5
C24: Conversion for the year | D24: =D27/'ACQUISITION ASSUMPTIONS'!$C$10 -> 0.029814514 | E24: =(E26-E25)/'ACQUISITION ASSUMPTIONS'!$C$10 -> 0.062859728 | F24: =(F26-F25)/'ACQUISITION ASSUMPTIONS'!$C$10 -> 0.056453685 | G24: =(G26-G25)/'ACQUISITION ASSUMPTIONS'!$C$10 -> 0.034207249 | H24: =(H26-H25)/'ACQUISITION ASSUMPTIONS'!$C$10 -> 0.020280978
C25: Opening Base | D25: ='<<KEY FINANCIAL INDICATORS>>'!D27+'<<KEY FINANCIAL INDICATORS>FLTE'!D25 -> 0 | E25: ='<<KEY FINANCIAL INDICATORS>>'!E27+'<<KEY FINANCIAL INDICATORS>FLTE'!E25 -> 325605.03 | F25: ='<<KEY FINANCIAL INDICATORS>>'!F27+'<<KEY FINANCIAL INDICATORS>FLTE'!F25 -> 1011719 | G25: ='<<KEY FINANCIAL INDICATORS>>'!G27+'<<KEY FINANCIAL INDICATORS>FLTE'!G25 -> 1627910.9 | H25: ='<<KEY FINANCIAL INDICATORS>>'!H27+'<<KEY FINANCIAL INDICATORS>FLTE'!H25 -> 2001283.1
C26: Closing Base | D26: ='<<KEY FINANCIAL INDICATORS>>'!D28+'<<KEY FINANCIAL INDICATORS>FLTE'!D26 -> 325605.03 | E26: ='<<KEY FINANCIAL INDICATORS>>'!E28+'<<KEY FINANCIAL INDICATORS>FLTE'!E26 -> 1011719 | F26: ='<<KEY FINANCIAL INDICATORS>>'!F28+'<<KEY FINANCIAL INDICATORS>FLTE'!F26 -> 1627910.9 | G26: ='<<KEY FINANCIAL INDICATORS>>'!G28+'<<KEY FINANCIAL INDICATORS>FLTE'!G26 -> 2001283.1 | H26: ='<<KEY FINANCIAL INDICATORS>>'!H28+'<<KEY FINANCIAL INDICATORS>FLTE'!H26 -> 2222649.9
C27: Active Base | D27: ='<<KEY FINANCIAL INDICATORS>>'!D29+'<<KEY FINANCIAL INDICATORS>FLTE'!D27 -> 325425.42 | E27: ='<<KEY FINANCIAL INDICATORS>>'!E29+'<<KEY FINANCIAL INDICATORS>FLTE'!E27 -> 1011092.8 | F27: ='<<KEY FINANCIAL INDICATORS>>'!F29+'<<KEY FINANCIAL INDICATORS>FLTE'!F27 -> 1626729.1 | G27: ='<<KEY FINANCIAL INDICATORS>>'!G29+'<<KEY FINANCIAL INDICATORS>FLTE'!G27 -> 1965339.1 | H27: ='<<KEY FINANCIAL INDICATORS>>'!H29+'<<KEY FINANCIAL INDICATORS>FLTE'!H27 -> 2220484.7
C28: Blended ARPU | D28: =('<<KEY FINANCIAL INDICATORS>>'!D30+'<<KEY FINANCIAL INDICATORS>FLTE'!D28)/2 -> 2655.939 | E28: =('<<KEY FINANCIAL INDICATORS>>'!E30+'<<KEY FINANCIAL INDICATORS>FLTE'!E28)/2 -> 2650.3783 | F28: =('<<KEY FINANCIAL INDICATORS>>'!F30+'<<KEY FINANCIAL INDICATORS>FLTE'!F28)/2 -> 3313.5409 | G28: =('<<KEY FINANCIAL INDICATORS>>'!G30+'<<KEY FINANCIAL INDICATORS>FLTE'!G28)/2 -> 3308.4946 | H28: =('<<KEY FINANCIAL INDICATORS>>'!H30+'<<KEY FINANCIAL INDICATORS>FLTE'!H28)/2 -> 3635.4216
C29: CAGR % | E29: =IF(E28>0,(E28-D28)/D28,0) -> -0.0020936906 | F29: =IF(F28>0,(F28-E28)/E28,0) -> 0.25021431 | G29: =IF(G28>0,(G28-F28)/F28,0) -> -0.0015229462 | H29: =IF(H28>0,(H28-G28)/G28,0) -> 0.098814432

Sheet <<CASH FLOW PROJECTIONS>> TOT
B3: =UPPER('<<VERSIONING NOTES>>'!$F$2)&TEXT(" CASH FLOW PROJECTIONS VERSION ","")&'<<VERSIONING NOTES>>'!$F$3 -> METL CASH FLOW PROJECTIONS VERSION MVNE Financial Framework Template Metl 20250604 1m | BR3: =TEXT("Prepared by ","") -> Prepared by
BR4: ='<<VERSIONING NOTES>>'!F4 -> Edward Wicks
C6: PM1 | D6: PM2 | E6: PM3 | F6: PM4 | G6: PM5 | H6: PM6 | I6: SL1 | J6: SL2 | K6: 1 | L6: 2 | M6: 3 | N6: 4 | O6: 5 | P6: 6 | Q6: 7 | R6: 8 | S6: 9 | T6: 10 | U6: 11 | V6: 12 | W6: 13 | X6: 14 | Y6: 15 | Z6: 16 | AA6: 17 | AB6: 18 | AC6: 19 | AD6: 20 | AE6: 21 | AF6: 22 | AG6: 23 | AH6: 24 | AI6: 25 | AJ6: 26 | AK6: 27 | AL6: 28 | AM6: 29 | AN6: 30 | AO6: 31 | AP6: 32 | AQ6: 33 | AR6: 34 | AS6: 35 | AT6: 36 | AU6: 37 | AV6: 38 | AW6: 39 | AX6: 40 | AY6: 41 | AZ6: 42 | BA6: 43 | BB6: 44 | BC6: 45 | BD6: 46 | BE6: 47 | BF6: 48 | BG6: 49 | BH6: 50 | BI6: 51 | BJ6: 52 | BK6: 53 | BL6: 54 | BM6: 55 | BN6: 56 | BO6: 57 | BP6: 58 | BQ6: 59 | BR6: 60
B8: Revenue | C8: =SUM(C9:C19) -> 0 | D8: =SUM(D9:D19) -> 0 | E8: =SUM(E9:E19) -> 0 | F8: =SUM(F9:F19) -> 0 | G8: =SUM(G9:G19) -> 0 | H8: =SUM(H9:H19) -> 0 | I8: =SUM(I9:I19) -> 0 | J8: =SUM(J9:J19) -> 0 | ... BR8: =SUM(BR9:BR19) -> 1.4321841e+10
B9: Connection Fees | C9: ='<<CASH FLOW PROJECTIONS>>'!C9+'<<CASH FLOW PROJECTIONS>>FLTE'!C9 -> 0 | D9: ='<<CASH FLOW PROJECTIONS>>'!D9+'<<CASH FLOW PROJECTIONS>>FLTE'!D9 -> 0 | E9: ='<<CASH FLOW PROJECTIONS>>'!E9+'<<CASH FLOW PROJECTIONS>>FLTE'!E9 -> 0 | F9: ='<<CASH FLOW PROJECTIONS>>'!F9+'<<CASH FLOW PROJECTIONS>>FLTE'!F9 -> 0 | G9: ='<<CASH FLOW PROJECTIONS>>'!G9+'<<CASH FLOW PROJECTIONS>>FLTE'!G9 -> 0 | H9: ='<<CASH FLOW PROJECTIONS>>'!H9+'<<CASH FLOW PROJECTIONS>>FLTE'!H9 -> 0 | I9: ='<<CASH FLOW PROJECTIONS>>'!I9+'<<CASH FLOW PROJECTIONS>>FLTE'!I9 -> 0 | J9: ='<<CASH FLOW PROJECTIONS>>'!J9+'<<CASH FLOW PROJECTIONS>>FLTE'!J9 -> 0 | ... BR9: ='<<CASH FLOW PROJECTIONS>>'!BR9+'<<CASH FLOW PROJECTIONS>>FLTE'!BR9 -> 0
B10: Courier Fees | C10: ='<<CASH FLOW PROJECTIONS>>'!C10+'<<CASH FLOW PROJECTIONS>>FLTE'!C10 -> 0 | D10: ='<<CASH FLOW PROJECTIONS>>'!D10+'<<CASH FLOW PROJECTIONS>>FLTE'!D10 -> 0 | E10: ='<<CASH FLOW PROJECTIONS>>'!E10+'<<CASH FLOW PROJECTIONS>>FLTE'!E10 -> 0 | F10: ='<<CASH FLOW PROJECTIONS>>'!F10+'<<CASH FLOW PROJECTIONS>>FLTE'!F10 -> 0 | G10: ='<<CASH FLOW PROJECTIONS>>'!G10+'<<CASH FLOW PROJECTIONS>>FLTE'!G10 -> 0 | H10: ='<<CASH FLOW PROJECTIONS>>'!H10+'<<CASH FLOW PROJECTIONS>>FLTE'!H10 -> 0 | I10: ='<<CASH FLOW PROJECTIONS>>'!I10+'<<CASH FLOW PROJECTIONS>>FLTE'!I10 -> 0 | J10: ='<<CASH FLOW PROJECTIONS>>'!J10+'<<CASH FLOW PROJECTIONS>>FLTE'!J10 -> 0 | ... BR10: ='<<CASH FLOW PROJECTIONS>>'!BR10+'<<CASH FLOW PROJECTIONS>>FLTE'!BR10 -> 805200
B11: Cash Device Sales Revenue | C11: ='<<CASH FLOW PROJECTIONS>>'!C11+'<<CASH FLOW PROJECTIONS>>FLTE'!C11 -> 0 | D11: ='<<CASH FLOW PROJECTIONS>>'!D11+'<<CASH FLOW PROJECTIONS>>FLTE'!D11 -> 0 | E11: ='<<CASH FLOW PROJECTIONS>>'!E11+'<<CASH FLOW PROJECTIONS>>FLTE'!E11 -> 0 | F11: ='<<CASH FLOW PROJECTIONS>>'!F11+'<<CASH FLOW PROJECTIONS>>FLTE'!F11 -> 0 | G11: ='<<CASH FLOW PROJECTIONS>>'!G11+'<<CASH FLOW PROJECTIONS>>FLTE'!G11 -> 0 | H11: ='<<CASH FLOW PROJECTIONS>>'!H11+'<<CASH FLOW PROJECTIONS>>FLTE'!H11 -> 0 | I11: ='<<CASH FLOW PROJECTIONS>>'!I11+'<<CASH FLOW PROJECTIONS>>FLTE'!I11 -> 0 | J11: ='<<CASH FLOW PROJECTIONS>>'!J11+'<<CASH FLOW PROJECTIONS>>FLTE'!J11 -> 0 | ... BR11: ='<<CASH FLOW PROJECTIONS>>'!BR11+'<<CASH FLOW PROJECTIONS>>FLTE'!BR11 -> 0
B12: Credit Device Pay in Revenue | C12: ='<<CASH FLOW PROJECTIONS>>'!C12+'<<CASH FLOW PROJECTIONS>>FLTE'!C12 -> 0 | D12: ='<<CASH FLOW PROJECTIONS>>'!D12+'<<CASH FLOW PROJECTIONS>>FLTE'!D12 -> 0 | E12: ='<<CASH FLOW PROJECTIONS>>'!E12+'<<CASH FLOW PROJECTIONS>>FLTE'!E12 -> 0 | F12: ='<<CASH FLOW PROJECTIONS>>'!F12+'<<CASH FLOW PROJECTIONS>>FLTE'!F12 -> 0 | G12: ='<<CASH FLOW PROJECTIONS>>'!G12+'<<CASH FLOW PROJECTIONS>>FLTE'!G12 -> 0 | H12: ='<<CASH FLOW PROJECTIONS>>'!H12+'<<CASH FLOW PROJECTIONS>>FLTE'!H12 -> 0 | I12: ='<<CASH FLOW PROJECTIONS>>'!I12+'<<CASH FLOW PROJECTIONS>>FLTE'!I12 -> 0 | J12: ='<<CASH FLOW PROJECTIONS>>'!J12+'<<CASH FLOW PROJECTIONS>>FLTE'!J12 -> 0 | ... BR12: ='<<CASH FLOW PROJECTIONS>>'!BR12+'<<CASH FLOW PROJECTIONS>>FLTE'!BR12 -> 0
B13: Device Subscription Revenue | C13: ='<<CASH FLOW PROJECTIONS>>'!C13+'<<CASH FLOW PROJECTIONS>>FLTE'!C13 -> 0 | D13: ='<<CASH FLOW PROJECTIONS>>'!D13+'<<CASH FLOW PROJECTIONS>>FLTE'!D13 -> 0 | E13: ='<<CASH FLOW PROJECTIONS>>'!E13+'<<CASH FLOW PROJECTIONS>>FLTE'!E13 -> 0 | F13: ='<<CASH FLOW PROJECTIONS>>'!F13+'<<CASH FLOW PROJECTIONS>>FLTE'!F13 -> 0 | G13: ='<<CASH FLOW PROJECTIONS>>'!G13+'<<CASH FLOW PROJECTIONS>>FLTE'!G13 -> 0 | H13: ='<<CASH FLOW PROJECTIONS>>'!H13+'<<CASH FLOW PROJECTIONS>>FLTE'!H13 -> 0 | I13: ='<<CASH FLOW PROJECTIONS>>'!I13+'<<CASH FLOW PROJECTIONS>>FLTE'!I13 -> 0 | J13: ='<<CASH FLOW PROJECTIONS>>'!J13+'<<CASH FLOW PROJECTIONS>>FLTE'!J13 -> 0 | ... BR13: ='<<CASH FLOW PROJECTIONS>>'!BR13+'<<CASH FLOW PROJECTIONS>>FLTE'!BR13 -> 0
B14: Subscription Revenue | C14: ='<<CASH FLOW PROJECTIONS>>'!C14+'<<CASH FLOW PROJECTIONS>>FLTE'!C14 -> 0 | D14: ='<<CASH FLOW PROJECTIONS>>'!D14+'<<CASH FLOW PROJECTIONS>>FLTE'!D14 -> 0 | E14: ='<<CASH FLOW PROJECTIONS>>'!E14+'<<CASH FLOW PROJECTIONS>>FLTE'!E14 -> 0 | F14: ='<<CASH FLOW PROJECTIONS>>'!F14+'<<CASH FLOW PROJECTIONS>>FLTE'!F14 -> 0 | G14: ='<<CASH FLOW PROJECTIONS>>'!G14+'<<CASH FLOW PROJECTIONS>>FLTE'!G14 -> 0 | H14: ='<<CASH FLOW PROJECTIONS>>'!H14+'<<CASH FLOW PROJECTIONS>>FLTE'!H14 -> 0 | I14: ='<<CASH FLOW PROJECTIONS>>'!I14+'<<CASH FLOW PROJECTIONS>>FLTE'!I14 -> 0 | J14: ='<<CASH FLOW PROJECTIONS>>'!J14+'<<CASH FLOW PROJECTIONS>>FLTE'!J14 -> 0 | ... BR14: ='<<CASH FLOW PROJECTIONS>>'!BR14+'<<CASH FLOW PROJECTIONS>>FLTE'!BR14 -> 1.4321036e+10
B15: OOB Spend Revenue | C15: ='<<CASH FLOW PROJECTIONS>>'!C15+'<<CASH FLOW PROJECTIONS>>FLTE'!C15 -> 0 | D15: ='<<CASH FLOW PROJECTIONS>>'!D15+'<<CASH FLOW PROJECTIONS>>FLTE'!D15 -> 0 | E15: ='<<CASH FLOW PROJECTIONS>>'!E15+'<<CASH FLOW PROJECTIONS>>FLTE'!E15 -> 0 | F15: ='<<CASH FLOW PROJECTIONS>>'!F15+'<<CASH FLOW PROJECTIONS>>FLTE'!F15 -> 0 | G15: ='<<CASH FLOW PROJECTIONS>>'!G15+'<<CASH FLOW PROJECTIONS>>FLTE'!G15 -> 0 | H15: ='<<CASH FLOW PROJECTIONS>>'!H15+'<<CASH FLOW PROJECTIONS>>FLTE'!H15 -> 0 | I15: ='<<CASH FLOW PROJECTIONS>>'!I15+'<<CASH FLOW PROJECTIONS>>FLTE'!I15 -> 0 | J15: ='<<CASH FLOW PROJECTIONS>>'!J15+'<<CASH FLOW PROJECTIONS>>FLTE'!J15 -> 0 | ... BR15: ='<<CASH FLOW PROJECTIONS>>'!BR15+'<<CASH FLOW PROJECTIONS>>FLTE'!BR15 -> 0
B16: Itemized Billing Revenue | C16: ='<<CASH FLOW PROJECTIONS>>'!C16+'<<CASH FLOW PROJECTIONS>>FLTE'!C16 -> 0 | D16: ='<<CASH FLOW PROJECTIONS>>'!D16+'<<CASH FLOW PROJECTIONS>>FLTE'!D16 -> 0 | E16: ='<<CASH FLOW PROJECTIONS>>'!E16+'<<CASH FLOW PROJECTIONS>>FLTE'!E16 -> 0 | F16: ='<<CASH FLOW PROJECTIONS>>'!F16+'<<CASH FLOW PROJECTIONS>>FLTE'!F16 -> 0 | G16: ='<<CASH FLOW PROJECTIONS>>'!G16+'<<CASH FLOW PROJECTIONS>>FLTE'!G16 -> 0 | H16: ='<<CASH FLOW PROJECTIONS>>'!H16+'<<CASH FLOW PROJECTIONS>>FLTE'!H16 -> 0 | I16: ='<<CASH FLOW PROJECTIONS>>'!I16+'<<CASH FLOW PROJECTIONS>>FLTE'!I16 -> 0 | J16: ='<<CASH FLOW PROJECTIONS>>'!J16+'<<CASH FLOW PROJECTIONS>>FLTE'!J16 -> 0 | ... BR16: ='<<CASH FLOW PROJECTIONS>>'!BR16+'<<CASH FLOW PROJECTIONS>>FLTE'!BR16 -> 0
B17: Converged Services Revenue | C17: ='<<CASH FLOW PROJECTIONS>>'!C17+'<<CASH FLOW PROJECTIONS>>FLTE'!C17 -> 0 | D17: ='<<CASH FLOW PROJECTIONS>>'!D17+'<<CASH FLOW PROJECTIONS>>FLTE'!D17 -> 0 | E17: ='<<CASH FLOW PROJECTIONS>>'!E17+'<<CASH FLOW PROJECTIONS>>FLTE'!E17 -> 0 | F17: ='<<CASH FLOW PROJECTIONS>>'!F17+'<<CASH FLOW PROJECTIONS>>FLTE'!F17 -> 0 | G17: ='<<CASH FLOW PROJECTIONS>>'!G17+'<<CASH FLOW PROJECTIONS>>FLTE'!G17 -> 0 | H17: ='<<CASH FLOW PROJECTIONS>>'!H17+'<<CASH FLOW PROJECTIONS>>FLTE'!H17 -> 0 | I17: ='<<CASH FLOW PROJECTIONS>>'!I17+'<<CASH FLOW PROJECTIONS>>FLTE'!I17 -> 0 | J17: ='<<CASH FLOW PROJECTIONS>>'!J17+'<<CASH FLOW PROJECTIONS>>FLTE'!J17 -> 0 | ... BR17: ='<<CASH FLOW PROJECTIONS>>'!BR17+'<<CASH FLOW PROJECTIONS>>FLTE'!BR17 -> 0
B18: Other Services Revenue | C18: ='<<CASH FLOW PROJECTIONS>>'!C18+'<<CASH FLOW PROJECTIONS>>FLTE'!C18 -> 0 | D18: ='<<CASH FLOW PROJECTIONS>>'!D18+'<<CASH FLOW PROJECTIONS>>FLTE'!D18 -> 0 | E18: ='<<CASH FLOW PROJECTIONS>>'!E18+'<<CASH FLOW PROJECTIONS>>FLTE'!E18 -> 0 | F18: ='<<CASH FLOW PROJECTIONS>>'!F18+'<<CASH FLOW PROJECTIONS>>FLTE'!F18 -> 0 | G18: ='<<CASH FLOW PROJECTIONS>>'!G18+'<<CASH FLOW PROJECTIONS>>FLTE'!G18 -> 0 | H18: ='<<CASH FLOW PROJECTIONS>>'!H18+'<<CASH FLOW PROJECTIONS>>FLTE'!H18 -> 0 | I18: ='<<CASH FLOW PROJECTIONS>>'!I18+'<<CASH FLOW PROJECTIONS>>FLTE'!I18 -> 0 | J18: ='<<CASH FLOW PROJECTIONS>>'!J18+'<<CASH FLOW PROJECTIONS>>FLTE'!J18 -> 0 | ... BR18: ='<<CASH FLOW PROJECTIONS>>'!BR18+'<<CASH FLOW PROJECTIONS>>FLTE'!BR18 -> 0
B19: Bundle Recharge Revenue | C19: ='<<CASH FLOW PROJECTIONS>>'!C19+'<<CASH FLOW PROJECTIONS>>FLTE'!C19 -> 0 | D19: ='<<CASH FLOW PROJECTIONS>>'!D19+'<<CASH FLOW PROJECTIONS>>FLTE'!D19 -> 0 | E19: ='<<CASH FLOW PROJECTIONS>>'!E19+'<<CASH FLOW PROJECTIONS>>FLTE'!E19 -> 0 | F19: ='<<CASH FLOW PROJECTIONS>>'!F19+'<<CASH FLOW PROJECTIONS>>FLTE'!F19 -> 0 | G19: ='<<CASH FLOW PROJECTIONS>>'!G19+'<<CASH FLOW PROJECTIONS>>FLTE'!G19 -> 0 | H19: ='<<CASH FLOW PROJECTIONS>>'!H19+'<<CASH FLOW PROJECTIONS>>FLTE'!H19 -> 0 | I19: ='<<CASH FLOW PROJECTIONS>>'!I19+'<<CASH FLOW PROJECTIONS>>FLTE'!I19 -> 0 | J19: ='<<CASH FLOW PROJECTIONS>>'!J19+'<<CASH FLOW PROJECTIONS>>FLTE'!J19 -> 0 | ... BR19: ='<<CASH FLOW PROJECTIONS>>'!BR19+'<<CASH FLOW PROJECTIONS>>FLTE'!BR19 -> 0
B20: Direct Costs | C20: =SUM(C21:C36) -> 0 | D20: =SUM(D21:D36) -> 0 | E20: =SUM(E21:E36) -> 0 | F20: =SUM(F21:F36) -> 0 | G20: =SUM(G21:G36) -> 0 | H20: =SUM(H21:H36) -> 0 | I20: =SUM(I21:I36) -> 0 | J20: =SUM(J21:J36) -> 135004800 | ... BR20: =SUM(BR21:BR36) -> 1.136693e+10
B21: Marketing | C21: ='<<CASH FLOW PROJECTIONS>>'!C21+'<<CASH FLOW PROJECTIONS>>FLTE'!C21 -> 0 | D21: ='<<CASH FLOW PROJECTIONS>>'!D21+'<<CASH FLOW PROJECTIONS>>FLTE'!D21 -> 0 | E21: ='<<CASH FLOW PROJECTIONS>>'!E21+'<<CASH FLOW PROJECTIONS>>FLTE'!E21 -> 0 | F21: ='<<CASH FLOW PROJECTIONS>>'!F21+'<<CASH FLOW PROJECTIONS>>FLTE'!F21 -> 0 | G21: ='<<CASH FLOW PROJECTIONS>>'!G21+'<<CASH FLOW PROJECTIONS>>FLTE'!G21 -> 0 | H21: ='<<CASH FLOW PROJECTIONS>>'!H21+'<<CASH FLOW PROJECTIONS>>FLTE'!H21 -> 0 | I21: ='<<CASH FLOW PROJECTIONS>>'!I21+'<<CASH FLOW PROJECTIONS>>FLTE'!I21 -> 0 | J21: ='<<CASH FLOW PROJECTIONS>>'!J21+'<<CASH FLOW PROJECTIONS>>FLTE'!J21 -> 0 | ... BR21: ='<<CASH FLOW PROJECTIONS>>'!BR21+'<<CASH FLOW PROJECTIONS>>FLTE'!BR21 -> 3.2359978e+08
B22: Logistics (3PL & Courier) | C22: ='<<CASH FLOW PROJECTIONS>>'!C22+'<<CASH FLOW PROJECTIONS>>FLTE'!C22 -> 0 | D22: ='<<CASH FLOW PROJECTIONS>>'!D22+'<<CASH FLOW PROJECTIONS>>FLTE'!D22 -> 0 | E22: ='<<CASH FLOW PROJECTIONS>>'!E22+'<<CASH FLOW PROJECTIONS>>FLTE'!E22 -> 0 | F22: ='<<CASH FLOW PROJECTIONS>>'!F22+'<<CASH FLOW PROJECTIONS>>FLTE'!F22 -> 0 | G22: ='<<CASH FLOW PROJECTIONS>>'!G22+'<<CASH FLOW PROJECTIONS>>FLTE'!G22 -> 0 | H22: ='<<CASH FLOW PROJECTIONS>>'!H22+'<<CASH FLOW PROJECTIONS>>FLTE'!H22 -> 0 | I22: ='<<CASH FLOW PROJECTIONS>>'!I22+'<<CASH FLOW PROJECTIONS>>FLTE'!I22 -> 0 | J22: ='<<CASH FLOW PROJECTIONS>>'!J22+'<<CASH FLOW PROJECTIONS>>FLTE'!J22 -> 22500000 | ... BR22: ='<<CASH FLOW PROJECTIONS>>'!BR22+'<<CASH FLOW PROJECTIONS>>FLTE'!BR22 -> 31516560
B23: SIM Cards | C23: ='<<CASH FLOW PROJECTIONS>>'!C23+'<<CASH FLOW PROJECTIONS>>FLTE'!C23 -> 0 | D23: ='<<CASH FLOW PROJECTIONS>>'!D23+'<<CASH FLOW PROJECTIONS>>FLTE'!D23 -> 0 | E23: ='<<CASH FLOW PROJECTIONS>>'!E23+'<<CASH FLOW PROJECTIONS>>FLTE'!E23 -> 0 | F23: ='<<CASH FLOW PROJECTIONS>>'!F23+'<<CASH FLOW PROJECTIONS>>FLTE'!F23 -> 0 | G23: ='<<CASH FLOW PROJECTIONS>>'!G23+'<<CASH FLOW PROJECTIONS>>FLTE'!G23 -> 0 | H23: ='<<CASH FLOW PROJECTIONS>>'!H23+'<<CASH FLOW PROJECTIONS>>FLTE'!H23 -> 0 | I23: ='<<CASH FLOW PROJECTIONS>>'!I23+'<<CASH FLOW PROJECTIONS>>FLTE'!I23 -> 0 | J23: ='<<CASH FLOW PROJECTIONS>>'!J23+'<<CASH FLOW PROJECTIONS>>FLTE'!J23 -> 112504800 | ... BR23: ='<<CASH FLOW PROJECTIONS>>'!BR23+'<<CASH FLOW PROJECTIONS>>FLTE'!BR23 -> 157500000
B24: Cash Sale Device Costs | C24: ='<<CASH FLOW PROJECTIONS>>'!C24+'<<CASH FLOW PROJECTIONS>>FLTE'!C24 -> 0 | D24: ='<<CASH FLOW PROJECTIONS>>'!D24+'<<CASH FLOW PROJECTIONS>>FLTE'!D24 -> 0 | E24: ='<<CASH FLOW PROJECTIONS>>'!E24+'<<CASH FLOW PROJECTIONS>>FLTE'!E24 -> 0 | F24: ='<<CASH FLOW PROJECTIONS>>'!F24+'<<CASH FLOW PROJECTIONS>>FLTE'!F24 -> 0 | G24: ='<<CASH FLOW PROJECTIONS>>'!G24+'<<CASH FLOW PROJECTIONS>>FLTE'!G24 -> 0 | H24: ='<<CASH FLOW PROJECTIONS>>'!H24+'<<CASH FLOW PROJECTIONS>>FLTE'!H24 -> 0 | I24: ='<<CASH FLOW PROJECTIONS>>'!I24+'<<CASH FLOW PROJECTIONS>>FLTE'!I24 -> 0 | J24: ='<<CASH FLOW PROJECTIONS>>'!J24+'<<CASH FLOW PROJECTIONS>>FLTE'!J24 -> 0 | ... BR24: ='<<CASH FLOW PROJECTIONS>>'!BR24+'<<CASH FLOW PROJECTIONS>>FLTE'!BR24 -> 0
B25: Credit Device Costs | C25: ='<<CASH FLOW PROJECTIONS>>'!C25+'<<CASH FLOW PROJECTIONS>>FLTE'!C25 -> 0 | D25: ='<<CASH FLOW PROJECTIONS>>'!D25+'<<CASH FLOW PROJECTIONS>>FLTE'!D25 -> 0 | E25: ='<<CASH FLOW PROJECTIONS>>'!E25+'<<CASH FLOW PROJECTIONS>>FLTE'!E25 -> 0 | F25: ='<<CASH FLOW PROJECTIONS>>'!F25+'<<CASH FLOW PROJECTIONS>>FLTE'!F25 -> 0 | G25: ='<<CASH FLOW PROJECTIONS>>'!G25+'<<CASH FLOW PROJECTIONS>>FLTE'!G25 -> 0 | H25: ='<<CASH FLOW PROJECTIONS>>'!H25+'<<CASH FLOW PROJECTIONS>>FLTE'!H25 -> 0 | I25: ='<<CASH FLOW PROJECTIONS>>'!I25+'<<CASH FLOW PROJECTIONS>>FLTE'!I25 -> 0 | J25: ='<<CASH FLOW PROJECTIONS>>'!J25+'<<CASH FLOW PROJECTIONS>>FLTE'!J25 -> 0 | ... BR25: ='<<CASH FLOW PROJECTIONS>>'!BR25+'<<CASH FLOW PROJECTIONS>>FLTE'!BR25 -> 0
B26: Upgrade Costs | C26: ='<<CASH FLOW PROJECTIONS>>'!C26+'<<CASH FLOW PROJECTIONS>>FLTE'!C26 -> 0 | D26: ='<<CASH FLOW PROJECTIONS>>'!D26+'<<CASH FLOW PROJECTIONS>>FLTE'!D26 -> 0 | E26: ='<<CASH FLOW PROJECTIONS>>'!E26+'<<CASH FLOW PROJECTIONS>>FLTE'!E26 -> 0 | F26: ='<<CASH FLOW PROJECTIONS>>'!F26+'<<CASH FLOW PROJECTIONS>>FLTE'!F26 -> 0 | G26: ='<<CASH FLOW PROJECTIONS>>'!G26+'<<CASH FLOW PROJECTIONS>>FLTE'!G26 -> 0 | H26: ='<<CASH FLOW PROJECTIONS>>'!H26+'<<CASH FLOW PROJECTIONS>>FLTE'!H26 -> 0 | I26: ='<<CASH FLOW PROJECTIONS>>'!I26+'<<CASH FLOW PROJECTIONS>>FLTE'!I26 -> 0 | J26: ='<<CASH FLOW PROJECTIONS>>'!J26+'<<CASH FLOW PROJECTIONS>>FLTE'!J26 -> 0 | ... BR26: ='<<CASH FLOW PROJECTIONS>>'!BR26+'<<CASH FLOW PROJECTIONS>>FLTE'!BR26 -> 0
B27: ='DIRECT COST'!B82 -> Channel Upfront Commissions: CIB | C27: ='<<CASH FLOW PROJECTIONS>>'!C27+'<<CASH FLOW PROJECTIONS>>FLTE'!C27 -> 0 | D27: ='<<CASH FLOW PROJECTIONS>>'!D27+'<<CASH FLOW PROJECTIONS>>FLTE'!D27 -> 0 | E27: ='<<CASH FLOW PROJECTIONS>>'!E27+'<<CASH FLOW PROJECTIONS>>FLTE'!E27 -> 0 | F27: ='<<CASH FLOW PROJECTIONS>>'!F27+'<<CASH FLOW PROJECTIONS>>FLTE'!F27 -> 0 | G27: ='<<CASH FLOW PROJECTIONS>>'!G27+'<<CASH FLOW PROJECTIONS>>FLTE'!G27 -> 0 | H27: ='<<CASH FLOW PROJECTIONS>>'!H27+'<<CASH FLOW PROJECTIONS>>FLTE'!H27 -> 0 | I27: ='<<CASH FLOW PROJECTIONS>>'!I27+'<<CASH FLOW PROJECTIONS>>FLTE'!I27 -> 0 | J27: ='<<CASH FLOW PROJECTIONS>>'!J27+'<<CASH FLOW PROJECTIONS>>FLTE'!J27 -> 0 | ... BR27: ='<<CASH FLOW PROJECTIONS>>'!BR27+'<<CASH FLOW PROJECTIONS>>FLTE'!BR27 -> 7.9245925e+08
B28: ='DIRECT COST'!B83 -> Channel Upfront Commissions: Device | C28: ='<<CASH FLOW PROJECTIONS>>'!C28+'<<CASH FLOW PROJECTIONS>>FLTE'!C28 -> 0 | D28: ='<<CASH FLOW PROJECTIONS>>'!D28+'<<CASH FLOW PROJECTIONS>>FLTE'!D28 -> 0 | E28: ='<<CASH FLOW PROJECTIONS>>'!E28+'<<CASH FLOW PROJECTIONS>>FLTE'!E28 -> 0 | F28: ='<<CASH FLOW PROJECTIONS>>'!F28+'<<CASH FLOW PROJECTIONS>>FLTE'!F28 -> 0 | G28: ='<<CASH FLOW PROJECTIONS>>'!G28+'<<CASH FLOW PROJECTIONS>>FLTE'!G28 -> 0 | H28: ='<<CASH FLOW PROJECTIONS>>'!H28+'<<CASH FLOW PROJECTIONS>>FLTE'!H28 -> 0 | I28: ='<<CASH FLOW PROJECTIONS>>'!I28+'<<CASH FLOW PROJECTIONS>>FLTE'!I28 -> 0 | J28: ='<<CASH FLOW PROJECTIONS>>'!J28+'<<CASH FLOW PROJECTIONS>>FLTE'!J28 -> 0 | ... BR28: ='<<CASH FLOW PROJECTIONS>>'!BR28+'<<CASH FLOW PROJECTIONS>>FLTE'!BR28 -> 0
B29: ='DIRECT COST'!B84 -> Channel Ongoing Commission: Subscription | C29: ='<<CASH FLOW PROJECTIONS>>'!C29+'<<CASH FLOW PROJECTIONS>>FLTE'!C29 -> 0 | D29: ='<<CASH FLOW PROJECTIONS>>'!D29+'<<CASH FLOW PROJECTIONS>>FLTE'!D29 -> 0 | E29: ='<<CASH FLOW PROJECTIONS>>'!E29+'<<CASH FLOW PROJECTIONS>>FLTE'!E29 -> 0 | F29: ='<<CASH FLOW PROJECTIONS>>'!F29+'<<CASH FLOW PROJECTIONS>>FLTE'!F29 -> 0 | G29: ='<<CASH FLOW PROJECTIONS>>'!G29+'<<CASH FLOW PROJECTIONS>>FLTE'!G29 -> 0 | H29: ='<<CASH FLOW PROJECTIONS>>'!H29+'<<CASH FLOW PROJECTIONS>>FLTE'!H29 -> 0 | I29: ='<<CASH FLOW PROJECTIONS>>'!I29+'<<CASH FLOW PROJECTIONS>>FLTE'!I29 -> 0 | J29: ='<<CASH FLOW PROJECTIONS>>'!J29+'<<CASH FLOW PROJECTIONS>>FLTE'!J29 -> 0 | ... BR29: ='<<CASH FLOW PROJECTIONS>>'!BR29+'<<CASH FLOW PROJECTIONS>>FLTE'!BR29 -> 0
B30: ='DIRECT COST'!B85 -> Channel Ongoing Commission: Ongoing | C30: ='<<CASH FLOW PROJECTIONS>>'!C30+'<<CASH FLOW PROJECTIONS>>FLTE'!C30 -> 0 | D30: ='<<CASH FLOW PROJECTIONS>>'!D30+'<<CASH FLOW PROJECTIONS>>FLTE'!D30 -> 0 | E30: ='<<CASH FLOW PROJECTIONS>>'!E30+'<<CASH FLOW PROJECTIONS>>FLTE'!E30 -> 0 | F30: ='<<CASH FLOW PROJECTIONS>>'!F30+'<<CASH FLOW PROJECTIONS>>FLTE'!F30 -> 0 | G30: ='<<CASH FLOW PROJECTIONS>>'!G30+'<<CASH FLOW PROJECTIONS>>FLTE'!G30 -> 0 | H30: ='<<CASH FLOW PROJECTIONS>>'!H30+'<<CASH FLOW PROJECTIONS>>FLTE'!H30 -> 0 | I30: ='<<CASH FLOW PROJECTIONS>>'!I30+'<<CASH FLOW PROJECTIONS>>FLTE'!I30 -> 0 | J30: ='<<CASH FLOW PROJECTIONS>>'!J30+'<<CASH FLOW PROJECTIONS>>FLTE'!J30 -> 0 | ... BR30: ='<<CASH FLOW PROJECTIONS>>'!BR30+'<<CASH FLOW PROJECTIONS>>FLTE'!BR30 -> 0
B31: Itemized Billing Costs | C31: ='<<CASH FLOW PROJECTIONS>>'!C31+'<<CASH FLOW PROJECTIONS>>FLTE'!C31 -> 0 | D31: ='<<CASH FLOW PROJECTIONS>>'!D31+'<<CASH FLOW PROJECTIONS>>FLTE'!D31 -> 0 | E31: ='<<CASH FLOW PROJECTIONS>>'!E31+'<<CASH FLOW PROJECTIONS>>FLTE'!E31 -> 0 | F31: ='<<CASH FLOW PROJECTIONS>>'!F31+'<<CASH FLOW PROJECTIONS>>FLTE'!F31 -> 0 | G31: ='<<CASH FLOW PROJECTIONS>>'!G31+'<<CASH FLOW PROJECTIONS>>FLTE'!G31 -> 0 | H31: ='<<CASH FLOW PROJECTIONS>>'!H31+'<<CASH FLOW PROJECTIONS>>FLTE'!H31 -> 0 | I31: ='<<CASH FLOW PROJECTIONS>>'!I31+'<<CASH FLOW PROJECTIONS>>FLTE'!I31 -> 0 | J31: ='<<CASH FLOW PROJECTIONS>>'!J31+'<<CASH FLOW PROJECTIONS>>FLTE'!J31 -> 0 | ... BR31: ='<<CASH FLOW PROJECTIONS>>'!BR31+'<<CASH FLOW PROJECTIONS>>FLTE'!BR31 -> 0
B32: Converged Services Costs | C32: ='<<CASH FLOW PROJECTIONS>>'!C32+'<<CASH FLOW PROJECTIONS>>FLTE'!C32 -> 0 | D32: ='<<CASH FLOW PROJECTIONS>>'!D32+'<<CASH FLOW PROJECTIONS>>FLTE'!D32 -> 0 | E32: ='<<CASH FLOW PROJECTIONS>>'!E32+'<<CASH FLOW PROJECTIONS>>FLTE'!E32 -> 0 | F32: ='<<CASH FLOW PROJECTIONS>>'!F32+'<<CASH FLOW PROJECTIONS>>FLTE'!F32 -> 0 | G32: ='<<CASH FLOW PROJECTIONS>>'!G32+'<<CASH FLOW PROJECTIONS>>FLTE'!G32 -> 0 | H32: ='<<CASH FLOW PROJECTIONS>>'!H32+'<<CASH FLOW PROJECTIONS>>FLTE'!H32 -> 0 | I32: ='<<CASH FLOW PROJECTIONS>>'!I32+'<<CASH FLOW PROJECTIONS>>FLTE'!I32 -> 0 | J32: ='<<CASH FLOW PROJECTIONS>>'!J32+'<<CASH FLOW PROJECTIONS>>FLTE'!J32 -> 0 | ... BR32: ='<<CASH FLOW PROJECTIONS>>'!BR32+'<<CASH FLOW PROJECTIONS>>FLTE'!BR32 -> 0
B33: Other Services Costs | C33: ='<<CASH FLOW PROJECTIONS>>'!C33+'<<CASH FLOW PROJECTIONS>>FLTE'!C33 -> 0 | D33: ='<<CASH FLOW PROJECTIONS>>'!D33+'<<CASH FLOW PROJECTIONS>>FLTE'!D33 -> 0 | E33: ='<<CASH FLOW PROJECTIONS>>'!E33+'<<CASH FLOW PROJECTIONS>>FLTE'!E33 -> 0 | F33: ='<<CASH FLOW PROJECTIONS>>'!F33+'<<CASH FLOW PROJECTIONS>>FLTE'!F33 -> 0 | G33: ='<<CASH FLOW PROJECTIONS>>'!G33+'<<CASH FLOW PROJECTIONS>>FLTE'!G33 -> 0 | H33: ='<<CASH FLOW PROJECTIONS>>'!H33+'<<CASH FLOW PROJECTIONS>>FLTE'!H33 -> 0 | I33: ='<<CASH FLOW PROJECTIONS>>'!I33+'<<CASH FLOW PROJECTIONS>>FLTE'!I33 -> 0 | J33: ='<<CASH FLOW PROJECTIONS>>'!J33+'<<CASH FLOW PROJECTIONS>>FLTE'!J33 -> 0 | ... BR33: ='<<CASH FLOW PROJECTIONS>>'!BR33+'<<CASH FLOW PROJECTIONS>>FLTE'!BR33 -> 0
B34: Wholesale Costs | C34: ='<<CASH FLOW PROJECTIONS>>'!C34+'<<CASH FLOW PROJECTIONS>>FLTE'!C34 -> 0 | D34: ='<<CASH FLOW PROJECTIONS>>'!D34+'<<CASH FLOW PROJECTIONS>>FLTE'!D34 -> 0 | E34: ='<<CASH FLOW PROJECTIONS>>'!E34+'<<CASH FLOW PROJECTIONS>>FLTE'!E34 -> 0 | F34: ='<<CASH FLOW PROJECTIONS>>'!F34+'<<CASH FLOW PROJECTIONS>>FLTE'!F34 -> 0 | G34: ='<<CASH FLOW PROJECTIONS>>'!G34+'<<CASH FLOW PROJECTIONS>>FLTE'!G34 -> 0 | H34: ='<<CASH FLOW PROJECTIONS>>'!H34+'<<CASH FLOW PROJECTIONS>>FLTE'!H34 -> 0 | I34: ='<<CASH FLOW PROJECTIONS>>'!I34+'<<CASH FLOW PROJECTIONS>>FLTE'!I34 -> 0 | J34: ='<<CASH FLOW PROJECTIONS>>'!J34+'<<CASH FLOW PROJECTIONS>>FLTE'!J34 -> 0 | ... BR34: ='<<CASH FLOW PROJECTIONS>>'!BR34+'<<CASH FLOW PROJECTIONS>>FLTE'!BR34 -> 7.2167615e+09
B35: MVNE Cost per Subscriber | C35: ='<<CASH FLOW PROJECTIONS>>'!C35+'<<CASH FLOW PROJECTIONS>>FLTE'!C35 -> 0 | D35: ='<<CASH FLOW PROJECTIONS>>'!D35+'<<CASH FLOW PROJECTIONS>>FLTE'!D35 -> 0 | E35: ='<<CASH FLOW PROJECTIONS>>'!E35+'<<CASH FLOW PROJECTIONS>>FLTE'!E35 -> 0 | F35: ='<<CASH FLOW PROJECTIONS>>'!F35+'<<CASH FLOW PROJECTIONS>>FLTE'!F35 -> 0 | G35: ='<<CASH FLOW PROJECTIONS>>'!G35+'<<CASH FLOW PROJECTIONS>>FLTE'!G35 -> 0 | H35: ='<<CASH FLOW PROJECTIONS>>'!H35+'<<CASH FLOW PROJECTIONS>>FLTE'!H35 -> 0 | I35: ='<<CASH FLOW PROJECTIONS>>'!I35+'<<CASH FLOW PROJECTIONS>>FLTE'!I35 -> 0 | J35: ='<<CASH FLOW PROJECTIONS>>'!J35+'<<CASH FLOW PROJECTIONS>>FLTE'!J35 -> 0 | ... BR35: ='<<CASH FLOW PROJECTIONS>>'!BR35+'<<CASH FLOW PROJECTIONS>>FLTE'!BR35 -> 2.409954e+09
B36: Customer Care Costs | C36: ='<<CASH FLOW PROJECTIONS>>'!C36+'<<CASH FLOW PROJECTIONS>>FLTE'!C36 -> 0 | D36: ='<<CASH FLOW PROJECTIONS>>'!D36+'<<CASH FLOW PROJECTIONS>>FLTE'!D36 -> 0 | E36: ='<<CASH FLOW PROJECTIONS>>'!E36+'<<CASH FLOW PROJECTIONS>>FLTE'!E36 -> 0 | F36: ='<<CASH FLOW PROJECTIONS>>'!F36+'<<CASH FLOW PROJECTIONS>>FLTE'!F36 -> 0 | G36: ='<<CASH FLOW PROJECTIONS>>'!G36+'<<CASH FLOW PROJECTIONS>>FLTE'!G36 -> 0 | H36: ='<<CASH FLOW PROJECTIONS>>'!H36+'<<CASH FLOW PROJECTIONS>>FLTE'!H36 -> 0 | I36: ='<<CASH FLOW PROJECTIONS>>'!I36+'<<CASH FLOW PROJECTIONS>>FLTE'!I36 -> 0 | J36: ='<<CASH FLOW PROJECTIONS>>'!J36+'<<CASH FLOW PROJECTIONS>>FLTE'!J36 -> 0 | ... BR36: ='<<CASH FLOW PROJECTIONS>>'!BR36+'<<CASH FLOW PROJECTIONS>>FLTE'!BR36 -> 4.3513838e+08
B37: Gross Profit | C37: =C8-C20 -> 0 | D37: =D8-D20 -> 0 | E37: =E8-E20 -> 0 | F37: =F8-F20 -> 0 | G37: =G8-G20 -> 0 | H37: =H8-H20 -> 0 | I37: =I8-I20 -> 0 | J37: =J8-J20 -> -135004800 | ... BR37: =BR8-BR20 -> 2.9549112e+09
B38: Gross Profit Percentage (%) | C38: =IF(C37>0,C37/C8,0) -> 0 | D38: =IF(D37>0,D37/D8,0) -> 0 | E38: =IF(E37>0,E37/E8,0) -> 0 | F38: =IF(F37>0,F37/F8,0) -> 0 | G38: =IF(G37>0,G37/G8,0) -> 0 | H38: =IF(H37>0,H37/H8,0) -> 0 | I38: =IF(I37>0,I37/I8,0) -> 0 | J38: =IF(J37>0,J37/J8,0) -> 0 | ... BR38: =IF(BR37>0,BR37/BR8,0) -> 0.20632203
B39: Operational Expenditure | C39: =SUM(C40:C44) -> 1608000000 | D39: =SUM(D40:D44) -> 0 | E39: =SUM(E40:E44) -> 0 | F39: =SUM(F40:F44) -> 48000000 | G39: =SUM(G40:G44) -> 60000000 | H39: =SUM(H40:H44) -> 48000000 | I39: =SUM(I40:I44) -> 81000000 | J39: =SUM(J40:J44) -> 81000000 | ... BR39: =SUM(BR40:BR44) -> 2.5265515e+08
B40: Facilities Costs | C40: ='<<CASH FLOW PROJECTIONS>>'!C41+'<<CASH FLOW PROJECTIONS>>FLTE'!C40 -> 0 | D40: ='<<CASH FLOW PROJECTIONS>>'!D41+'<<CASH FLOW PROJECTIONS>>FLTE'!D40 -> 0 | E40: ='<<CASH FLOW PROJECTIONS>>'!E41+'<<CASH FLOW PROJECTIONS>>FLTE'!E40 -> 0 | F40: ='<<CASH FLOW PROJECTIONS>>'!F41+'<<CASH FLOW PROJECTIONS>>FLTE'!F40 -> 0 | G40: ='<<CASH FLOW PROJECTIONS>>'!G41+'<<CASH FLOW PROJECTIONS>>FLTE'!G40 -> 0 | H40: ='<<CASH FLOW PROJECTIONS>>'!H41+'<<CASH FLOW PROJECTIONS>>FLTE'!H40 -> 0 | I40: ='<<CASH FLOW PROJECTIONS>>'!I41+'<<CASH FLOW PROJECTIONS>>FLTE'!I40 -> 0 | J40: ='<<CASH FLOW PROJECTIONS>>'!J41+'<<CASH FLOW PROJECTIONS>>FLTE'!J40 -> 0 | ... BR40: ='<<CASH FLOW PROJECTIONS>>'!BR41+'<<CASH FLOW PROJECTIONS>>FLTE'!BR40 -> 0
B41: Regulatory Costs | C41: ='<<CASH FLOW PROJECTIONS>>'!C42+'<<CASH FLOW PROJECTIONS>>FLTE'!C41 -> 1608000000 | D41: ='<<CASH FLOW PROJECTIONS>>'!D42+'<<CASH FLOW PROJECTIONS>>FLTE'!D41 -> 0 | E41: ='<<CASH FLOW PROJECTIONS>>'!E42+'<<CASH FLOW PROJECTIONS>>FLTE'!E41 -> 0 | F41: ='<<CASH FLOW PROJECTIONS>>'!F42+'<<CASH FLOW PROJECTIONS>>FLTE'!F41 -> 0 | G41: ='<<CASH FLOW PROJECTIONS>>'!G42+'<<CASH FLOW PROJECTIONS>>FLTE'!G41 -> 0 | H41: ='<<CASH FLOW PROJECTIONS>>'!H42+'<<CASH FLOW PROJECTIONS>>FLTE'!H41 -> 0 | I41: ='<<CASH FLOW PROJECTIONS>>'!I42+'<<CASH FLOW PROJECTIONS>>FLTE'!I41 -> 0 | J41: ='<<CASH FLOW PROJECTIONS>>'!J42+'<<CASH FLOW PROJECTIONS>>FLTE'!J41 -> 0 | ... BR41: ='<<CASH FLOW PROJECTIONS>>'!BR42+'<<CASH FLOW PROJECTIONS>>FLTE'!BR41 -> 1.4289452e+08
B42: Resource Costs | C42: ='<<CASH FLOW PROJECTIONS>>'!C43+'<<CASH FLOW PROJECTIONS>>FLTE'!C42 -> 0 | D42: ='<<CASH FLOW PROJECTIONS>>'!D43+'<<CASH FLOW PROJECTIONS>>FLTE'!D42 -> 0 | E42: ='<<CASH FLOW PROJECTIONS>>'!E43+'<<CASH FLOW PROJECTIONS>>FLTE'!E42 -> 0 | F42: ='<<CASH FLOW PROJECTIONS>>'!F43+'<<CASH FLOW PROJECTIONS>>FLTE'!F42 -> 48000000 | G42: ='<<CASH FLOW PROJECTIONS>>'!G43+'<<CASH FLOW PROJECTIONS>>FLTE'!G42 -> 48000000 | H42: ='<<CASH FLOW PROJECTIONS>>'!H43+'<<CASH FLOW PROJECTIONS>>FLTE'!H42 -> 48000000 | I42: ='<<CASH FLOW PROJECTIONS>>'!I43+'<<CASH FLOW PROJECTIONS>>FLTE'!I42 -> 81000000 | J42: ='<<CASH FLOW PROJECTIONS>>'!J43+'<<CASH FLOW PROJECTIONS>>FLTE'!J42 -> 81000000 | ... BR42: ='<<CASH FLOW PROJECTIONS>>'!BR43+'<<CASH FLOW PROJECTIONS>>FLTE'!BR42 -> 1.0226063e+08
B43: 3rd Party Vendors & Supplier Costs | C43: ='<<CASH FLOW PROJECTIONS>>'!C44+'<<CASH FLOW PROJECTIONS>>FLTE'!C43 -> 0 | D43: ='<<CASH FLOW PROJECTIONS>>'!D44+'<<CASH FLOW PROJECTIONS>>FLTE'!D43 -> 0 | E43: ='<<CASH FLOW PROJECTIONS>>'!E44+'<<CASH FLOW PROJECTIONS>>FLTE'!E43 -> 0 | F43: ='<<CASH FLOW PROJECTIONS>>'!F44+'<<CASH FLOW PROJECTIONS>>FLTE'!F43 -> 0 | G43: ='<<CASH FLOW PROJECTIONS>>'!G44+'<<CASH FLOW PROJECTIONS>>FLTE'!G43 -> 12000000 | H43: ='<<CASH FLOW PROJECTIONS>>'!H44+'<<CASH FLOW PROJECTIONS>>FLTE'!H43 -> 0 | I43: ='<<CASH FLOW PROJECTIONS>>'!I44+'<<CASH FLOW PROJECTIONS>>FLTE'!I43 -> 0 | J43: ='<<CASH FLOW PROJECTIONS>>'!J44+'<<CASH FLOW PROJECTIONS>>FLTE'!J43 -> 0 | ... BR43: ='<<CASH FLOW PROJECTIONS>>'!BR44+'<<CASH FLOW PROJECTIONS>>FLTE'!BR43 -> 0
B44: Other Costs | C44: ='<<CASH FLOW PROJECTIONS>>'!C45+'<<CASH FLOW PROJECTIONS>>FLTE'!C44 -> 0 | D44: ='<<CASH FLOW PROJECTIONS>>'!D45+'<<CASH FLOW PROJECTIONS>>FLTE'!D44 -> 0 | E44: ='<<CASH FLOW PROJECTIONS>>'!E45+'<<CASH FLOW PROJECTIONS>>FLTE'!E44 -> 0 | F44: ='<<CASH FLOW PROJECTIONS>>'!F45+'<<CASH FLOW PROJECTIONS>>FLTE'!F44 -> 0 | G44: ='<<CASH FLOW PROJECTIONS>>'!G45+'<<CASH FLOW PROJECTIONS>>FLTE'!G44 -> 0 | H44: ='<<CASH FLOW PROJECTIONS>>'!H45+'<<CASH FLOW PROJECTIONS>>FLTE'!H44 -> 0 | I44: ='<<CASH FLOW PROJECTIONS>>'!I45+'<<CASH FLOW PROJECTIONS>>FLTE'!I44 -> 0 | J44: ='<<CASH FLOW PROJECTIONS>>'!J45+'<<CASH FLOW PROJECTIONS>>FLTE'!J44 -> 0 | ... BR44: ='<<CASH FLOW PROJECTIONS>>'!BR45+'<<CASH FLOW PROJECTIONS>>FLTE'!BR44 -> 7500000
B45: EBITDA | C45: =C37-C39 -> -1608000000 | D45: =D37-D39 -> 0 | E45: =E37-E39 -> 0 | F45: =F37-F39 -> -48000000 | G45: =G37-G39 -> -60000000 | H45: =H37-H39 -> -48000000 | I45: =I37-I39 -> -81000000 | J45: =J37-J39 -> -216004800 | ... BR45: =BR37-BR39 -> 2.7022561e+09
B46: Net Margin Percentage (%) | C46: =IF(C45>0,C45/C8,0) -> 0 | D46: =IF(D45>0,D45/D8,0) -> 0 | E46: =IF(E45>0,E45/E8,0) -> 0 | F46: =IF(F45>0,F45/F8,0) -> 0 | G46: =IF(G45>0,G45/G8,0) -> 0 | H46: =IF(H45>0,H45/H8,0) -> 0 | I46: =IF(I45>0,I45/I8,0) -> 0 | J46: =IF(J45>0,J45/J8,0) -> 0 | ... BR46: =IF(BR45>0,BR45/BR8,0) -> 0.18868078
B47: Capital Expenditure | C47: =SUM(C48:C54) -> 40500000 | D47: =SUM(D48:D54) -> 91500000 | E47: =SUM(E48:E54) -> 91500000 | F47: =SUM(F48:F54) -> 103500000 | G47: =SUM(G48:G54) -> 189400000 | H47: =SUM(H48:H54) -> 91900000 | I47: =SUM(I48:I54) -> 500000 | J47: =SUM(J48:J54) -> 0 | ... BR47: =SUM(BR48:BR54) -> 0
B48: Project Team Costs | C48: ='<<CASH FLOW PROJECTIONS>>'!C49+'<<CASH FLOW PROJECTIONS>>FLTE'!C48 -> 40500000 | D48: ='<<CASH FLOW PROJECTIONS>>'!D49+'<<CASH FLOW PROJECTIONS>>FLTE'!D48 -> 40500000 | E48: ='<<CASH FLOW PROJECTIONS>>'!E49+'<<CASH FLOW PROJECTIONS>>FLTE'!E48 -> 40500000 | F48: ='<<CASH FLOW PROJECTIONS>>'!F49+'<<CASH FLOW PROJECTIONS>>FLTE'!F48 -> 40500000 | G48: ='<<CASH FLOW PROJECTIONS>>'!G49+'<<CASH FLOW PROJECTIONS>>FLTE'!G48 -> 40500000 | H48: ='<<CASH FLOW PROJECTIONS>>'!H49+'<<CASH FLOW PROJECTIONS>>FLTE'!H48 -> 40500000 | I48: ='<<CASH FLOW PROJECTIONS>>'!I49+'<<CASH FLOW PROJECTIONS>>FLTE'!I48 -> 0 | J48: ='<<CASH FLOW PROJECTIONS>>'!J49+'<<CASH FLOW PROJECTIONS>>FLTE'!J48 -> 0 | ... BR48: ='<<CASH FLOW PROJECTIONS>>'!BR49+'<<CASH FLOW PROJECTIONS>>FLTE'!BR48 -> 0
B49: Professional Services Fees | C49: ='<<CASH FLOW PROJECTIONS>>'!C50+'<<CASH FLOW PROJECTIONS>>FLTE'!C49 -> 0 | D49: ='<<CASH FLOW PROJECTIONS>>'!D50+'<<CASH FLOW PROJECTIONS>>FLTE'!D49 -> 0 | E49: ='<<CASH FLOW PROJECTIONS>>'!E50+'<<CASH FLOW PROJECTIONS>>FLTE'!E49 -> 0 | F49: ='<<CASH FLOW PROJECTIONS>>'!F50+'<<CASH FLOW PROJECTIONS>>FLTE'!F49 -> 0 | G49: ='<<CASH FLOW PROJECTIONS>>'!G50+'<<CASH FLOW PROJECTIONS>>FLTE'!G49 -> 0 | H49: ='<<CASH FLOW PROJECTIONS>>'!H50+'<<CASH FLOW PROJECTIONS>>FLTE'!H49 -> 0 | I49: ='<<CASH FLOW PROJECTIONS>>'!I50+'<<CASH FLOW PROJECTIONS>>FLTE'!I49 -> 0 | J49: ='<<CASH FLOW PROJECTIONS>>'!J50+'<<CASH FLOW PROJECTIONS>>FLTE'!J49 -> 0 | ... BR49: ='<<CASH FLOW PROJECTIONS>>'!BR50+'<<CASH FLOW PROJECTIONS>>FLTE'!BR49 -> 0
B50: Mvne Platform Customization | C50: ='<<CASH FLOW PROJECTIONS>>'!C51+'<<CASH FLOW PROJECTIONS>>FLTE'!C50 -> 0 | D50: ='<<CASH FLOW PROJECTIONS>>'!D51+'<<CASH FLOW PROJECTIONS>>FLTE'!D50 -> 51000000 | E50: ='<<CASH FLOW PROJECTIONS>>'!E51+'<<CASH FLOW PROJECTIONS>>FLTE'!E50 -> 51000000 | F50: ='<<CASH FLOW PROJECTIONS>>'!F51+'<<CASH FLOW PROJECTIONS>>FLTE'!F50 -> 51000000 | G50: ='<<CASH FLOW PROJECTIONS>>'!G51+'<<CASH FLOW PROJECTIONS>>FLTE'!G50 -> 51400000 | H50: ='<<CASH FLOW PROJECTIONS>>'!H51+'<<CASH FLOW PROJECTIONS>>FLTE'!H50 -> 51400000 | I50: ='<<CASH FLOW PROJECTIONS>>'!I51+'<<CASH FLOW PROJECTIONS>>FLTE'!I50 -> 0 | J50: ='<<CASH FLOW PROJECTIONS>>'!J51+'<<CASH FLOW PROJECTIONS>>FLTE'!J50 -> 0 | ... BR50: ='<<CASH FLOW PROJECTIONS>>'!BR51+'<<CASH FLOW PROJECTIONS>>FLTE'!BR50 -> 0
B51: 3Pl Integration Costs | C51: ='<<CASH FLOW PROJECTIONS>>'!C52+'<<CASH FLOW PROJECTIONS>>FLTE'!C51 -> 0 | D51: ='<<CASH FLOW PROJECTIONS>>'!D52+'<<CASH FLOW PROJECTIONS>>FLTE'!D51 -> 0 | E51: ='<<CASH FLOW PROJECTIONS>>'!E52+'<<CASH FLOW PROJECTIONS>>FLTE'!E51 -> 0 | F51: ='<<CASH FLOW PROJECTIONS>>'!F52+'<<CASH FLOW PROJECTIONS>>FLTE'!F51 -> 0 | G51: ='<<CASH FLOW PROJECTIONS>>'!G52+'<<CASH FLOW PROJECTIONS>>FLTE'!G51 -> 22500000 | H51: ='<<CASH FLOW PROJECTIONS>>'!H52+'<<CASH FLOW PROJECTIONS>>FLTE'!H51 -> 0 | I51: ='<<CASH FLOW PROJECTIONS>>'!I52+'<<CASH FLOW PROJECTIONS>>FLTE'!I51 -> 0 | J51: ='<<CASH FLOW PROJECTIONS>>'!J52+'<<CASH FLOW PROJECTIONS>>FLTE'!J51 -> 0 | ... BR51: ='<<CASH FLOW PROJECTIONS>>'!BR52+'<<CASH FLOW PROJECTIONS>>FLTE'!BR51 -> 0
B52: Credit, Collections & Vetting Implementation Fee | C52: ='<<CASH FLOW PROJECTIONS>>'!C53+'<<CASH FLOW PROJECTIONS>>FLTE'!C52 -> 0 | D52: ='<<CASH FLOW PROJECTIONS>>'!D53+'<<CASH FLOW PROJECTIONS>>FLTE'!D52 -> 0 | E52: ='<<CASH FLOW PROJECTIONS>>'!E53+'<<CASH FLOW PROJECTIONS>>FLTE'!E52 -> 0 | F52: ='<<CASH FLOW PROJECTIONS>>'!F53+'<<CASH FLOW PROJECTIONS>>FLTE'!F52 -> 0 | G52: ='<<CASH FLOW PROJECTIONS>>'!G53+'<<CASH FLOW PROJECTIONS>>FLTE'!G52 -> 0 | H52: ='<<CASH FLOW PROJECTIONS>>'!H53+'<<CASH FLOW PROJECTIONS>>FLTE'!H52 -> 0 | I52: ='<<CASH FLOW PROJECTIONS>>'!I53+'<<CASH FLOW PROJECTIONS>>FLTE'!I52 -> 0 | J52: ='<<CASH FLOW PROJECTIONS>>'!J53+'<<CASH FLOW PROJECTIONS>>FLTE'!J52 -> 0 | ... BR52: ='<<CASH FLOW PROJECTIONS>>'!BR53+'<<CASH FLOW PROJECTIONS>>FLTE'!BR52 -> 0
B53: Call Center Setup | C53: ='<<CASH FLOW PROJECTIONS>>'!C54+'<<CASH FLOW PROJECTIONS>>FLTE'!C53 -> 0 | D53: ='<<CASH FLOW PROJECTIONS>>'!D54+'<<CASH FLOW PROJECTIONS>>FLTE'!D53 -> 0 | E53: ='<<CASH FLOW PROJECTIONS>>'!E54+'<<CASH FLOW PROJECTIONS>>FLTE'!E53 -> 0 | F53: ='<<CASH FLOW PROJECTIONS>>'!F54+'<<CASH FLOW PROJECTIONS>>FLTE'!F53 -> 12000000 | G53: ='<<CASH FLOW PROJECTIONS>>'!G54+'<<CASH FLOW PROJECTIONS>>FLTE'!G53 -> 0 | H53: ='<<CASH FLOW PROJECTIONS>>'!H54+'<<CASH FLOW PROJECTIONS>>FLTE'!H53 -> 0 | I53: ='<<CASH FLOW PROJECTIONS>>'!I54+'<<CASH FLOW PROJECTIONS>>FLTE'!I53 -> 0 | J53: ='<<CASH FLOW PROJECTIONS>>'!J54+'<<CASH FLOW PROJECTIONS>>FLTE'!J53 -> 0 | ... BR53: ='<<CASH FLOW PROJECTIONS>>'!BR54+'<<CASH FLOW PROJECTIONS>>FLTE'!BR53 -> 0
B54: Network Connection & Integration Fees | C54: ='<<CASH FLOW PROJECTIONS>>'!C55+'<<CASH FLOW PROJECTIONS>>FLTE'!C54 -> 0 | D54: ='<<CASH FLOW PROJECTIONS>>'!D55+'<<CASH FLOW PROJECTIONS>>FLTE'!D54 -> 0 | E54: ='<<CASH FLOW PROJECTIONS>>'!E55+'<<CASH FLOW PROJECTIONS>>FLTE'!E54 -> 0 | F54: ='<<CASH FLOW PROJECTIONS>>'!F55+'<<CASH FLOW PROJECTIONS>>FLTE'!F54 -> 0 | G54: ='<<CASH FLOW PROJECTIONS>>'!G55+'<<CASH FLOW PROJECTIONS>>FLTE'!G54 -> 75000000 | H54: ='<<CASH FLOW PROJECTIONS>>'!H55+'<<CASH FLOW PROJECTIONS>>FLTE'!H54 -> 0 | I54: ='<<CASH FLOW PROJECTIONS>>'!I55+'<<CASH FLOW PROJECTIONS>>FLTE'!I54 -> 500000 | J54: ='<<CASH FLOW PROJECTIONS>>'!J55+'<<CASH FLOW PROJECTIONS>>FLTE'!J54 -> 0 | ... BR54: ='<<CASH FLOW PROJECTIONS>>'!BR55+'<<CASH FLOW PROJECTIONS>>FLTE'!BR54 -> 0
B55: Provisions | C55: =SUM(C56:C59) -> 0 | D55: =SUM(D56:D59) -> 0 | E55: =SUM(E56:E59) -> 0 | F55: =SUM(F56:F59) -> 0 | G55: =SUM(G56:G59) -> 0 | H55: =SUM(H56:H59) -> 0 | I55: =SUM(I56:I59) -> 0 | J55: =SUM(J56:J59) -> 0 | ... BR55: =SUM(BR56:BR59) -> 4.8965345e+08
B56: Provisions for Bad Debt | C56: ='<<CASH FLOW PROJECTIONS>>'!C57+'<<CASH FLOW PROJECTIONS>>FLTE'!C56 -> 0 | D56: ='<<CASH FLOW PROJECTIONS>>'!D57+'<<CASH FLOW PROJECTIONS>>FLTE'!D56 -> 0 | E56: ='<<CASH FLOW PROJECTIONS>>'!E57+'<<CASH FLOW PROJECTIONS>>FLTE'!E56 -> 0 | F56: ='<<CASH FLOW PROJECTIONS>>'!F57+'<<CASH FLOW PROJECTIONS>>FLTE'!F56 -> 0 | G56: ='<<CASH FLOW PROJECTIONS>>'!G57+'<<CASH FLOW PROJECTIONS>>FLTE'!G56 -> 0 | H56: ='<<CASH FLOW PROJECTIONS>>'!H57+'<<CASH FLOW PROJECTIONS>>FLTE'!H56 -> 0 | I56: ='<<CASH FLOW PROJECTIONS>>'!I57+'<<CASH FLOW PROJECTIONS>>FLTE'!I56 -> 0 | J56: ='<<CASH FLOW PROJECTIONS>>'!J57+'<<CASH FLOW PROJECTIONS>>FLTE'!J56 -> 0 | ... BR56: ='<<CASH FLOW PROJECTIONS>>'!BR57+'<<CASH FLOW PROJECTIONS>>FLTE'!BR56 -> 4.2965522e+08
B57: Provisions for Fraud | C57: ='<<CASH FLOW PROJECTIONS>>'!C58+'<<CASH FLOW PROJECTIONS>>FLTE'!C57 -> 0 | D57: ='<<CASH FLOW PROJECTIONS>>'!D58+'<<CASH FLOW PROJECTIONS>>FLTE'!D57 -> 0 | E57: ='<<CASH FLOW PROJECTIONS>>'!E58+'<<CASH FLOW PROJECTIONS>>FLTE'!E57 -> 0 | F57: ='<<CASH FLOW PROJECTIONS>>'!F58+'<<CASH FLOW PROJECTIONS>>FLTE'!F57 -> 0 | G57: ='<<CASH FLOW PROJECTIONS>>'!G58+'<<CASH FLOW PROJECTIONS>>FLTE'!G57 -> 0 | H57: ='<<CASH FLOW PROJECTIONS>>'!H58+'<<CASH FLOW PROJECTIONS>>FLTE'!H57 -> 0 | I57: ='<<CASH FLOW PROJECTIONS>>'!I58+'<<CASH FLOW PROJECTIONS>>FLTE'!I57 -> 0 | J57: ='<<CASH FLOW PROJECTIONS>>'!J58+'<<CASH FLOW PROJECTIONS>>FLTE'!J57 -> 0 | ... BR57: ='<<CASH FLOW PROJECTIONS>>'!BR58+'<<CASH FLOW PROJECTIONS>>FLTE'!BR57 -> 323892.62
B58: Provision for Retail Price Erosion | C58: ='<<CASH FLOW PROJECTIONS>>'!C59+'<<CASH FLOW PROJECTIONS>>FLTE'!C58 -> 0 | D58: ='<<CASH FLOW PROJECTIONS>>'!D59+'<<CASH FLOW PROJECTIONS>>FLTE'!D58 -> 0 | E58: ='<<CASH FLOW PROJECTIONS>>'!E59+'<<CASH FLOW PROJECTIONS>>FLTE'!E58 -> 0 | F58: ='<<CASH FLOW PROJECTIONS>>'!F59+'<<CASH FLOW PROJECTIONS>>FLTE'!F58 -> 0 | G58: ='<<CASH FLOW PROJECTIONS>>'!G59+'<<CASH FLOW PROJECTIONS>>FLTE'!G58 -> 0 | H58: ='<<CASH FLOW PROJECTIONS>>'!H59+'<<CASH FLOW PROJECTIONS>>FLTE'!H58 -> 0 | I58: ='<<CASH FLOW PROJECTIONS>>'!I59+'<<CASH FLOW PROJECTIONS>>FLTE'!I58 -> 0 | J58: ='<<CASH FLOW PROJECTIONS>>'!J59+'<<CASH FLOW PROJECTIONS>>FLTE'!J58 -> 0 | ... BR58: ='<<CASH FLOW PROJECTIONS>>'!BR59+'<<CASH FLOW PROJECTIONS>>FLTE'!BR58 -> 59674337
B59: Other Provisions | C59: ='<<CASH FLOW PROJECTIONS>>'!C60+'<<CASH FLOW PROJECTIONS>>FLTE'!C59 -> 0 | D59: ='<<CASH FLOW PROJECTIONS>>'!D60+'<<CASH FLOW PROJECTIONS>>FLTE'!D59 -> 0 | E59: ='<<CASH FLOW PROJECTIONS>>'!E60+'<<CASH FLOW PROJECTIONS>>FLTE'!E59 -> 0 | F59: ='<<CASH FLOW PROJECTIONS>>'!F60+'<<CASH FLOW PROJECTIONS>>FLTE'!F59 -> 0 | G59: ='<<CASH FLOW PROJECTIONS>>'!G60+'<<CASH FLOW PROJECTIONS>>FLTE'!G59 -> 0 | H59: ='<<CASH FLOW PROJECTIONS>>'!H60+'<<CASH FLOW PROJECTIONS>>FLTE'!H59 -> 0 | I59: ='<<CASH FLOW PROJECTIONS>>'!I60+'<<CASH FLOW PROJECTIONS>>FLTE'!I59 -> 0 | J59: ='<<CASH FLOW PROJECTIONS>>'!J60+'<<CASH FLOW PROJECTIONS>>FLTE'!J59 -> 0 | ... BR59: ='<<CASH FLOW PROJECTIONS>>'!BR60+'<<CASH FLOW PROJECTIONS>>FLTE'!BR59 -> 0
B60: EBIT | C60: =C45-C47-C55 -> -1648500000 | D60: =D45-D47-D55 -> -91500000 | E60: =E45-E47-E55 -> -91500000 | F60: =F45-F47-F55 -> -151500000 | G60: =G45-G47-G55 -> -249400000 | H60: =H45-H47-H55 -> -139900000 | I60: =I45-I47-I55 -> -81500000 | J60: =J45-J47-J55 -> -216004800 | ... BR60: =BR45-BR47-BR55 -> 2.2126026e+09
B61: Net Margin Percentage (%) | C61: =IF(C60>0,C60/C8,0) -> 0 | D61: =IF(D60>0,D60/D8,0) -> 0 | E61: =IF(E60>0,E60/E8,0) -> 0 | F61: =IF(F60>0,F60/F8,0) -> 0 | G61: =IF(G60>0,G60/G8,0) -> 0 | H61: =IF(H60>0,H60/H8,0) -> 0 | I61: =IF(I60>0,I60/I8,0) -> 0 | J61: =IF(J60>0,J60/J8,0) -> 0 | ... BR61: =IF(BR60>0,BR60/BR8,0) -> 0.1544915
B62: CUMULATIVE EBIT | C62: =C60 -> -1648500000 | D62: =D60+C62 -> -1740000000 | E62: =E60+D62 -> -1831500000 | F62: =F60+E62 -> -1983000000 | G62: =G60+F62 -> -2232400000 | H62: =H60+G62 -> -2372300000 | I62: =I60+H62 -> -2453800000 | J62: =J60+I62 -> -2669804800 | K62: =K60+J62 -> -3.0130242e+09 | ... BR62: =BR60+BQ62 -> 4.0569124e+10
B64: Cash Flow Positive in Month | C64: =IF(C60>0,C6,"") | D64: =IF(D60>0,D6,"") | E64: =IF(E60>0,E6,"") | F64: =IF(F60>0,F6,"") | G64: =IF(G60>0,G6,"") | H64: =IF(H60>0,H6,"") | I64: =IF(I60>0,I6,"") | J64: =IF(J60>0,J6,"") | ... BR64: =IF(BR60>0,BR6,"") -> 60
B65: Break Even in Month | C65: =IF(C62>0,C6,"") | D65: =IF(D62>0,D6,"") | E65: =IF(E62>0,E6,"") | F65: =IF(F62>0,F6,"") | G65: =IF(G62>0,G6,"") | H65: =IF(H62>0,H6,"") | I65: =IF(I62>0,I6,"") | J65: =IF(J62>0,J6,"") | ... BR65: =IF(BR62>0,BR6,"") -> 60
B67: ARPU | C67: =IF('SUBSCRIBER BASE'!C$79>0,SUM(C68:C72)/'SUBSCRIBER BASE'!C$79,0) -> 0 | D67: =IF('SUBSCRIBER BASE'!D$79>0,SUM(D68:D72)/'SUBSCRIBER BASE'!D$79,0) -> 0 | E67: =IF('SUBSCRIBER BASE'!E$79>0,SUM(E68:E72)/'SUBSCRIBER BASE'!E$79,0) -> 0 | F67: =IF('SUBSCRIBER BASE'!F$79>0,SUM(F68:F72)/'SUBSCRIBER BASE'!F$79,0) -> 0 | G67: =IF('SUBSCRIBER BASE'!G$79>0,SUM(G68:G72)/'SUBSCRIBER BASE'!G$79,0) -> 0 | H67: =IF('SUBSCRIBER BASE'!H$79>0,SUM(H68:H72)/'SUBSCRIBER BASE'!H$79,0) -> 0 | I67: =IF('SUBSCRIBER BASE'!I$79>0,SUM(I68:I72)/'SUBSCRIBER BASE'!I$79,0) -> 0 | J67: =IF('SUBSCRIBER BASE'!J$79>0,SUM(J68:J72)/'SUBSCRIBER BASE'!J$79,0) -> 0 | K67: =IF('SUBSCRIBER BASE'!L$79>0,SUM(K68:K74)/'SUBSCRIBER BASE'!L$79,0) -> 5182.2756 | L67: =IF('SUBSCRIBER BASE'!M$79>0,SUM(L68:L74)/'SUBSCRIBER BASE'!M$79,0) -> 5180.9515 | M67: =IF('SUBSCRIBER BASE'!N$79>0,SUM(M68:M74)/'SUBSCRIBER BASE'!N$79,0) -> 5179.333 | N67: =IF('SUBSCRIBER BASE'!O$79>0,SUM(N68:N74)/'SUBSCRIBER BASE'!O$79,0) -> 5177.7925 | O67: =IF('SUBSCRIBER BASE'!P$79>0,SUM(O68:O74)/'SUBSCRIBER BASE'!P$79,0) -> 5176.5559 | P67: =IF('SUBSCRIBER BASE'!Q$79>0,SUM(P68:P74)/'SUBSCRIBER BASE'!Q$79,0) -> 5175.3537 | Q67: =IF('SUBSCRIBER BASE'!R$79>0,SUM(Q68:Q74)/'SUBSCRIBER BASE'!R$79,0) -> 5173.9325 | R67: =IF('SUBSCRIBER BASE'!S$79>0,SUM(R68:R74)/'SUBSCRIBER BASE'!S$79,0) -> 5172.732 | ... BR67: =IF('SUBSCRIBER BASE'!BS$79>0,SUM(BR68:BR74)/'SUBSCRIBER BASE'!BS$79,0) -> 7138.6385
B68: Device Subscription Revenue | C68: =C13 -> 0 | D68: =D13 -> 0 | E68: =E13 -> 0 | F68: =F13 -> 0 | G68: =G13 -> 0 | H68: =H13 -> 0 | I68: =I13 -> 0 | J68: =J13 -> 0 | ... BR68: =BR13 -> 0
B69: Subscription Revenue | C69: =C14 -> 0 | D69: =D14 -> 0 | E69: =E14 -> 0 | F69: =F14 -> 0 | G69: =G14 -> 0 | H69: =H14 -> 0 | I69: =I14 -> 0 | J69: =J14 -> 0 | ... BR69: =BR14 -> 1.4321036e+10
B70: OOB Spend Revenue | C70: =C15 -> 0 | D70: =D15 -> 0 | E70: =E15 -> 0 | F70: =F15 -> 0 | G70: =G15 -> 0 | H70: =H15 -> 0 | I70: =I15 -> 0 | J70: =J15 -> 0 | ... BR70: =BR15 -> 0
B71: Itemized Billing Revenue | C71: =C16 -> 0 | D71: =D16 -> 0 | E71: =E16 -> 0 | F71: =F16 -> 0 | G71: =G16 -> 0 | H71: =H16 -> 0 | I71: =I16 -> 0 | J71: =J16 -> 0 | ... BR71: =BR16 -> 0
B72: Converged Services Revenue | C72: =C17 -> 0 | D72: =D17 -> 0 | E72: =E17 -> 0 | F72: =F17 -> 0 | G72: =G17 -> 0 | H72: =H17 -> 0 | I72: =I17 -> 0 | J72: =J17 -> 0 | ... BR72: =BR17 -> 0
B73: Other Services Revenue | C73: =C18 -> 0 | D73: =D18 -> 0 | E73: =E18 -> 0 | F73: =F18 -> 0 | G73: =G18 -> 0 | H73: =H18 -> 0 | I73: =I18 -> 0 | J73: =J18 -> 0 | ... BR73: =BR18 -> 0
B74: Bundle Recharge Revenue | C74: =C19 -> 0 | D74: =D19 -> 0 | E74: =E19 -> 0 | F74: =F19 -> 0 | G74: =G19 -> 0 | H74: =H19 -> 0 | I74: =I19 -> 0 | J74: =J19 -> 0 | ... BR74: =BR19 -> 0

Sheet <<VERSIONING NOTES>>
E2: Prepared for: | F2: Metl
C3: PROJECT VERSIONING NOTES | E3: Version: | F3: MVNE Financial Framework Template Metl 20250604 1m
E4: Author: | F4: Edward Wicks
B6: Versioning Notes & Comments | D6: Changed By | E6: Sheet | F6: Cell
B8: 1
B9: 2
B10: 3 | C10: Sections marked with this colour should calculate automatically
B11: 4 | C11: Sections marked with this colour denote input sections
B12: 5
B13: 6
B14: 7
B15: 8
B16: 9
B17: 10
B18: 11
B19: 12
B20: 13
B21: 14
B22: 15
B23: 16
... B32: 25

Sheet <<KEY FINANCIAL INDICATORS>>
B3: =UPPER('<<VERSIONING NOTES>>'!$F$2)&TEXT(" KEY FINANCIAL INDICATORS VERSION ","")&'<<VERSIONING NOTES>>'!$F$3 -> METL KEY FINANCIAL INDICATORS VERSION MVNE Financial Framework Template Metl 20250604 1m | H3: =TEXT("Prepared by ","") -> Prepared by
H4: ='<<VERSIONING NOTES>>'!F4 -> Edward Wicks
C6: Rewards | D6: Projected | E6: Cumulative EBIT | F6: Cash Flow First | G6: Cash Flow First | H6: Cumulative Revenue
C7: Spend | D7: Peak Funding | E7: over 60 Months | F7: Positive in Month | G7: BreakEven in Month | H7: Over 60 Months
C8: ='<<CASH FLOW PROJECTIONS>>'!BT57 -> 1.2981102e+10 | D8: =ABS(MIN('<<CASH FLOW PROJECTIONS>>'!C63:BR63)) -> 9.7724678e+09 | E8: =H23 -> 3.2411041e+10 | F8: =MIN('<<CASH FLOW PROJECTIONS>>'!C65:BR65) -> 25 | G8: =MIN('<<CASH FLOW PROJECTIONS>>'!C66:BR66) -> 39 | H8: =SUM('<<CASH FLOW PROJECTIONS>>'!C8:BR8) -> 4.3270342e+11
C9: =C8*0.00038 -> 4932818.9 | D9: =D8*0.0004 -> 3908987.1 | E9: =E8*0.0004 -> 12964416 | H9: =H8*0.0004 -> 1.7308137e+08
B10: Projections | C10: Project Phase | D10: Year 1 | E10: Year 2 | F10: Year 3 | G10: Year 4 | H10: Year 5
C11: EBITDA Margin | D11: =D16/D12 -> -0.38269923 | E11: =E16/E12 -> -0.065608481 | F11: =F16/F12 -> 0.10885712 | G11: =G16/G12 -> 0.12766081 | H11: =H16/H12 -> 0.17622897
B12: Revenue | C12: =SUM('<<CASH FLOW PROJECTIONS>>'!C8:H8) -> 0 | D12: =SUM('<<CASH FLOW PROJECTIONS>>'!I8:V8) -> 8.7795904e+09 | E12: =SUM('<<CASH FLOW PROJECTIONS>>'!W8:AH8) -> 3.7494868e+10 | F12: =SUM('<<CASH FLOW PROJECTIONS>>'!AI8:AT8) -> 9.592046e+10 | G12: =SUM('<<CASH FLOW PROJECTIONS>>'!AU8:BF8) -> 1.2870861e+11 | H12: =SUM('<<CASH FLOW PROJECTIONS>>'!BG8:BR8) -> 1.6179989e+11
B13: Direct Costs | C13: =SUM('<<CASH FLOW PROJECTIONS>>'!C20:H20) -> 0 | D13: =SUM('<<CASH FLOW PROJECTIONS>>'!I20:V20) -> 1.0827737e+10 | E13: =SUM('<<CASH FLOW PROJECTIONS>>'!W20:AH20) -> 3.845958e+10 | F13: =SUM('<<CASH FLOW PROJECTIONS>>'!AI20:AT20) -> 8.3337491e+10 | G13: =SUM('<<CASH FLOW PROJECTIONS>>'!AU20:BF20) -> 1.0974281e+11 | H13: =SUM('<<CASH FLOW PROJECTIONS>>'!BG20:BR20) -> 1.3035093e+11
B14: Gross Profit | C14: =C12-C13 -> 0 | D14: =D12-D13 -> -2.0481466e+09 | E14: =E12-E13 -> -9.6471264e+08 | F14: =F12-F13 -> 1.2582969e+10 | G14: =G12-G13 -> 1.8965798e+10 | H14: =H12-H13 -> 3.1448954e+10
B15: Operational Expenditure | C15: =SUM('<<CASH FLOW PROJECTIONS>>'!C40:H40) -> 1764000000 | D15: =SUM('<<CASH FLOW PROJECTIONS>>'!I40:V40) -> 1.3117959e+09 | E15: =SUM('<<CASH FLOW PROJECTIONS>>'!W40:AH40) -> 1.4952687e+09 | F15: =SUM('<<CASH FLOW PROJECTIONS>>'!AI40:AT40) -> 2.1413438e+09 | G15: =SUM('<<CASH FLOW PROJECTIONS>>'!AU40:BF40) -> 2.5347536e+09 | H15: =SUM('<<CASH FLOW PROJECTIONS>>'!BG40:BR40) -> 2.9351265e+09
B16: EBITDA | C16: =C14-C15 -> -1764000000 | D16: =D14-D15 -> -3.3599425e+09 | E16: =E14-E15 -> -2.4599813e+09 | F16: =F14-F15 -> 1.0441625e+10 | G16: =G14-G15 -> 1.6431045e+10 | H16: =H14-H15 -> 2.8513828e+10 | I16: =H16/H12 -> 0.17622897
B17: Capital Expenditure | C17: =SUM('<<CASH FLOW PROJECTIONS>>'!C48:H48) -> 607500000 | D17: =SUM('<<CASH FLOW PROJECTIONS>>'!I48:V48) -> 0 | E17: =SUM('<<CASH FLOW PROJECTIONS>>'!W48:AH48) -> 0 | F17: =SUM('<<CASH FLOW PROJECTIONS>>'!AI48:AT48) -> 0 | G17: =SUM('<<CASH FLOW PROJECTIONS>>'!AU48:BF48) -> 0 | H17: =SUM('<<CASH FLOW PROJECTIONS>>'!BG48:BR48) -> 0
B18: Depreciation | C18: 0 | D18: 0 | E18: 0 | F18: 0 | G18: 0 | H18: 0
B19: Provisions | C19: =SUM('<<CASH FLOW PROJECTIONS>>'!C56:H56) -> 0 | D19: =SUM('<<CASH FLOW PROJECTIONS>>'!I56:V56) -> 2.9996934e+08 | E19: =SUM('<<CASH FLOW PROJECTIONS>>'!W56:AH56) -> 1.2810746e+09 | F19: =SUM('<<CASH FLOW PROJECTIONS>>'!AI56:AT56) -> 3.2772824e+09 | G19: =SUM('<<CASH FLOW PROJECTIONS>>'!AU56:BF56) -> 4.3975441e+09 | H19: =SUM('<<CASH FLOW PROJECTIONS>>'!BG56:BR56) -> 5.5281629e+09
B20: EBIT | C20: =C16-C17-C18-C19 -> -2371500000 | D20: =D16-D17-D18-D19 -> -3.6599118e+09 | E20: =E16-E17-E18-E19 -> -3.741056e+09 | F20: =F16-F17-F18-F19 -> 7.1643429e+09 | G20: =G16-G17-G18-G19 -> 1.2033501e+10 | H20: =H16-H17-H18-H19 -> 2.2985665e+10
D21: =D20/'BASIC INPUT ASSUMPTIONS'!D7 -> -24399412 | E21: =E20/'BASIC INPUT ASSUMPTIONS'!D7 -> -24940373 | F21: =F20/'BASIC INPUT ASSUMPTIONS'!D7 -> 47762286 | G21: =G20/'BASIC INPUT ASSUMPTIONS'!D7 -> 80223337 | H21: =H20/'BASIC INPUT ASSUMPTIONS'!D7 -> 1.5323777e+08
D22: =D20/D12 -> -0.4168659 | E22: =E20/E12 -> -0.099775148 | F22: =F20/F12 -> 0.074690456 | G22: =G20/G12 -> 0.093494139 | H22: =H20/H12 -> 0.1420623
B23: CUMULATIVE EBIT | C23: =C20 -> -2371500000 | D23: =D20+C23 -> -6.0314118e+09 | E23: =E20+D23 -> -9.7724678e+09 | F23: =F20+E23 -> -2.6081249e+09 | G23: =G20+F23 -> 9.4253757e+09 | H23: =H20+G23 -> 3.2411041e+10
B24: Value of the Base | D24: =D28*D30*24 -> 3.8142961e+10 | E24: =E28*E30*24 -> 1.1742075e+11 | F24: =F28*F30*24 -> 2.3483591e+11 | G24: =G28*G30*24 -> 2.8443758e+11 | H24: =H28*H30*24 -> 3.4304683e+11
C25: Susbcriber Base | D25: Year 1 | E25: Year 2 | F25: Year 3 | G25: Year 4 | H25: Year 5
C26: =C29 -> Active Base | D26: =D29 -> 307643.96 | E26: =E29 -> 949105.93 | F26: =F29 -> 1509722.3 | G26: =G29 -> 1801279 | H26: =H29 -> 2006129.8
C27: Opening Base | D27: 0 | E27: =D28 -> 307643.96 | F27: =E28 -> 949105.93 | G27: =F28 -> 1509722.3 | H27: =G28 -> 1831455.4 | J27: Acquisition | K27: 0.75
C28: Closing Base | D28: ='SUBSCRIBER BASE'!W79 -> 307643.96 | E28: ='SUBSCRIBER BASE'!AI79 -> 949105.93 | F28: ='SUBSCRIBER BASE'!AU79 -> 1509722.3 | G28: ='SUBSCRIBER BASE'!BG79 -> 1831455.4 | H28: ='SUBSCRIBER BASE'!BS79 -> 2006129.8 | J28: Churn | K28: 0.6 | L28: =K28/12 -> 0.05
C29: Active Base | D29: ='SUBSCRIBER BASE'!W101 -> 307643.96 | E29: ='SUBSCRIBER BASE'!AI101 -> 949105.93 | F29: ='SUBSCRIBER BASE'!AU101 -> 1509722.3 | G29: ='SUBSCRIBER BASE'!BF101 -> 1801279 | H29: ='SUBSCRIBER BASE'!BS101 -> 2006129.8 | J29: Avg GP | K29: ='MVLP DASHBOARD'!G13 -> 0.39899632 | L29: 1.2
C30: Blended ARPU | D30: =AVERAGE('<<CASH FLOW PROJECTIONS>>'!K68:V68) -> 5166.0044 | E30: =AVERAGE('<<CASH FLOW PROJECTIONS>>'!W68:AH68) -> 5154.8844 | F30: =AVERAGE('<<CASH FLOW PROJECTIONS>>'!AI68:AT68) -> 6481.2114 | G30: =AVERAGE('<<CASH FLOW PROJECTIONS>>'!AU68:BF68) -> 6471.1191 | H30: =AVERAGE('<<CASH FLOW PROJECTIONS>>'!BG68:BR68) -> 7124.9716 | J30: Rewards | K30: 0
C31: Blended ARPU | D31: =D30*0.00038 -> 1.9630817 | E31: =E30*0.00038 -> 1.9588561 | F31: =F30*0.00038 -> 2.4628603 | G31: =G30*0.00038 -> 2.4590253 | H31: =H30*0.00038 -> 2.7074892
C32: CAC | D32: =('MVLP DASHBOARD'!C110+'COMMISSION COSTS'!$K$41+'DIRECT COST'!V7+'BASIC INPUT ASSUMPTIONS'!$D$25)*0.0004 -> 3.0161514 | E32: =('MVLP DASHBOARD'!D110+'COMMISSION COSTS'!$K$41+'DIRECT COST'!AH7+'BASIC INPUT ASSUMPTIONS'!$D$25)*0.0004 -> 1.9524939 | F32: =('MVLP DASHBOARD'!E110+'COMMISSION COSTS'!$K$41+'DIRECT COST'!AT7+'BASIC INPUT ASSUMPTIONS'!$D$25)*0.0004 -> 1.9417578 | G32: =('MVLP DASHBOARD'!F110+'COMMISSION COSTS'!$K$41+'DIRECT COST'!BF7+'BASIC INPUT ASSUMPTIONS'!$D$25)*0.0004 -> 1.9063105 | H32: =('MVLP DASHBOARD'!G110+'COMMISSION COSTS'!$K$41+'DIRECT COST'!BR7+'BASIC INPUT ASSUMPTIONS'!$D$25)*0.0004 -> 1.9116012

Sheet <<CASH FLOW PROJECTIONS>>
B3: =UPPER('<<VERSIONING NOTES>>'!$F$2)&TEXT(" CASH FLOW PROJECTIONS VERSION ","")&'<<VERSIONING NOTES>>'!$F$3 -> METL CASH FLOW PROJECTIONS VERSION MVNE Financial Framework Template Metl 20250604 1m | BR3: =TEXT("Prepared by ","") -> Prepared by
BR4: ='<<VERSIONING NOTES>>'!F4 -> Edward Wicks
C6: PM1 | D6: PM2 | E6: PM3 | F6: PM4 | G6: PM5 | H6: PM6 | I6: SL1 | J6: SL2 | K6: 1 | L6: 2 | M6: 3 | N6: 4 | O6: 5 | P6: 6 | Q6: 7 | R6: 8 | S6: 9 | T6: 10 | U6: 11 | V6: 12 | W6: 13 | X6: 14 | Y6: 15 | Z6: 16 | AA6: 17 | AB6: 18 | AC6: 19 | AD6: 20 | AE6: 21 | AF6: 22 | AG6: 23 | AH6: 24 | AI6: 25 | AJ6: 26 | AK6: 27 | AL6: 28 | AM6: 29 | AN6: 30 | AO6: 31 | AP6: 32 | AQ6: 33 | AR6: 34 | AS6: 35 | AT6: 36 | AU6: 37 | AV6: 38 | AW6: 39 | AX6: 40 | AY6: 41 | AZ6: 42 | BA6: 43 | BB6: 44 | BC6: 45 | BD6: 46 | BE6: 47 | BF6: 48 | BG6: 49 | BH6: 50 | BI6: 51 | BJ6: 52 | BK6: 53 | BL6: 54 | BM6: 55 | BN6: 56 | BO6: 57 | BP6: 58 | BQ6: 59 | BR6: 60
BR7: 1.5
B8: Revenue | C8: =SUM(C9:C19) -> 0 | D8: =SUM(D9:D19) -> 0 | E8: =SUM(E9:E19) -> 0 | F8: =SUM(F9:F19) -> 0 | G8: =SUM(G9:G19) -> 0 | H8: =SUM(H9:H19) -> 0 | I8: =SUM(I9:I19) -> 0 | J8: =SUM(J9:J19) -> 0 | ... BR8: =SUM(BR9:BR19) -> 1.4289452e+10 | BT8: =SUM(C8:BS8) -> 4.3270342e+11 | BU8: =BT8/'BASIC INPUT ASSUMPTIONS'!$D$7 -> 2.8846894e+09 | BV8: =BU8*0.1/19 -> 15182576
B9: Connection Fees | C9: =REVENUE!C8 -> 0 | D9: =REVENUE!D8 -> 0 | E9: =REVENUE!E8 -> 0 | F9: =REVENUE!F8 -> 0 | G9: =REVENUE!G8 -> 0 | H9: =REVENUE!H8 -> 0 | I9: =REVENUE!I8 -> 0 | J9: =REVENUE!J8 -> 0 | ... BR9: =REVENUE!BR8 -> 0
B10: Courier Fees | C10: =REVENUE!C19 -> 0 | D10: =REVENUE!D19 -> 0 | E10: =REVENUE!E19 -> 0 | F10: =REVENUE!F19 -> 0 | G10: =REVENUE!G19 -> 0 | H10: =REVENUE!H19 -> 0 | I10: =REVENUE!I19 -> 0 | J10: =REVENUE!J19 -> 0 | ... BR10: =REVENUE!BR19 -> 0
B11: Cash Device Sales Revenue | C11: =REVENUE!C30 -> 0 | D11: =REVENUE!D30 -> 0 | E11: =REVENUE!E30 -> 0 | F11: =REVENUE!F30 -> 0 | G11: =REVENUE!G30 -> 0 | H11: =REVENUE!H30 -> 0 | I11: =REVENUE!I30 -> 0 | J11: =REVENUE!J30 -> 0 | ... BR11: =REVENUE!BR30 -> 0
B12: Credit Device Pay in Revenue | C12: =REVENUE!C41 -> 0 | D12: =REVENUE!D41 -> 0 | E12: =REVENUE!E41 -> 0 | F12: =REVENUE!F41 -> 0 | G12: =REVENUE!G41 -> 0 | H12: =REVENUE!H41 -> 0 | I12: =REVENUE!I41 -> 0 | J12: =REVENUE!J41 -> 0 | ... BR12: =REVENUE!BR41 -> 0
B13: Device Subscription Revenue | C13: =REVENUE!C52 -> 0 | D13: =REVENUE!D52 -> 0 | E13: =REVENUE!E52 -> 0 | F13: =REVENUE!F52 -> 0 | G13: =REVENUE!G52 -> 0 | H13: =REVENUE!H52 -> 0 | I13: =REVENUE!I52 -> 0 | J13: =REVENUE!J52 -> 0 | ... BR13: =REVENUE!BR52 -> 0
B14: Subscription Revenue | C14: =REVENUE!C63 -> 0 | D14: =REVENUE!D63 -> 0 | E14: =REVENUE!E63 -> 0 | F14: =REVENUE!F63 -> 0 | G14: =REVENUE!G63 -> 0 | H14: =REVENUE!H63 -> 0 | I14: =REVENUE!I63 -> 0 | J14: =REVENUE!J63 -> 0 | ... BR14: =REVENUE!BR63 -> 1.4289452e+10
B15: OOB Spend Revenue | C15: =REVENUE!C74 -> 0 | D15: =REVENUE!D74 -> 0 | E15: =REVENUE!E74 -> 0 | F15: =REVENUE!F74 -> 0 | G15: =REVENUE!G74 -> 0 | H15: =REVENUE!H74 -> 0 | I15: =REVENUE!I74 -> 0 | J15: =REVENUE!J74 -> 0 | ... BR15: =REVENUE!BR74 -> 0
B16: Itemized Billing Revenue | C16: =REVENUE!C85 -> 0 | D16: =REVENUE!D85 -> 0 | E16: =REVENUE!E85 -> 0 | F16: =REVENUE!F85 -> 0 | G16: =REVENUE!G85 -> 0 | H16: =REVENUE!H85 -> 0 | I16: =REVENUE!I85 -> 0 | J16: =REVENUE!J85 -> 0 | ... BR16: =REVENUE!BR85 -> 0
B17: Converged Services Revenue | C17: =REVENUE!C96 -> 0 | D17: =REVENUE!D96 -> 0 | E17: =REVENUE!E96 -> 0 | F17: =REVENUE!F96 -> 0 | G17: =REVENUE!G96 -> 0 | H17: =REVENUE!H96 -> 0 | I17: =REVENUE!I96 -> 0 | J17: =REVENUE!J96 -> 0 | ... BR17: =REVENUE!BR96 -> 0
B18: Other Services Revenue | C18: =REVENUE!C107 -> 0 | D18: =REVENUE!D107 -> 0 | E18: =REVENUE!E107 -> 0 | F18: =REVENUE!F107 -> 0 | G18: =REVENUE!G107 -> 0 | H18: =REVENUE!H107 -> 0 | I18: =REVENUE!I107 -> 0 | J18: =REVENUE!J107 -> 0 | ... BR18: =REVENUE!BR107 -> 0
B19: Bundle Recharge Revenue | C19: =REVENUE!C118 -> 0 | D19: =REVENUE!D118 -> 0 | E19: =REVENUE!E118 -> 0 | F19: =REVENUE!F118 -> 0 | G19: =REVENUE!G118 -> 0 | H19: =REVENUE!H118 -> 0 | I19: =REVENUE!I118 -> 0 | J19: =REVENUE!J118 -> 0 | ... BR19: =REVENUE!BR118 -> 0
B20: Costs | C20: =SUM(C21:C36) -> 0 | D20: =SUM(D21:D36) -> 0 | E20: =SUM(E21:E36) -> 0 | F20: =SUM(F21:F36) -> 0 | G20: =SUM(G21:G36) -> 0 | H20: =SUM(H21:H36) -> 0 | I20: =SUM(I21:I37) -> 0 | J20: =SUM(J21:J37) -> 135000000 | K20: =SUM(K21:K37) -> 3.7188809e+08 | L20: =SUM(L21:L37) -> 2.8760795e+08 | M20: =SUM(M21:M37) -> 3.7141736e+08 | N20: =SUM(N21:N37) -> 5.7748656e+08 | O20: =SUM(O21:O37) -> 6.6032702e+08 | P20: =SUM(P21:P37) -> 7.7834701e+08 | ... BR20: =SUM(BR21:BR37) -> 1.1528564e+10 | BT20: =SUM(C20:BS20) -> 3.7271855e+11 | BU20: =BT20/'BASIC INPUT ASSUMPTIONS'!$D$7 -> 2.4847904e+09
B21: Marketing | C21: ='DIRECT COST'!C8 -> 0 | D21: ='DIRECT COST'!D8 -> 0 | E21: ='DIRECT COST'!E8 -> 0 | F21: ='DIRECT COST'!F8 -> 0 | G21: ='DIRECT COST'!G8 -> 0 | H21: ='DIRECT COST'!H8 -> 0 | I21: ='DIRECT COST'!I8 -> 0 | J21: ='DIRECT COST'!J8 -> 0 | ... BR21: ='DIRECT COST'!BR8 -> 3.2359978e+08 | BU21: ,
B22: Logistics (3PL & Courier) | C22: ='DIRECT COST'!C15 -> 0 | D22: ='DIRECT COST'!D15 -> 0 | E22: ='DIRECT COST'!E15 -> 0 | F22: ='DIRECT COST'!F15 -> 0 | G22: ='DIRECT COST'!G15 -> 0 | H22: ='DIRECT COST'!H15 -> 0 | I22: ='DIRECT COST'!I15 -> 0 | J22: ='DIRECT COST'!J15 -> 22500000 | ... BR22: ='DIRECT COST'!BR15 -> 31500000 | BT22: =SUM(C22:BS22) -> 1350000000 | BU22: =BT22/'BASIC INPUT ASSUMPTIONS'!$D$7 -> 9000000
B23: SIM Cards | C23: ='DIRECT COST'!C38 -> 0 | D23: ='DIRECT COST'!D38 -> 0 | E23: ='DIRECT COST'!E38 -> 0 | F23: ='DIRECT COST'!F38 -> 0 | G23: ='DIRECT COST'!G38 -> 0 | H23: ='DIRECT COST'!H38 -> 0 | I23: ='DIRECT COST'!I38 -> 0 | J23: ='DIRECT COST'!J38 -> 112500000 | ... BR23: ='DIRECT COST'!BR38 -> 157500000 | BT23: =SUM(C23:BS23) -> 6750000000 | BU23: =BT23/'BASIC INPUT ASSUMPTIONS'!$D$7 -> 45000000
B24: Cash Sale Device Costs | C24: ='DIRECT COST'!C49 -> 0 | D24: ='DIRECT COST'!D49 -> 0 | E24: ='DIRECT COST'!E49 -> 0 | F24: ='DIRECT COST'!F49 -> 0 | G24: ='DIRECT COST'!G49 -> 0 | H24: ='DIRECT COST'!H49 -> 0 | I24: ='DIRECT COST'!I49 -> 0 | J24: ='DIRECT COST'!J49 -> 0 | ... BR24: ='DIRECT COST'!BR49 -> 0
B25: Credit Device Costs | C25: ='DIRECT COST'!C60 -> 0 | D25: ='DIRECT COST'!D60 -> 0 | E25: ='DIRECT COST'!E60 -> 0 | F25: ='DIRECT COST'!F60 -> 0 | G25: ='DIRECT COST'!G60 -> 0 | H25: ='DIRECT COST'!H60 -> 0 | I25: ='DIRECT COST'!I60 -> 0 | J25: ='DIRECT COST'!J60 -> 0 | ... BR25: ='DIRECT COST'!BR60 -> 0
B26: Upgrade Costs | C26: ='DIRECT COST'!C71 -> 0 | D26: ='DIRECT COST'!D71 -> 0 | E26: ='DIRECT COST'!E71 -> 0 | F26: ='DIRECT COST'!F71 -> 0 | G26: ='DIRECT COST'!G71 -> 0 | H26: ='DIRECT COST'!H71 -> 0 | I26: ='DIRECT COST'!I71 -> 0 | J26: ='DIRECT COST'!J71 -> 0 | ... BR26: ='DIRECT COST'!BR71 -> 0
B27: ='DIRECT COST'!B82 -> Channel Upfront Commissions: CIB | C27: ='DIRECT COST'!C82 -> 0 | D27: ='DIRECT COST'!D82 -> 0 | E27: ='DIRECT COST'!E82 -> 0 | F27: ='DIRECT COST'!F82 -> 0 | G27: ='DIRECT COST'!G82 -> 0 | H27: ='DIRECT COST'!H82 -> 0 | I27: ='DIRECT COST'!I82 -> 0 | ... BR27: ='DIRECT COST'!BR82 -> 7.9199626e+08
B28: ='DIRECT COST'!B83 -> Channel Upfront Commissions: Device | C28: ='DIRECT COST'!C83 -> 0 | D28: ='DIRECT COST'!D83 -> 0 | E28: ='DIRECT COST'!E83 -> 0 | F28: ='DIRECT COST'!F83 -> 0 | G28: ='DIRECT COST'!G83 -> 0 | H28: ='DIRECT COST'!H83 -> 0 | I28: ='DIRECT COST'!I83 -> 0 | ... BR28: ='DIRECT COST'!BR83 -> 0
B29: ='DIRECT COST'!B84 -> Channel Ongoing Commission: Subscription | C29: ='DIRECT COST'!C84 -> 0 | D29: ='DIRECT COST'!D84 -> 0 | E29: ='DIRECT COST'!E84 -> 0 | F29: ='DIRECT COST'!F84 -> 0 | G29: ='DIRECT COST'!G84 -> 0 | H29: ='DIRECT COST'!H84 -> 0 | I29: ='DIRECT COST'!I84 -> 0 | ... BR29: ='DIRECT COST'!BR84 -> 0
B30: ='DIRECT COST'!B85 -> Channel Ongoing Commission: Ongoing | C30: ='DIRECT COST'!C85 -> 0 | D30: ='DIRECT COST'!D85 -> 0 | E30: ='DIRECT COST'!E85 -> 0 | F30: ='DIRECT COST'!F85 -> 0 | G30: ='DIRECT COST'!G85 -> 0 | H30: ='DIRECT COST'!H85 -> 0 | I30: ='DIRECT COST'!I85 -> 0 | ... BR30: ='DIRECT COST'!BR85 -> 0 | BT30: =SUM(C30:BS30) -> 0 | BU30: =BT30/'BASIC INPUT ASSUMPTIONS'!$D$7 -> 0
B31: Itemized Billing Costs | C31: ='DIRECT COST'!C86 -> 0 | D31: ='DIRECT COST'!D86 -> 0 | E31: ='DIRECT COST'!E86 -> 0 | F31: ='DIRECT COST'!F86 -> 0 | G31: ='DIRECT COST'!G86 -> 0 | H31: ='DIRECT COST'!H86 -> 0 | I31: ='DIRECT COST'!I86 -> 0 | J31: ='DIRECT COST'!J86 -> 0 | ... BR31: ='DIRECT COST'!BR86 -> 0
B32: Converged Services Costs | C32: ='DIRECT COST'!C97 -> 0 | D32: ='DIRECT COST'!D97 -> 0 | E32: ='DIRECT COST'!E97 -> 0 | F32: ='DIRECT COST'!F97 -> 0 | G32: ='DIRECT COST'!G97 -> 0 | H32: ='DIRECT COST'!H97 -> 0 | I32: ='DIRECT COST'!I97 -> 0 | J32: ='DIRECT COST'!J97 -> 0 | ... BR32: ='DIRECT COST'!BR97 -> 0
B33: Other Services Costs | C33: ='DIRECT COST'!C108 -> 0 | D33: ='DIRECT COST'!D108 -> 0 | E33: ='DIRECT COST'!E108 -> 0 | F33: ='DIRECT COST'!F108 -> 0 | G33: ='DIRECT COST'!G108 -> 0 | H33: ='DIRECT COST'!H108 -> 0 | I33: ='DIRECT COST'!I108 -> 0 | J33: ='DIRECT COST'!J108 -> 0 | ... BR33: ='DIRECT COST'!BR108 -> 0
B34: Wholesale Costs | C34: ='DIRECT COST'!C119 -> 0 | D34: ='DIRECT COST'!D119 -> 0 | E34: ='DIRECT COST'!E119 -> 0 | F34: ='DIRECT COST'!F119 -> 0 | G34: ='DIRECT COST'!G119 -> 0 | H34: ='DIRECT COST'!H119 -> 0 | I34: ='DIRECT COST'!I119 -> 0 | J34: ='DIRECT COST'!J119 -> 0 | ... BR34: ='DIRECT COST'!BR119 -> 7.2010519e+09 | BT34: =SUM(C34:BS34) -> 2.2164395e+11 | BU34: =BT34/'BASIC INPUT ASSUMPTIONS'!$D$7 -> 1.4776264e+09 | BV34: =BU34/BU8 -> 0.51223065
B35: MVNE Cost per Subscriber | C35: ='DIRECT COST'!C123 -> 0 | D35: ='DIRECT COST'!D123 -> 0 | E35: ='DIRECT COST'!E123 -> 0 | F35: ='DIRECT COST'!F123 -> 0 | G35: ='DIRECT COST'!G123 -> 0 | H35: ='DIRECT COST'!H123 -> 0 | I35: ='DIRECT COST'!I123 -> 0 | J35: ='DIRECT COST'!J123 -> 0 | ... BR35: ='DIRECT COST'!BR123 -> 2.4073558e+09 | BT35: =SUM(C35:BS35) -> 7.9668052e+10 | BU35: =BT35/'BASIC INPUT ASSUMPTIONS'!$D$7 -> 5.3112035e+08
B36: Customer Care Costs | C36: ='DIRECT COST'!C135 -> 0 | D36: ='DIRECT COST'!D135 -> 0 | E36: ='DIRECT COST'!E135 -> 0 | F36: ='DIRECT COST'!F135 -> 0 | G36: ='DIRECT COST'!G135 -> 0 | H36: ='DIRECT COST'!H135 -> 0 | I36: ='DIRECT COST'!I135 -> 0 | J36: ='DIRECT COST'!J135 -> 0 | ... BR36: ='DIRECT COST'!BR135 -> 4.3482864e+08 | BT36: =SUM(C36:BS36) -> 1.4386671e+10 | BU36: =BT36/'BASIC INPUT ASSUMPTIONS'!$D$7 -> 95911143
B37: KYC | C37: ='DIRECT COST'!C146 -> 0 | D37: ='DIRECT COST'!D146 -> 0 | E37: ='DIRECT COST'!E146 -> 0 | F37: ='DIRECT COST'!F146 -> 0 | G37: ='DIRECT COST'!G146 -> 0 | H37: ='DIRECT COST'!H146 -> 0 | I37: ='DIRECT COST'!I146 -> 0 | J37: ='DIRECT COST'!J146 -> 0 | ... BR37: ='DIRECT COST'!BR146 -> 180732000
B38: Gross Profit | C38: =C8-C20 -> 0 | D38: =D8-D20 -> 0 | E38: =E8-E20 -> 0 | F38: =F8-F20 -> 0 | G38: =G8-G20 -> 0 | H38: =H8-H20 -> 0 | I38: =I8-I20 -> 0 | J38: =J8-J20 -> -135000000 | ... BR38: =BR8-BR20 -> 2.7608871e+09 | BS38: =SUM(C38:BR38) -> 5.9984862e+10
B39: Gross Profit Percentage (%) | C39: =IF(C38>0,C38/C8,0) -> 0 | D39: =IF(D38>0,D38/D8,0) -> 0 | E39: =IF(E38>0,E38/E8,0) -> 0 | F39: =IF(F38>0,F38/F8,0) -> 0 | G39: =IF(G38>0,G38/G8,0) -> 0 | H39: =IF(H38>0,H38/H8,0) -> 0 | I39: =IF(I38>0,I38/I8,0) -> 0 | J39: =IF(J38>0,J38/J8,0) -> 0 | ... BR39: =IF(BR38>0,BR38/BR8,0) -> 0.19321155
B40: Operational Expenditure | C40: =SUM(C41:C45) -> 1608000000 | D40: =SUM(D41:D45) -> 0 | E40: =SUM(E41:E45) -> 0 | F40: =SUM(F41:F45) -> 48000000 | G40: =SUM(G41:G45) -> 60000000 | H40: =SUM(H41:H45) -> 48000000 | I40: =SUM(I41:I45) -> 81000000 | J40: =SUM(J41:J45) -> 81000000 | ... BR40: =SUM(BR41:BR45) -> 2.5265515e+08
B41: Facilities Costs | C41: ='OPERATIONAL EXPENDITURE'!C10 -> 0 | D41: ='OPERATIONAL EXPENDITURE'!D10 -> 0 | E41: ='OPERATIONAL EXPENDITURE'!E10 -> 0 | F41: ='OPERATIONAL EXPENDITURE'!F10 -> 0 | G41: ='OPERATIONAL EXPENDITURE'!G10 -> 0 | H41: ='OPERATIONAL EXPENDITURE'!H10 -> 0 | I41: ='OPERATIONAL EXPENDITURE'!I10 -> 0 | J41: ='OPERATIONAL EXPENDITURE'!J10 -> 0 | ... BR41: ='OPERATIONAL EXPENDITURE'!BR10 -> 0 | BT41: =SUM(C41:BS41) -> 0 | BU41: =BT41/'BASIC INPUT ASSUMPTIONS'!$D$7 -> 0
B42: Regulatory Costs | C42: ='OPERATIONAL EXPENDITURE'!C11 -> 1608000000 | D42: ='OPERATIONAL EXPENDITURE'!D11 -> 0 | E42: ='OPERATIONAL EXPENDITURE'!E11 -> 0 | F42: ='OPERATIONAL EXPENDITURE'!F11 -> 0 | G42: ='OPERATIONAL EXPENDITURE'!G11 -> 0 | H42: ='OPERATIONAL EXPENDITURE'!H11 -> 0 | I42: ='OPERATIONAL EXPENDITURE'!I11 -> 0 | J42: ='OPERATIONAL EXPENDITURE'!J11 -> 0 | ... BR42: ='OPERATIONAL EXPENDITURE'!BR11 -> 1.4289452e+08 | BT42: =SUM(C42:BS42) -> 5.9350342e+09 | BU42: =BT42/'BASIC INPUT ASSUMPTIONS'!$D$7 -> 39566894
B43: Resource Costs | C43: ='OPERATIONAL EXPENDITURE'!C12 -> 0 | D43: ='OPERATIONAL EXPENDITURE'!D12 -> 0 | E43: ='OPERATIONAL EXPENDITURE'!E12 -> 0 | F43: ='OPERATIONAL EXPENDITURE'!F12 -> 48000000 | G43: ='OPERATIONAL EXPENDITURE'!G12 -> 48000000 | H43: ='OPERATIONAL EXPENDITURE'!H12 -> 48000000 | I43: ='OPERATIONAL EXPENDITURE'!I12 -> 81000000 | J43: ='OPERATIONAL EXPENDITURE'!J12 -> 81000000 | ... BR43: ='OPERATIONAL EXPENDITURE'!BR12 -> 1.0226063e+08 | BS43: =BR43/135 -> 757486.18 | BT43: =SUM(C43:BS43) -> 5.7860118e+09 | BU43: =BT43/'BASIC INPUT ASSUMPTIONS'!$D$7 -> 38573412
B44: 3rd Party Vendors & Supplier Costs | C44: ='OPERATIONAL EXPENDITURE'!C13 -> 0 | D44: ='OPERATIONAL EXPENDITURE'!D13 -> 0 | E44: ='OPERATIONAL EXPENDITURE'!E13 -> 0 | F44: ='OPERATIONAL EXPENDITURE'!F13 -> 0 | G44: ='OPERATIONAL EXPENDITURE'!G13 -> 12000000 | H44: ='OPERATIONAL EXPENDITURE'!H13 -> 0 | I44: ='OPERATIONAL EXPENDITURE'!I13 -> 0 | J44: ='OPERATIONAL EXPENDITURE'!J13 -> 0 | ... BR44: ='OPERATIONAL EXPENDITURE'!BR13 -> 0 | BT44: =SUM(C44:BS44) -> 12000000 | BU44: =BT44/'BASIC INPUT ASSUMPTIONS'!$D$7 -> 80000
B45: Other Costs | C45: ='OPERATIONAL EXPENDITURE'!C14 -> 0 | D45: ='OPERATIONAL EXPENDITURE'!D14 -> 0 | E45: ='OPERATIONAL EXPENDITURE'!E14 -> 0 | F45: ='OPERATIONAL EXPENDITURE'!F14 -> 0 | G45: ='OPERATIONAL EXPENDITURE'!G14 -> 0 | H45: ='OPERATIONAL EXPENDITURE'!H14 -> 0 | I45: ='OPERATIONAL EXPENDITURE'!I14 -> 0 | J45: ='OPERATIONAL EXPENDITURE'!J14 -> 0 | ... BR45: ='OPERATIONAL EXPENDITURE'!BR14 -> 7500000 | BT45: =SUM(C45:BS45) -> 450000000 | BU45: =BT45/'BASIC INPUT ASSUMPTIONS'!$D$7 -> 3000000
B46: EBITDA | C46: =C38-C40 -> -1608000000 | D46: =D38-D40 -> 0 | E46: =E38-E40 -> 0 | F46: =F38-F40 -> -48000000 | G46: =G38-G40 -> -60000000 | H46: =H38-H40 -> -48000000 | I46: =I38-I40 -> -81000000 | J46: =J38-J40 -> -216000000 | ... BR46: =BR38-BR40 -> 2.508232e+09
B47: Net Margin Percentage (%) | C47: =IF(C46>0,C46/C8,0) -> 0 | D47: =IF(D46>0,D46/D8,0) -> 0 | E47: =IF(E46>0,E46/E8,0) -> 0 | F47: =IF(F46>0,F46/F8,0) -> 0 | G47: =IF(G46>0,G46/G8,0) -> 0 | H47: =IF(H46>0,H46/H8,0) -> 0 | I47: =IF(I46>0,I46/I8,0) -> 0 | J47: =IF(J46>0,J46/J8,0) -> 0 | ... BR47: =IF(BR46>0,BR46/BR8,0) -> 0.17553032
B48: Capital Expenditure | C48: =SUM(C49:C55) -> 40500000 | D48: =SUM(D49:D55) -> 91500000 | E48: =SUM(E49:E55) -> 91500000 | F48: =SUM(F49:F55) -> 103500000 | G48: =SUM(G49:G55) -> 189000000 | H48: =SUM(H49:H55) -> 91500000 | I48: =SUM(I49:I55) -> 0 | J48: =SUM(J49:J55) -> 0 | ... BR48: =SUM(BR49:BR55) -> 0
B49: Project Team Costs | C49: ='CAPITAL EXPENDITURE'!C10 -> 40500000 | D49: ='CAPITAL EXPENDITURE'!D10 -> 40500000 | E49: ='CAPITAL EXPENDITURE'!E10 -> 40500000 | F49: ='CAPITAL EXPENDITURE'!F10 -> 40500000 | G49: ='CAPITAL EXPENDITURE'!G10 -> 40500000 | H49: ='CAPITAL EXPENDITURE'!H10 -> 40500000 | I49: ='CAPITAL EXPENDITURE'!I10 -> 0 | J49: ='CAPITAL EXPENDITURE'!J10 -> 0 | ... BR49: ='CAPITAL EXPENDITURE'!BR10 -> 0 | BT49: =SUM(C49:BS49) -> 243000000 | BU49: =BT49/'BASIC INPUT ASSUMPTIONS'!$D$7 -> 1620000
B50: Professional Services Fees | C50: ='CAPITAL EXPENDITURE'!C11 -> 0 | D50: ='CAPITAL EXPENDITURE'!D11 -> 0 | E50: ='CAPITAL EXPENDITURE'!E11 -> 0 | F50: ='CAPITAL EXPENDITURE'!F11 -> 0 | G50: ='CAPITAL EXPENDITURE'!G11 -> 0 | H50: ='CAPITAL EXPENDITURE'!H11 -> 0 | I50: ='CAPITAL EXPENDITURE'!I11 -> 0 | J50: ='CAPITAL EXPENDITURE'!J11 -> 0 | ... BR50: ='CAPITAL EXPENDITURE'!BR11 -> 0 | BT50: =SUM(C50:BS50) -> 0 | BU50: =BT50/'BASIC INPUT ASSUMPTIONS'!$D$7 -> 0
B51: Mvne Platform Customization | C51: ='CAPITAL EXPENDITURE'!C12 -> 0 | D51: ='CAPITAL EXPENDITURE'!D12 -> 51000000 | E51: ='CAPITAL EXPENDITURE'!E12 -> 51000000 | F51: ='CAPITAL EXPENDITURE'!F12 -> 51000000 | G51: ='CAPITAL EXPENDITURE'!G12 -> 51000000 | H51: ='CAPITAL EXPENDITURE'!H12 -> 51000000 | I51: ='CAPITAL EXPENDITURE'!I12 -> 0 | J51: ='CAPITAL EXPENDITURE'!J12 -> 0 | ... BR51: ='CAPITAL EXPENDITURE'!BR12 -> 0 | BT51: =SUM(C51:BS51) -> 255000000 | BU51: =BT51/'BASIC INPUT ASSUMPTIONS'!$D$7 -> 1700000
B52: 3Pl Integration Costs | C52: ='CAPITAL EXPENDITURE'!C13 -> 0 | D52: ='CAPITAL EXPENDITURE'!D13 -> 0 | E52: ='CAPITAL EXPENDITURE'!E13 -> 0 | F52: ='CAPITAL EXPENDITURE'!F13 -> 0 | G52: ='CAPITAL EXPENDITURE'!G13 -> 22500000 | H52: ='CAPITAL EXPENDITURE'!H13 -> 0 | I52: ='CAPITAL EXPENDITURE'!I13 -> 0 | J52: ='CAPITAL EXPENDITURE'!J13 -> 0 | ... BR52: ='CAPITAL EXPENDITURE'!BR13 -> 0 | BT52: =SUM(C52:BS52) -> 22500000 | BU52: =BT52/'BASIC INPUT ASSUMPTIONS'!$D$7 -> 150000
B53: Credit, Collections & Vetting Implementation Fee | C53: ='CAPITAL EXPENDITURE'!C14 -> 0 | D53: ='CAPITAL EXPENDITURE'!D14 -> 0 | E53: ='CAPITAL EXPENDITURE'!E14 -> 0 | F53: ='CAPITAL EXPENDITURE'!F14 -> 0 | G53: ='CAPITAL EXPENDITURE'!G14 -> 0 | H53: ='CAPITAL EXPENDITURE'!H14 -> 0 | I53: ='CAPITAL EXPENDITURE'!I14 -> 0 | J53: ='CAPITAL EXPENDITURE'!J14 -> 0 | ... BR53: ='CAPITAL EXPENDITURE'!BR14 -> 0 | BT53: =SUM(C53:BS53) -> 0 | BU53: =BT53/'BASIC INPUT ASSUMPTIONS'!$D$7 -> 0
B54: Call Center Setup | C54: ='CAPITAL EXPENDITURE'!C15 -> 0 | D54: ='CAPITAL EXPENDITURE'!D15 -> 0 | E54: ='CAPITAL EXPENDITURE'!E15 -> 0 | F54: ='CAPITAL EXPENDITURE'!F15 -> 12000000 | G54: ='CAPITAL EXPENDITURE'!G15 -> 0 | H54: ='CAPITAL EXPENDITURE'!H15 -> 0 | I54: ='CAPITAL EXPENDITURE'!I15 -> 0 | J54: ='CAPITAL EXPENDITURE'!J15 -> 0 | ... BR54: ='CAPITAL EXPENDITURE'!BR15 -> 0 | BT54: =SUM(C54:BS54) -> 12000000 | BU54: =BT54/'BASIC INPUT ASSUMPTIONS'!$D$7 -> 80000
B55: Network Connection & Integration Fees | C55: ='CAPITAL EXPENDITURE'!C16 -> 0 | D55: ='CAPITAL EXPENDITURE'!D16 -> 0 | E55: ='CAPITAL EXPENDITURE'!E16 -> 0 | F55: ='CAPITAL EXPENDITURE'!F16 -> 0 | G55: ='CAPITAL EXPENDITURE'!G16 -> 75000000 | H55: ='CAPITAL EXPENDITURE'!H16 -> 0 | I55: ='CAPITAL EXPENDITURE'!I16 -> 0 | J55: ='CAPITAL EXPENDITURE'!J16 -> 0 | ... BR55: ='CAPITAL EXPENDITURE'!BR16 -> 0 | BT55: =SUM(C55:BS55) -> 75000000 | BU55: =BT55/'BASIC INPUT ASSUMPTIONS'!$D$7 -> 500000
B56: Provisions | C56: =SUM(C57:C60) -> 0 | D56: =SUM(D57:D60) -> 0 | E56: =SUM(E57:E60) -> 0 | F56: =SUM(F57:F60) -> 0 | G56: =SUM(G57:G60) -> 0 | H56: =SUM(H57:H60) -> 0 | I56: =SUM(I57:I60) -> 0 | J56: =SUM(J57:J60) -> 0 | ... BR56: =SUM(BR57:BR60) -> 4.8822293e+08
B57: ='BASIC INPUT ASSUMPTIONS'!C15 -> Rewards/Loyalty Provision expressed as a % of Revenue | C57: =C8*'BASIC INPUT ASSUMPTIONS'!$D$15 -> 0 | D57: =D8*'BASIC INPUT ASSUMPTIONS'!$D$15 -> 0 | E57: =E8*'BASIC INPUT ASSUMPTIONS'!$D$15 -> 0 | F57: =F8*'BASIC INPUT ASSUMPTIONS'!$D$15 -> 0 | G57: =G8*'BASIC INPUT ASSUMPTIONS'!$D$15 -> 0 | H57: =H8*'BASIC INPUT ASSUMPTIONS'!$D$15 -> 0 | I57: =I8*'BASIC INPUT ASSUMPTIONS'!$D$15 -> 0 | J57: =J8*'BASIC INPUT ASSUMPTIONS'!$D$15 -> 0 | ... BR57: =BR8*'BASIC INPUT ASSUMPTIONS'!$D$15 -> 4.2868355e+08 | BT57: =SUM(C57:BS57) -> 1.2981102e+10 | BU57: =BT57/'BASIC INPUT ASSUMPTIONS'!$D$7 -> 86540683
B58: Provisions for Fraud | C58: =C8*'BASIC INPUT ASSUMPTIONS'!$D$16 -> 0 | D58: =D8*'BASIC INPUT ASSUMPTIONS'!$D$16 -> 0 | E58: =E8*'BASIC INPUT ASSUMPTIONS'!$D$16 -> 0 | F58: =F8*'BASIC INPUT ASSUMPTIONS'!$D$16 -> 0 | G58: =G8*'BASIC INPUT ASSUMPTIONS'!$D$16 -> 0 | H58: =H8*'BASIC INPUT ASSUMPTIONS'!$D$16 -> 0 | I58: =I8*'BASIC INPUT ASSUMPTIONS'!$D$16 -> 0 | J58: =J8*'BASIC INPUT ASSUMPTIONS'!$D$16 -> 0 | ... BR58: =BR8*'BASIC INPUT ASSUMPTIONS'!$D$16 -> 0 | BT58: =SUM(C58:BS58) -> 0 | BU58: =BT58/'BASIC INPUT ASSUMPTIONS'!$D$7 -> 0
B59: Provision for Retail Price Erosion | C59: =C8*('BASIC INPUT ASSUMPTIONS'!$D$14/12) -> 0 | D59: =D8*('BASIC INPUT ASSUMPTIONS'!$D$14/12) -> 0 | E59: =E8*('BASIC INPUT ASSUMPTIONS'!$D$14/12) -> 0 | F59: =F8*('BASIC INPUT ASSUMPTIONS'!$D$14/12) -> 0 | G59: =G8*('BASIC INPUT ASSUMPTIONS'!$D$14/12) -> 0 | H59: =H8*('BASIC INPUT ASSUMPTIONS'!$D$14/12) -> 0 | I59: =I8*('BASIC INPUT ASSUMPTIONS'!$D$14/12) -> 0 | J59: =J8*('BASIC INPUT ASSUMPTIONS'!$D$14/12) -> 0 | ... BR59: =BR8*('BASIC INPUT ASSUMPTIONS'!$D$14/12) -> 59539381 | BT59: =SUM(C59:BS59) -> 1.8029309e+09 | BU59: =BT59/'BASIC INPUT ASSUMPTIONS'!$D$7 -> 12019539
B60: Other Provisions | C60: 0 | D60: 0 | E60: 0 | F60: 0 | G60: 0 | H60: 0 | I60: 0 | J60: 0 | K60: 0 | L60: 0 | M60: 0 | N60: 0 | O60: 0 | P60: 0 | Q60: 0 | R60: 0 | S60: 0 | T60: 0 | U60: 0 | V60: 0 | W60: 0 | X60: 0 | Y60: 0 | Z60: 0 | AA60: 0 | AB60: 0 | AC60: 0 | AD60: 0 | AE60: 0 | AF60: 0 | AG60: 0 | AH60: 0 | AI60: 0 | AJ60: 0 | AK60: 0 | AL60: 0 | AM60: 0 | AN60: 0 | AO60: 0 | AP60: 0 | AQ60: 0 | AR60: 0 | AS60: 0 | AT60: 0 | AU60: 0 | AV60: 0 | AW60: 0 | AX60: 0 | AY60: 0 | AZ60: 0 | BA60: 0 | BB60: 0 | BC60: 0 | BD60: 0 | BE60: 0 | BF60: 0 | BG60: 0 | BH60: 0 | BI60: 0 | BJ60: 0 | BK60: 0 | BL60: 0 | BM60: 0 | BN60: 0 | BO60: 0 | BP60: 0 | BQ60: 0 | BR60: 0 | BT60: =SUM(C60:BS60) -> 0 | BU60: =BT60/'BASIC INPUT ASSUMPTIONS'!$D$7 -> 0
B61: EBIT | C61: =C46-C48-C56 -> -1648500000 | D61: =D46-D48-D56 -> -91500000 | E61: =E46-E48-E56 -> -91500000 | F61: =F46-F48-F56 -> -151500000 | G61: =G46-G48-G56 -> -249000000 | H61: =H46-H48-H56 -> -139500000 | I61: =I46-I48-I56 -> -81000000 | J61: =J46-J48-J56 -> -216000000 | ... BR61: =BR46-BR48-BR56 -> 2.020009e+09
B62: Net Margin Percentage (%) | C62: =IF(C61>0,C61/C8,0) -> 0 | D62: =IF(D61>0,D61/D8,0) -> 0 | E62: =IF(E61>0,E61/E8,0) -> 0 | F62: =IF(F61>0,F61/F8,0) -> 0 | G62: =IF(G61>0,G61/G8,0) -> 0 | H62: =IF(H61>0,H61/H8,0) -> 0 | I62: =IF(I61>0,I61/I8,0) -> 0 | J62: =IF(J61>0,J61/J8,0) -> 0 | ... BR62: =IF(BR61>0,BR61/BR8,0) -> 0.14136365
B63: CUMULATIVE EBIT | C63: =C61 -> -1648500000 | D63: =D61+C63 -> -1740000000 | E63: =E61+D63 -> -1831500000 | F63: =F61+E63 -> -1983000000 | G63: =G61+F63 -> -2232000000 | H63: =H61+G63 -> -2371500000 | I63: =I61+H63 -> -2452500000 | J63: =J61+I63 -> -2668500000 | K63: =K61+J63 -> -3.038885e+09 | ... BR63: =BR61+BQ63 -> 3.2411041e+10
B65: Cash Flow Positive in Month | C65: =IF(C61>0,C6,"") | D65: =IF(D61>0,D6,"") | E65: =IF(E61>0,E6,"") | F65: =IF(F61>0,F6,"") | G65: =IF(G61>0,G6,"") | H65: =IF(H61>0,H6,"") | I65: =IF(I61>0,I6,"") | J65: =IF(J61>0,J6,"") | ... BR65: =IF(BR61>0,BR6,"") -> 60
B66: Break Even in Month | C66: =IF(C63>0,C6,"") | D66: =IF(D63>0,D6,"") | E66: =IF(E63>0,E6,"") | F66: =IF(F63>0,F6,"") | G66: =IF(G63>0,G6,"") | H66: =IF(H63>0,H6,"") | I66: =IF(I63>0,I6,"") | J66: =IF(J63>0,J6,"") | ... BR66: =IF(BR63>0,BR6,"") -> 60
B68: ARPU | C68: =IF('SUBSCRIBER BASE'!C$79>0,SUM(C69:C73)/'SUBSCRIBER BASE'!C$79,0) -> 0 | D68: =IF('SUBSCRIBER BASE'!D$79>0,SUM(D69:D73)/'SUBSCRIBER BASE'!D$79,0) -> 0 | E68: =IF('SUBSCRIBER BASE'!E$79>0,SUM(E69:E73)/'SUBSCRIBER BASE'!E$79,0) -> 0 | F68: =IF('SUBSCRIBER BASE'!F$79>0,SUM(F69:F73)/'SUBSCRIBER BASE'!F$79,0) -> 0 | G68: =IF('SUBSCRIBER BASE'!G$79>0,SUM(G69:G73)/'SUBSCRIBER BASE'!G$79,0) -> 0 | H68: =IF('SUBSCRIBER BASE'!H$79>0,SUM(H69:H73)/'SUBSCRIBER BASE'!H$79,0) -> 0 | I68: =IF('SUBSCRIBER BASE'!I$79>0,SUM(I69:I73)/'SUBSCRIBER BASE'!I$79,0) -> 0 | J68: =IF('SUBSCRIBER BASE'!J$79>0,SUM(J69:J73)/'SUBSCRIBER BASE'!J$79,0) -> 0 | K68: =IF('SUBSCRIBER BASE'!L$79>0,SUM(K69:K75)/'SUBSCRIBER BASE'!L$79,0) -> 5173.7288 | L68: =IF('SUBSCRIBER BASE'!M$79>0,SUM(L69:L75)/'SUBSCRIBER BASE'!M$79,0) -> 5171.7295 | M68: =IF('SUBSCRIBER BASE'!N$79>0,SUM(M69:M75)/'SUBSCRIBER BASE'!N$79,0) -> 5170.1027 | N68: =IF('SUBSCRIBER BASE'!O$79>0,SUM(N69:N75)/'SUBSCRIBER BASE'!O$79,0) -> 5168.2178 | O68: =IF('SUBSCRIBER BASE'!P$79>0,SUM(O69:O75)/'SUBSCRIBER BASE'!P$79,0) -> 5166.8392 | P68: =IF('SUBSCRIBER BASE'!Q$79>0,SUM(P69:P75)/'SUBSCRIBER BASE'!Q$79,0) -> 5165.9962 | Q68: =IF('SUBSCRIBER BASE'!R$79>0,SUM(Q69:Q75)/'SUBSCRIBER BASE'!R$79,0) -> 5165.1734 | R68: =IF('SUBSCRIBER BASE'!S$79>0,SUM(R69:R75)/'SUBSCRIBER BASE'!S$79,0) -> 5164.2696 | ... BR68: =IF('SUBSCRIBER BASE'!BS$79>0,SUM(BR69:BR75)/'SUBSCRIBER BASE'!BS$79,0) -> 7122.8947
B69: Device Subscription Revenue | C69: =C13 -> 0 | D69: =D13 -> 0 | E69: =E13 -> 0 | F69: =F13 -> 0 | G69: =G13 -> 0 | H69: =H13 -> 0 | I69: =I13 -> 0 | J69: =J13 -> 0 | ... BR69: =BR13 -> 0
B70: Subscription Revenue | C70: =C14 -> 0 | D70: =D14 -> 0 | E70: =E14 -> 0 | F70: =F14 -> 0 | G70: =G14 -> 0 | H70: =H14 -> 0 | I70: =I14 -> 0 | J70: =J14 -> 0 | ... BR70: =BR14 -> 1.4289452e+10
B71: OOB Spend Revenue | C71: =C15 -> 0 | D71: =D15 -> 0 | E71: =E15 -> 0 | F71: =F15 -> 0 | G71: =G15 -> 0 | H71: =H15 -> 0 | I71: =I15 -> 0 | J71: =J15 -> 0 | ... BR71: =BR15 -> 0
B72: Itemized Billing Revenue | C72: =C16 -> 0 | D72: =D16 -> 0 | E72: =E16 -> 0 | F72: =F16 -> 0 | G72: =G16 -> 0 | H72: =H16 -> 0 | I72: =I16 -> 0 | J72: =J16 -> 0 | ... BR72: =BR16 -> 0
B73: Converged Services Revenue | C73: =C17 -> 0 | D73: =D17 -> 0 | E73: =E17 -> 0 | F73: =F17 -> 0 | G73: =G17 -> 0 | H73: =H17 -> 0 | I73: =I17 -> 0 | J73: =J17 -> 0 | ... BR73: =BR17 -> 0
B74: Other Services Revenue | C74: =C18 -> 0 | D74: =D18 -> 0 | E74: =E18 -> 0 | F74: =F18 -> 0 | G74: =G18 -> 0 | H74: =H18 -> 0 | I74: =I18 -> 0 | J74: =J18 -> 0 | ... BR74: =BR18 -> 0
B75: Bundle Recharge Revenue | C75: =C19 -> 0 | D75: =D19 -> 0 | E75: =E19 -> 0 | F75: =F19 -> 0 | G75: =G19 -> 0 | H75: =H19 -> 0 | I75: =I19 -> 0 | J75: =J19 -> 0 | ... BR75: =BR19 -> 0

Sheet BASIC INPUT ASSUMPTIONS
C3: KEY INPUT ASSUMPTIONS UNDERPINNING PROVISIONS & THE MODEL
B6: Versioning Notes & Comments | D6: Changed By
C7: FX TZS to ZAR | D7: 150
B8: 1 | C8: VAT Rate for the Client in the Territory | D8: 0.18
B9: 2 | C9: Threshold for Package Profitability (i.e. cannot be less than x%) | D9: 0.25
B10: 3 | C10: Number of Calls Handled by single seat in call centre per month | D10: 2500
B11: 4 | C11: Cost per Seat per Month | D11: =D7*25000 -> 3750000
B12: 5 | C12: Outbound call costs per Customer per month | D12: =4.45*D7 -> 667.5
B13: 6 | C13: Contact Ratio per Month | D13: 0.1
B14: 7 | C14: Provision for Retail Price Erosion per annum expressed as a % of Revenue | D14: 0.05
B15: 8 | C15: Rewards/Loyalty Provision expressed as a % of Revenue | D15: 0.03
B16: 9 | C16: Fraud Provision expressed as a % of Revenue | D16: 0
B17: 10 | C17: MVNE Minimum Monthly Fee | D17: =G17*D7 -> 40500000 | F17: Platform minimum | G17: 270000
B18: 11 | C18: Regulatory fees | D18: 0.01
B19: 12 | C19: Channel Commission | D19: 0.07
B20: 13 | C20: Data wastage | D20: 0
B21: 14 | C21: Voice wastage | D21: 0.5
B22: 15 | C22: SMS Wastage | D22: 0.3
B23: 16 | C23: Marketing | D23: 15%,8%,3.8%,3%,2.4%
B24: 17 | C24: Churn | D24: 0.05
B25: 18 | C25: KYC | D25: =10*'BASIC INPUT ASSUMPTIONS'!D7 -> 1500
B26: 19 | C26: Logistics B to B | D26: 450
B27: 20 | C27: SIM + packaging | D27: 2250
B28: 21 | C28: MVNE per subscriber fee | D28: =8*'BASIC INPUT ASSUMPTIONS'!D7 -> 1200
B29: 22 | C29: MVLP1 - Recharges per sub - Mths 1-24 X 1, mths 25-48 X 6, mths 48-60 X 10
B30: 23 | C30: MVLP2 - Recharges per sub - Mths 1-24 X 1, mths 25-48 X 2
B31: 24 | C31: Blended customer Care fee per sub | D31: =(('BASIC INPUT ASSUMPTIONS'!$D$11/'BASIC INPUT ASSUMPTIONS'!$D$10)+'BASIC INPUT ASSUMPTIONS'!D12)*'BASIC INPUT ASSUMPTIONS'!D13 -> 216.75

Sheet MVLP INPUT
D3: =UPPER('<<VERSIONING NOTES>>'!$F$2)&TEXT(" MINIMUM VIABLE LAUNCH PROPOSITION (MVLP) VERSION ","")&'<<VERSIONING NOTES>>'!$F$3 -> METL MINIMUM VIABLE LAUNCH PROPOSITION (MVLP) VERSION MVNE Financial Framework Template Metl 20250604 1m | N3: =TEXT("Prepared by ","") -> Prepared by
N4: ='<<VERSIONING NOTES>>'!F4 -> Edward Wicks
D6: PRICING ASSUMPTIONS FOR BASELINE PACKAGES
G7: 1.5
D8: Baseline Packages (Incl VAT) | E8: Connection Fee | F8: Subscription Fee | G8: Allocated airtime | H8: Courier Fee | I8: Itemized Billing | J8: Converged Services | K8: Other Services | L8: Out of Bundle Tariff for Minutes | M8: Out of Bundle Tariff for Megabytes | N8: Out of Bundle Tariff for Messages
A10: 950 | B10: 500 | C10: 1 day | D10: MVLP1 | E10: 0 | F10: 500 | G10: 0 | H10: 0 | I10: 0 | J10: 0 | K10: 0 | L10: 1 | M10: 9 | N10: 8 | Q10: =F10/'BASIC INPUT ASSUMPTIONS'!$D$7 -> 3.3333333
A11: 1750 | B11: 2500 | C11: 1 week | D11: MVLP2 | E11: 0 | F11: 2500 | G11: 0 | H11: 0 | I11: 0 | J11: 0 | K11: 0 | L11: 1 | M11: 9 | N11: 8 | Q11: =F11/'BASIC INPUT ASSUMPTIONS'!$D$7 -> 16.666667
A12: 5000 | B12: 10000 | C12: 1 month | D12: MVLP3 | E12: 0 | F12: 5500 | G12: 0 | H12: 0 | I12: 0 | J12: 0 | K12: 0 | L12: 1 | M12: 9 | N12: 8 | Q12: =F12/'BASIC INPUT ASSUMPTIONS'!$D$7 -> 36.666667
A13: 12000 | B13: 15000 | C13: 1 month | D13: MVLP4 | E13: 0 | F13: 12500 | G13: 0 | H13: 0 | I13: 0 | J13: 0 | K13: 0 | L13: 1 | M13: 9 | N13: 8 | Q13: =F13/'BASIC INPUT ASSUMPTIONS'!$D$7 -> 83.333333
A14: 18000 | B14: 20000 | C14: 1 month | D14: MVLP5 | E14: 0 | F14: 18500 | G14: 0 | H14: 0 | I14: 0 | J14: 0 | K14: 0 | L14: 1 | M14: 9 | N14: 8 | Q14: =F14/'BASIC INPUT ASSUMPTIONS'!$D$7 -> 123.33333
B15: 40000 | C15: 90 days | D15: MVLP6 | E15: 0 | F15: 39000 | G15: 0 | H15: 0 | I15: 0 | J15: 0 | K15: 0 | L15: 1 | M15: 9 | N15: 8
D16: 200 MB | E16: 0 | F16: 500 | G16: 0 | H16: 0 | I16: 0 | J16: 0 | K16: 0 | L16: 1 | M16: 9 | N16: 8
D17: 500 MB | E17: 0 | F17: 1000 | G17: 0 | H17: 0 | I17: 0 | J17: 0 | K17: 0 | L17: 1 | M17: 9 | N17: 8
D18: 1.2 GB | E18: 0 | F18: 2500 | G18: =F18*$G$9 -> 0 | H18: 0 | I18: 0 | J18: 0 | K18: 0 | L18: 1 | M18: 9 | N18: 8
D19: 2.5 GB | E19: 0 | F19: 5000 | G19: =F19*$G$9 -> 0 | H19: 0 | I19: 0 | J19: 0 | K19: 0 | L19: 1 | M19: 9 | N19: 8
D20: 5 GB | E20: 0 | F20: 10000 | G20: =F20*$G$9 -> 0 | H20: 0 | I20: 0 | J20: 0 | K20: 0 | L20: 1 | M20: 9 | N20: 8
D21: 8.2 GB | E21: 0 | F21: 15000 | G21: =F21*$G$9 -> 0 | H21: 0 | I21: 0 | J21: 0 | K21: 0 | L21: 1 | M21: 9 | N21: 8
D22: 12.3 GB | E22: 0 | F22: 20000 | G22: =F22*$G$9 -> 0 | H22: 0 | I22: 0 | J22: 0 | K22: 0 | L22: 1 | M22: 9 | N22: 8
D23: 40 MIN | E23: 0 | F23: 500 | G23: =F23*$G$9 -> 0 | H23: 0 | I23: 0 | J23: 0 | K23: 0 | L23: 1 | M23: 9 | N23: 8
D24: 80 MIN | E24: 0 | F24: 950 | G24: =F24*$G$9 -> 0 | H24: 0 | I24: 0 | J24: 0 | K24: 0 | L24: 1 | M24: 9 | N24: 8
D25: 160 MIN | E25: 0 | F25: 1800 | G25: =F25*$G$9 -> 0 | H25: 0 | I25: 0 | J25: 0 | K25: 0 | L25: 1 | M25: 9 | N25: 8
D26: 300 SMS | E26: 0 | F26: 500 | G26: =F26*$G$9 -> 0 | H26: 0 | I26: 0 | J26: 0 | K26: 0 | L26: 1 | M26: 9 | N26: 8
D27: 500 SMS | E27: 0 | F27: 750 | G27: =F27*$G$9 -> 0 | H27: 0 | I27: 0 | J27: 0 | K27: 0 | L27: 1 | M27: 9 | N27: 8
D28: 2000 SMS | E28: 0 | F28: 2700 | G28: =F28*$G$9 -> 0 | H28: 0 | I28: 0 | J28: 0 | K28: 0 | L28: 1 | M28: 9 | N28: 8
D30: EXCLUDING VAT CALCULATIONS
D32: Baseline Packages (Excl VAT) | E32: Connection Fee | F32: Subscription Fee | G32: Courier Fee | H32: Itemized Billing | I32: Converged Services | J32: Other Services | K32: Out of Bundle Tariff for Minutes | L32: Out of Bundle Tariff for Megabytes | M32: Out of Bundle Tariff for Messages
D34: =D10 -> MVLP1 | E34: =(E10/(100+('BASIC INPUT ASSUMPTIONS'!$D$8*100)))*100 -> 0 | F34: =(F10/(100+('BASIC INPUT ASSUMPTIONS'!$D$8*100)))*100 -> 423.72881 | G34: =(H10/(100+('BASIC INPUT ASSUMPTIONS'!$D$8*100)))*100 -> 0 | H34: =(I10/(100+('BASIC INPUT ASSUMPTIONS'!$D$8*100)))*100 -> 0 | I34: =(J10/(100+('BASIC INPUT ASSUMPTIONS'!$D$8*100)))*100 -> 0 | J34: =(K10/(100+('BASIC INPUT ASSUMPTIONS'!$D$8*100)))*100 -> 0 | K34: =(L10/(100+('BASIC INPUT ASSUMPTIONS'!$D$8*100)))*100 -> 0.84745763 | L34: =(M10/(100+('BASIC INPUT ASSUMPTIONS'!$D$8*100)))*100 -> 7.6271186 | M34: =(N10/(100+('BASIC INPUT ASSUMPTIONS'!$D$8*100)))*100 -> 6.779661
D35: =D11 -> MVLP2 | E35: =(E11/(100+('BASIC INPUT ASSUMPTIONS'!$D$8*100)))*100 -> 0 | F35: =(F11/(100+('BASIC INPUT ASSUMPTIONS'!$D$8*100)))*100 -> 2118.6441 | G35: =(H11/(100+('BASIC INPUT ASSUMPTIONS'!$D$8*100)))*100 -> 0 | H35: =(I11/(100+('BASIC INPUT ASSUMPTIONS'!$D$8*100)))*100 -> 0 | I35: =(J11/(100+('BASIC INPUT ASSUMPTIONS'!$D$8*100)))*100 -> 0 | J35: =(K11/(100+('BASIC INPUT ASSUMPTIONS'!$D$8*100)))*100 -> 0 | K35: =(L11/(100+('BASIC INPUT ASSUMPTIONS'!$D$8*100)))*100 -> 0.84745763 | L35: =(M11/(100+('BASIC INPUT ASSUMPTIONS'!$D$8*100)))*100 -> 7.6271186 | M35: =(N11/(100+('BASIC INPUT ASSUMPTIONS'!$D$8*100)))*100 -> 6.779661
D36: =D12 -> MVLP3 | E36: =(E12/(100+('BASIC INPUT ASSUMPTIONS'!$D$8*100)))*100 -> 0 | F36: =(F12/(100+('BASIC INPUT ASSUMPTIONS'!$D$8*100)))*100 -> 4661.0169 | G36: =(H12/(100+('BASIC INPUT ASSUMPTIONS'!$D$8*100)))*100 -> 0 | H36: =(I12/(100+('BASIC INPUT ASSUMPTIONS'!$D$8*100)))*100 -> 0 | I36: =(J12/(100+('BASIC INPUT ASSUMPTIONS'!$D$8*100)))*100 -> 0 | J36: =(K12/(100+('BASIC INPUT ASSUMPTIONS'!$D$8*100)))*100 -> 0 | K36: =(L12/(100+('BASIC INPUT ASSUMPTIONS'!$D$8*100)))*100 -> 0.84745763 | L36: =(M12/(100+('BASIC INPUT ASSUMPTIONS'!$D$8*100)))*100 -> 7.6271186 | M36: =(N12/(100+('BASIC INPUT ASSUMPTIONS'!$D$8*100)))*100 -> 6.779661
D37: =D13 -> MVLP4 | E37: =(E13/(100+('BASIC INPUT ASSUMPTIONS'!$D$8*100)))*100 -> 0 | F37: =(F13/(100+('BASIC INPUT ASSUMPTIONS'!$D$8*100)))*100 -> 10593.22 | G37: =(H13/(100+('BASIC INPUT ASSUMPTIONS'!$D$8*100)))*100 -> 0 | H37: =(I13/(100+('BASIC INPUT ASSUMPTIONS'!$D$8*100)))*100 -> 0 | I37: =(J13/(100+('BASIC INPUT ASSUMPTIONS'!$D$8*100)))*100 -> 0 | J37: =(K13/(100+('BASIC INPUT ASSUMPTIONS'!$D$8*100)))*100 -> 0 | K37: =(L13/(100+('BASIC INPUT ASSUMPTIONS'!$D$8*100)))*100 -> 0.84745763 | L37: =(M13/(100+('BASIC INPUT ASSUMPTIONS'!$D$8*100)))*100 -> 7.6271186 | M37: =(N13/(100+('BASIC INPUT ASSUMPTIONS'!$D$8*100)))*100 -> 6.779661
D38: =D14 -> MVLP5 | E38: =(E14/(100+('BASIC INPUT ASSUMPTIONS'!$D$8*100)))*100 -> 0 | F38: =(F14/(100+('BASIC INPUT ASSUMPTIONS'!$D$8*100)))*100 -> 15677.966 | G38: =(H14/(100+('BASIC INPUT ASSUMPTIONS'!$D$8*100)))*100 -> 0 | H38: =(I14/(100+('BASIC INPUT ASSUMPTIONS'!$D$8*100)))*100 -> 0 | I38: =(J14/(100+('BASIC INPUT ASSUMPTIONS'!$D$8*100)))*100 -> 0 | J38: =(K14/(100+('BASIC INPUT ASSUMPTIONS'!$D$8*100)))*100 -> 0 | K38: =(L14/(100+('BASIC INPUT ASSUMPTIONS'!$D$8*100)))*100 -> 0.84745763 | L38: =(M14/(100+('BASIC INPUT ASSUMPTIONS'!$D$8*100)))*100 -> 7.6271186 | M38: =(N14/(100+('BASIC INPUT ASSUMPTIONS'!$D$8*100)))*100 -> 6.779661
D39: =D15 -> MVLP6 | E39: =(E15/(100+('BASIC INPUT ASSUMPTIONS'!$D$8*100)))*100 -> 0 | F39: =(F15/(100+('BASIC INPUT ASSUMPTIONS'!$D$8*100)))*100 -> 33050.847 | G39: =(H15/(100+('BASIC INPUT ASSUMPTIONS'!$D$8*100)))*100 -> 0 | H39: =(I15/(100+('BASIC INPUT ASSUMPTIONS'!$D$8*100)))*100 -> 0 | I39: =(J15/(100+('BASIC INPUT ASSUMPTIONS'!$D$8*100)))*100 -> 0 | J39: =(K15/(100+('BASIC INPUT ASSUMPTIONS'!$D$8*100)))*100 -> 0 | K39: =(L15/(100+('BASIC INPUT ASSUMPTIONS'!$D$8*100)))*100 -> 0.84745763 | L39: =(M15/(100+('BASIC INPUT ASSUMPTIONS'!$D$8*100)))*100 -> 7.6271186 | M39: =(N15/(100+('BASIC INPUT ASSUMPTIONS'!$D$8*100)))*100 -> 6.779661
D40: =D16 -> 200 MB | E40: =(E16/(100+('BASIC INPUT ASSUMPTIONS'!$D$8*100)))*100 -> 0 | F40: =(F16/(100+('BASIC INPUT ASSUMPTIONS'!$D$8*100)))*100 -> 423.72881 | G40: =(H16/(100+('BASIC INPUT ASSUMPTIONS'!$D$8*100)))*100 -> 0 | H40: =(I16/(100+('BASIC INPUT ASSUMPTIONS'!$D$8*100)))*100 -> 0 | I40: =(J16/(100+('BASIC INPUT ASSUMPTIONS'!$D$8*100)))*100 -> 0 | J40: =(K16/(100+('BASIC INPUT ASSUMPTIONS'!$D$8*100)))*100 -> 0 | K40: =(L16/(100+('BASIC INPUT ASSUMPTIONS'!$D$8*100)))*100 -> 0.84745763 | L40: =(M16/(100+('BASIC INPUT ASSUMPTIONS'!$D$8*100)))*100 -> 7.6271186 | M40: =(N16/(100+('BASIC INPUT ASSUMPTIONS'!$D$8*100)))*100 -> 6.779661
D41: =D17 -> 500 MB | E41: =(E17/(100+('BASIC INPUT ASSUMPTIONS'!$D$8*100)))*100 -> 0 | F41: =(F17/(100+('BASIC INPUT ASSUMPTIONS'!$D$8*100)))*100 -> 847.45763 | G41: =(H17/(100+('BASIC INPUT ASSUMPTIONS'!$D$8*100)))*100 -> 0 | H41: =(I17/(100+('BASIC INPUT ASSUMPTIONS'!$D$8*100)))*100 -> 0 | I41: =(J17/(100+('BASIC INPUT ASSUMPTIONS'!$D$8*100)))*100 -> 0 | J41: =(K17/(100+('BASIC INPUT ASSUMPTIONS'!$D$8*100)))*100 -> 0 | K41: =(L17/(100+('BASIC INPUT ASSUMPTIONS'!$D$8*100)))*100 -> 0.84745763 | L41: =(M17/(100+('BASIC INPUT ASSUMPTIONS'!$D$8*100)))*100 -> 7.6271186 | M41: =(N17/(100+('BASIC INPUT ASSUMPTIONS'!$D$8*100)))*100 -> 6.779661
D42: =D18 -> 1.2 GB | E42: =(E18/(100+('BASIC INPUT ASSUMPTIONS'!$D$8*100)))*100 -> 0 | F42: =(F18/(100+('BASIC INPUT ASSUMPTIONS'!$D$8*100)))*100 -> 2118.6441 | G42: =(H18/(100+('BASIC INPUT ASSUMPTIONS'!$D$8*100)))*100 -> 0 | H42: =(I18/(100+('BASIC INPUT ASSUMPTIONS'!$D$8*100)))*100 -> 0 | I42: =(J18/(100+('BASIC INPUT ASSUMPTIONS'!$D$8*100)))*100 -> 0 | J42: =(K18/(100+('BASIC INPUT ASSUMPTIONS'!$D$8*100)))*100 -> 0 | K42: =(L18/(100+('BASIC INPUT ASSUMPTIONS'!$D$8*100)))*100 -> 0.84745763 | L42: =(M18/(100+('BASIC INPUT ASSUMPTIONS'!$D$8*100)))*100 -> 7.6271186 | M42: =(N18/(100+('BASIC INPUT ASSUMPTIONS'!$D$8*100)))*100 -> 6.779661
D43: =D19 -> 2.5 GB | E43: =(E19/(100+('BASIC INPUT ASSUMPTIONS'!$D$8*100)))*100 -> 0 | F43: =(F19/(100+('BASIC INPUT ASSUMPTIONS'!$D$8*100)))*100 -> 4237.2881 | G43: =(H19/(100+('BASIC INPUT ASSUMPTIONS'!$D$8*100)))*100 -> 0 | H43: =(I19/(100+('BASIC INPUT ASSUMPTIONS'!$D$8*100)))*100 -> 0 | I43: =(J19/(100+('BASIC INPUT ASSUMPTIONS'!$D$8*100)))*100 -> 0 | J43: =(K19/(100+('BASIC INPUT ASSUMPTIONS'!$D$8*100)))*100 -> 0 | K43: =(L19/(100+('BASIC INPUT ASSUMPTIONS'!$D$8*100)))*100 -> 0.84745763 | L43: =(M19/(100+('BASIC INPUT ASSUMPTIONS'!$D$8*100)))*100 -> 7.6271186 | M43: =(N19/(100+('BASIC INPUT ASSUMPTIONS'!$D$8*100)))*100 -> 6.779661
D44: =D20 -> 5 GB | E44: =(E20/(100+('BASIC INPUT ASSUMPTIONS'!$D$8*100)))*100 -> 0 | F44: =(F20/(100+('BASIC INPUT ASSUMPTIONS'!$D$8*100)))*100 -> 8474.5763 | G44: =(H20/(100+('BASIC INPUT ASSUMPTIONS'!$D$8*100)))*100 -> 0 | H44: =(I20/(100+('BASIC INPUT ASSUMPTIONS'!$D$8*100)))*100 -> 0 | I44: =(J20/(100+('BASIC INPUT ASSUMPTIONS'!$D$8*100)))*100 -> 0 | J44: =(K20/(100+('BASIC INPUT ASSUMPTIONS'!$D$8*100)))*100 -> 0 | K44: =(L20/(100+('BASIC INPUT ASSUMPTIONS'!$D$8*100)))*100 -> 0.84745763 | L44: =(M20/(100+('BASIC INPUT ASSUMPTIONS'!$D$8*100)))*100 -> 7.6271186 | M44: =(N20/(100+('BASIC INPUT ASSUMPTIONS'!$D$8*100)))*100 -> 6.779661
D45: =D21 -> 8.2 GB | E45: =(E21/(100+('BASIC INPUT ASSUMPTIONS'!$D$8*100)))*100 -> 0 | F45: =(F21/(100+('BASIC INPUT ASSUMPTIONS'!$D$8*100)))*100 -> 12711.864 | G45: =(H21/(100+('BASIC INPUT ASSUMPTIONS'!$D$8*100)))*100 -> 0 | H45: =(I21/(100+('BASIC INPUT ASSUMPTIONS'!$D$8*100)))*100 -> 0 | I45: =(J21/(100+('BASIC INPUT ASSUMPTIONS'!$D$8*100)))*100 -> 0 | J45: =(K21/(100+('BASIC INPUT ASSUMPTIONS'!$D$8*100)))*100 -> 0 | K45: =(L21/(100+('BASIC INPUT ASSUMPTIONS'!$D$8*100)))*100 -> 0.84745763 | L45: =(M21/(100+('BASIC INPUT ASSUMPTIONS'!$D$8*100)))*100 -> 7.6271186 | M45: =(N21/(100+('BASIC INPUT ASSUMPTIONS'!$D$8*100)))*100 -> 6.779661
... D52: =D28 -> 2000 SMS | E52: =(E28/(100+('BASIC INPUT ASSUMPTIONS'!$D$8*100)))*100 -> 0 | F52: =(F28/(100+('BASIC INPUT ASSUMPTIONS'!$D$8*100)))*100 -> 2288.1356 | G52: =(H28/(100+('BASIC INPUT ASSUMPTIONS'!$D$8*100)))*100 -> 0 | H52: =(I28/(100+('BASIC INPUT ASSUMPTIONS'!$D$8*100)))*100 -> 0 | I52: =(J28/(100+('BASIC INPUT ASSUMPTIONS'!$D$8*100)))*100 -> 0 | J52: =(K28/(100+('BASIC INPUT ASSUMPTIONS'!$D$8*100)))*100 -> 0 | K52: =(L28/(100+('BASIC INPUT ASSUMPTIONS'!$D$8*100)))*100 -> 0.84745763 | L52: =(M28/(100+('BASIC INPUT ASSUMPTIONS'!$D$8*100)))*100 -> 7.6271186 | M52: =(N28/(100+('BASIC INPUT ASSUMPTIONS'!$D$8*100)))*100 -> 6.779661
D54: INCLUSIVE VALUE & BREAKAGE ASSUMPTIONS
D56: Baseline Packages (Incl VAT) | E56: Inclusive Minutes | F56: Inclusive Megabytes | G56: Inclusive SMS | H56: OOB Spend | I56: Out of Bundle Minutes | J56: Out of Bundle Megabytes | K56: Out of Bundle SMS | L56: Bundle Minutes rand value | M56: Bundle Megabytes rand value | N56: Bundle SMS rand value | O56: M | P56: D | Q56: S | R56: Bundle Minutes selected | S56: Bundle Megabytes selected | T56: Bundle SMS selected | U56: Bundle Minutes rand value selected | V56: Bundle Megabytes rand value selected | W56: Bundle SMS rand value selected | X56: Remainder value minutes | Y56: Remainder value Megabytes | Z56: Remainder value SMS
I57: 0.2 | J57: 0.75 | K57: 0.05 | L57: 0.2 | M57: 0.75 | N57: 0.05
A58: 20 | B58: 250 | C58: 20 | D58: =D10 -> MVLP1 | E58: 5 | F58: 150 | G58: 10 | I58: =H58*$I$57 -> 0 | J58: =H58*$J$57 -> 0 | K58: =H58*$K$57 -> 0 | L58: =$G10*$L$57 -> 0 | M58: =$G10*$M$57 -> 0 | N58: =$G10*$N$57 -> 0 | O58: =VLOOKUP(L58,BUNDLES!$B$10:$D$24,1,TRUE) -> #N/A | P58: =VLOOKUP(M58,BUNDLES!$B$30:$D$44,1,TRUE) -> #N/A
A59: 35 | B59: 600 | C59: 20 | D59: =D11 -> MVLP2 | E59: 25 | F59: 1024 | G59: 30 | I59: =H59*$I$57 -> 0 | J59: =H59*$J$57 -> 0 | K59: =H59*$K$57 -> 0 | L59: =$G11*$L$57 -> 0 | M59: =$G11*$M$57 -> 0 | N59: =$G11*$N$57 -> 0 | O59: =VLOOKUP(L59,BUNDLES!$B$10:$D$24,1,TRUE) -> #N/A | P59: =VLOOKUP(M59,BUNDLES!$B$30:$D$44,1,TRUE) -> #N/A | Q59: =VLOOKUP(N59,BUNDLES!$B$50:$D$64,1,TRUE) -> #N/A
A60: 75 | B60: 2048 | C60: 30 | D60: =D12 -> MVLP3 | E60: 60 | F60: 2048 | G60: 30 | I60: =H60*$I$57 -> 0 | J60: =H60*$J$57 -> 0 | K60: =H60*$K$57 -> 0 | L60: =$G12*$L$57 -> 0 | M60: =$G12*$M$57 -> 0 | N60: =$G12*$N$57 -> 0 | O60: =VLOOKUP(L60,BUNDLES!$B$10:$D$24,1,TRUE) -> #N/A | P60: =VLOOKUP(M60,BUNDLES!$B$30:$D$44,1,TRUE) -> #N/A | Q60: =VLOOKUP(N60,BUNDLES!$B$50:$D$64,1,TRUE) -> #N/A
A61: 200 | B61: 5120 | C61: 40 | D61: =D13 -> MVLP4 | E61: 80 | F61: 5120 | G61: 30 | H61: 0 | I61: =H61*$I$57 -> 0 | J61: =H61*$J$57 -> 0 | K61: =H61*$K$57 -> 0 | L61: =$G13*$L$57 -> 0 | M61: =$G13*$M$57 -> 0 | N61: =$G13*$N$57 -> 0 | O61: =VLOOKUP(L61,BUNDLES!$B$10:$D$24,1,TRUE) -> #N/A | P61: =VLOOKUP(M61,BUNDLES!$B$30:$D$44,1,TRUE) -> #N/A | Q61: =VLOOKUP(N61,BUNDLES!$B$50:$D$64,1,TRUE) -> #N/A
A62: 400 | B62: 7168 | C62: 100 | D62: =D14 -> MVLP5 | E62: 80 | F62: 9216 | G62: 30 | H62: 0 | I62: =H62*$I$57 -> 0 | J62: =H62*$J$57 -> 0 | K62: =H62*$K$57 -> 0 | L62: =$G14*$L$57 -> 0 | M62: =$G14*$M$57 -> 0 | N62: =$G14*$N$57 -> 0
D63: =D15 -> MVLP6 | E63: 240 | F63: 15360 | G63: 100 | H63: 0 | I63: =H63*$I$57 -> 0 | J63: =H63*$J$57 -> 0 | K63: =H63*$K$57 -> 0 | L63: =$G15*$L$57 -> 0 | M63: =$G15*$M$57 -> 0 | N63: =$G15*$N$57 -> 0
D64: =D16 -> 200 MB | E64: =X64/L16 -> 0 | F64: 200 | G64: =Z64/N16 -> 0 | H64: 0 | I64: =H64*$I$57 -> 0 | J64: =H64*$J$57 -> 0 | K64: =H64*$K$57 -> 0 | L64: =$G16*$L$57 -> 0 | M64: =$G16*$M$57 -> 0 | N64: =$G16*$N$57 -> 0
D65: =D17 -> 500 MB | E65: =X65/L17 -> 0 | F65: 500 | G65: =Z65/N17 -> 0 | H65: 0 | I65: =H65*$I$57 -> 0 | J65: =H65*$J$57 -> 0 | K65: =H65*$K$57 -> 0 | L65: =$G17*$L$57 -> 0 | M65: =$G17*$M$57 -> 0 | N65: =$G17*$N$57 -> 0
D66: =D18 -> 1.2 GB | E66: =X66/L18 -> 0 | F66: 1200 | G66: =Z66/N18 -> 0 | H66: 0 | I66: =H66*$I$57 -> 0 | J66: =H66*$J$57 -> 0 | K66: =H66*$K$57 -> 0 | L66: =$G18*$L$57 -> 0 | M66: =$G18*$M$57 -> 0 | N66: =$G18*$N$57 -> 0
D67: =D19 -> 2.5 GB | E67: =X67/L19 -> 0 | F67: 2500 | G67: =Z67/N19 -> 0 | H67: 0 | I67: =H67*$I$57 -> 0 | J67: =H67*$J$57 -> 0 | K67: =H67*$K$57 -> 0 | L67: =$G19*$L$57 -> 0 | M67: =$G19*$M$57 -> 0 | N67: =$G19*$N$57 -> 0
D68: =D20 -> 5 GB | E68: =X68/L20 -> 0 | F68: 5000 | G68: =Z68/N20 -> 0 | H68: 0 | I68: =H68*$I$57 -> 0 | J68: =H68*$J$57 -> 0 | K68: =H68*$K$57 -> 0 | L68: =$G20*$L$57 -> 0 | M68: =$G20*$M$57 -> 0 | N68: =$G20*$N$57 -> 0
D69: =D21 -> 8.2 GB | E69: =X69/L21 -> 0 | F69: 8192 | G69: =Z69/N21 -> 0 | H69: 0 | I69: =H69*$I$57 -> 0 | J69: =H69*$J$57 -> 0 | K69: =H69*$K$57 -> 0 | L69: =$G21*$L$57 -> 0 | M69: =$G21*$M$57 -> 0 | N69: =$G21*$N$57 -> 0
D70: =D22 -> 12.3 GB | E70: =X70/L22 -> 0 | F70: 12288 | G70: =Z70/N22 -> 0 | H70: 0 | I70: 0 | J70: =H70*$J$57 -> 0 | K70: =H70*$K$57 -> 0 | L70: =$G22*$L$57 -> 0 | M70: =$G22*$M$57 -> 0 | N70: =$G22*$N$57 -> 0
D71: =D23 -> 40 MIN | E71: 40 | F71: 0 | G71: =Z71/N23 -> 0 | H71: 0 | I71: 40 | J71: =H71*$J$57 -> 0 | K71: =H71*$K$57 -> 0 | L71: =$G23*$L$57 -> 0 | M71: =$G23*$M$57 -> 0 | N71: =$G23*$N$57 -> 0
D72: =D24 -> 80 MIN | E72: 80 | F72: 0 | G72: =Z72/N24 -> 0 | H72: 0 | I72: 80 | J72: =H72*$J$57 -> 0 | K72: =H72*$K$57 -> 0 | L72: =$G24*$L$57 -> 0 | M72: =$G24*$M$57 -> 0 | N72: =$G24*$N$57 -> 0
D73: =D25 -> 160 MIN | E73: 160 | F73: 0 | G73: =Z73/N25 -> 0 | H73: 0 | I73: 160 | J73: =H73*$J$57 -> 0 | K73: =H73*$K$57 -> 0 | L73: =$G25*$L$57 -> 0 | M73: =$G25*$M$57 -> 0 | N73: =$G25*$N$57 -> 0
D74: =D26 -> 300 SMS | E74: =X74/L26 -> 0 | F74: 0 | G74: 300 | H74: 0 | I74: 0 | J74: =H74*$J$57 -> 0 | K74: =H74*$K$57 -> 0 | L74: =$G26*$L$57 -> 0 | M74: =$G26*$M$57 -> 0 | N74: =$G26*$N$57 -> 0
D75: =D27 -> 500 SMS | E75: =X75/L27 -> 0 | F75: 0 | G75: 500 | H75: 0 | I75: 0 | J75: =H75*$J$57 -> 0 | K75: =H75*$K$57 -> 0 | L75: =$G27*$L$57 -> 0 | M75: =$G27*$M$57 -> 0 | N75: =$G27*$N$57 -> 0
D76: =D28 -> 2000 SMS | E76: =X76/L28 -> 0 | F76: 0 | G76: 2000 | H76: 0 | I76: 0 | J76: =H76*$J$57 -> 0 | K76: =H76*$K$57 -> 0 | L76: =$G28*$L$57 -> 0 | M76: =$G28*$M$57 -> 0 | N76: =$G28*$N$57 -> 0
U77: =O77 -> 0 | V77: =P77 -> 0 | W77: =Q77 -> 0 | X77: =L77-O77 -> 0 | Y77: =M77-P77 -> 0 | Z77: =N77-Q77 -> 0
D78: WASTAGE & BEHAVIOR
D80: Baseline Packages (Incl VAT) | E80: Wastage on Voice Minutes | F80: Wastage on Megabytes | G80: Wastage on SMS | H80: Percentage of Base Take Up on Itemized Billing | I80: Percentage of Base Take Up on Converged Services | J80: Percentage of Base Take Up on Other Services | K80: Percentage (%) that will be retained after 24 months | L80: Percentage (%) Voluntary Churn per month | M80: Percentage (%) Involuntary Churn per month | N80: Dormancy
L81: =L82*12 -> 0.6 | M81: =M82*12 -> 0
D82: =D58 -> MVLP1 | H82: 0.1 | I82: 0 | J82: 0 | K82: 0.6 | L82: ='<<KEY FINANCIAL INDICATORS>>'!L28 -> 0.05 | N82: 0
D83: =D59 -> MVLP2 | H83: 0.1 | I83: 0 | J83: 0 | K83: 0.6 | L83: =L82 -> 0.05 | N83: 0
D84: =D60 -> MVLP3 | H84: 0.1 | I84: 0 | J84: 0 | K84: 0.6 | L84: =L83 -> 0.05 | N84: 0
D85: =D61 -> MVLP4 | H85: 0.1 | I85: 0 | J85: 0 | K85: 0.6 | L85: =L84 -> 0.05 | N85: 0
D86: =D62 -> MVLP5 | H86: 0.1 | I86: 0 | J86: 0 | K86: 0.6 | L86: =L85 -> 0.05 | N86: 0
D87: =D63 -> MVLP6 | H87: 0.1 | I87: 0 | J87: 0 | K87: 0.6 | L87: =L86 -> 0.05 | M87: 0.0025 | N87: 0
D88: =D64 -> 200 MB | H88: 0.1 | I88: 0 | J88: 0 | K88: 0.6 | L88: =L87 -> 0.05 | M88: 0.0025 | N88: 0
D89: =D65 -> 500 MB | H89: 0.1 | I89: 0 | J89: 0 | K89: 0.6 | L89: =L88 -> 0.05 | M89: 0.0025 | N89: 0
D90: =D66 -> 1.2 GB | H90: 0.1 | I90: 0 | J90: 0 | K90: 0.6 | L90: =L89 -> 0.05 | M90: 0.0025 | N90: 0
D91: =D67 -> 2.5 GB | H91: 0.1 | I91: 0 | J91: 0 | K91: 0.6 | L91: =L90 -> 0.05 | M91: 0.0025 | N91: 0
D92: =D68 -> 5 GB | H92: 0.1 | I92: 0 | J92: 0 | K92: 0.6 | L92: =L91 -> 0.05 | M92: 0.0025 | N92: 0
D93: =D69 -> 8.2 GB | H93: 0.1 | I93: 0 | J93: 0 | K93: 0.6 | L93: =L92 -> 0.05 | M93: 0.0025 | N93: 0
D94: =D70 -> 12.3 GB | H94: 0.1 | I94: 0 | J94: 0 | K94: 0.6 | L94: =L93 -> 0.05 | M94: 0.0025 | N94: 0
D95: =D71 -> 40 MIN | H95: 0.1 | I95: 0 | J95: 0 | K95: 0.6 | L95: =L94 -> 0.05 | M95: 0.0025 | N95: 0
D96: =D72 -> 80 MIN | H96: 0.1 | I96: 0 | J96: 0 | K96: 0.6 | L96: =L95 -> 0.05 | M96: 0.0025 | N96: 0
D97: =D73 -> 160 MIN | H97: 0.1 | I97: 0 | J97: 0 | K97: 0.6 | L97: =L96 -> 0.05 | M97: 0.0025 | N97: 0
D98: =D74 -> 300 SMS | H98: 0.1 | I98: 0 | J98: 0 | K98: 0.6 | L98: =L97 -> 0.05 | M98: 0.0025 | N98: 0
... D100: =D76 -> 2000 SMS | H100: 0.1 | I100: 0 | J100: 0 | K100: 0.6 | L100: =L99 -> 0.05 | M100: 0.0025 | N100: 0
D102: RELATED COSTS (EXCL VAT)
D104: Baseline Packages (Incl VAT) | E104: Cost of SIM Card & Packaging | F104: Cost of Courier | G104: Cost of Itemized Billing | H104: Cost of Converged Services | I104: Cost of Other Services | J104: Blended per Minute Wholesale Rate | K104: Blended per Megabyte Wholesale Rate | L104: Blended per SMS Wholesale Rate | M104: MVNE Fee per Subscriber | N104: Blended Customer Care Fee per Subscriber
D106: =D82 -> MVLP1 | E106: =15*'BASIC INPUT ASSUMPTIONS'!$D$7 -> 2250 | F106: 0 | G106: 0 | H106: 0 | I106: 0 | J106: =AVERAGE('WHOLESALE COSTS'!N26:BU26) -> 6.3559322 | K106: ='WHOLESALE COSTS'!E41 -> 1.0169492 | L106: =AVERAGE('WHOLESALE COSTS'!N81:BU81) -> 0.8475 | M106: =8*'BASIC INPUT ASSUMPTIONS'!$D$7 -> 1200 | N106: =(('BASIC INPUT ASSUMPTIONS'!$D$11/'BASIC INPUT ASSUMPTIONS'!$D$10)+'BASIC INPUT ASSUMPTIONS'!D12)*'BASIC INPUT ASSUMPTIONS'!D13 -> 216.75
D107: =D83 -> MVLP2 | E107: =15*'BASIC INPUT ASSUMPTIONS'!$D$7 -> 2250 | F107: 0 | G107: 0 | H107: 0 | I107: 0 | J107: =J106 -> 6.3559322 | K107: ='WHOLESALE COSTS'!E42 -> 1.0169492 | L107: =L106 -> 0.8475 | M107: =8*'BASIC INPUT ASSUMPTIONS'!$D$7 -> 1200 | N107: =N106 -> 216.75
D108: =D84 -> MVLP3 | E108: =15*'BASIC INPUT ASSUMPTIONS'!$D$7 -> 2250 | F108: 0 | G108: 0 | H108: 0 | I108: 0 | J108: =J107 -> 6.3559322 | K108: ='WHOLESALE COSTS'!E43 -> 1.0169492 | L108: =L107 -> 0.8475 | M108: =8*'BASIC INPUT ASSUMPTIONS'!$D$7 -> 1200 | N108: =N107 -> 216.75
D109: =D85 -> MVLP4 | E109: =15*'BASIC INPUT ASSUMPTIONS'!$D$7 -> 2250 | F109: 0 | G109: 0 | H109: 0 | I109: 0 | J109: =J108 -> 6.3559322 | K109: ='WHOLESALE COSTS'!E44 -> 1.0169492 | L109: =L108 -> 0.8475 | M109: =8*'BASIC INPUT ASSUMPTIONS'!$D$7 -> 1200 | N109: =N108 -> 216.75
D110: =D86 -> MVLP5 | E110: =15*'BASIC INPUT ASSUMPTIONS'!$D$7 -> 2250 | F110: 0 | G110: 0 | H110: 0 | I110: 0 | J110: =J109 -> 6.3559322 | K110: ='WHOLESALE COSTS'!E45 -> 1.0169492 | L110: =L109 -> 0.8475 | M110: =8*'BASIC INPUT ASSUMPTIONS'!$D$7 -> 1200 | N110: =N109 -> 216.75
D111: =D87 -> MVLP6 | E111: =15*'BASIC INPUT ASSUMPTIONS'!$D$7 -> 2250 | F111: 0 | G111: 0 | H111: 0 | I111: 0 | J111: =J110 -> 6.3559322 | K111: ='WHOLESALE COSTS'!E46 -> 1.0169492 | L111: =L110 -> 0.8475 | M111: =8*'BASIC INPUT ASSUMPTIONS'!$D$7 -> 1200 | N111: =N110 -> 216.75
D112: =D88 -> 200 MB | E112: 0 | F112: 0 | G112: 0 | H112: 0 | I112: 0 | J112: =J111 -> 6.3559322 | K112: ='WHOLESALE COSTS'!E47 -> 1.0169492 | L112: =L111 -> 0.8475 | M112: =8*'BASIC INPUT ASSUMPTIONS'!$D$7 -> 1200 | N112: =N111 -> 216.75
D113: =D89 -> 500 MB | E113: 0 | F113: 0 | G113: 0 | H113: 0 | I113: 0 | J113: =J112 -> 6.3559322 | K113: ='WHOLESALE COSTS'!E48 -> 1.0169492 | L113: =L112 -> 0.8475 | M113: =8*'BASIC INPUT ASSUMPTIONS'!$D$7 -> 1200 | N113: =N112 -> 216.75
D114: =D90 -> 1.2 GB | E114: 0 | F114: 0 | G114: 0 | H114: 0 | I114: 0 | J114: =J113 -> 6.3559322 | K114: ='WHOLESALE COSTS'!E49 -> 1.0169492 | L114: =L113 -> 0.8475 | M114: =8*'BASIC INPUT ASSUMPTIONS'!$D$7 -> 1200 | N114: =N113 -> 216.75
D115: =D91 -> 2.5 GB | E115: 0 | F115: 0 | G115: 0 | H115: 0 | I115: 0 | J115: =J109 -> 6.3559322 | K115: ='WHOLESALE COSTS'!E50 -> 1.0169492 | L115: =L109 -> 0.8475 | M115: =8*'BASIC INPUT ASSUMPTIONS'!$D$7 -> 1200 | N115: =N109 -> 216.75
D116: =D92 -> 5 GB | E116: 0 | F116: 0 | G116: 0 | H116: 0 | I116: 0 | J116: =J110 -> 6.3559322 | K116: ='WHOLESALE COSTS'!E57 -> 1.0169492 | L116: =L110 -> 0.8475 | M116: =8*'BASIC INPUT ASSUMPTIONS'!$D$7 -> 1200 | N116: =N110 -> 216.75
D117: =D93 -> 8.2 GB | E117: 0 | F117: 0 | G117: 0 | H117: 0 | I117: 0 | J117: =J111 -> 6.3559322 | K117: ='WHOLESALE COSTS'!E58 -> 1.0169492 | L117: =L111 -> 0.8475 | M117: =8*'BASIC INPUT ASSUMPTIONS'!$D$7 -> 1200 | N117: =N111 -> 216.75
D118: =D94 -> 12.3 GB | E118: 0 | F118: 0 | G118: 0 | H118: 0 | I118: 0 | J118: =J112 -> 6.3559322 | K118: ='WHOLESALE COSTS'!E59 -> 1.0169492 | L118: =L112 -> 0.8475 | M118: =8*'BASIC INPUT ASSUMPTIONS'!$D$7 -> 1200 | N118: =N112 -> 216.75
D119: =D95 -> 40 MIN | E119: 0 | F119: 0 | G119: 0 | H119: 0 | I119: 0 | J119: =J113 -> 6.3559322 | K119: ='WHOLESALE COSTS'!E60 -> 0 | L119: =L113 -> 0.8475 | M119: =8*'BASIC INPUT ASSUMPTIONS'!$D$7 -> 1200 | N119: =N113 -> 216.75
D120: =D96 -> 80 MIN | E120: 0 | F120: 0 | G120: 0 | H120: 0 | I120: 0 | J120: =J114 -> 6.3559322 | K120: ='WHOLESALE COSTS'!E61 -> 0 | L120: =L114 -> 0.8475 | M120: =8*'BASIC INPUT ASSUMPTIONS'!$D$7 -> 1200 | N120: =N114 -> 216.75
...

Sheet BUNDLES
B3: =UPPER('<<VERSIONING NOTES>>'!$F$2)&TEXT(" MINIMUM VIABLE LAUNCH PROPOSITION BUNDLES VERSION ","")&'<<VERSIONING NOTES>>'!$F$3 -> METL MINIMUM VIABLE LAUNCH PROPOSITION BUNDLES VERSION MVNE Financial Framework Template Metl 20250604 1m | M3: =TEXT("Prepared by ","") -> Prepared by
M4: ='<<VERSIONING NOTES>>'!F4 -> Edward Wicks
B6: MINUTE BUNDLES
B8: Retail Price Including VAT | C8: Retail Price Excluding VAT | D8: Included Minutes | E8: Wastage | F8: Cost | G8: Percentage (%) of the Base that will use it every month | H8: Monthly Revenue | I8: Monthly Units Used | J8: Profitability | K8: Profitability Percentage (%)
C10: =(B10/(100+('[4]BASIC INPUT ASSUMPTIONS'!$D$8*100)))*100 -> 0 | D10: ='MVLP INPUT'!E58 -> 5 | E10: 0.5 | F10: =(D10*(100%-E10))*'MVLP INPUT'!$J$106 -> 15.889831 | H10: =C10*G10 -> 0 | I10: =D10*G10 -> 0 | J10: =B10-F10 -> -15.889831 | K10: =IF(D10>0,J10/B10,0) -> #DIV/0! | L10: =K10*G10 -> #DIV/0! | M10: =D10*G10 -> 0
C11: =(B11/(100+('[4]BASIC INPUT ASSUMPTIONS'!$D$8*100)))*100 -> 0 | D11: ='MVLP INPUT'!E59 -> 25 | E11: 0.5 | F11: =(D11*(100%-E11))*'MVLP INPUT'!$J$106 -> 79.449153 | H11: =C11*G11 -> 0 | I11: =D11*G11 -> 0 | J11: =B11-F11 -> -79.449153 | K11: =IF(D11>0,J11/B11,0) -> #DIV/0! | L11: =K11*G11 -> #DIV/0! | M11: =D11*G11 -> 0
C12: =(B12/(100+('[4]BASIC INPUT ASSUMPTIONS'!$D$8*100)))*100 -> 0 | D12: ='MVLP INPUT'!E60 -> 60 | E12: 0.5 | F12: =(D12*(100%-E12))*'MVLP INPUT'!$J$106 -> 190.67797 | H12: =C12*G12 -> 0 | I12: =D12*G12 -> 0 | J12: =B12-F12 -> -190.67797 | K12: =IF(D12>0,J12/B12,0) -> #DIV/0! | L12: =K12*G12 -> #DIV/0! | M12: =D12*G12 -> 0
C13: =(B13/(100+('[4]BASIC INPUT ASSUMPTIONS'!$D$8*100)))*100 -> 0 | D13: ='MVLP INPUT'!E61 -> 80 | E13: 0.5 | F13: =(D13*(100%-E13))*'MVLP INPUT'!$J$106 -> 254.23729 | H13: =C13*G13 -> 0 | I13: =D13*G13 -> 0 | J13: =B13-F13 -> -254.23729 | K13: =IF(D13>0,J13/B13,0) -> #DIV/0! | L13: =K13*G13 -> #DIV/0! | M13: =D13*G13 -> 0
C14: =(B14/(100+('[4]BASIC INPUT ASSUMPTIONS'!$D$8*100)))*100 -> 0 | D14: ='MVLP INPUT'!E62 -> 80 | E14: 0.5 | F14: =(D14*(100%-E14))*'MVLP INPUT'!$J$106 -> 254.23729 | H14: =C14*G14 -> 0 | I14: =D14*G14 -> 0 | J14: =B14-F14 -> -254.23729 | K14: =IF(D14>0,J14/B14,0) -> #DIV/0! | L14: =K14*G14 -> #DIV/0! | M14: =D14*G14 -> 0
C15: =(B15/(100+('[4]BASIC INPUT ASSUMPTIONS'!$D$8*100)))*100 -> 0 | D15: ='MVLP INPUT'!E63 -> 240 | E15: 0.5 | F15: =(D15*(100%-E15))*'MVLP INPUT'!$J$106 -> 762.71186
C16: =(B16/(100+('[4]BASIC INPUT ASSUMPTIONS'!$D$8*100)))*100 -> 0 | D16: ='MVLP INPUT'!E71 -> 40 | E16: 0.5 | F16: =(D16*(100%-E16))*'MVLP INPUT'!$J$106 -> 127.11864
C17: =(B17/(100+('[4]BASIC INPUT ASSUMPTIONS'!$D$8*100)))*100 -> 0 | D17: ='MVLP INPUT'!E72 -> 80 | E17: 0.5 | F17: =(D17*(100%-E17))*'MVLP INPUT'!$J$106 -> 254.23729
C18: =(B18/(100+('[4]BASIC INPUT ASSUMPTIONS'!$D$8*100)))*100 -> 0 | D18: ='MVLP INPUT'!E73 -> 160 | E18: 0.5 | F18: =(D18*(100%-E18))*'MVLP INPUT'!$J$106 -> 508.47458
L24: =SUM(L10:L23) -> #DIV/0! | M24: =SUM(M10:M23) -> 0
B26: DATA BUNDLES
B28: Retail Price Including VAT | C28: Retail Price Excluding VAT | D28: Included Megabytes | E28: Wastage | F28: Cost | G28: Percentage (%) of the Base that will use it every month | H28: Monthly Revenue | J28: Profitability | K28: Profitability Percentage (%)
C30: =(B30/(100+('BASIC INPUT ASSUMPTIONS'!$D$8*100)))*100 -> 0 | D30: ='MVLP INPUT'!F58 -> 150 | E30: 0 | F30: =(D30*(100%-E30))*'MVLP INPUT'!$K$106 -> 152.54237 | H30: =C30*G30 -> 0 | I30: =D30*G30 -> 0 | J30: =B30-F30 -> -152.54237 | K30: =IF(D30>0,J30/B30,0) -> #DIV/0! | L30: =K30*G30 -> #DIV/0! | M30: =D30*G30 -> 0
C31: =(B31/(100+('BASIC INPUT ASSUMPTIONS'!$D$8*100)))*100 -> 0 | D31: ='MVLP INPUT'!F59 -> 1024 | E31: 0 | F31: =(D31*(100%-E31))*'MVLP INPUT'!$K$106 -> 1041.3559 | H31: =C31*G31 -> 0 | I31: =D31*G31 -> 0 | J31: =B31-F31 -> -1041.3559 | K31: =IF(D31>0,J31/B31,0) -> #DIV/0! | L31: =K31*G31 -> #DIV/0! | M31: =D31*G31 -> 0
C32: =(B32/(100+('BASIC INPUT ASSUMPTIONS'!$D$8*100)))*100 -> 0 | D32: ='MVLP INPUT'!F60 -> 2048 | E32: 0 | F32: =(D32*(100%-E32))*'MVLP INPUT'!$K$106 -> 2082.7119 | H32: =C32*G32 -> 0 | I32: =D32*G32 -> 0 | J32: =B32-F32 -> -2082.7119 | K32: =IF(D32>0,J32/B32,0) -> #DIV/0! | L32: =K32*G32 -> #DIV/0! | M32: =D32*G32 -> 0
C33: =(B33/(100+('BASIC INPUT ASSUMPTIONS'!$D$8*100)))*100 -> 0 | D33: ='MVLP INPUT'!F61 -> 5120 | E33: 0 | F33: =(D33*(100%-E33))*'MVLP INPUT'!$K$106 -> 5206.7797 | H33: =C33*G33 -> 0 | I33: =D33*G33 -> 0 | J33: =B33-F33 -> -5206.7797 | K33: =IF(D33>0,J33/B33,0) -> #DIV/0! | L33: =K33*G33 -> #DIV/0! | M33: =D33*G33 -> 0
C34: =(B34/(100+('BASIC INPUT ASSUMPTIONS'!$D$8*100)))*100 -> 0 | D34: ='MVLP INPUT'!F62 -> 9216 | E34: 0 | F34: =(D34*(100%-E34))*'MVLP INPUT'!$K$106 -> 9372.2034 | H34: =C34*G34 -> 0 | I34: =D34*G34 -> 0 | J34: =B34-F34 -> -9372.2034 | K34: =IF(D34>0,J34/B34,0) -> #DIV/0! | L34: =K34*G34 -> #DIV/0! | M34: =D34*G34 -> 0
C35: =(B35/(100+('BASIC INPUT ASSUMPTIONS'!$D$8*100)))*100 -> 0 | D35: ='MVLP INPUT'!F63 -> 15360 | E35: 0 | F35: =(D35*(100%-E35))*'MVLP INPUT'!$K$106 -> 15620.339 | H35: =C35*G35 -> 0 | I35: =D35*G35 -> 0 | J35: =B35-F35 -> -15620.339 | K35: =IF(D35>0,J35/B35,0) -> #DIV/0! | L35: =K35*G35 -> #DIV/0! | M35: =D35*G35 -> 0
C36: =(B36/(100+('BASIC INPUT ASSUMPTIONS'!$D$8*100)))*100 -> 0 | D36: ='MVLP INPUT'!F64 -> 200 | E36: 0 | F36: =(D36*(100%-E36))*'MVLP INPUT'!$K$106 -> 203.38983 | H36: =C36*G36 -> 0 | I36: =D36*G36 -> 0 | J36: =B36-F36 -> -203.38983 | K36: =IF(D36>0,J36/B36,0) -> #DIV/0! | L36: =K36*G36 -> #DIV/0! | M36: =D36*G36 -> 0
C37: =(B37/(100+('BASIC INPUT ASSUMPTIONS'!$D$8*100)))*100 -> 0 | D37: ='MVLP INPUT'!F65 -> 500 | E37: 0 | F37: =(D37*(100%-E37))*'MVLP INPUT'!$K$106 -> 508.47458
C38: =(B38/(100+('BASIC INPUT ASSUMPTIONS'!$D$8*100)))*100 -> 0 | D38: ='MVLP INPUT'!F66 -> 1200 | E38: 0 | F38: =(D38*(100%-E38))*'MVLP INPUT'!$K$106 -> 1220.339
C39: =(B39/(100+('BASIC INPUT ASSUMPTIONS'!$D$8*100)))*100 -> 0 | D39: ='MVLP INPUT'!F67 -> 2500 | E39: 0 | F39: =(D39*(100%-E39))*'MVLP INPUT'!$K$106 -> 2542.3729
C40: =(B40/(100+('BASIC INPUT ASSUMPTIONS'!$D$8*100)))*100 -> 0 | D40: ='MVLP INPUT'!F68 -> 5000 | E40: 0 | F40: =(D40*(100%-E40))*'MVLP INPUT'!$K$106 -> 5084.7458
C41: =(B41/(100+('BASIC INPUT ASSUMPTIONS'!$D$8*100)))*100 -> 0 | D41: ='MVLP INPUT'!F69 -> 8192 | E41: 0 | F41: =(D41*(100%-E41))*'MVLP INPUT'!$K$106 -> 8330.8475
C42: =(B42/(100+('BASIC INPUT ASSUMPTIONS'!$D$8*100)))*100 -> 0 | D42: ='MVLP INPUT'!F70 -> 12288 | E42: 0 | F42: =(D42*(100%-E42))*'MVLP INPUT'!$K$106 -> 12496.271
G44: =SUM(G30:G43) -> 0 | L44: =SUM(L30:L43) -> #DIV/0! | M44: =SUM(M30:M43) -> 0
B46: SMS BUNDLES
B48: Retail Price Including VAT | C48: Retail Price Excluding VAT | D48: Included SMS | E48: Wastage | F48: Cost | G48: Percentage (%) of the Base that will use it every month | H48: Monthly Revenue | J48: Profitability | K48: Profitability Percentage (%)
C50: =(B50/(100+('[4]BASIC INPUT ASSUMPTIONS'!$D$8*100)))*100 -> 0 | D50: 5 | E50: 0.3 | F50: =(D50*(100%-E50))*'MVLP INPUT'!$L$106 -> 2.96625 | H50: =C50*G50 -> 0 | I50: =D50*G50 -> 0 | J50: =B50-F50 -> -2.96625 | K50: =IF(B50,J50/B50,0) -> 0 | L50: =K50*G50 -> 0 | M50: =D50*G50 -> 0
C51: =(B51/(100+('[4]BASIC INPUT ASSUMPTIONS'!$D$8*100)))*100 -> 0 | D51: 90 | E51: 0.3 | F51: =(D51*(100%-E51))*'MVLP INPUT'!$L$106 -> 53.3925 | H51: =C51*G51 -> 0 | I51: =D51*G51 -> 0 | J51: =B51-F51 -> -53.3925 | K51: =IF(B51,J51/B51,0) -> 0 | L51: =K51*G51 -> 0 | M51: =D51*G51 -> 0
C52: =(B52/(100+('[4]BASIC INPUT ASSUMPTIONS'!$D$8*100)))*100 -> 0 | D52: 100 | E52: 0.3 | F52: =(D52*(100%-E52))*'MVLP INPUT'!$L$106 -> 59.325 | H52: =C52*G52 -> 0 | I52: =D52*G52 -> 0 | J52: =B52-F52 -> -59.325 | K52: =IF(B52,J52/B52,0) -> 0 | L52: =K52*G52 -> 0 | M52: =D52*G52 -> 0
C53: =(B53/(100+('[4]BASIC INPUT ASSUMPTIONS'!$D$8*100)))*100 -> 0 | D53: 100 | E53: 0.3 | F53: =(D53*(100%-E53))*'MVLP INPUT'!$L$106 -> 59.325 | H53: =C53*G53 -> 0 | I53: =D53*G53 -> 0 | J53: =B53-F53 -> -59.325 | K53: =IF(B53,J53/B53,0) -> 0 | L53: =K53*G53 -> 0 | M53: =D53*G53 -> 0
C54: =(B54/(100+('[4]BASIC INPUT ASSUMPTIONS'!$D$8*100)))*100 -> 0 | D54: 100 | E54: 0.3 | F54: =(D54*(100%-E54))*'MVLP INPUT'!$L$106 -> 59.325 | H54: =C54*G54 -> 0 | I54: =D54*G54 -> 0 | J54: =B54-F54 -> -59.325 | K54: =IF(B54,J54/B54,0) -> 0 | L54: =K54*G54 -> 0 | M54: =D54*G54 -> 0
C55: =(B55/(100+('[4]BASIC INPUT ASSUMPTIONS'!$D$8*100)))*100 -> 0 | D55: 300 | E55: 0.3 | F55: =(D55*(100%-E55))*'MVLP INPUT'!$L$106 -> 177.975 | H55: =C55*G55 -> 0 | I55: =D55*G55 -> 0 | J55: =B55-F55 -> -177.975 | K55: =IF(B55,J55/B55,0) -> 0 | M55: =D55*G55 -> 0
C56: =(B56/(100+('[4]BASIC INPUT ASSUMPTIONS'!$D$8*100)))*100 -> 0 | D56: 500 | E56: 0.3 | F56: =(D56*(100%-E56))*'MVLP INPUT'!$L$106 -> 296.625 | H56: =C56*G56 -> 0 | I56: =D56*G56 -> 0 | J56: =B56-F56 -> -296.625 | K56: =IF(B56,J56/B56,0) -> 0 | M56: =D56*G56 -> 0
C57: =(B57/(100+('[4]BASIC INPUT ASSUMPTIONS'!$D$8*100)))*100 -> 0 | D57: 2000 | E57: 0.3 | F57: =(D57*(100%-E57))*'MVLP INPUT'!$L$106 -> 1186.5 | H57: =C57*G57 -> 0 | I57: =D57*G57 -> 0 | J57: =B57-F57 -> -1186.5 | K57: =IF(B57,J57/B57,0) -> 0
G64: =SUM(G50:G63) -> 0 | L64: =SUM(L50:L63) -> 0 | M64: =SUM(M50:M63) -> 0

Sheet MVLP DASHBOARD
B3: =UPPER('<<VERSIONING NOTES>>'!$F$2)&TEXT(" MINIMUM VIABLE LAUNCH PROPOSITION DASHBOARD BY PACKAGE VERSION ","")&'<<VERSIONING NOTES>>'!$F$3 -> METL MINIMUM VIABLE LAUNCH PROPOSITION DASHBOARD BY PACKAGE VERSION MVNE Financial Framework Template Metl 20250604 1m | K3: =TEXT("Prepared by ","") -> Prepared by
K4: ='<<VERSIONING NOTES>>'!F4 -> Edward Wicks
B6: PACKAGE SUMMARY | H6: This information is indicative based on blended wholesale rates, but provides a summary of Package Profitability. Red or green Shading indicates comparison against threshold rate set for packages.
B8: Baseline Packages (Excl VAT) | C8: Total Revenue over 24 Months | D8: Total Cost over 24 Months | E8: Profitability | F8: Profit Percentage (%)
A9: Daily | B9: ='MVLP INPUT'!D10 -> MVLP1 | C9: =E36*1 -> 10169.492 | D9: =(C110+D110+(SUM(E110:K110)*24))*1 -> 6877.1288 | E9: =C9-D9 -> 3292.3627 | F9: =IF(C9>0,E9/C9,0) -> 0.323749 | G9: ='<<KEY FINANCIAL INDICATORS>>'!L29 -> 1.2
A10: Weekly | B10: ='MVLP INPUT'!D11 -> MVLP2 | C10: =E37*1 -> 50847.458 | D10: =(C111+D111+(SUM(E111:K111)*24))*1 -> 31666.302 | E10: =C10-D10 -> 19181.156 | F10: =IF(C10>0,E10/C10,0) -> 0.3772294
A11: Monthly | B11: ='MVLP INPUT'!D12 -> MVLP3 | C11: =E38 -> 111864.41 | D11: =C112+D112+(SUM(E112:K112)*24) -> 61997.827 | E11: =C11-D11 -> 49866.58 | F11: =IF(C11>0,E11/C11,0) -> 0.445777
A12: Monthly | B12: ='MVLP INPUT'!D13 -> MVLP4 | C12: =E39 -> 254237.29 | D12: =C113+D113+(SUM(E113:K113)*24) -> 140026.3 | E12: =C12-D12 -> 114210.99 | F12: =IF(C12>0,E12/C12,0) -> 0.44922988
A13: Monthly | B13: ='MVLP INPUT'!D14 -> MVLP5 | C13: =E40 -> 376271.19 | D13: =C114+D114+(SUM(E114:K114)*24) -> 239996.47 | E13: =C13-D13 -> 136274.72 | F13: =IF(C13>0,E13/C13,0) -> 0.36217154 | G13: =AVERAGE(F9:F12) -> 0.39899632
A14: 3 Months | B14: ='MVLP INPUT'!D15 -> MVLP6 | C14: =E41 -> 793220.34 | D14: =C115+D115+(SUM(E115:K115)*24) -> 415782.31 | E14: =C14-D14 -> 377438.03 | F14: =IF(C14>0,E14/C14,0) -> 0.47583
B15: Baseline Packages (Excl VAT) | C15: Total Revenue per month | D15: Total Cost per month | E15: Profitability | F15: Profit Percentage (%)
B16: 200 MB | C16: =E43 -> 423.72881 | D16: =C116+D116+(SUM(E116:K116)) -> 203.38983 | E16: =C16-D16 -> 220.33898 | F16: =IF(C16>0,E16/C16,0) -> 0.52
B17: 500 MB | C17: =E44 -> 847.45763 | D17: =C117+D117+(SUM(E117:K117)) -> 508.47458 | E17: =C17-D17 -> 338.98305 | F17: =IF(C17>0,E17/C17,0) -> 0.4
B18: 1.2 GB | C18: =E45 -> 2118.6441 | D18: =C118+D118+(SUM(E118:K118)) -> 1220.339 | E18: =C18-D18 -> 898.30508 | F18: =IF(C18>0,E18/C18,0) -> 0.424
B19: 2.5 GB | C19: =E46 -> 4237.2881 | D19: =C119+D119+(SUM(E119:K119)) -> 2542.3729 | E19: =C19-D19 -> 1694.9153 | F19: =IF(C19>0,E19/C19,0) -> 0.4
B20: 5 GB | C20: =E47 -> 8474.5763 | D20: =C120+D120+(SUM(E120:K120)) -> 5084.7458 | E20: =C20-D20 -> 3389.8305 | F20: =IF(C20>0,E20/C20,0) -> 0.4
B21: 8.2 GB | C21: =E48 -> 12711.864 | D21: =C121+D121+(SUM(E121:K121)) -> 8330.8475 | E21: =C21-D21 -> 4381.0169 | F21: =IF(C21>0,E21/C21,0) -> 0.34464
B22: 12.3 GB | C22: =E49 -> 16949.153 | D22: =C122+D122+(SUM(E122:K122)) -> 12496.271 | E22: =C22-D22 -> 4452.8814 | F22: =IF(C22>0,E22/C22,0) -> 0.26272
B23: 40 MIN | C23: =E50 -> 423.72881 | D23: =C123+D123+(SUM(E123:K123)) -> 254.23729 | E23: =C23-D23 -> 169.49153 | F23: =IF(C23>0,E23/C23,0) -> 0.4
B24: 80 MIN | C24: =E51 -> 805.08475 | D24: =C124+D124+(SUM(E124:K124)) -> 508.47458 | E24: =C24-D24 -> 296.61017 | F24: =IF(C24>0,E24/C24,0) -> 0.36842105
B25: 160 MIN | C25: =E52 -> 1525.4237 | D25: =C125+D125+(SUM(E125:K125)) -> 1016.9492 | E25: =C25-D25 -> 508.47458 | F25: =IF(C25>0,E25/C25,0) -> 0.33333333
B26: 300 SMS | C26: =E53 -> 423.72881 | D26: =C126+D126+(SUM(E126:K126)) -> 254.25 | E26: =C26-D26 -> 169.47881 | F26: =IF(C26>0,E26/C26,0) -> 0.39997
B27: 500 SMS | C27: =E54 -> 635.59322 | D27: =C127+D127+(SUM(E127:K127)) -> 423.75 | E27: =C27-D27 -> 211.84322 | F27: =IF(C27>0,E27/C27,0) -> 0.3333
B28: 2000 SMS | C28: =E55 -> 2288.1356 | D28: =C128+D128+(SUM(E128:K128)) -> 1695 | E28: =C28-D28 -> 593.13559 | F28: =IF(C28>0,E28/C28,0) -> 0.25922222
B32: REVENUE SUMMARY
B34: Baseline Packages (Excl VAT) | C34: Up Front Revenues | D34: Recurring Revenues | E34: Revenue over 24 Months (Incl Up Front) | F34: Revenue over 24 Months (Excl Up Front) | G34: Minutes used Per Month | H34: Megabytes used Per Month | I34: SMS used Per Month
B36: =B9 -> MVLP1 | C36: =SUM(C86:D86) -> 0 | D36: =SUM(E86:K86) -> 423.72881 | E36: =C36+(D36*24) -> 10169.492 | F36: =D36*24 -> 10169.492 | G36: =C62+F62 -> 5 | H36: =D62+G62 -> 150 | I36: =E62+H62 -> 10
B37: =B10 -> MVLP2 | C37: =SUM(C87:D87) -> 0 | D37: =SUM(E87:K87) -> 2118.6441 | E37: =C37+(D37*24) -> 50847.458 | F37: =D37*24 -> 50847.458 | G37: =C63+F63 -> 25 | H37: =D63+G63 -> 1024 | I37: =E63+H63 -> 30
B38: =B11 -> MVLP3 | C38: =SUM(C88:D88) -> 0 | D38: =SUM(E88:K88) -> 4661.0169 | E38: =C38+(D38*24) -> 111864.41 | F38: =D38*24 -> 111864.41 | G38: =C64+F64 -> 60 | H38: =D64+G64 -> 2048 | I38: =E64+H64 -> 30
B39: =B12 -> MVLP4 | C39: =SUM(C89:D89) -> 0 | D39: =SUM(E89:K89) -> 10593.22 | E39: =C39+(D39*24) -> 254237.29 | F39: =D39*24 -> 254237.29 | G39: =C65+F65 -> 80 | H39: =D65+G65 -> 5120 | I39: =E65+H65 -> 30
B40: =B13 -> MVLP5 | C40: =SUM(C90:D90) -> 0 | D40: =SUM(E90:K90) -> 15677.966 | E40: =C40+(D40*24) -> 376271.19 | F40: =D40*24 -> 376271.19 | G40: =C66+F66 -> 80 | H40: =D66+G66 -> 9216 | I40: =E66+H66 -> 30
B41: =B14 -> MVLP6 | C41: =SUM(C91:D91) -> 0 | D41: =SUM(E91:K91) -> 33050.847 | E41: =C41+(D41*24) -> 793220.34 | F41: =D41*24 -> 793220.34 | G41: =C67+F67 -> 240 | H41: =D67+G67 -> 15360 | I41: =E67+H67 -> 100
B42: Baseline Packages (Excl VAT) | C42: Up Front Revenues | D42: Recurring Revenues | E42: Revenue over 1 Months (Incl Up Front) | F42: Revenue over 1 Month (Excl Up Front) | G42: Minutes used Per Month | H42: Megabytes used Per Month | I42: SMS used Per Month
B43: 200 MB | C43: =SUM(C92:D92) -> 0 | D43: =SUM(E92:K92) -> 423.72881 | E43: =D43 -> 423.72881 | F43: =D43 -> 423.72881 | G43: =C68+F68 -> 0 | H43: =D68+G68 -> 200 | I43: =E68+H68 -> 0
B44: 500 MB | C44: =SUM(C93:D93) -> 0 | D44: =SUM(E93:K93) -> 847.45763 | E44: =D44 -> 847.45763 | F44: =D44 -> 847.45763 | G44: =C69+F69 -> 0 | H44: =D69+G69 -> 500 | I44: =E69+H69 -> 0
B45: 1.2 GB | C45: =SUM(C94:D94) -> 0 | D45: =SUM(E94:K94) -> 2118.6441 | E45: =D45 -> 2118.6441 | F45: =D45 -> 2118.6441 | G45: =C70+F70 -> 0 | H45: =D70+G70 -> 1200 | I45: =E70+H70 -> 0
B46: 2.5 GB | C46: =SUM(C95:D95) -> 0 | D46: =SUM(E95:K95) -> 4237.2881 | E46: =D46 -> 4237.2881 | F46: =D46 -> 4237.2881 | G46: =C71+F71 -> 0 | H46: =D71+G71 -> 2500 | I46: =E71+H71 -> 0
B47: 5 GB | C47: =SUM(C96:D96) -> 0 | D47: =SUM(E96:K96) -> 8474.5763 | E47: =D47 -> 8474.5763 | F47: =D47 -> 8474.5763 | G47: =C72+F72 -> 0 | H47: =D72+G72 -> 5000 | I47: =E72+H72 -> 0
B48: 8.2 GB | C48: =SUM(C97:D97) -> 0 | D48: =SUM(E97:K97) -> 12711.864 | E48: =D48 -> 12711.864 | F48: =D48 -> 12711.864 | G48: =C73+F73 -> 0 | H48: =D73+G73 -> 8192 | I48: =E73+H73 -> 0
B49: 12.3 GB | C49: =SUM(C98:D98) -> 0 | D49: =SUM(E98:K98) -> 16949.153 | E49: =D49 -> 16949.153 | F49: =D49 -> 16949.153 | G49: =C74+F74 -> 0 | H49: =D74+G74 -> 12288 | I49: =E74+H74 -> 0
B50: 40 MIN | C50: =SUM(C99:D99) -> 0 | D50: =SUM(E99:K99) -> 423.72881 | E50: =D50 -> 423.72881 | F50: =D50 -> 423.72881 | G50: =C75+F75 -> 40 | H50: =D75+G75 -> 0 | I50: =E75+H75 -> 0
B51: 80 MIN | C51: =SUM(C100:D100) -> 0 | D51: =SUM(E100:K100) -> 805.08475 | E51: =D51 -> 805.08475 | F51: =D51 -> 805.08475 | G51: =C76+F76 -> 80 | H51: =D76+G76 -> 0 | I51: =E76+H76 -> 0
B52: 160 MIN | C52: =SUM(C101:D101) -> 0 | D52: =SUM(E101:K101) -> 1525.4237 | E52: =D52 -> 1525.4237 | F52: =D52 -> 1525.4237 | G52: =C77+F77 -> 160 | H52: =D77+G77 -> 0 | I52: =E77+H77 -> 0
B53: 300 SMS | C53: =SUM(C102:D102) -> 0 | D53: =SUM(E102:K102) -> 423.72881 | E53: =D53 -> 423.72881 | F53: =D53 -> 423.72881 | G53: =C78+F78 -> 0 | H53: =D78+G78 -> 0 | I53: =E78+H78 -> 300
B54: 500 SMS | C54: =SUM(C103:D103) -> 0 | D54: =SUM(E103:K103) -> 635.59322 | E54: =D54 -> 635.59322 | F54: =D54 -> 635.59322 | G54: =C79+F79 -> 0 | H54: =D79+G79 -> 0 | I54: =E79+H79 -> 500
B55: 2000 SMS | C55: =SUM(C104:D104) -> 0 | D55: =SUM(E104:K104) -> 2288.1356 | E55: =D55 -> 2288.1356 | F55: =D55 -> 2288.1356 | G55: =C80+F80 -> 0 | H55: =D80+G80 -> 0 | I55: =E80+H80 -> 2000
D57: x
B58: USAGE SUMMARY
B60: Baseline Packages (Excl VAT) | C60: Inclusive Minutes used Per Month | D60: Inclusive Megabytes used Per Month | E60: Inclusive SMS used Per Month | F60: OOB Minutes used Per Month | G60: OOB Megabytes used Per Month | H60: OOB SMS used Per Month
B62: =B9 -> MVLP1 | C62: =('MVLP INPUT'!E58+'MVLP INPUT'!R58)*(100%-'MVLP INPUT'!E82) -> 5 | D62: =('MVLP INPUT'!F58+'MVLP INPUT'!S58)*(100%-'MVLP INPUT'!F82) -> 150 | E62: =('MVLP INPUT'!G58+'MVLP INPUT'!T58)*(100%-'MVLP INPUT'!G82) -> 10 | F62: ='MVLP INPUT'!I58 -> 0 | G62: ='MVLP INPUT'!J58 -> 0 | H62: ='MVLP INPUT'!K58 -> 0
B63: =B10 -> MVLP2 | C63: =('MVLP INPUT'!E59+'MVLP INPUT'!R59)*(100%-'MVLP INPUT'!E83) -> 25 | D63: =('MVLP INPUT'!F59+'MVLP INPUT'!S59)*(100%-'MVLP INPUT'!F83) -> 1024 | E63: =('MVLP INPUT'!G59+'MVLP INPUT'!T59)*(100%-'MVLP INPUT'!G83) -> 30 | F63: ='MVLP INPUT'!I59 -> 0 | G63: ='MVLP INPUT'!J59 -> 0 | H63: ='MVLP INPUT'!K59 -> 0
B64: =B11 -> MVLP3 | C64: =('MVLP INPUT'!E60+'MVLP INPUT'!R60)*(100%-'MVLP INPUT'!E84) -> 60 | D64: =('MVLP INPUT'!F60+'MVLP INPUT'!S60)*(100%-'MVLP INPUT'!F84) -> 2048 | E64: =('MVLP INPUT'!G60+'MVLP INPUT'!T60)*(100%-'MVLP INPUT'!G84) -> 30 | F64: ='MVLP INPUT'!I60 -> 0 | G64: ='MVLP INPUT'!J60 -> 0 | H64: ='MVLP INPUT'!K60 -> 0
B65: =B12 -> MVLP4 | C65: =('MVLP INPUT'!E61+'MVLP INPUT'!R61)*(100%-'MVLP INPUT'!E85) -> 80 | D65: =('MVLP INPUT'!F61+'MVLP INPUT'!S61)*(100%-'MVLP INPUT'!F85) -> 5120 | E65: =('MVLP INPUT'!G61+'MVLP INPUT'!T61)*(100%-'MVLP INPUT'!G85) -> 30 | F65: ='MVLP INPUT'!I61 -> 0 | G65: ='MVLP INPUT'!J61 -> 0 | H65: ='MVLP INPUT'!K61 -> 0
B66: =B13 -> MVLP5 | C66: =('MVLP INPUT'!E62+'MVLP INPUT'!R62)*(100%-'MVLP INPUT'!E86) -> 80 | D66: =('MVLP INPUT'!F62+'MVLP INPUT'!S62)*(100%-'MVLP INPUT'!F86) -> 9216 | E66: =('MVLP INPUT'!G62+'MVLP INPUT'!T62)*(100%-'MVLP INPUT'!G86) -> 30 | F66: ='MVLP INPUT'!I62 -> 0 | G66: ='MVLP INPUT'!J62 -> 0 | H66: ='MVLP INPUT'!K62 -> 0
B67: =B14 -> MVLP6 | C67: =('MVLP INPUT'!E63+'MVLP INPUT'!R63)*(100%-'MVLP INPUT'!E87) -> 240 | D67: =('MVLP INPUT'!F63+'MVLP INPUT'!S63)*(100%-'MVLP INPUT'!F87) -> 15360 | E67: =('MVLP INPUT'!G63+'MVLP INPUT'!T63)*(100%-'MVLP INPUT'!G87) -> 100 | F67: ='MVLP INPUT'!I63 -> 0 | G67: ='MVLP INPUT'!J63 -> 0 | H67: ='MVLP INPUT'!K63 -> 0
B68: 200 MB | C68: =('MVLP INPUT'!E64+'MVLP INPUT'!R64)*(100%-'MVLP INPUT'!E88) -> 0 | D68: =('MVLP INPUT'!F64+'MVLP INPUT'!S64)*(100%-'MVLP INPUT'!F88) -> 200 | E68: =('MVLP INPUT'!G64+'MVLP INPUT'!T64)*(100%-'MVLP INPUT'!G88) -> 0 | F68: ='MVLP INPUT'!I64 -> 0 | G68: ='MVLP INPUT'!J64 -> 0 | H68: ='MVLP INPUT'!K64 -> 0
B69: 500 MB | C69: =('MVLP INPUT'!E65+'MVLP INPUT'!R65)*(100%-'MVLP INPUT'!E89) -> 0 | D69: =('MVLP INPUT'!F65+'MVLP INPUT'!S65)*(100%-'MVLP INPUT'!F89) -> 500 | E69: =('MVLP INPUT'!G65+'MVLP INPUT'!T65)*(100%-'MVLP INPUT'!G89) -> 0 | F69: ='MVLP INPUT'!I65 -> 0 | G69: ='MVLP INPUT'!J65 -> 0 | H69: ='MVLP INPUT'!K65 -> 0
B70: 1.2 GB | C70: =('MVLP INPUT'!E66+'MVLP INPUT'!R66)*(100%-'MVLP INPUT'!E90) -> 0 | D70: =('MVLP INPUT'!F66+'MVLP INPUT'!S66)*(100%-'MVLP INPUT'!F90) -> 1200 | E70: =('MVLP INPUT'!G66+'MVLP INPUT'!T66)*(100%-'MVLP INPUT'!G90) -> 0 | F70: ='MVLP INPUT'!I66 -> 0 | G70: ='MVLP INPUT'!J66 -> 0 | H70: ='MVLP INPUT'!K66 -> 0
B71: 2.5 GB | C71: =('MVLP INPUT'!E67+'MVLP INPUT'!R67)*(100%-'MVLP INPUT'!E91) -> 0 | D71: =('MVLP INPUT'!F67+'MVLP INPUT'!S67)*(100%-'MVLP INPUT'!F91) -> 2500 | E71: =('MVLP INPUT'!G67+'MVLP INPUT'!T67)*(100%-'MVLP INPUT'!G91) -> 0 | F71: ='MVLP INPUT'!I67 -> 0 | G71: ='MVLP INPUT'!J67 -> 0 | H71: ='MVLP INPUT'!K67 -> 0
B72: 5 GB | C72: =('MVLP INPUT'!E68+'MVLP INPUT'!R68)*(100%-'MVLP INPUT'!E92) -> 0 | D72: =('MVLP INPUT'!F68+'MVLP INPUT'!S68)*(100%-'MVLP INPUT'!F92) -> 5000 | E72: =('MVLP INPUT'!G68+'MVLP INPUT'!T68)*(100%-'MVLP INPUT'!G92) -> 0 | F72: ='MVLP INPUT'!I68 -> 0 | G72: ='MVLP INPUT'!J68 -> 0 | H72: ='MVLP INPUT'!K68 -> 0
B73: 8.2 GB | C73: =('MVLP INPUT'!E69+'MVLP INPUT'!R69)*(100%-'MVLP INPUT'!E93) -> 0 | D73: =('MVLP INPUT'!F69+'MVLP INPUT'!S69)*(100%-'MVLP INPUT'!F93) -> 8192 | E73: =('MVLP INPUT'!G69+'MVLP INPUT'!T69)*(100%-'MVLP INPUT'!G93) -> 0 | F73: ='MVLP INPUT'!I69 -> 0 | G73: ='MVLP INPUT'!J69 -> 0 | H73: ='MVLP INPUT'!K69 -> 0
B74: 12.3 GB | C74: =('MVLP INPUT'!E70+'MVLP INPUT'!R70)*(100%-'MVLP INPUT'!E94) -> 0 | D74: =('MVLP INPUT'!F70+'MVLP INPUT'!S70)*(100%-'MVLP INPUT'!F94) -> 12288 | E74: =('MVLP INPUT'!G70+'MVLP INPUT'!T70)*(100%-'MVLP INPUT'!G94) -> 0 | F74: 0 | G74: ='MVLP INPUT'!J70 -> 0 | H74: ='MVLP INPUT'!K70 -> 0
B75: 40 MIN | C75: =('MVLP INPUT'!E71+'MVLP INPUT'!R71)*(100%-'MVLP INPUT'!E95) -> 40 | D75: =('MVLP INPUT'!F71+'MVLP INPUT'!S71)*(100%-'MVLP INPUT'!F95) -> 0 | E75: =('MVLP INPUT'!G71+'MVLP INPUT'!T71)*(100%-'MVLP INPUT'!G95) -> 0 | F75: 0 | G75: ='MVLP INPUT'!J71 -> 0 | H75: ='MVLP INPUT'!K71 -> 0
B76: 80 MIN | C76: =('MVLP INPUT'!E72+'MVLP INPUT'!R72)*(100%-'MVLP INPUT'!E96) -> 80 | D76: =('MVLP INPUT'!F72+'MVLP INPUT'!S72)*(100%-'MVLP INPUT'!F96) -> 0 | E76: =('MVLP INPUT'!G72+'MVLP INPUT'!T72)*(100%-'MVLP INPUT'!G96) -> 0 | F76: 0 | G76: ='MVLP INPUT'!J72 -> 0 | H76: ='MVLP INPUT'!K72 -> 0
B77: 160 MIN | C77: =('MVLP INPUT'!E73+'MVLP INPUT'!R73)*(100%-'MVLP INPUT'!E97) -> 160 | D77: =('MVLP INPUT'!F73+'MVLP INPUT'!S73)*(100%-'MVLP INPUT'!F97) -> 0 | E77: =('MVLP INPUT'!G73+'MVLP INPUT'!T73)*(100%-'MVLP INPUT'!G97) -> 0 | F77: 0 | G77: ='MVLP INPUT'!J73 -> 0 | H77: ='MVLP INPUT'!K73 -> 0
B78: 300 SMS | C78: =('MVLP INPUT'!E74+'MVLP INPUT'!R74)*(100%-'MVLP INPUT'!E98) -> 0 | D78: =('MVLP INPUT'!F74+'MVLP INPUT'!S74)*(100%-'MVLP INPUT'!F98) -> 0 | E78: =('MVLP INPUT'!G74+'MVLP INPUT'!T74)*(100%-'MVLP INPUT'!G98) -> 300 | F78: ='MVLP INPUT'!I74 -> 0 | G78: ='MVLP INPUT'!J74 -> 0 | H78: ='MVLP INPUT'!K74 -> 0
B79: 500 SMS | C79: =('MVLP INPUT'!E75+'MVLP INPUT'!R75)*(100%-'MVLP INPUT'!E99) -> 0 | D79: =('MVLP INPUT'!F75+'MVLP INPUT'!S75)*(100%-'MVLP INPUT'!F99) -> 0 | E79: =('MVLP INPUT'!G75+'MVLP INPUT'!T75)*(100%-'MVLP INPUT'!G99) -> 500 | F79: ='MVLP INPUT'!I75 -> 0 | G79: ='MVLP INPUT'!J75 -> 0 | H79: ='MVLP INPUT'!K75 -> 0
B80: 2000 SMS | C80: =('MVLP INPUT'!E76+'MVLP INPUT'!R76)*(100%-'MVLP INPUT'!E100) -> 0 | D80: =('MVLP INPUT'!F76+'MVLP INPUT'!S76)*(100%-'MVLP INPUT'!F100) -> 0 | E80: =('MVLP INPUT'!G76+'MVLP INPUT'!T76)*(100%-'MVLP INPUT'!G100) -> 2000 | F80: ='MVLP INPUT'!I76 -> 0 | G80: ='MVLP INPUT'!J76 -> 0 | H80: ='MVLP INPUT'!K76 -> 0
B82: REVENUE CALCULATIONS
B84: Baseline Packages (Excl VAT) | C84: Connection Fee | D84: Courier Fee | E84: Subscription Fee | F84: Itemized Billing | G84: Converged Services | H84: Other Services | I84: Out of Bundle Minutes | J84: Out of Bundle Megabytes | K84: Out of Bundle SMS
B86: =B62 -> MVLP1 | C86: ='MVLP INPUT'!E34 -> 0 | D86: ='MVLP INPUT'!G34 -> 0 | E86: ='MVLP INPUT'!F34 -> 423.72881 | F86: =('MVLP INPUT'!$I10*'MVLP INPUT'!$H82) -> 0 | G86: =('MVLP INPUT'!$J10*'MVLP INPUT'!$I82) -> 0 | H86: =('MVLP INPUT'!$K10*'MVLP INPUT'!$J82) -> 0 | I86: ='MVLP INPUT'!I58*'MVLP INPUT'!$L10 -> 0 | J86: ='MVLP INPUT'!J58*'MVLP INPUT'!M10 -> 0 | K86: ='MVLP INPUT'!K58*'MVLP INPUT'!N10 -> 0
B87: =B63 -> MVLP2 | C87: ='MVLP INPUT'!E35 -> 0 | D87: ='MVLP INPUT'!G35 -> 0 | E87: ='MVLP INPUT'!F35 -> 2118.6441 | F87: =('MVLP INPUT'!$I11*'MVLP INPUT'!$H83) -> 0 | G87: =('MVLP INPUT'!$J11*'MVLP INPUT'!$I83) -> 0 | H87: =('MVLP INPUT'!$K11*'MVLP INPUT'!$J83) -> 0 | I87: ='MVLP INPUT'!I59*'MVLP INPUT'!$L11 -> 0 | J87: ='MVLP INPUT'!J59*'MVLP INPUT'!M11 -> 0 | K87: ='MVLP INPUT'!K59*'MVLP INPUT'!N11 -> 0
B88: =B64 -> MVLP3 | C88: ='MVLP INPUT'!E36 -> 0 | D88: ='MVLP INPUT'!G36 -> 0 | E88: ='MVLP INPUT'!F36 -> 4661.0169 | F88: =('MVLP INPUT'!$I12*'MVLP INPUT'!$H84) -> 0 | G88: =('MVLP INPUT'!$J12*'MVLP INPUT'!$I84) -> 0 | H88: =('MVLP INPUT'!$K12*'MVLP INPUT'!$J84) -> 0 | I88: ='MVLP INPUT'!I60*'MVLP INPUT'!$L12 -> 0 | J88: ='MVLP INPUT'!J60*'MVLP INPUT'!M12 -> 0 | K88: ='MVLP INPUT'!K60*'MVLP INPUT'!N12 -> 0
B89: =B65 -> MVLP4 | C89: ='MVLP INPUT'!E37 -> 0 | D89: ='MVLP INPUT'!G37 -> 0 | E89: ='MVLP INPUT'!F37 -> 10593.22 | F89: =('MVLP INPUT'!$I13*'MVLP INPUT'!$H85) -> 0 | G89: =('MVLP INPUT'!$J13*'MVLP INPUT'!$I85) -> 0 | H89: =('MVLP INPUT'!$K13*'MVLP INPUT'!$J85) -> 0 | I89: ='MVLP INPUT'!I61*'MVLP INPUT'!$L13 -> 0 | J89: ='MVLP INPUT'!J61*'MVLP INPUT'!M13 -> 0 | K89: ='MVLP INPUT'!K61*'MVLP INPUT'!N13 -> 0
B90: =B66 -> MVLP5 | C90: ='MVLP INPUT'!E38 -> 0 | D90: ='MVLP INPUT'!G38 -> 0 | E90: ='MVLP INPUT'!F38 -> 15677.966 | F90: =('MVLP INPUT'!$I14*'MVLP INPUT'!$H86) -> 0 | G90: =('MVLP INPUT'!$J14*'MVLP INPUT'!$I86) -> 0 | H90: =('MVLP INPUT'!$K14*'MVLP INPUT'!$J86) -> 0 | I90: ='MVLP INPUT'!I62*'MVLP INPUT'!$L14 -> 0 | J90: ='MVLP INPUT'!J62*'MVLP INPUT'!M14 -> 0 | K90: ='MVLP INPUT'!K62*'MVLP INPUT'!N14 -> 0
B91: =B67 -> MVLP6 | C91: ='MVLP INPUT'!E39 -> 0 | D91: ='MVLP INPUT'!G39 -> 0 | E91: ='MVLP INPUT'!F39 -> 33050.847 | F91: =('MVLP INPUT'!$I15*'MVLP INPUT'!$H87) -> 0 | G91: =('MVLP INPUT'!$J15*'MVLP INPUT'!$I87) -> 0 | H91: =('MVLP INPUT'!$K15*'MVLP INPUT'!$J87) -> 0 | I91: ='MVLP INPUT'!I63*'MVLP INPUT'!$L15 -> 0 | J91: ='MVLP INPUT'!J63*'MVLP INPUT'!M15 -> 0 | K91: ='MVLP INPUT'!K63*'MVLP INPUT'!N15 -> 0
B92: 200 MB | C92: ='MVLP INPUT'!E40 -> 0 | D92: ='MVLP INPUT'!G40 -> 0 | E92: ='MVLP INPUT'!F40 -> 423.72881 | F92: =('MVLP INPUT'!$I16*'MVLP INPUT'!$H88) -> 0 | G92: =('MVLP INPUT'!$J16*'MVLP INPUT'!$I88) -> 0 | H92: =('MVLP INPUT'!$K16*'MVLP INPUT'!$J88) -> 0 | I92: ='MVLP INPUT'!I64*'MVLP INPUT'!$L16 -> 0 | J92: ='MVLP INPUT'!J64*'MVLP INPUT'!M16 -> 0 | K92: ='MVLP INPUT'!K64*'MVLP INPUT'!N16 -> 0
B93: 500 MB | C93: ='MVLP INPUT'!E41 -> 0 | D93: ='MVLP INPUT'!G41 -> 0 | E93: ='MVLP INPUT'!F41 -> 847.45763 | F93: =('MVLP INPUT'!$I17*'MVLP INPUT'!$H89) -> 0 | G93: =('MVLP INPUT'!$J17*'MVLP INPUT'!$I89) -> 0 | H93: =('MVLP INPUT'!$K17*'MVLP INPUT'!$J89) -> 0 | I93: ='MVLP INPUT'!I65*'MVLP INPUT'!$L17 -> 0 | J93: ='MVLP INPUT'!J65*'MVLP INPUT'!M17 -> 0 | K93: ='MVLP INPUT'!K65*'MVLP INPUT'!N17 -> 0
B94: 1.2 GB | C94: ='MVLP INPUT'!E42 -> 0 | D94: ='MVLP INPUT'!G42 -> 0 | E94: ='MVLP INPUT'!F42 -> 2118.6441 | F94: =('MVLP INPUT'!$I18*'MVLP INPUT'!$H90) -> 0 | G94: =('MVLP INPUT'!$J18*'MVLP INPUT'!$I90) -> 0 | H94: =('MVLP INPUT'!$K18*'MVLP INPUT'!$J90) -> 0 | I94: ='MVLP INPUT'!I66*'MVLP INPUT'!$L18 -> 0 | J94: ='MVLP INPUT'!J66*'MVLP INPUT'!M18 -> 0 | K94: ='MVLP INPUT'!K66*'MVLP INPUT'!N18 -> 0
B95: 2.5 GB | C95: ='MVLP INPUT'!E43 -> 0 | D95: ='MVLP INPUT'!G43 -> 0 | E95: ='MVLP INPUT'!F43 -> 4237.2881 | F95: =('MVLP INPUT'!$I19*'MVLP INPUT'!$H91) -> 0 | G95: =('MVLP INPUT'!$J19*'MVLP INPUT'!$I91) -> 0 | H95: =('MVLP INPUT'!$K19*'MVLP INPUT'!$J91) -> 0 | I95: ='MVLP INPUT'!I67*'MVLP INPUT'!$L19 -> 0 | J95: ='MVLP INPUT'!J67*'MVLP INPUT'!M19 -> 0 | K95: ='MVLP INPUT'!K67*'MVLP INPUT'!N19 -> 0
B96: 5 GB | C96: ='MVLP INPUT'!E44 -> 0 | D96: ='MVLP INPUT'!G44 -> 0 | E96: ='MVLP INPUT'!F44 -> 8474.5763 | F96: =('MVLP INPUT'!$I20*'MVLP INPUT'!$H92) -> 0 | G96: =('MVLP INPUT'!$J20*'MVLP INPUT'!$I92) -> 0 | H96: =('MVLP INPUT'!$K20*'MVLP INPUT'!$J92) -> 0 | I96: ='MVLP INPUT'!I68*'MVLP INPUT'!$L20 -> 0 | J96: ='MVLP INPUT'!J68*'MVLP INPUT'!M20 -> 0 | K96: ='MVLP INPUT'!K68*'MVLP INPUT'!N20 -> 0
B97: 8.2 GB | C97: ='MVLP INPUT'!E45 -> 0 | D97: ='MVLP INPUT'!G45 -> 0 | E97: ='MVLP INPUT'!F45 -> 12711.864 | F97: =('MVLP INPUT'!$I21*'MVLP INPUT'!$H93) -> 0 | G97: =('MVLP INPUT'!$J21*'MVLP INPUT'!$I93) -> 0 | H97: =('MVLP INPUT'!$K21*'MVLP INPUT'!$J93) -> 0 | I97: ='MVLP INPUT'!I69*'MVLP INPUT'!$L21 -> 0 | J97: ='MVLP INPUT'!J69*'MVLP INPUT'!M21 -> 0 | K97: ='MVLP INPUT'!K69*'MVLP INPUT'!N21 -> 0
B98: 12.3 GB | C98: ='MVLP INPUT'!E46 -> 0 | D98: ='MVLP INPUT'!G46 -> 0 | E98: ='MVLP INPUT'!F46 -> 16949.153 | F98: =('MVLP INPUT'!$I22*'MVLP INPUT'!$H94) -> 0 | G98: =('MVLP INPUT'!$J22*'MVLP INPUT'!$I94) -> 0 | H98: =('MVLP INPUT'!$K22*'MVLP INPUT'!$J94) -> 0 | I98: ='MVLP INPUT'!I70*'MVLP INPUT'!$L22 -> 0 | J98: ='MVLP INPUT'!J70*'MVLP INPUT'!M22 -> 0 | K98: ='MVLP INPUT'!K70*'MVLP INPUT'!N22 -> 0
B99: 40 MIN | C99: ='MVLP INPUT'!E47 -> 0 | D99: ='MVLP INPUT'!G47 -> 0 | E99: ='MVLP INPUT'!F47 -> 423.72881 | F99: =('MVLP INPUT'!$I23*'MVLP INPUT'!$H95) -> 0 | G99: =('MVLP INPUT'!$J23*'MVLP INPUT'!$I95) -> 0 | H99: =('MVLP INPUT'!$K23*'MVLP INPUT'!$J95) -> 0 | I99: 0 | J99: ='MVLP INPUT'!J71*'MVLP INPUT'!M23 -> 0 | K99: ='MVLP INPUT'!K71*'MVLP INPUT'!N23 -> 0
B100: 80 MIN | C100: ='MVLP INPUT'!E48 -> 0 | D100: ='MVLP INPUT'!G48 -> 0 | E100: ='MVLP INPUT'!F48 -> 805.08475 | F100: =('MVLP INPUT'!$I24*'MVLP INPUT'!$H96) -> 0 | G100: =('MVLP INPUT'!$J24*'MVLP INPUT'!$I96) -> 0 | H100: =('MVLP INPUT'!$K24*'MVLP INPUT'!$J96) -> 0 | I100: 0 | J100: ='MVLP INPUT'!J72*'MVLP INPUT'!M24 -> 0 | K100: ='MVLP INPUT'!K72*'MVLP INPUT'!N24 -> 0
B101: 160 MIN | C101: ='MVLP INPUT'!E49 -> 0 | D101: ='MVLP INPUT'!G49 -> 0 | E101: ='MVLP INPUT'!F49 -> 1525.4237 | F101: =('MVLP INPUT'!$I25*'MVLP INPUT'!$H97) -> 0 | G101: =('MVLP INPUT'!$J25*'MVLP INPUT'!$I97) -> 0 | H101: =('MVLP INPUT'!$K25*'MVLP INPUT'!$J97) -> 0 | I101: 0 | J101: ='MVLP INPUT'!J73*'MVLP INPUT'!M25 -> 0 | K101: ='MVLP INPUT'!K73*'MVLP INPUT'!N25 -> 0
B102: 300 SMS | C102: ='MVLP INPUT'!E50 -> 0 | D102: ='MVLP INPUT'!G50 -> 0 | E102: ='MVLP INPUT'!F50 -> 423.72881 | F102: =('MVLP INPUT'!$I26*'MVLP INPUT'!$H98) -> 0 | G102: =('MVLP INPUT'!$J26*'MVLP INPUT'!$I98) -> 0 | H102: =('MVLP INPUT'!$K26*'MVLP INPUT'!$J98) -> 0 | I102: ='MVLP INPUT'!I74*'MVLP INPUT'!$L26 -> 0 | J102: ='MVLP INPUT'!J74*'MVLP INPUT'!M26 -> 0 | K102: ='MVLP INPUT'!K74*'MVLP INPUT'!N26 -> 0
B103: 500 SMS | C103: ='MVLP INPUT'!E51 -> 0 | D103: ='MVLP INPUT'!G51 -> 0 | E103: ='MVLP INPUT'!F51 -> 635.59322 | F103: =('MVLP INPUT'!$I27*'MVLP INPUT'!$H99) -> 0 | G103: =('MVLP INPUT'!$J27*'MVLP INPUT'!$I99) -> 0 | H103: =('MVLP INPUT'!$K27*'MVLP INPUT'!$J99) -> 0 | I103: ='MVLP INPUT'!I75*'MVLP INPUT'!$L27 -> 0 | J103: ='MVLP INPUT'!J75*'MVLP INPUT'!M27 -> 0 | K103: ='MVLP INPUT'!K75*'MVLP INPUT'!N27 -> 0
B104: 2000 SMS | C104: ='MVLP INPUT'!E52 -> 0 | D104: ='MVLP INPUT'!G52 -> 0 | E104: ='MVLP INPUT'!F52 -> 2288.1356 | F104: =('MVLP INPUT'!$I28*'MVLP INPUT'!$H100) -> 0 | G104: =('MVLP INPUT'!$J28*'MVLP INPUT'!$I100) -> 0 | H104: =('MVLP INPUT'!$K28*'MVLP INPUT'!$J100) -> 0 | I104: ='MVLP INPUT'!I76*'MVLP INPUT'!$L28 -> 0 | J104: ='MVLP INPUT'!J76*'MVLP INPUT'!M28 -> 0 | K104: ='MVLP INPUT'!K76*'MVLP INPUT'!N28 -> 0
B106: COST CALCULATIONS
B108: Baseline Packages (Excl VAT) | C108: SIM & Packaging | D108: Courier Fee | E108: Inclusive Value | F108: Itemized Billing | G108: Converged Services | H108: Other Services | I108: Out of Bundle Minutes | J108: Out of Bundle Megabytes | K108: Out of Bundle SMS
B110: =B86 -> MVLP1 | C110: ='MVLP INPUT'!E106 -> 2250 | D110: ='MVLP INPUT'!F106 -> 0 | E110: =(C62*'MVLP INPUT'!J106)+('MVLP DASHBOARD'!D62*'MVLP INPUT'!K106)+('MVLP DASHBOARD'!E62*'MVLP INPUT'!L106)+('MVLP DASHBOARD'!F62*'MVLP INPUT'!J106)+('MVLP DASHBOARD'!G62*'MVLP INPUT'!K106)+('MVLP DASHBOARD'!H62*'MVLP INPUT'!L106) -> 192.79703 | F110: =('MVLP INPUT'!G106*'MVLP INPUT'!H82) -> 0 | G110: =('MVLP INPUT'!H106*'MVLP INPUT'!I82) -> 0 | H110: ='MVLP INPUT'!I106*'MVLP INPUT'!J82 -> 0 | I110: ='MVLP INPUT'!I58*'MVLP INPUT'!J106 -> 0 | J110: ='MVLP INPUT'!J58*'MVLP INPUT'!K106 -> 0 | K110: ='MVLP INPUT'!K58*'MVLP INPUT'!L106 -> 0
B111: =B87 -> MVLP2 | C111: ='MVLP INPUT'!E107 -> 2250 | D111: ='MVLP INPUT'!F107 -> 0 | E111: =(C63*'MVLP INPUT'!J107)+('MVLP DASHBOARD'!D63*'MVLP INPUT'!K107)+('MVLP DASHBOARD'!E63*'MVLP INPUT'!L107)+('MVLP DASHBOARD'!F63*'MVLP INPUT'!J107)+('MVLP DASHBOARD'!G63*'MVLP INPUT'!K107)+('MVLP DASHBOARD'!H63*'MVLP INPUT'!L107) -> 1225.6792 | F111: =('MVLP INPUT'!G107*'MVLP INPUT'!H83) -> 0 | G111: =('MVLP INPUT'!H107*'MVLP INPUT'!I83) -> 0 | H111: ='MVLP INPUT'!I107*'MVLP INPUT'!J83 -> 0 | I111: ='MVLP INPUT'!I59*'MVLP INPUT'!J107 -> 0 | J111: ='MVLP INPUT'!J59*'MVLP INPUT'!K107 -> 0 | K111: ='MVLP INPUT'!K59*'MVLP INPUT'!L107 -> 0
B112: =B88 -> MVLP3 | C112: ='MVLP INPUT'!E108 -> 2250 | D112: ='MVLP INPUT'!F108 -> 0 | E112: =(C64*'MVLP INPUT'!J108)+('MVLP DASHBOARD'!D64*'MVLP INPUT'!K108)+('MVLP DASHBOARD'!E64*'MVLP INPUT'!L108)+('MVLP DASHBOARD'!F64*'MVLP INPUT'!J108)+('MVLP DASHBOARD'!G64*'MVLP INPUT'!K108)+('MVLP DASHBOARD'!H64*'MVLP INPUT'!L108) -> 2489.4928 | F112: =('MVLP INPUT'!G108*'MVLP INPUT'!H84) -> 0 | G112: =('MVLP INPUT'!H108*'MVLP INPUT'!I84) -> 0 | H112: ='MVLP INPUT'!I108*'MVLP INPUT'!J84 -> 0 | I112: ='MVLP INPUT'!I60*'MVLP INPUT'!J108 -> 0 | J112: ='MVLP INPUT'!J60*'MVLP INPUT'!K108 -> 0 | K112: ='MVLP INPUT'!K60*'MVLP INPUT'!L108 -> 0
B113: =B89 -> MVLP4 | C113: ='MVLP INPUT'!E109 -> 2250 | D113: ='MVLP INPUT'!F109 -> 0 | E113: =(C65*'MVLP INPUT'!J109)+('MVLP DASHBOARD'!D65*'MVLP INPUT'!K109)+('MVLP DASHBOARD'!E65*'MVLP INPUT'!L109)+('MVLP DASHBOARD'!F65*'MVLP INPUT'!J109)+('MVLP DASHBOARD'!G65*'MVLP INPUT'!K109)+('MVLP DASHBOARD'!H65*'MVLP INPUT'!L109) -> 5740.6792 | F113: =('MVLP INPUT'!G109*'MVLP INPUT'!H85) -> 0 | G113: =('MVLP INPUT'!H109*'MVLP INPUT'!I85) -> 0 | H113: ='MVLP INPUT'!I109*'MVLP INPUT'!J85 -> 0 | I113: ='MVLP INPUT'!I61*'MVLP INPUT'!J109 -> 0 | J113: ='MVLP INPUT'!J61*'MVLP INPUT'!K109 -> 0 | K113: ='MVLP INPUT'!K61*'MVLP INPUT'!L109 -> 0
B114: =B90 -> MVLP5 | C114: ='MVLP INPUT'!E110 -> 2250 | D114: ='MVLP INPUT'!F110 -> 0 | E114: =(C66*'MVLP INPUT'!J110)+('MVLP DASHBOARD'!D66*'MVLP INPUT'!K110)+('MVLP DASHBOARD'!E66*'MVLP INPUT'!L110)+('MVLP DASHBOARD'!F66*'MVLP INPUT'!J110)+('MVLP DASHBOARD'!G66*'MVLP INPUT'!K110)+('MVLP DASHBOARD'!H66*'MVLP INPUT'!L110) -> 9906.103 | F114: =('MVLP INPUT'!G110*'MVLP INPUT'!H86) -> 0 | G114: =('MVLP INPUT'!H110*'MVLP INPUT'!I86) -> 0 | H114: ='MVLP INPUT'!I110*'MVLP INPUT'!J86 -> 0 | I114: ='MVLP INPUT'!I62*'MVLP INPUT'!J110 -> 0 | J114: ='MVLP INPUT'!J62*'MVLP INPUT'!K110 -> 0 | K114: ='MVLP INPUT'!K62*'MVLP INPUT'!L110 -> 0
B115: =B91 -> MVLP6 | C115: ='MVLP INPUT'!E111 -> 2250 | D115: ='MVLP INPUT'!F111 -> 0 | E115: =(C67*'MVLP INPUT'!J111)+('MVLP DASHBOARD'!D67*'MVLP INPUT'!K111)+('MVLP DASHBOARD'!E67*'MVLP INPUT'!L111)+('MVLP DASHBOARD'!F67*'MVLP INPUT'!J111)+('MVLP DASHBOARD'!G67*'MVLP INPUT'!K111)+('MVLP DASHBOARD'!H67*'MVLP INPUT'!L111) -> 17230.513 | F115: =('MVLP INPUT'!G111*'MVLP INPUT'!H87) -> 0 | G115: =('MVLP INPUT'!H111*'MVLP INPUT'!I87) -> 0 | H115: ='MVLP INPUT'!I111*'MVLP INPUT'!J87 -> 0 | I115: ='MVLP INPUT'!I63*'MVLP INPUT'!J111 -> 0 | J115: ='MVLP INPUT'!J63*'MVLP INPUT'!K111 -> 0 | K115: ='MVLP INPUT'!K63*'MVLP INPUT'!L111 -> 0
B116: 200 MB | C116: 0 | D116: ='MVLP INPUT'!F112 -> 0 | E116: =(C68*'MVLP INPUT'!J112)+('MVLP DASHBOARD'!D68*'MVLP INPUT'!K112)+('MVLP DASHBOARD'!E68*'MVLP INPUT'!L112)+('MVLP DASHBOARD'!F68*'MVLP INPUT'!J112)+('MVLP DASHBOARD'!G68*'MVLP INPUT'!K112)+('MVLP DASHBOARD'!H68*'MVLP INPUT'!L112) -> 203.38983 | F116: =('MVLP INPUT'!G112*'MVLP INPUT'!H88) -> 0 | G116: =('MVLP INPUT'!H112*'MVLP INPUT'!I88) -> 0 | H116: ='MVLP INPUT'!I112*'MVLP INPUT'!J88 -> 0 | I116: ='MVLP INPUT'!I64*'MVLP INPUT'!J112 -> 0 | J116: ='MVLP INPUT'!J64*'MVLP INPUT'!K112 -> 0 | K116: ='MVLP INPUT'!K64*'MVLP INPUT'!L112 -> 0
B117: 500 MB | C117: 0 | D117: ='MVLP INPUT'!F113 -> 0 | E117: =(C69*'MVLP INPUT'!J113)+('MVLP DASHBOARD'!D69*'MVLP INPUT'!K113)+('MVLP DASHBOARD'!E69*'MVLP INPUT'!L113)+('MVLP DASHBOARD'!F69*'MVLP INPUT'!J113)+('MVLP DASHBOARD'!G69*'MVLP INPUT'!K113)+('MVLP DASHBOARD'!H69*'MVLP INPUT'!L113) -> 508.47458 | F117: =('MVLP INPUT'!G113*'MVLP INPUT'!H89) -> 0 | G117: =('MVLP INPUT'!H113*'MVLP INPUT'!I89) -> 0 | H117: ='MVLP INPUT'!I113*'MVLP INPUT'!J89 -> 0 | I117: ='MVLP INPUT'!I65*'MVLP INPUT'!J113 -> 0 | J117: ='MVLP INPUT'!J65*'MVLP INPUT'!K113 -> 0 | K117: ='MVLP INPUT'!K65*'MVLP INPUT'!L113 -> 0
B118: 1.2 GB | C118: 0 | D118: ='MVLP INPUT'!F114 -> 0 | E118: =(C70*'MVLP INPUT'!J114)+('MVLP DASHBOARD'!D70*'MVLP INPUT'!K114)+('MVLP DASHBOARD'!E70*'MVLP INPUT'!L114)+('MVLP DASHBOARD'!F70*'MVLP INPUT'!J114)+('MVLP DASHBOARD'!G70*'MVLP INPUT'!K114)+('MVLP DASHBOARD'!H70*'MVLP INPUT'!L114) -> 1220.339 | F118: =('MVLP INPUT'!G114*'MVLP INPUT'!H90) -> 0 | G118: =('MVLP INPUT'!H114*'MVLP INPUT'!I90) -> 0 | H118: ='MVLP INPUT'!I114*'MVLP INPUT'!J90 -> 0 | I118: ='MVLP INPUT'!I66*'MVLP INPUT'!J114 -> 0 | J118: ='MVLP INPUT'!J66*'MVLP INPUT'!K114 -> 0 | K118: ='MVLP INPUT'!K66*'MVLP INPUT'!L114 -> 0
...

Sheet SUBSCRIBER NORMALIZATION
B3: =UPPER('<<VERSIONING NOTES>>'!$F$2)&TEXT(" SUBSCRIBER BASE NORMALIZATION VERSION ","")&'<<VERSIONING NOTES>>'!$F$3 -> METL SUBSCRIBER BASE NORMALIZATION VERSION MVNE Financial Framework Template Metl 20250604 1m | I3: =TEXT("Prepared by ","") -> Prepared by
I4: ='<<VERSIONING NOTES>>'!F4 -> Edward Wicks
B6: SIGMOID CURVE ASSUMPTIONS | F6: SEASONALITY | I6: Pre-paid Sims | L6: Post -paid
I7: 44652 | J7: 31067 | K7: =J7/$J$10 -> 0.62755277 | L7: 44652 | M7: 2180 | N7: =M7/$M$14 -> 0.57855626
B8: Start value | C8: =100%/6 -> 0.16666667 | F8: JANUARY | G8: =K16 -> 0.69071811 | I8: 44682 | J8: 32978 | K8: =J8/$J$10 -> 0.66615493 | L8: 44682 | M8: 3675 | N8: =M8/$M$14 -> 0.97531847
B9: Target value | C9: 1 | F9: FEBRUARY | G9: =K17 -> 0.61914958 | I9: 44713 | J9: 41198 | K9: =J9/$J$10 -> 0.83219877 | L9: 44713 | M9: 2715 | N9: =M9/$M$14 -> 0.7205414
B10: Start of fast growth (month) | C10: 3 | F10: MARCH | G10: =K18 -> 0.68778911 | I10: 44743 | J10: 49505 | K10: =J10/$J$10 -> 1 | L10: 44743 | M10: 2342 | N10: =M10/$M$14 -> 0.62154989
B11: Takeover time (count of months) | C11: 24 | F11: APRIL | G11: =K7 -> 0.62755277 | I11: 44774 | J11: 47865 | K11: =J11/$J$10 -> 0.96687203 | L11: 44774 | M11: 2524 | N11: =M11/$M$14 -> 0.66985138
B12: Curviness parameter | C12: 350 | F12: MAY | G12: =K8 -> 0.66615493 | I12: 44805 | J12: 46807 | K12: =J12/$J$10 -> 0.94550045 | L12: 44805 | M12: 2453 | N12: =M12/$M$14 -> 0.65100849
F13: JUNE | G13: =K9 -> 0.83219877 | I13: 44835 | J13: 38914 | K13: =J13/$J$10 -> 0.78606201 | L13: 44835 | M13: 3580 | N13: =M13/$M$14 -> 0.95010616
F14: JULY | G14: =K10 -> 1 | I14: 44866 | J14: 42270 | K14: =J14/$J$10 -> 0.85385315 | L14: 44866 | M14: 3768 | N14: =M14/$M$14 -> 1
B15: Month # | C15: Growth Sigmoid Curve Factor | F15: AUGUST | G15: =K11 -> 0.96687203 | I15: 44896 | J15: 43719 | K15: =J15/$J$10 -> 0.88312292 | L15: 44896 | M15: 3274 | N15: =M15/$M$14 -> 0.86889597
B16: 1 | C16: =myStartValue+(myTargetValue-myStartValue)/(1+myCurviness^((myStartofFastGrowth+myTakeoverPeriod/2-B16)/myTakeoverPeriod)) -> 0.19313704 | F16: SEPTEMBER | G16: =K12 -> 0.94550045 | I16: 44927 | J16: 34194 | K16: =J16/$J$10 -> 0.69071811 | L16: 44927 | M16: 2128 | N16: =M16/$M$14 -> 0.56475584
B17: =B16+1 -> 2 | C17: =$C$8+($C$9-$C$8)/(1+$C$12^(($C$10+$C$11/2-B17)/$C$11)) -> 0.20016058 | F17: OCTOBER | G17: =K13 -> 0.78606201 | I17: 44958 | J17: 30651 | K17: =J17/$J$10 -> 0.61914958 | L17: 44958 | M17: 2027 | N17: =M17/$M$14 -> 0.53795117
B18: =B17+1 -> 3 | C18: =$C$8+($C$9-$C$8)/(1+$C$12^(($C$10+$C$11/2-B18)/$C$11)) -> 0.20895006 | F18: NOVEMBER | G18: =K14 -> 0.85385315 | I18: 44986 | J18: 34049 | K18: =J18/$J$10 -> 0.68778911 | L18: 44986 | M18: 3045 | N18: =M18/$M$14 -> 0.80812102
B19: =B18+1 -> 4 | C19: =$C$8+($C$9-$C$8)/(1+$C$12^(($C$10+$C$11/2-B19)/$C$11)) -> 0.21989259 | F19: DECEMBER | G19: =K15 -> 0.88312292 | J19: =SUM(J7:J18) -> 473217 | M19: =SUM(M7:M18) -> 33711
B20: =B19+1 -> 5 | C20: =$C$8+($C$9-$C$8)/(1+$C$12^(($C$10+$C$11/2-B20)/$C$11)) -> 0.23342794 | L20: =M19/J19 -> 0.071237931
B21: =B20+1 -> 6 | C21: =$C$8+($C$9-$C$8)/(1+$C$12^(($C$10+$C$11/2-B21)/$C$11)) -> 0.25003748 | F21: CHURN FACTOR APPROXIMATION
B22: =B21+1 -> 7 | C22: =$C$8+($C$9-$C$8)/(1+$C$12^(($C$10+$C$11/2-B22)/$C$11)) -> 0.27022108
B23: =B22+1 -> 8 | C23: =$C$8+($C$9-$C$8)/(1+$C$12^(($C$10+$C$11/2-B23)/$C$11)) -> 0.2944584 | F23: Month # | G23: Opening Base | H23: Voluntary Churn | I23: Involuntary Churn | J23: Closing Base
B24: =B23+1 -> 9 | C24: =$C$8+($C$9-$C$8)/(1+$C$12^(($C$10+$C$11/2-B24)/$C$11)) -> 0.32315215 | F24: 1 | G24: 100 | H24: 5 | I24: =ROUND(G24*AVERAGE('MVLP INPUT'!$M$82:$M$91),0) -> 0 | J24: =G24-H24-I24 -> 95
B25: =B24+1 -> 10 | C25: =$C$8+($C$9-$C$8)/(1+$C$12^(($C$10+$C$11/2-B25)/$C$11)) -> 0.35655465 | F25: =F24+1 -> 2 | G25: =J24 -> 95 | H25: 5 | I25: =ROUND(G25*AVERAGE('MVLP INPUT'!$M$82:$M$91),0) -> 0 | J25: =G25-H25-I25 -> 90
B26: =B25+1 -> 11 | C26: =$C$8+($C$9-$C$8)/(1+$C$12^(($C$10+$C$11/2-B26)/$C$11)) -> 0.39468513 | F26: =F25+1 -> 3 | G26: =J25 -> 90 | H26: 5 | I26: =ROUND(G26*AVERAGE('MVLP INPUT'!$M$82:$M$91),0) -> 0 | J26: =G26-H26-I26 -> 85
B27: =B26+1 -> 12 | C27: =$C$8+($C$9-$C$8)/(1+$C$12^(($C$10+$C$11/2-B27)/$C$11)) -> 0.43725251 | F27: =F26+1 -> 4 | G27: =J26 -> 85 | H27: 5 | I27: =ROUND(G27*AVERAGE('MVLP INPUT'!$M$82:$M$91),0) -> 0 | J27: =G27-H27-I27 -> 80
B28: =B27+1 -> 13 | C28: =$C$8+($C$9-$C$8)/(1+$C$12^(($C$10+$C$11/2-B28)/$C$11)) -> 0.48360572 | F28: =F27+1 -> 5 | G28: =J27 -> 80 | H28: 5 | I28: =ROUND(G28*AVERAGE('MVLP INPUT'!$M$82:$M$91),0) -> 0 | J28: =G28-H28-I28 -> 75
B29: =B28+1 -> 14 | C29: =$C$8+($C$9-$C$8)/(1+$C$12^(($C$10+$C$11/2-B29)/$C$11)) -> 0.53273418 | F29: =F28+1 -> 6 | G29: =J28 -> 75 | H29: 5 | I29: =ROUND(G29*AVERAGE('MVLP INPUT'!$M$82:$M$91),0) -> 0 | J29: =G29-H29-I29 -> 70
B30: =B29+1 -> 15 | C30: =$C$8+($C$9-$C$8)/(1+$C$12^(($C$10+$C$11/2-B30)/$C$11)) -> 0.58333333 | F30: =F29+1 -> 7 | G30: =J29 -> 70 | H30: 5 | I30: =ROUND(G30*AVERAGE('MVLP INPUT'!$M$82:$M$91),0) -> 0 | J30: =G30-H30-I30 -> 65
B31: =B30+1 -> 16 | C31: =$C$8+($C$9-$C$8)/(1+$C$12^(($C$10+$C$11/2-B31)/$C$11)) -> 0.63393249 | F31: =F30+1 -> 8 | G31: =J30 -> 65 | H31: 5 | I31: =ROUND(G31*AVERAGE('MVLP INPUT'!$M$82:$M$91),0) -> 0 | J31: =G31-H31-I31 -> 60
B32: =B31+1 -> 17 | C32: =$C$8+($C$9-$C$8)/(1+$C$12^(($C$10+$C$11/2-B32)/$C$11)) -> 0.68306095 | F32: =F31+1 -> 9 | G32: =J31 -> 60 | H32: 5 | I32: =ROUND(G32*AVERAGE('MVLP INPUT'!$M$82:$M$91),0) -> 0 | J32: =G32-H32-I32 -> 55
B33: =B32+1 -> 18 | C33: =$C$8+($C$9-$C$8)/(1+$C$12^(($C$10+$C$11/2-B33)/$C$11)) -> 0.72941416 | F33: =F32+1 -> 10 | G33: =J32 -> 55 | H33: 5 | I33: =ROUND(G33*AVERAGE('MVLP INPUT'!$M$82:$M$91),0) -> 0 | J33: =G33-H33-I33 -> 50
B34: =B33+1 -> 19 | C34: =$C$8+($C$9-$C$8)/(1+$C$12^(($C$10+$C$11/2-B34)/$C$11)) -> 0.77198154 | F34: =F33+1 -> 11 | G34: =J33 -> 50 | H34: 5 | I34: =ROUND(G34*AVERAGE('MVLP INPUT'!$M$82:$M$91),0) -> 0 | J34: =G34-H34-I34 -> 45
B35: =B34+1 -> 20 | C35: =$C$8+($C$9-$C$8)/(1+$C$12^(($C$10+$C$11/2-B35)/$C$11)) -> 0.81011201 | F35: =F34+1 -> 12 | G35: =J34 -> 45 | H35: 5 | I35: =ROUND(G35*AVERAGE('MVLP INPUT'!$M$82:$M$91),0) -> 0 | J35: =G35-H35-I35 -> 40
B36: =B35+1 -> 21 | C36: =$C$8+($C$9-$C$8)/(1+$C$12^(($C$10+$C$11/2-B36)/$C$11)) -> 0.84351452 | F36: =F35+1 -> 13 | G36: =J35 -> 40 | H36: 5 | I36: =ROUND(G36*AVERAGE('MVLP INPUT'!$M$82:$M$91),0) -> 0 | J36: =G36-H36-I36 -> 35
... B47: =B46+1 -> 32 | C47: =$C$8+($C$9-$C$8)/(1+$C$12^(($C$10+$C$11/2-B47)/$C$11)) -> 0.98705884 | F47: =F46+1 -> 24 | G47: =J46 -> -15 | H47: 5 | I47: =ROUND(G47*AVERAGE('MVLP INPUT'!$M$82:$M$91),0) -> 0 | J47: =G47-H47-I47 -> -20
B48: =B47+1 -> 33 | C48: =$C$8+($C$9-$C$8)/(1+$C$12^(($C$10+$C$11/2-B48)/$C$11)) -> 0.98982736
B49: =B48+1 -> 34 | C49: =$C$8+($C$9-$C$8)/(1+$C$12^(($C$10+$C$11/2-B49)/$C$11)) -> 0.99200938 | I49: CHURN FACTOR | J49: =J47/G24 -> -0.2
B50: =B49+1 -> 35 | C50: =$C$8+($C$9-$C$8)/(1+$C$12^(($C$10+$C$11/2-B50)/$C$11)) -> 0.99372693
B51: =B50+1 -> 36 | C51: =$C$8+($C$9-$C$8)/(1+$C$12^(($C$10+$C$11/2-B51)/$C$11)) -> 0.99507749
B52: =B51+1 -> 37 | C52: =$C$8+($C$9-$C$8)/(1+$C$12^(($C$10+$C$11/2-B52)/$C$11)) -> 0.99613865
B53: =B52+1 -> 38 | C53: =$C$8+($C$9-$C$8)/(1+$C$12^(($C$10+$C$11/2-B53)/$C$11)) -> 0.99697188
B54: =B53+1 -> 39 | C54: =$C$8+($C$9-$C$8)/(1+$C$12^(($C$10+$C$11/2-B54)/$C$11)) -> 0.99762583
B55: =B54+1 -> 40 | C55: =$C$8+($C$9-$C$8)/(1+$C$12^(($C$10+$C$11/2-B55)/$C$11)) -> 0.99813887
B56: =B55+1 -> 41 | C56: =$C$8+($C$9-$C$8)/(1+$C$12^(($C$10+$C$11/2-B56)/$C$11)) -> 0.99854124
B57: =B56+1 -> 42 | C57: =$C$8+($C$9-$C$8)/(1+$C$12^(($C$10+$C$11/2-B57)/$C$11)) -> 0.99885674
B58: =B57+1 -> 43 | C58: =$C$8+($C$9-$C$8)/(1+$C$12^(($C$10+$C$11/2-B58)/$C$11)) -> 0.99910407
B59: =B58+1 -> 44 | C59: =$C$8+($C$9-$C$8)/(1+$C$12^(($C$10+$C$11/2-B59)/$C$11)) -> 0.99929795
B60: =B59+1 -> 45 | C60: =$C$8+($C$9-$C$8)/(1+$C$12^(($C$10+$C$11/2-B60)/$C$11)) -> 0.99944989
B61: =B60+1 -> 46 | C61: =$C$8+($C$9-$C$8)/(1+$C$12^(($C$10+$C$11/2-B61)/$C$11)) -> 0.99956897
... B75: =B74+1 -> 60 | C75: =$C$8+($C$9-$C$8)/(1+$C$12^(($C$10+$C$11/2-B75)/$C$11)) -> 0.99998585

Sheet ACQUISITION ASSUMPTIONS
B3: =UPPER('<<VERSIONING NOTES>>'!$F$2)&TEXT(" GROSS ACQUISITION ASSUMPTIONS VERSION ","")&'<<VERSIONING NOTES>>'!$F$3 -> METL GROSS ACQUISITION ASSUMPTIONS VERSION MVNE Financial Framework Template Metl 20250604 1m | G3: =TEXT("Prepared by ","") -> Prepared by
G4: ='<<VERSIONING NOTES>>'!F4 -> Edward Wicks
B6: ACQUISITION & COMMISSION ASSUMPTIONS
B8: Penetration Assumptions & Targets | C8: Population | D8: High Level Assumption Percentage (%)
B10: Total Market Population | C10: 10915000 | D10: ='<<KEY FINANCIAL INDICATORS>>'!K27 -> 0.75
B11: Targeted Closing Base | C11: =C10*D10 -> 8186250 | F11: ='<<KEY FINANCIAL INDICATORS>>'!H27 -> 1831455.4 | G11: =71000000 -> 71000000 | I11: =F11/G11 -> 0.025795146
B12: Approximated Annual Target | C12: =C11/5 -> 1637250
B13: Approximated Monthly Target | C13: =C12/12 -> 136437.5
B15: Assumed Split of Acquisitions | C15: Assumption Percentage (%) | D15: Monthly Acquisition Target | F15: Up Front Sales Commission | G15: Ongoing Sales Commission on Usage
E16: =D17/2 -> 26605.312
B17: ='MVLP INPUT'!D10 -> MVLP1 | C17: 0.39 | D17: =$C$13*C17 -> 53210.625 | F17: 40 | G17: 0.1 | H17: 0.42
B18: ='MVLP INPUT'!D11 -> MVLP2 | C18: 0.24 | D18: =$C$13*C18 -> 32745 | F18: 40 | G18: 0.1 | H18: 0.46
B19: ='MVLP INPUT'!D12 -> MVLP3 | C19: 0.16 | D19: =$C$13*C19 -> 21830 | F19: 40 | G19: 0.1 | H19: 0.04 | I19: ='<<KEY FINANCIAL INDICATORS>>'!D31 -> 1.9630817
B20: ='MVLP INPUT'!D13 -> MVLP4 | C20: 0.08 | D20: =$C$13*C20 -> 10915 | F20: 40 | G20: 0.1 | H20: 0.02
B21: ='MVLP INPUT'!D14 -> MVLP5 | C21: 0.08 | D21: =$C$13*C21 -> 10915 | H21: 0.04
B22: ='MVLP INPUT'!D15 -> MVLP6 | C22: 0.05 | D22: =$C$13*C22 -> 6821.875 | H22: 0.02
B23: ='MVLP INPUT'!D16 -> 200 MB | C23: 0 | D23: =$C$13*C23 -> 0 | H23: 0.01
B24: ='MVLP INPUT'!D17 -> 500 MB | C24: 0 | D24: =$C$13*C24 -> 0 | H24: 0.01
B25: ='MVLP INPUT'!D18 -> 1.2 GB | C25: 0 | D25: =$C$13*C25 -> 0
B26: ='MVLP INPUT'!D19 -> 2.5 GB | C26: 0 | D26: =$C$13*C26 -> 0 | F26: 40 | G26: 0.1
C27: =SUM(C17:C26) -> 1 | D27: =SUM(D17:D26)+'ACQUISITION ASSUMPTIONS FLTE'!D22 -> 141957.5
B28: Logistics Assumptions | C28: Cost of B2B Shipment | D28: Cost of B2C Shipment | F28: Cost of B2B Shipment | G28: Cost of B2C Shipment
C29: 100 | F29: 100
B31: =B17 -> MVLP1 | C31: =3*'BASIC INPUT ASSUMPTIONS'!$D$7 -> 450 | D31: =210*'BASIC INPUT ASSUMPTIONS'!$D$7 -> 31500 | F31: 3 | G31: 210
B32: =B18 -> MVLP2 | C32: =3*'BASIC INPUT ASSUMPTIONS'!$D$7 -> 450 | D32: =210*'BASIC INPUT ASSUMPTIONS'!$D$7 -> 31500 | F32: 3 | G32: 210
B33: =B19 -> MVLP3 | C33: =3*'BASIC INPUT ASSUMPTIONS'!$D$7 -> 450 | D33: =210*'BASIC INPUT ASSUMPTIONS'!$D$7 -> 31500 | F33: 3 | G33: 210
B34: =B20 -> MVLP4 | C34: =3*'BASIC INPUT ASSUMPTIONS'!$D$7 -> 450 | D34: =210*'BASIC INPUT ASSUMPTIONS'!$D$7 -> 31500 | F34: 3 | G34: 210
B35: =B21 -> MVLP5 | C35: =3*'BASIC INPUT ASSUMPTIONS'!$D$7 -> 450 | D35: =210*'BASIC INPUT ASSUMPTIONS'!$D$7 -> 31500
B36: =B22 -> MVLP6 | C36: =3*'BASIC INPUT ASSUMPTIONS'!$D$7 -> 450 | D36: =210*'BASIC INPUT ASSUMPTIONS'!$D$7 -> 31500
B37: =B23 -> 200 MB | C37: =3*'BASIC INPUT ASSUMPTIONS'!$D$7 -> 450 | D37: =210*'BASIC INPUT ASSUMPTIONS'!$D$7 -> 31500
B38: =B24 -> 500 MB | C38: =3*'BASIC INPUT ASSUMPTIONS'!$D$7 -> 450 | D38: =210*'BASIC INPUT ASSUMPTIONS'!$D$7 -> 31500
B39: =B25 -> 1.2 GB | C39: =3*'BASIC INPUT ASSUMPTIONS'!$D$7 -> 450 | D39: =210*'BASIC INPUT ASSUMPTIONS'!$D$7 -> 31500
B40: =B26 -> 2.5 GB | C40: =3*'BASIC INPUT ASSUMPTIONS'!$D$7 -> 450 | D40: =210*'BASIC INPUT ASSUMPTIONS'!$D$7 -> 31500 | F40: =G40/$F$29 -> 0 | G40: 0

Sheet DEVICE ASSUMPTIONS
B3: =UPPER('<<VERSIONING NOTES>>'!$F$2)&TEXT(" DEVICE ASSUMPTIONS VERSION ","")&'<<VERSIONING NOTES>>'!$F$3 -> METL DEVICE ASSUMPTIONS VERSION MVNE Financial Framework Template Metl 20250604 1m | H3: =TEXT("Prepared by ","") -> Prepared by
H4: ='<<VERSIONING NOTES>>'!F4 -> Edward Wicks
B6: CASH DEVICE SALE ASSUMPTIONS
C8: Average Device Cost Price | D8: Retail Margin Percentage (%) | E8: Average Retail Price | F8: Percentage (%) of Activations that will buy Cash Devices
B10: ='MVLP INPUT'!D82 -> MVLP1 | C10: 0 | D10: 0.1 | E10: =C10+(C10*D10) -> 0 | F10: 0 | G10: 0
B11: ='MVLP INPUT'!D83 -> MVLP2 | C11: 0 | D11: 0.1 | E11: =C11+(C11*D11) -> 0 | F11: 0 | G11: 0
B12: ='MVLP INPUT'!D84 -> MVLP3 | C12: 0 | D12: 0.1 | E12: =C12+(C12*D12) -> 0 | F12: 0 | G12: 0
B13: ='MVLP INPUT'!D85 -> MVLP4 | C13: 0 | D13: 0.1 | E13: =C13+(C13*D13) -> 0 | F13: 0 | G13: 0
B14: ='MVLP INPUT'!D86 -> MVLP5 | C14: 0 | D14: 0.1 | E14: =C14+(C14*D14) -> 0 | F14: 0
B15: ='MVLP INPUT'!D87 -> MVLP6 | C15: 0 | D15: 0.1 | E15: =C15+(C15*D15) -> 0 | F15: 0
B16: ='MVLP INPUT'!D88 -> 200 MB | C16: 0 | D16: 0.1 | E16: =C16+(C16*D16) -> 0 | F16: 0
B17: ='MVLP INPUT'!D89 -> 500 MB | C17: 0 | D17: 0.1 | E17: =C17+(C17*D17) -> 0 | F17: 0
B18: ='MVLP INPUT'!D90 -> 1.2 GB | C18: 0 | D18: 0.1 | E18: =C18+(C18*D18) -> 0 | F18: 0
B19: ='MVLP INPUT'!D91 -> 2.5 GB | C19: 0 | D19: 0.1 | E19: =C19+(C19*D19) -> 0 | F19: 0 | G19: 0
B21: CREDIT DEVICE SALE ASSUMPTIONS
C23: Average Device Cost Price | D23: Retail Margin Percentage (%) | E23: Average Retail Price | F23: Percentage (%) of Activations that will Finance a Device | G23: Up Front Pay In Amount | H23: Monthly Device Subscription
B25: =B10 -> MVLP1 | C25: 0 | D25: 0.1 | E25: =C25+(C25*D25) -> 0 | F25: 0 | G25: =E25*15% -> 0 | H25: =(E25-G25)/24 -> 0
B26: =B11 -> MVLP2 | C26: 0 | D26: 0.1 | E26: =C26+(C26*D26) -> 0 | F26: 0 | G26: =E26*15% -> 0 | H26: =(E26-G26)/24 -> 0
B27: =B12 -> MVLP3 | C27: 0 | D27: 0.1 | E27: =C27+(C27*D27) -> 0 | F27: 0 | G27: =E27*15% -> 0 | H27: =(E27-G27)/24 -> 0
B28: =B13 -> MVLP4 | C28: 0 | D28: 0.1 | E28: =C28+(C28*D28) -> 0 | F28: 0 | G28: =E28*15% -> 0 | H28: =(E28-G28)/24 -> 0
B29: =B14 -> MVLP5 | C29: 0 | D29: 0.1 | E29: =C29+(C29*D29) -> 0 | F29: 0 | G29: =E29*15% -> 0 | H29: =(E29-G29)/24 -> 0
B30: =B15 -> MVLP6 | C30: 0 | D30: 0.1 | E30: =C30+(C30*D30) -> 0 | F30: 0 | G30: =E30*15% -> 0 | H30: =(E30-G30)/24 -> 0
B31: =B16 -> 200 MB | C31: 0 | D31: 0.1 | E31: =C31+(C31*D31) -> 0 | F31: 0 | G31: =E31*15% -> 0 | H31: =(E31-G31)/24 -> 0
B32: =B17 -> 500 MB | C32: 0 | D32: 0.1 | E32: =C32+(C32*D32) -> 0 | F32: 0 | G32: =E32*15% -> 0 | H32: =(E32-G32)/24 -> 0
B33: =B18 -> 1.2 GB | C33: 0 | D33: 0.1 | E33: =C33+(C33*D33) -> 0 | F33: 0 | G33: =E33*15% -> 0 | H33: =(E33-G33)/24 -> 0
B34: =B19 -> 2.5 GB | C34: 0 | D34: 0.1 | E34: =C34+(C34*D34) -> 0 | F34: 0 | G34: =E34*15% -> 0 | H34: =(E34-G34)/24 -> 0

Sheet COMMISSION ASSUMPTIONS
B3: SUMMARY OF CHANNELS TO MARKET
B5: ACQUISITION SPLIT ACROSS CHANNELS
B7: PROPOSITION | C7: EXISTING AGENTS | D7: ONLINE SALES WEB | E7: DIRECT MARKETING | F7: ONLINE SALES APP | G7: ? | H7: TOTAL
B9: ='MVLP INPUT'!D10 -> MVLP1 | C9: 1 | H9: =SUM(C9:G9) -> 1 | N9: 0.74 | O9: 0.04 | P9: 0.08 | Q9: 0.02 | R9: 0.12 | S9: =SUM(N9:R9) -> 1
B10: ='MVLP INPUT'!D11 -> MVLP2 | C10: 1 | H10: =SUM(C10:G10) -> 1
B11: ='MVLP INPUT'!D12 -> MVLP3 | C11: 1 | H11: =SUM(C11:G11) -> 1
B12: ='MVLP INPUT'!D13 -> MVLP4 | C12: 1 | H12: =SUM(C12:G12) -> 1
B13: ='MVLP INPUT'!D14 -> MVLP5 | C13: 1 | H13: =SUM(C13:G13) -> 1
B14: ='MVLP INPUT'!D15 -> MVLP6 | C14: 1 | H14: =SUM(C14:G14) -> 1
B15: ='MVLP INPUT'!D16 -> 200 MB | D15: 0 | E15: 0 | F15: 0 | G15: 0 | H15: =SUM(C15:G15) -> 0
B16: ='MVLP INPUT'!D17 -> 500 MB | D16: 0 | E16: 0 | F16: 0 | G16: 0 | H16: =SUM(C16:G16) -> 0
B17: ='MVLP INPUT'!D18 -> 1.2 GB | D17: 0 | E17: 0 | F17: 0 | G17: 0 | H17: =SUM(C17:G17) -> 0
B18: ='MVLP INPUT'!D19 -> 2.5 GB | D18: 0 | E18: 0 | F18: 0 | G18: 0 | H18: =SUM(C18:G18) -> 0
B20: CHANNEL | C20: SEGMENT | D20: COMMISSION ON ACTIVATION | E20: SALES COMMISSION SUBSCRIPTION | F20: Commission on sale | G20: % B2B | H20: %B2C | I20: % WITH DEVICE | J20: Device Commission
L21: =SUM(L22:L27) -> 6591330.5 | V21: TOTAL PER MONTH | W21: PROPOSITION | X21: PACKAGE SPLIT | Y21: EXISTING STORES | Z21: ONLINE SALES WEB | AA21: DIRECT MARKETING | AB21: ONLINE SALES APP | AC21: ? | AD21: TOTAL
B22: =C7 -> EXISTING AGENTS | C22: =B9 -> MVLP1 | D22: ='MVLP INPUT'!F34 -> 423.72881 | E22: 0.07 | F22: 0 | G22: 1 | H22: =100%-G22 -> 0 | J22: 0.3 | K22: =D22*E22 -> 29.661017 | L22: =K22*('SUBSCRIBER BASE'!$L$79*'ACQUISITION ASSUMPTIONS'!$C17) -> 210533.9
C23: =B10 -> MVLP2 | D23: ='MVLP INPUT'!F35 -> 2118.6441 | E23: 0.07 | F23: 0 | G23: 1 | H23: =100%-G23 -> 0 | J23: 0.3 | K23: =D23*E23 -> 148.30508 | L23: =K23*('SUBSCRIBER BASE'!$L$79*'ACQUISITION ASSUMPTIONS'!$C18) -> 647796.61 | V23: ='ACQUISITION ASSUMPTIONS'!D17 -> 53210.625 | W23: =B9 -> MVLP1 | X23: ='ACQUISITION ASSUMPTIONS'!C17 -> 0.39 | Y23: 0.53 | Z23: 0.05 | AA23: 0.4 | AB23: 0.02 | AC23: 0 | AD23: =SUM(Y23:AC23) -> 1
C24: =B11 -> MVLP3 | D24: ='MVLP INPUT'!F36 -> 4661.0169 | E24: 0.07 | F24: 0 | G24: 1 | H24: =100%-G24 -> 0 | J24: 0.3 | K24: =D24*E24 -> 326.27119 | L24: =K24*('SUBSCRIBER BASE'!$L$79*'ACQUISITION ASSUMPTIONS'!$C19) -> 950101.69 | V24: ='ACQUISITION ASSUMPTIONS'!D18 -> 32745 | W24: =B10 -> MVLP2 | X24: ='ACQUISITION ASSUMPTIONS'!C18 -> 0.24 | Y24: 0.53 | Z24: 0.05 | AA24: 0.4 | AB24: 0.02 | AC24: 0 | AD24: =SUM(Y24:AC24) -> 1
C25: =B12 -> MVLP4 | D25: ='MVLP INPUT'!F37 -> 10593.22 | E25: 0.07 | F25: 0 | G25: 1 | H25: =100%-G25 -> 0 | J25: 0.3 | K25: =D25*E25 -> 741.52542 | L25: =K25*('SUBSCRIBER BASE'!$L$79*'ACQUISITION ASSUMPTIONS'!$C20) -> 1079661 | V25: ='ACQUISITION ASSUMPTIONS'!D19 -> 21830 | W25: =B11 -> MVLP3 | X25: ='ACQUISITION ASSUMPTIONS'!C19 -> 0.16 | Y25: 0.33 | Z25: 0.05 | AA25: 0.6 | AB25: 0.02 | AC25: 0 | AD25: =SUM(Y25:AC25) -> 1
C26: =B13 -> MVLP5 | D26: ='MVLP INPUT'!F38 -> 15677.966 | E26: 0.07 | F26: 0 | G26: 1 | H26: =100%-G26 -> 0 | J26: 0.3 | K26: =D26*E26 -> 1097.4576 | L26: =K26*('SUBSCRIBER BASE'!$L$79*'ACQUISITION ASSUMPTIONS'!$C21) -> 1597898.3
C27: =B14 -> MVLP6 | D27: ='MVLP INPUT'!F39 -> 33050.847 | E27: 0.07 | F27: 0 | G27: 1 | H27: =100%-G27 -> 0 | J27: 0.3 | K27: =D27*E27 -> 2313.5593 | L27: =K27*('SUBSCRIBER BASE'!$L$79*'ACQUISITION ASSUMPTIONS'!$C22) -> 2105339
C28: =B15 -> 200 MB | E28: 0.07 | F28: 0 | G28: 1 | H28: =100%-G28 -> 0 | J28: 0.3
C29: =B16 -> 500 MB | E29: 0.07 | F29: 0 | G29: 1 | H29: =100%-G29 -> 0 | J29: 0.3
C30: =B17 -> 1.2 GB | E30: 0.07 | F30: 0 | G30: 1 | H30: =100%-G30 -> 0 | J30: 0.3
C31: =B18 -> 2.5 GB | E31: 0.07 | F31: 0 | G31: 1 | H31: =100%-G31 -> 0 | J31: 0.3 | V31: ='ACQUISITION ASSUMPTIONS'!D20 -> 10915 | W31: =B12 -> MVLP4 | X31: ='ACQUISITION ASSUMPTIONS'!C20 -> 0.08 | Y31: 0.33 | Z31: 0.05 | AA31: 0.6 | AB31: 0.02 | AC31: 0 | AD31: =SUM(Y31:AC31) -> 1
V32: ='ACQUISITION ASSUMPTIONS'!D26 -> 0 | W32: =B18 -> 2.5 GB | X32: ='ACQUISITION ASSUMPTIONS'!C26 -> 0 | Y32: 1 | Z32: 0 | AA32: 0 | AB32: 0 | AC32: 0 | AD32: =SUM(Y32:AC32) -> 1
B33: =D7 -> ONLINE SALES WEB | C33: =C22 -> MVLP1 | D33: 0 | E33: 0.07 | F33: 0 | G33: 0 | H33: =100%-G33 -> 1 | J33: 0.1 | V33: ='ACQUISITION ASSUMPTIONS'!$C$13*'COMMISSION ASSUMPTIONS'!X33 -> 2728.75 | W33: Mass 1GB | X33: 0.02 | Y33: 0.53 | Z33: 0.05 | AA33: 0.4 | AB33: 0.02
C34: =C23 -> MVLP2 | D34: 0 | E34: 0.07 | F34: 0 | G34: 0 | H34: =100%-G34 -> 1 | J34: 0.1 | V34: ='ACQUISITION ASSUMPTIONS'!$C$13*'COMMISSION ASSUMPTIONS'!X34 -> 1364.375 | W34: Mass 2GB | X34: 0.01 | Y34: 0.53 | Z34: 0.05 | AA34: 0.4 | AB34: 0.02
C35: =C24 -> MVLP3 | D35: 0 | E35: 0.07 | F35: 0 | G35: 0 | H35: =100%-G35 -> 1 | J35: 0.1 | V35: ='ACQUISITION ASSUMPTIONS'!$C$13*'COMMISSION ASSUMPTIONS'!X35 -> 682.1875 | W35: Mass 5GB | X35: 0.005 | Y35: 0.53 | Z35: 0.05 | AA35: 0.4 | AB35: 0.02
C36: =C25 -> MVLP4 | D36: 0 | E36: 0.07 | F36: 0 | G36: 0 | H36: =100%-G36 -> 1 | J36: 0.1 | V36: ='ACQUISITION ASSUMPTIONS'!$C$13*'COMMISSION ASSUMPTIONS'!X36 -> 6821.875 | W36: Mass 50GB | X36: 0.05 | Y36: 0.53 | Z36: 0.05 | AA36: 0.4 | AB36: 0.02
C37: =C26 -> MVLP5 | D37: 0 | E37: 0.07 | F37: 0 | G37: 0 | H37: =100%-G37 -> 1 | J37: 0.1
C38: =C27 -> MVLP6 | D38: 0 | E38: 0.07 | F38: 0 | G38: 0 | H38: =100%-G38 -> 1 | J38: 0.1
C39: =C28 -> 200 MB | D39: 0 | E39: 0 | F39: 0 | G39: 0 | H39: =100%-G39 -> 1 | J39: 0.1
C40: =C29 -> 500 MB | D40: 0 | E40: 0 | F40: 0 | G40: 0 | H40: =100%-G40 -> 1 | J40: 0.1
C41: =C30 -> 1.2 GB | D41: 0 | E41: 0 | F41: 0 | G41: 0 | H41: =100%-G41 -> 1 | J41: 0.1
C42: =C31 -> 2.5 GB | D42: 0 | E42: 0 | F42: 0 | G42: 0 | H42: =100%-G42 -> 1 | J42: 0.1 | V42: ='ACQUISITION ASSUMPTIONS'!$C$13*'COMMISSION ASSUMPTIONS'!X42 -> 4093.125 | W42: Mass 100GB | X42: 0.03 | Y42: 0.53 | Z42: 0.05 | AA42: 0.4 | AB42: 0.02
V43: ='ACQUISITION ASSUMPTIONS'!$C$13*'COMMISSION ASSUMPTIONS'!X43 -> 4093.125 | W43: Mass 250GB | X43: 0.03 | Y43: 0.53 | Z43: 0.05 | AA43: 0.4 | AB43: 0.02
B44: =E7 -> DIRECT MARKETING | C44: =C33 -> MVLP1 | E44: 0.07 | F44: 0 | G44: 0 | H44: 1 | V44: ='ACQUISITION ASSUMPTIONS'!$C$13*'COMMISSION ASSUMPTIONS'!X44 -> 1364.375 | W44: Mass 500GB | X44: 0.01 | Y44: 0.53 | Z44: 0.05 | AA44: 0.4 | AB44: 0.02
C45: =C34 -> MVLP2 | E45: 0.07 | F45: 0 | G45: 0 | H45: 1
C46: =C35 -> MVLP3 | E46: 0.07 | F46: 0 | G46: 0 | H46: 1 | V46: =SUM(V23:V45) -> 139848.44
C47: =C36 -> MVLP4 | E47: 0.07 | F47: 0 | G47: 0 | H47: 1
C48: =C37 -> MVLP5 | E48: 0.07 | F48: 0 | G48: 0 | H48: 1
C49: =C38 -> MVLP6 | E49: 0.07 | F49: 0 | G49: 0 | H49: 1
C50: =C39 -> 200 MB | E50: 0 | F50: 0 | G50: 0 | H50: 1
C51: =C40 -> 500 MB | E51: 0 | F51: 0 | G51: 0 | H51: 1
C52: =C41 -> 1.2 GB | E52: 0 | F52: 0 | G52: 0 | H52: 1
C53: =C42 -> 2.5 GB | E53: 0 | F53: 0 | G53: 0 | H53: 1
B55: =F7 -> ONLINE SALES APP | C55: =C44 -> MVLP1 | D55: 0 | E55: 0.07 | F55: 0 | G55: 0 | H55: 1 | J55: 0
C56: =C45 -> MVLP2 | D56: 0 | E56: 0.07 | F56: 0 | G56: 0 | H56: 1 | J56: 0
C57: =C46 -> MVLP3 | D57: 0 | E57: 0.07 | F57: 0 | G57: 0 | H57: 1 | J57: 0
C58: =C47 -> MVLP4 | D58: 0 | E58: 0.07 | F58: 0 | G58: 0 | H58: 1 | J58: 0
C59: =C48 -> MVLP5 | D59: 0 | E59: 0.07 | F59: 0 | G59: 0 | H59: 1 | J59: 0
C60: =C49 -> MVLP6 | D60: 0 | E60: 0.07 | F60: 0 | G60: 0 | H60: 1 | J60: 0
C61: =C50 -> 200 MB | D61: 0 | E61: 0 | F61: 0 | G61: 0 | H61: 1 | J61: 0
C62: =C51 -> 500 MB | D62: 0 | E62: 0 | F62: 0 | G62: 0 | H62: 1 | J62: 0
C63: =C52 -> 1.2 GB | D63: 0 | E63: 0 | F63: 0 | G63: 0 | H63: 1 | J63: 0
C64: =C53 -> 2.5 GB | D64: 0 | E64: 0 | F64: 0 | G64: 0 | H64: 1 | J64: 0
B66: =G7 -> ? | C66: =C55 -> MVLP1 | E66: 0.015 | G66: 1 | H66: =100%-G66 -> 0 | J66: 0.3
C67: =C56 -> MVLP2 | E67: 0.015 | G67: 1 | H67: =100%-G67 -> 0 | J67: 0.3
C68: =C57 -> MVLP3 | E68: 0.015 | G68: 1 | H68: =100%-G68 -> 0 | J68: 0.3
C69: =C58 -> MVLP4 | E69: 0.015 | G69: 1 | H69: =100%-G69 -> 0 | J69: 0.3
C70: =C59 -> MVLP5 | E70: 0.015 | G70: 1 | H70: =100%-G70 -> 0 | J70: 0.3
C71: =C60 -> MVLP6 | E71: 0.015 | G71: 1 | H71: =100%-G71 -> 0 | J71: 0.3
C72: =C61 -> 200 MB | E72: 0.015 | G72: 1 | H72: =100%-G72 -> 0 | J72: 0.3
C73: =C62 -> 500 MB | E73: 0.015 | G73: 1 | H73: =100%-G73 -> 0 | J73: 0.3
C74: =C63 -> 1.2 GB | E74: 0.015 | G74: 1 | H74: =100%-G74 -> 0 | J74: 0.3
C75: =C64 -> 2.5 GB | E75: 0.015 | G75: 1 | H75: =100%-G75 -> 0 | J75: 0.3
B78: ACQUISITION SPLIT ACROSS CHANNELS
B80: PROPOSITION | C80: =C7 -> EXISTING AGENTS | D80: =D7 -> ONLINE SALES WEB | E80: =E7 -> DIRECT MARKETING | F80: =F7 -> ONLINE SALES APP | G80: =G7 -> ? | H80: TOTAL
B82: =B9 -> MVLP1 | C82: =C9 -> 1 | D82: =D9 -> 0 | E82: =E9 -> 0 | F82: =F9 -> 0 | G82: =G9 -> 0 | H82: =H9 -> 1
B83: =B10 -> MVLP2 | C83: =C10 -> 1 | D83: =D10 -> 0 | E83: =E10 -> 0 | F83: =F10 -> 0 | G83: =G10 -> 0 | H83: =H10 -> 1
B84: =B11 -> MVLP3 | C84: =C11 -> 1 | D84: =D11 -> 0 | E84: =E11 -> 0 | F84: =F11 -> 0 | G84: =G11 -> 0 | H84: =H11 -> 1
B85: =B12 -> MVLP4 | C85: =C12 -> 1 | D85: =D12 -> 0 | E85: =E12 -> 0 | F85: =F12 -> 0 | G85: =G12 -> 0 | H85: =H12 -> 1
B86: =B13 -> MVLP5 | C86: =C13 -> 1 | D86: =D13 -> 0 | E86: =E13 -> 0 | F86: =F13 -> 0 | G86: =G13 -> 0 | H86: =H13 -> 1
B87: =B14 -> MVLP6 | C87: =C14 -> 1 | D87: =D14 -> 0 | E87: =E14 -> 0 | F87: =F14 -> 0 | G87: =G14 -> 0 | H87: =H14 -> 1
B88: =B15 -> 200 MB | C88: =C15 -> 0 | D88: =D15 -> 0 | E88: =E15 -> 0 | F88: =F15 -> 0 | G88: =G15 -> 0 | H88: =H15 -> 0
B89: =B16 -> 500 MB | C89: =C16 -> 0 | D89: =D16 -> 0 | E89: =E16 -> 0 | F89: =F16 -> 0 | G89: =G16 -> 0 | H89: =H16 -> 0
B90: =B17 -> 1.2 GB | C90: =C17 -> 0 | D90: =D17 -> 0 | E90: =E17 -> 0 | F90: =F17 -> 0 | G90: =G17 -> 0 | H90: =H17 -> 0
B91: =B18 -> 2.5 GB | C91: =C18 -> 0 | D91: =D18 -> 0 | E91: =E18 -> 0 | F91: =F18 -> 0 | G91: =G18 -> 0 | H91: =H18 -> 0
B94: LEAD & CREDIT VETTING
B96: PROPOSITION | C96: LEAD VETTING | D96: CREDIT VETTING
B98: COST PER VET | C98: 4 | D98: 10 | E98: This is the cost per record vetted
B99: CONVERSION RATE | C99: 0.05 | D99: 0.8 | E99: This is the expected conversion rate, in other words requiring 100%-x to achieve sales
C100: This is only applicable to credit applications in the particular month

Sheet COMMISSION COSTS
B3: SUMMARY OF CHANNEL COMMISSIONS
C5: PM1 | D5: PM2 | E5: PM3 | F5: PM4 | G5: PM5 | H5: PM6 | I5: SLM1 | J5: SLM2 | K5: M1 | L5: M2 | M5: M3 | N5: M4 | O5: M5 | P5: M6 | Q5: M7 | R5: M8 | S5: M9 | T5: M10 | U5: M11 | V5: M12 | W5: M13 | X5: M14 | Y5: M15 | Z5: M16 | AA5: M17 | AB5: M18 | AC5: M19 | AD5: M20 | AE5: M21 | AF5: M22 | AG5: M23 | AH5: M24 | AI5: M25 | AJ5: M26 | AK5: M27 | AL5: M28 | AM5: M29 | AN5: M30 | AO5: M31 | AP5: M32 | AQ5: M33 | AR5: M34 | AS5: M35 | AT5: M36 | AU5: M37 | AV5: M38 | AW5: M39 | AX5: M40 | AY5: M41 | AZ5: M42 | BA5: M43 | BB5: M44 | BC5: M45 | BD5: M46 | BE5: M47 | BF5: M48 | BG5: M49 | BH5: M50 | BI5: M51 | BJ5: M52 | BK5: M53 | BL5: M54 | BM5: M55 | BN5: M56 | BO5: M57 | BP5: M58 | BQ5: M59 | BR5: M60
B7: MVNE MANAGED SERVICES COSTS | C7: 0 | D7: 0 | E7: 0 | F7: 0 | G7: 0 | H7: 0 | I7: =MAX(SUM(I9:I14),'[5]COST TO SERVE ASSUMPTIONS'!$D$6) -> 250000 | J7: =MAX(SUM(J9:J14),'[5]COST TO SERVE ASSUMPTIONS'!$D$6) -> 250000 | K7: =MAX(SUM(K9:K14),'[5]COST TO SERVE ASSUMPTIONS'!$D$6) -> 250000 | L7: =MAX(SUM(L9:L14),'[5]COST TO SERVE ASSUMPTIONS'!$D$6) -> 250000 | M7: =MAX(SUM(M9:M14),'[5]COST TO SERVE ASSUMPTIONS'!$D$6) -> 250000 | N7: =MAX(SUM(N9:N14),'[5]COST TO SERVE ASSUMPTIONS'!$D$6) -> 250000 | O7: =MAX(SUM(O9:O14),'[5]COST TO SERVE ASSUMPTIONS'!$D$6) -> 250000 | P7: =MAX(SUM(P9:P14),'[5]COST TO SERVE ASSUMPTIONS'!$D$6) -> 250000 | ... BR7: =MAX(SUM(BR9:BR14),'[5]COST TO SERVE ASSUMPTIONS'!$D$6) -> 551910
B9: =[5]ACTIVATIONS!B13 -> HIGH NET WORTH | C9: ='[5]SUBSCRIBER BASE'!C72*'[5]COST TO SERVE ASSUMPTIONS'!$C$6 -> 0 | D9: ='[5]SUBSCRIBER BASE'!D72*'[5]COST TO SERVE ASSUMPTIONS'!$C$6 -> 0 | E9: ='[5]SUBSCRIBER BASE'!E72*'[5]COST TO SERVE ASSUMPTIONS'!$C$6 -> 0 | F9: ='[5]SUBSCRIBER BASE'!F72*'[5]COST TO SERVE ASSUMPTIONS'!$C$6 -> 0 | G9: ='[5]SUBSCRIBER BASE'!G72*'[5]COST TO SERVE ASSUMPTIONS'!$C$6 -> 0 | H9: ='[5]SUBSCRIBER BASE'!H72*'[5]COST TO SERVE ASSUMPTIONS'!$C$6 -> 0 | I9: ='[5]SUBSCRIBER BASE'!K72*'[5]COST TO SERVE ASSUMPTIONS'!$C$6 -> 0 | J9: ='[5]SUBSCRIBER BASE'!L72*'[5]COST TO SERVE ASSUMPTIONS'!$C$6 -> 0 | K9: ='[5]SUBSCRIBER BASE'!O72*'[5]COST TO SERVE ASSUMPTIONS'!$C$6 -> 0 | L9: ='[5]SUBSCRIBER BASE'!P72*'[5]COST TO SERVE ASSUMPTIONS'!$C$6 -> 0 | M9: ='[5]SUBSCRIBER BASE'!Q72*'[5]COST TO SERVE ASSUMPTIONS'!$C$6 -> 0 | N9: ='[5]SUBSCRIBER BASE'!R72*'[5]COST TO SERVE ASSUMPTIONS'!$C$6 -> 0 | O9: ='[5]SUBSCRIBER BASE'!S72*'[5]COST TO SERVE ASSUMPTIONS'!$C$6 -> 0 | P9: ='[5]SUBSCRIBER BASE'!T72*'[5]COST TO SERVE ASSUMPTIONS'!$C$6 -> 0 | Q9: ='[5]SUBSCRIBER BASE'!U72*'[5]COST TO SERVE ASSUMPTIONS'!$C$6 -> 0 | R9: ='[5]SUBSCRIBER BASE'!V72*'[5]COST TO SERVE ASSUMPTIONS'!$C$6 -> 0 | ... BR9: ='[5]SUBSCRIBER BASE'!BV72*'[5]COST TO SERVE ASSUMPTIONS'!$C$6 -> 0
B10: =[5]ACTIVATIONS!B14 -> HIGH INCOME | C10: ='[5]SUBSCRIBER BASE'!C73*'[5]COST TO SERVE ASSUMPTIONS'!$C$6 -> 0 | D10: ='[5]SUBSCRIBER BASE'!D73*'[5]COST TO SERVE ASSUMPTIONS'!$C$6 -> 0 | E10: ='[5]SUBSCRIBER BASE'!E73*'[5]COST TO SERVE ASSUMPTIONS'!$C$6 -> 0 | F10: ='[5]SUBSCRIBER BASE'!F73*'[5]COST TO SERVE ASSUMPTIONS'!$C$6 -> 0 | G10: ='[5]SUBSCRIBER BASE'!G73*'[5]COST TO SERVE ASSUMPTIONS'!$C$6 -> 0 | H10: ='[5]SUBSCRIBER BASE'!H73*'[5]COST TO SERVE ASSUMPTIONS'!$C$6 -> 0 | I10: ='[5]SUBSCRIBER BASE'!K73*'[5]COST TO SERVE ASSUMPTIONS'!$C$6 -> 200 | J10: ='[5]SUBSCRIBER BASE'!L73*'[5]COST TO SERVE ASSUMPTIONS'!$C$6 -> 400 | K10: ='[5]SUBSCRIBER BASE'!O73*'[5]COST TO SERVE ASSUMPTIONS'!$C$6 -> 790 | L10: ='[5]SUBSCRIBER BASE'!P73*'[5]COST TO SERVE ASSUMPTIONS'!$C$6 -> 790 | M10: ='[5]SUBSCRIBER BASE'!Q73*'[5]COST TO SERVE ASSUMPTIONS'!$C$6 -> 790 | N10: ='[5]SUBSCRIBER BASE'!R73*'[5]COST TO SERVE ASSUMPTIONS'!$C$6 -> 790 | O10: ='[5]SUBSCRIBER BASE'!S73*'[5]COST TO SERVE ASSUMPTIONS'!$C$6 -> 790 | P10: ='[5]SUBSCRIBER BASE'!T73*'[5]COST TO SERVE ASSUMPTIONS'!$C$6 -> 790 | Q10: ='[5]SUBSCRIBER BASE'!U73*'[5]COST TO SERVE ASSUMPTIONS'!$C$6 -> 790 | R10: ='[5]SUBSCRIBER BASE'!V73*'[5]COST TO SERVE ASSUMPTIONS'!$C$6 -> 790 | ... BR10: ='[5]SUBSCRIBER BASE'!BV73*'[5]COST TO SERVE ASSUMPTIONS'!$C$6 -> 3170
B11: =[5]ACTIVATIONS!B15 -> GOLD | C11: ='[5]SUBSCRIBER BASE'!C74*'[5]COST TO SERVE ASSUMPTIONS'!$C$6 -> 0 | D11: ='[5]SUBSCRIBER BASE'!D74*'[5]COST TO SERVE ASSUMPTIONS'!$C$6 -> 0 | E11: ='[5]SUBSCRIBER BASE'!E74*'[5]COST TO SERVE ASSUMPTIONS'!$C$6 -> 0 | F11: ='[5]SUBSCRIBER BASE'!F74*'[5]COST TO SERVE ASSUMPTIONS'!$C$6 -> 0 | G11: ='[5]SUBSCRIBER BASE'!G74*'[5]COST TO SERVE ASSUMPTIONS'!$C$6 -> 0 | H11: ='[5]SUBSCRIBER BASE'!H74*'[5]COST TO SERVE ASSUMPTIONS'!$C$6 -> 0 | I11: ='[5]SUBSCRIBER BASE'!K74*'[5]COST TO SERVE ASSUMPTIONS'!$C$6 -> 200 | J11: ='[5]SUBSCRIBER BASE'!L74*'[5]COST TO SERVE ASSUMPTIONS'!$C$6 -> 400 | K11: ='[5]SUBSCRIBER BASE'!O74*'[5]COST TO SERVE ASSUMPTIONS'!$C$6 -> 1770 | L11: ='[5]SUBSCRIBER BASE'!P74*'[5]COST TO SERVE ASSUMPTIONS'!$C$6 -> 2760 | M11: ='[5]SUBSCRIBER BASE'!Q74*'[5]COST TO SERVE ASSUMPTIONS'!$C$6 -> 3780 | N11: ='[5]SUBSCRIBER BASE'!R74*'[5]COST TO SERVE ASSUMPTIONS'!$C$6 -> 4830 | O11: ='[5]SUBSCRIBER BASE'!S74*'[5]COST TO SERVE ASSUMPTIONS'!$C$6 -> 5890 | P11: ='[5]SUBSCRIBER BASE'!T74*'[5]COST TO SERVE ASSUMPTIONS'!$C$6 -> 6990 | Q11: ='[5]SUBSCRIBER BASE'!U74*'[5]COST TO SERVE ASSUMPTIONS'!$C$6 -> 8100 | R11: ='[5]SUBSCRIBER BASE'!V74*'[5]COST TO SERVE ASSUMPTIONS'!$C$6 -> 9210 | ... BR11: ='[5]SUBSCRIBER BASE'!BV74*'[5]COST TO SERVE ASSUMPTIONS'!$C$6 -> 79890
B12: =[5]ACTIVATIONS!B16 -> SILVER | C12: ='[5]SUBSCRIBER BASE'!C75*'[5]COST TO SERVE ASSUMPTIONS'!$C$6 -> 0 | D12: ='[5]SUBSCRIBER BASE'!D75*'[5]COST TO SERVE ASSUMPTIONS'!$C$6 -> 0 | E12: ='[5]SUBSCRIBER BASE'!E75*'[5]COST TO SERVE ASSUMPTIONS'!$C$6 -> 0 | F12: ='[5]SUBSCRIBER BASE'!F75*'[5]COST TO SERVE ASSUMPTIONS'!$C$6 -> 0 | G12: ='[5]SUBSCRIBER BASE'!G75*'[5]COST TO SERVE ASSUMPTIONS'!$C$6 -> 0 | H12: ='[5]SUBSCRIBER BASE'!H75*'[5]COST TO SERVE ASSUMPTIONS'!$C$6 -> 0 | I12: ='[5]SUBSCRIBER BASE'!K75*'[5]COST TO SERVE ASSUMPTIONS'!$C$6 -> 200 | J12: ='[5]SUBSCRIBER BASE'!L75*'[5]COST TO SERVE ASSUMPTIONS'!$C$6 -> 400 | K12: ='[5]SUBSCRIBER BASE'!O75*'[5]COST TO SERVE ASSUMPTIONS'!$C$6 -> 2160 | L12: ='[5]SUBSCRIBER BASE'!P75*'[5]COST TO SERVE ASSUMPTIONS'!$C$6 -> 3540 | M12: ='[5]SUBSCRIBER BASE'!Q75*'[5]COST TO SERVE ASSUMPTIONS'!$C$6 -> 4960 | N12: ='[5]SUBSCRIBER BASE'!R75*'[5]COST TO SERVE ASSUMPTIONS'!$C$6 -> 6420 | O12: ='[5]SUBSCRIBER BASE'!S75*'[5]COST TO SERVE ASSUMPTIONS'!$C$6 -> 7900 | P12: ='[5]SUBSCRIBER BASE'!T75*'[5]COST TO SERVE ASSUMPTIONS'!$C$6 -> 9440 | Q12: ='[5]SUBSCRIBER BASE'!U75*'[5]COST TO SERVE ASSUMPTIONS'!$C$6 -> 10990 | R12: ='[5]SUBSCRIBER BASE'!V75*'[5]COST TO SERVE ASSUMPTIONS'!$C$6 -> 12550 | ... BR12: ='[5]SUBSCRIBER BASE'!BV75*'[5]COST TO SERVE ASSUMPTIONS'!$C$6 -> 110090
B13: =[5]ACTIVATIONS!B17 -> MASS | C13: ='[5]SUBSCRIBER BASE'!C76*'[5]COST TO SERVE ASSUMPTIONS'!$C$6 -> 0 | D13: ='[5]SUBSCRIBER BASE'!D76*'[5]COST TO SERVE ASSUMPTIONS'!$C$6 -> 0 | E13: ='[5]SUBSCRIBER BASE'!E76*'[5]COST TO SERVE ASSUMPTIONS'!$C$6 -> 0 | F13: ='[5]SUBSCRIBER BASE'!F76*'[5]COST TO SERVE ASSUMPTIONS'!$C$6 -> 0 | G13: ='[5]SUBSCRIBER BASE'!G76*'[5]COST TO SERVE ASSUMPTIONS'!$C$6 -> 0 | H13: ='[5]SUBSCRIBER BASE'!H76*'[5]COST TO SERVE ASSUMPTIONS'!$C$6 -> 0 | I13: ='[5]SUBSCRIBER BASE'!K76*'[5]COST TO SERVE ASSUMPTIONS'!$C$6 -> 200 | J13: ='[5]SUBSCRIBER BASE'!L76*'[5]COST TO SERVE ASSUMPTIONS'!$C$6 -> 400 | K13: ='[5]SUBSCRIBER BASE'!O76*'[5]COST TO SERVE ASSUMPTIONS'!$C$6 -> 6160 | L13: ='[5]SUBSCRIBER BASE'!P76*'[5]COST TO SERVE ASSUMPTIONS'!$C$6 -> 11580 | M13: ='[5]SUBSCRIBER BASE'!Q76*'[5]COST TO SERVE ASSUMPTIONS'!$C$6 -> 17110 | N13: ='[5]SUBSCRIBER BASE'!R76*'[5]COST TO SERVE ASSUMPTIONS'!$C$6 -> 22810 | O13: ='[5]SUBSCRIBER BASE'!S76*'[5]COST TO SERVE ASSUMPTIONS'!$C$6 -> 28610 | P13: ='[5]SUBSCRIBER BASE'!T76*'[5]COST TO SERVE ASSUMPTIONS'!$C$6 -> 34580 | Q13: ='[5]SUBSCRIBER BASE'!U76*'[5]COST TO SERVE ASSUMPTIONS'!$C$6 -> 40590 | R13: ='[5]SUBSCRIBER BASE'!V76*'[5]COST TO SERVE ASSUMPTIONS'!$C$6 -> 46650 | ... BR13: ='[5]SUBSCRIBER BASE'!BV76*'[5]COST TO SERVE ASSUMPTIONS'!$C$6 -> 324690
B14: =[5]ACTIVATIONS!B18 -> SMALL COMMERCIAL | C14: ='[5]SUBSCRIBER BASE'!C77*'[5]COST TO SERVE ASSUMPTIONS'!$C$6 -> 0 | D14: ='[5]SUBSCRIBER BASE'!D77*'[5]COST TO SERVE ASSUMPTIONS'!$C$6 -> 0 | E14: ='[5]SUBSCRIBER BASE'!E77*'[5]COST TO SERVE ASSUMPTIONS'!$C$6 -> 0 | F14: ='[5]SUBSCRIBER BASE'!F77*'[5]COST TO SERVE ASSUMPTIONS'!$C$6 -> 0 | G14: ='[5]SUBSCRIBER BASE'!G77*'[5]COST TO SERVE ASSUMPTIONS'!$C$6 -> 0 | H14: ='[5]SUBSCRIBER BASE'!H77*'[5]COST TO SERVE ASSUMPTIONS'!$C$6 -> 0 | I14: ='[5]SUBSCRIBER BASE'!K77*'[5]COST TO SERVE ASSUMPTIONS'!$C$6 -> 200 | J14: ='[5]SUBSCRIBER BASE'!L77*'[5]COST TO SERVE ASSUMPTIONS'!$C$6 -> 400 | K14: ='[5]SUBSCRIBER BASE'!O77*'[5]COST TO SERVE ASSUMPTIONS'!$C$6 -> 1190 | L14: ='[5]SUBSCRIBER BASE'!P77*'[5]COST TO SERVE ASSUMPTIONS'!$C$6 -> 1600 | M14: ='[5]SUBSCRIBER BASE'!Q77*'[5]COST TO SERVE ASSUMPTIONS'!$C$6 -> 2010 | N14: ='[5]SUBSCRIBER BASE'!R77*'[5]COST TO SERVE ASSUMPTIONS'!$C$6 -> 2440 | O14: ='[5]SUBSCRIBER BASE'!S77*'[5]COST TO SERVE ASSUMPTIONS'!$C$6 -> 2870 | P14: ='[5]SUBSCRIBER BASE'!T77*'[5]COST TO SERVE ASSUMPTIONS'!$C$6 -> 3320 | Q14: ='[5]SUBSCRIBER BASE'!U77*'[5]COST TO SERVE ASSUMPTIONS'!$C$6 -> 3770 | R14: ='[5]SUBSCRIBER BASE'!V77*'[5]COST TO SERVE ASSUMPTIONS'!$C$6 -> 4230 | ... BR14: ='[5]SUBSCRIBER BASE'!BV77*'[5]COST TO SERVE ASSUMPTIONS'!$C$6 -> 34070
B16: CALL CENTER OUTSOURCED SERVICES COSTS | I16: =SUM(I18:I19) -> 79396 | J16: =SUM(J18:J19) -> 79448 | K16: =SUM(K18:K19) -> 79978.4 | L16: =SUM(L18:L19) -> 80399.6 | M16: =SUM(M18:M19) -> 80836.4 | N16: =SUM(N18:N19) -> 81278.4 | O16: =SUM(O18:O19) -> 81741.2 | P16: =SUM(P18:P19) -> 82209.2 | ... BR16: =SUM(BR18:BR19) -> 108048
B18: SEAT COSTS | C18: ='[5]CUSTOMER CARE COSTS'!C28 -> 0 | D18: ='[5]CUSTOMER CARE COSTS'!D28 -> 0 | E18: ='[5]CUSTOMER CARE COSTS'!E28 -> 0 | F18: ='[5]CUSTOMER CARE COSTS'!F28 -> 0 | G18: ='[5]CUSTOMER CARE COSTS'!G28 -> 0 | H18: ='[5]CUSTOMER CARE COSTS'!H28 -> 0 | I18: ='[5]CUSTOMER CARE COSTS'!K28 -> 79344 | J18: ='[5]CUSTOMER CARE COSTS'!L28 -> 79344 | K18: ='[5]CUSTOMER CARE COSTS'!O28 -> 79344 | L18: ='[5]CUSTOMER CARE COSTS'!P28 -> 79344 | M18: ='[5]CUSTOMER CARE COSTS'!Q28 -> 79344 | N18: ='[5]CUSTOMER CARE COSTS'!R28 -> 79344 | O18: ='[5]CUSTOMER CARE COSTS'!S28 -> 79344 | P18: ='[5]CUSTOMER CARE COSTS'!T28 -> 79344 | Q18: ='[5]CUSTOMER CARE COSTS'!U28 -> 79344 | R18: ='[5]CUSTOMER CARE COSTS'!V28 -> 79344 | ... BR18: ='[5]CUSTOMER CARE COSTS'!BV28 -> 79344
B19: TELEPHONY COSTS | C19: ='[5]CUSTOMER CARE COSTS'!C29 -> 0 | D19: ='[5]CUSTOMER CARE COSTS'!D29 -> 0 | E19: ='[5]CUSTOMER CARE COSTS'!E29 -> 0 | F19: ='[5]CUSTOMER CARE COSTS'!F29 -> 0 | G19: ='[5]CUSTOMER CARE COSTS'!G29 -> 0 | H19: ='[5]CUSTOMER CARE COSTS'!H29 -> 0 | I19: ='[5]CUSTOMER CARE COSTS'!K29 -> 52 | J19: ='[5]CUSTOMER CARE COSTS'!L29 -> 104 | K19: ='[5]CUSTOMER CARE COSTS'!O29 -> 634.4 | L19: ='[5]CUSTOMER CARE COSTS'!P29 -> 1055.6 | M19: ='[5]CUSTOMER CARE COSTS'!Q29 -> 1492.4 | N19: ='[5]CUSTOMER CARE COSTS'!R29 -> 1934.4 | O19: ='[5]CUSTOMER CARE COSTS'!S29 -> 2397.2 | P19: ='[5]CUSTOMER CARE COSTS'!T29 -> 2865.2 | Q19: ='[5]CUSTOMER CARE COSTS'!U29 -> 3343.6 | R19: ='[5]CUSTOMER CARE COSTS'!V29 -> 3822 | ... BR19: ='[5]CUSTOMER CARE COSTS'!BV29 -> 28704
B21: WHOLESALE COSTS | C21: =SUM(C23:C25) -> 0 | D21: =SUM(D23:D25) -> 0 | E21: =SUM(E23:E25) -> 0 | F21: =SUM(F23:F25) -> 0 | G21: =SUM(G23:G25) -> 0 | H21: =SUM(H23:H25) -> 0 | I21: =SUM(I23:I25) -> 11267.411 | J21: =SUM(J23:J25) -> 22534.916 | ... BR21: =SUM(BR23:BR25) -> 2666375.3
B23: VOICE | C23: ='[5]WHOLESALE CHARGES'!D5 -> 0 | D23: ='[5]WHOLESALE CHARGES'!E5 -> 0 | E23: ='[5]WHOLESALE CHARGES'!F5 -> 0 | F23: ='[5]WHOLESALE CHARGES'!G5 -> 0 | G23: ='[5]WHOLESALE CHARGES'!H5 -> 0 | H23: ='[5]WHOLESALE CHARGES'!I5 -> 0 | I23: ='[5]WHOLESALE CHARGES'!L5 -> 3435.0508 | J23: ='[5]WHOLESALE CHARGES'!M5 -> 6870.1301 | K23: ='[5]WHOLESALE CHARGES'!P5 -> 23992.67 | L23: ='[5]WHOLESALE CHARGES'!Q5 -> 34561.871 | M23: ='[5]WHOLESALE CHARGES'!R5 -> 45102.582 | N23: ='[5]WHOLESALE CHARGES'!S5 -> 55905.404 | O23: ='[5]WHOLESALE CHARGES'!T5 -> 66808.036 | P23: ='[5]WHOLESALE CHARGES'!U5 -> 78146.065 | Q23: ='[5]WHOLESALE CHARGES'!V5 -> 89539.931 | R23: ='[5]WHOLESALE CHARGES'!W5 -> 101052.15 | ... BR23: ='[5]WHOLESALE CHARGES'!BW5 -> 766923.38
B24: DATA | C24: ='[5]WHOLESALE CHARGES'!D16 -> 0 | D24: ='[5]WHOLESALE CHARGES'!E16 -> 0 | E24: ='[5]WHOLESALE CHARGES'!F16 -> 0 | F24: ='[5]WHOLESALE CHARGES'!G16 -> 0 | G24: ='[5]WHOLESALE CHARGES'!H16 -> 0 | H24: ='[5]WHOLESALE CHARGES'!I16 -> 0 | I24: ='[5]WHOLESALE CHARGES'!L16 -> 7566.1469 | J24: ='[5]WHOLESALE CHARGES'!M16 -> 15132.357 | K24: ='[5]WHOLESALE CHARGES'!P16 -> 50806.337 | L24: ='[5]WHOLESALE CHARGES'!Q16 -> 71990.692 | M24: ='[5]WHOLESALE CHARGES'!R16 -> 93637.254 | N24: ='[5]WHOLESALE CHARGES'!S16 -> 116004.06 | O24: ='[5]WHOLESALE CHARGES'!T16 -> 138580.87 | P24: ='[5]WHOLESALE CHARGES'!U16 -> 162075.13 | Q24: ='[5]WHOLESALE CHARGES'!V16 -> 185700.76 | R24: ='[5]WHOLESALE CHARGES'!W16 -> 209523.38 | ... BR24: ='[5]WHOLESALE CHARGES'!BW16 -> 1701718.3
B25: SMS | C25: ='[5]WHOLESALE CHARGES'!D27 -> 0 | D25: ='[5]WHOLESALE CHARGES'!E27 -> 0 | E25: ='[5]WHOLESALE CHARGES'!F27 -> 0 | F25: ='[5]WHOLESALE CHARGES'!G27 -> 0 | G25: ='[5]WHOLESALE CHARGES'!H27 -> 0 | H25: ='[5]WHOLESALE CHARGES'!I27 -> 0 | I25: ='[5]WHOLESALE CHARGES'!L27 -> 266.21357 | J25: ='[5]WHOLESALE CHARGES'!M27 -> 532.42917 | K25: ='[5]WHOLESALE CHARGES'!P27 -> 2935.3659 | L25: ='[5]WHOLESALE CHARGES'!Q27 -> 4836.899 | M25: ='[5]WHOLESALE CHARGES'!R27 -> 6781.4525 | N25: ='[5]WHOLESALE CHARGES'!S27 -> 8785.1314 | O25: ='[5]WHOLESALE CHARGES'!T27 -> 10820.01 | P25: ='[5]WHOLESALE CHARGES'!U27 -> 12920.853 | Q25: ='[5]WHOLESALE CHARGES'!V27 -> 84937.19 | R25: ='[5]WHOLESALE CHARGES'!W27 -> 87102.212 | ... BR25: ='[5]WHOLESALE CHARGES'!BW27 -> 197733.62
B27: BILL PRESENTATION COSTS | C27: =SUM(C29:C34) -> 0 | D27: =SUM(D29:D34) -> 0 | E27: =SUM(E29:E34) -> 0 | F27: =SUM(F29:F34) -> 0 | G27: =SUM(G29:G34) -> 0 | H27: =SUM(H29:H34) -> 0 | I27: =SUM(I29:I34) -> 34.37226 | J27: =SUM(J29:J34) -> 68.687233 | ... BR27: =SUM(BR29:BR34) -> 61791.656
B29: =[5]ACTIVATIONS!B40 -> HIGH NET WORTH | C29: ='[5]SUBSCRIBER BASE'!C81*'[5]COST TO SERVE ASSUMPTIONS'!$C$21 -> 0 | D29: ='[5]SUBSCRIBER BASE'!D81*'[5]COST TO SERVE ASSUMPTIONS'!$C$21 -> 0 | E29: ='[5]SUBSCRIBER BASE'!E81*'[5]COST TO SERVE ASSUMPTIONS'!$C$21 -> 0 | F29: ='[5]SUBSCRIBER BASE'!F81*'[5]COST TO SERVE ASSUMPTIONS'!$C$21 -> 0 | G29: ='[5]SUBSCRIBER BASE'!G81*'[5]COST TO SERVE ASSUMPTIONS'!$C$21 -> 0 | H29: ='[5]SUBSCRIBER BASE'!H81*'[5]COST TO SERVE ASSUMPTIONS'!$C$21 -> 0 | I29: ='[5]SUBSCRIBER BASE'!K81*'[5]COST TO SERVE ASSUMPTIONS'!$C$21 -> 0 | J29: ='[5]SUBSCRIBER BASE'!L81*'[5]COST TO SERVE ASSUMPTIONS'!$C$21 -> 0 | K29: ='[5]SUBSCRIBER BASE'!O81*'[5]COST TO SERVE ASSUMPTIONS'!$C$21 -> 0 | L29: ='[5]SUBSCRIBER BASE'!P81*'[5]COST TO SERVE ASSUMPTIONS'!$C$21 -> 0 | M29: ='[5]SUBSCRIBER BASE'!Q81*'[5]COST TO SERVE ASSUMPTIONS'!$C$21 -> 0 | N29: ='[5]SUBSCRIBER BASE'!R81*'[5]COST TO SERVE ASSUMPTIONS'!$C$21 -> 0 | O29: ='[5]SUBSCRIBER BASE'!S81*'[5]COST TO SERVE ASSUMPTIONS'!$C$21 -> 0 | P29: ='[5]SUBSCRIBER BASE'!T81*'[5]COST TO SERVE ASSUMPTIONS'!$C$21 -> 0 | Q29: ='[5]SUBSCRIBER BASE'!U81*'[5]COST TO SERVE ASSUMPTIONS'!$C$21 -> 0 | R29: ='[5]SUBSCRIBER BASE'!V81*'[5]COST TO SERVE ASSUMPTIONS'!$C$21 -> 0 | ... BR29: ='[5]SUBSCRIBER BASE'!BV81*'[5]COST TO SERVE ASSUMPTIONS'!$C$21 -> 0
B30: =[5]ACTIVATIONS!B41 -> HIGH INCOME | C30: ='[5]SUBSCRIBER BASE'!C82*'[5]COST TO SERVE ASSUMPTIONS'!$C$21 -> 0 | D30: ='[5]SUBSCRIBER BASE'!D82*'[5]COST TO SERVE ASSUMPTIONS'!$C$21 -> 0 | E30: ='[5]SUBSCRIBER BASE'!E82*'[5]COST TO SERVE ASSUMPTIONS'!$C$21 -> 0 | F30: ='[5]SUBSCRIBER BASE'!F82*'[5]COST TO SERVE ASSUMPTIONS'!$C$21 -> 0 | G30: ='[5]SUBSCRIBER BASE'!G82*'[5]COST TO SERVE ASSUMPTIONS'!$C$21 -> 0 | H30: ='[5]SUBSCRIBER BASE'!H82*'[5]COST TO SERVE ASSUMPTIONS'!$C$21 -> 0 | I30: ='[5]SUBSCRIBER BASE'!K82*'[5]COST TO SERVE ASSUMPTIONS'!$C$21 -> 7.63828 | J30: ='[5]SUBSCRIBER BASE'!L82*'[5]COST TO SERVE ASSUMPTIONS'!$C$21 -> 15.26383 | K30: ='[5]SUBSCRIBER BASE'!O82*'[5]COST TO SERVE ASSUMPTIONS'!$C$21 -> 30.426027 | L30: ='[5]SUBSCRIBER BASE'!P82*'[5]COST TO SERVE ASSUMPTIONS'!$C$21 -> 30.375317 | M30: ='[5]SUBSCRIBER BASE'!Q82*'[5]COST TO SERVE ASSUMPTIONS'!$C$21 -> 30.324692 | N30: ='[5]SUBSCRIBER BASE'!R82*'[5]COST TO SERVE ASSUMPTIONS'!$C$21 -> 30.274151 | O30: ='[5]SUBSCRIBER BASE'!S82*'[5]COST TO SERVE ASSUMPTIONS'!$C$21 -> 30.223694 | P30: ='[5]SUBSCRIBER BASE'!T82*'[5]COST TO SERVE ASSUMPTIONS'!$C$21 -> 30.173321 | Q30: ='[5]SUBSCRIBER BASE'!U82*'[5]COST TO SERVE ASSUMPTIONS'!$C$21 -> 30.123032 | R30: ='[5]SUBSCRIBER BASE'!V82*'[5]COST TO SERVE ASSUMPTIONS'!$C$21 -> 30.072827 | ... BR30: ='[5]SUBSCRIBER BASE'!BV82*'[5]COST TO SERVE ASSUMPTIONS'!$C$21 -> 965.39054
B31: =[5]ACTIVATIONS!B42 -> GOLD | C31: ='[5]SUBSCRIBER BASE'!C83*'[5]COST TO SERVE ASSUMPTIONS'!$C$21 -> 0 | D31: ='[5]SUBSCRIBER BASE'!D83*'[5]COST TO SERVE ASSUMPTIONS'!$C$21 -> 0 | E31: ='[5]SUBSCRIBER BASE'!E83*'[5]COST TO SERVE ASSUMPTIONS'!$C$21 -> 0 | F31: ='[5]SUBSCRIBER BASE'!F83*'[5]COST TO SERVE ASSUMPTIONS'!$C$21 -> 0 | G31: ='[5]SUBSCRIBER BASE'!G83*'[5]COST TO SERVE ASSUMPTIONS'!$C$21 -> 0 | H31: ='[5]SUBSCRIBER BASE'!H83*'[5]COST TO SERVE ASSUMPTIONS'!$C$21 -> 0 | I31: ='[5]SUBSCRIBER BASE'!K83*'[5]COST TO SERVE ASSUMPTIONS'!$C$21 -> 7.63828 | J31: ='[5]SUBSCRIBER BASE'!L83*'[5]COST TO SERVE ASSUMPTIONS'!$C$21 -> 15.26383 | K31: ='[5]SUBSCRIBER BASE'!O83*'[5]COST TO SERVE ASSUMPTIONS'!$C$21 -> 60.979147 | L31: ='[5]SUBSCRIBER BASE'!P83*'[5]COST TO SERVE ASSUMPTIONS'!$C$21 -> 91.430635 | M31: ='[5]SUBSCRIBER BASE'!Q83*'[5]COST TO SERVE ASSUMPTIONS'!$C$21 -> 121.83137 | N31: ='[5]SUBSCRIBER BASE'!R83*'[5]COST TO SERVE ASSUMPTIONS'!$C$21 -> 156.00058 | O31: ='[5]SUBSCRIBER BASE'!S83*'[5]COST TO SERVE ASSUMPTIONS'!$C$21 -> 190.11284 | P31: ='[5]SUBSCRIBER BASE'!T83*'[5]COST TO SERVE ASSUMPTIONS'!$C$21 -> 224.16824 | Q31: ='[5]SUBSCRIBER BASE'!U83*'[5]COST TO SERVE ASSUMPTIONS'!$C$21 -> 261.98603 | R31: ='[5]SUBSCRIBER BASE'!V83*'[5]COST TO SERVE ASSUMPTIONS'!$C$21 -> 299.74079 | ... BR31: ='[5]SUBSCRIBER BASE'!BV83*'[5]COST TO SERVE ASSUMPTIONS'!$C$21 -> 12890.41
B32: =[5]ACTIVATIONS!B43 -> SILVER | C32: ='[5]SUBSCRIBER BASE'!C84*'[5]COST TO SERVE ASSUMPTIONS'!$C$21 -> 0 | D32: ='[5]SUBSCRIBER BASE'!D84*'[5]COST TO SERVE ASSUMPTIONS'!$C$21 -> 0 | E32: ='[5]SUBSCRIBER BASE'!E84*'[5]COST TO SERVE ASSUMPTIONS'!$C$21 -> 0 | F32: ='[5]SUBSCRIBER BASE'!F84*'[5]COST TO SERVE ASSUMPTIONS'!$C$21 -> 0 | G32: ='[5]SUBSCRIBER BASE'!G84*'[5]COST TO SERVE ASSUMPTIONS'!$C$21 -> 0 | H32: ='[5]SUBSCRIBER BASE'!H84*'[5]COST TO SERVE ASSUMPTIONS'!$C$21 -> 0 | I32: ='[5]SUBSCRIBER BASE'!K84*'[5]COST TO SERVE ASSUMPTIONS'!$C$21 -> 7.63828 | J32: ='[5]SUBSCRIBER BASE'!L84*'[5]COST TO SERVE ASSUMPTIONS'!$C$21 -> 15.26383 | K32: ='[5]SUBSCRIBER BASE'!O84*'[5]COST TO SERVE ASSUMPTIONS'!$C$21 -> 72.436567 | L32: ='[5]SUBSCRIBER BASE'!P84*'[5]COST TO SERVE ASSUMPTIONS'!$C$21 -> 114.32638 | M32: ='[5]SUBSCRIBER BASE'!Q84*'[5]COST TO SERVE ASSUMPTIONS'!$C$21 -> 159.96552 | N32: ='[5]SUBSCRIBER BASE'!R84*'[5]COST TO SERVE ASSUMPTIONS'!$C$21 -> 205.52859 | O32: ='[5]SUBSCRIBER BASE'!S84*'[5]COST TO SERVE ASSUMPTIONS'!$C$21 -> 251.01572 | P32: ='[5]SUBSCRIBER BASE'!T84*'[5]COST TO SERVE ASSUMPTIONS'!$C$21 -> 300.24618 | Q32: ='[5]SUBSCRIBER BASE'!U84*'[5]COST TO SERVE ASSUMPTIONS'!$C$21 -> 349.39459 | R32: ='[5]SUBSCRIBER BASE'!V84*'[5]COST TO SERVE ASSUMPTIONS'!$C$21 -> 402.28022 | ... BR32: ='[5]SUBSCRIBER BASE'!BV84*'[5]COST TO SERVE ASSUMPTIONS'!$C$21 -> 17575.704
B33: =[5]ACTIVATIONS!B44 -> MASS | C33: ='[5]SUBSCRIBER BASE'!C85*'[5]COST TO SERVE ASSUMPTIONS'!$C$21 -> 0 | D33: ='[5]SUBSCRIBER BASE'!D85*'[5]COST TO SERVE ASSUMPTIONS'!$C$21 -> 0 | E33: ='[5]SUBSCRIBER BASE'!E85*'[5]COST TO SERVE ASSUMPTIONS'!$C$21 -> 0 | F33: ='[5]SUBSCRIBER BASE'!F85*'[5]COST TO SERVE ASSUMPTIONS'!$C$21 -> 0 | G33: ='[5]SUBSCRIBER BASE'!G85*'[5]COST TO SERVE ASSUMPTIONS'!$C$21 -> 0 | H33: ='[5]SUBSCRIBER BASE'!H85*'[5]COST TO SERVE ASSUMPTIONS'!$C$21 -> 0 | I33: ='[5]SUBSCRIBER BASE'!K85*'[5]COST TO SERVE ASSUMPTIONS'!$C$21 -> 3.81914 | J33: ='[5]SUBSCRIBER BASE'!L85*'[5]COST TO SERVE ASSUMPTIONS'!$C$21 -> 7.6319148 | K33: ='[5]SUBSCRIBER BASE'!O85*'[5]COST TO SERVE ASSUMPTIONS'!$C$21 -> 76.319254 | L33: ='[5]SUBSCRIBER BASE'!P85*'[5]COST TO SERVE ASSUMPTIONS'!$C$21 -> 141.11743 | M33: ='[5]SUBSCRIBER BASE'!Q85*'[5]COST TO SERVE ASSUMPTIONS'!$C$21 -> 205.80762 | N33: ='[5]SUBSCRIBER BASE'!R85*'[5]COST TO SERVE ASSUMPTIONS'!$C$21 -> 274.20913 | O33: ='[5]SUBSCRIBER BASE'!S85*'[5]COST TO SERVE ASSUMPTIONS'!$C$21 -> 342.49663 | P33: ='[5]SUBSCRIBER BASE'!T85*'[5]COST TO SERVE ASSUMPTIONS'!$C$21 -> 414.48946 | Q33: ='[5]SUBSCRIBER BASE'!U85*'[5]COST TO SERVE ASSUMPTIONS'!$C$21 -> 486.36231 | R33: ='[5]SUBSCRIBER BASE'!V85*'[5]COST TO SERVE ASSUMPTIONS'!$C$21 -> 561.9345 | ... BR33: ='[5]SUBSCRIBER BASE'!BV85*'[5]COST TO SERVE ASSUMPTIONS'!$C$21 -> 24691.961
B34: =[5]ACTIVATIONS!B45 -> SMALL COMMERCIAL | C34: ='[5]SUBSCRIBER BASE'!C86*'[5]COST TO SERVE ASSUMPTIONS'!$C$21 -> 0 | D34: ='[5]SUBSCRIBER BASE'!D86*'[5]COST TO SERVE ASSUMPTIONS'!$C$21 -> 0 | E34: ='[5]SUBSCRIBER BASE'!E86*'[5]COST TO SERVE ASSUMPTIONS'!$C$21 -> 0 | F34: ='[5]SUBSCRIBER BASE'!F86*'[5]COST TO SERVE ASSUMPTIONS'!$C$21 -> 0 | G34: ='[5]SUBSCRIBER BASE'!G86*'[5]COST TO SERVE ASSUMPTIONS'!$C$21 -> 0 | H34: ='[5]SUBSCRIBER BASE'!H86*'[5]COST TO SERVE ASSUMPTIONS'!$C$21 -> 0 | I34: ='[5]SUBSCRIBER BASE'!K86*'[5]COST TO SERVE ASSUMPTIONS'!$C$21 -> 7.63828 | J34: ='[5]SUBSCRIBER BASE'!L86*'[5]COST TO SERVE ASSUMPTIONS'!$C$21 -> 15.26383 | K34: ='[5]SUBSCRIBER BASE'!O86*'[5]COST TO SERVE ASSUMPTIONS'!$C$21 -> 41.883447 | L34: ='[5]SUBSCRIBER BASE'!P86*'[5]COST TO SERVE ASSUMPTIONS'!$C$21 -> 53.271062 | M34: ='[5]SUBSCRIBER BASE'!Q86*'[5]COST TO SERVE ASSUMPTIONS'!$C$21 -> 64.639696 | N34: ='[5]SUBSCRIBER BASE'!R86*'[5]COST TO SERVE ASSUMPTIONS'!$C$21 -> 79.808524 | O34: ='[5]SUBSCRIBER BASE'!S86*'[5]COST TO SERVE ASSUMPTIONS'!$C$21 -> 94.952069 | P34: ='[5]SUBSCRIBER BASE'!T86*'[5]COST TO SERVE ASSUMPTIONS'!$C$21 -> 110.07038 | Q34: ='[5]SUBSCRIBER BASE'!U86*'[5]COST TO SERVE ASSUMPTIONS'!$C$21 -> 125.16349 | R34: ='[5]SUBSCRIBER BASE'!V86*'[5]COST TO SERVE ASSUMPTIONS'!$C$21 -> 140.23144 | ... BR34: ='[5]SUBSCRIBER BASE'!BV86*'[5]COST TO SERVE ASSUMPTIONS'!$C$21 -> 5668.1903
B36: CIB Commission | C36: =C55+C68+C81+C94+C42 -> 0 | D36: =D55+D68+D81+D94+D42 -> 0 | E36: =E55+E68+E81+E94+E42 -> 0 | F36: =F55+F68+F81+F94+F42 -> 0 | G36: =G55+G68+G81+G94+G42 -> 0 | H36: =H55+H68+H81+H94+H42 -> 0 | I36: =I55+I68+I81+I94+I42 -> 0 | J36: =J55+J68+J81+J94+J42 -> 0 | ... BR36: =BR55+BR68+BR81+BR94+BR42 -> 7.9199626e+08
B37: Subscription | C37: =C107+C120+C133+C146+C159 -> 0 | D37: =D107+D120+D133+D146+D159 -> 0 | E37: =E107+E120+E133+E146+E159 -> 0 | F37: =F107+F120+F133+F146+F159 -> 0 | G37: =G107+G120+G133+G146+G159 -> 0 | H37: =H107+H120+H133+H146+H159 -> 0 | I37: =I107+I120+I133+I146+I159 -> 0 | J37: =J107+J120+J133+J146+J159 -> 0 | ... BR37: =BR107+BR120+BR133+BR146+BR159 -> 0
B38: Ongoing | C38: =C172+C185+C198+C211+C224 -> 0 | D38: =D172+D185+D198+D211+D224 -> 0 | E38: =E172+E185+E198+E211+E224 -> 0 | F38: =F172+F185+F198+F211+F224 -> 0 | G38: =G172+G185+G198+G211+G224 -> 0 | H38: =H172+H185+H198+H211+H224 -> 0 | I38: =I172+I185+I198+I211+I224 -> 0 | J38: =J172+J185+J198+J211+J224 -> 0 | ... BR38: =BR172+BR185+BR198+BR211+BR224 -> 0
B39: ='COMMISSION ASSUMPTIONS'!J20 -> Device Commission | C39: =C237+C250+C263+C276+C289 -> 0 | D39: =D237+D250+D263+D276+D289 -> 0 | E39: =E237+E250+E263+E276+E289 -> 0 | F39: =F237+F250+F263+F276+F289 -> 0 | G39: =G237+G250+G263+G276+G289 -> 0 | H39: =H237+H250+H263+H276+H289 -> 0 | I39: =I237+I250+I263+I276+I289 -> 0 | J39: =J237+J250+J263+J276+J289 -> 0 | ... BR39: =BR237+BR250+BR263+BR276+BR289 -> 0
K41: =K42/'SUBSCRIBER BASE'!L24 -> 301.35593 | L41: =L42/'SUBSCRIBER BASE'!M79 -> 301.35593 | M41: =M42/'SUBSCRIBER BASE'!N79 -> 301.35593 | N41: =N42/'SUBSCRIBER BASE'!O79 -> 301.35593 | O41: =O42/'SUBSCRIBER BASE'!P79 -> 301.35593 | P41: =P42/'SUBSCRIBER BASE'!Q79 -> 301.35593 | Q41: =Q42/'SUBSCRIBER BASE'!R79 -> 301.35593 | R41: =R42/'SUBSCRIBER BASE'!S79 -> 301.35593 | S41: =S42/'SUBSCRIBER BASE'!T79 -> 301.35593 | ... BR41: =BR42/'SUBSCRIBER BASE'!BS79 -> 394.78814
B42: ='COMMISSION ASSUMPTIONS'!C7 -> EXISTING AGENTS | C42: =SUM(C44:C53) -> 0 | D42: =SUM(D44:D53) -> 0 | E42: =SUM(E44:E53) -> 0 | F42: =SUM(F44:F53) -> 0 | G42: =SUM(G44:G53) -> 0 | H42: =SUM(H44:H53) -> 0 | I42: =SUM(I44:I53) -> 0 | J42: =SUM(J44:J53) -> 0 | ... BR42: =SUM(BR44:BR53) -> 7.9199626e+08
B43: CIB
